Workbook
Name EPLookupCol: '[1]From Reinsurance Report'!$E$2:$E$4
Name PaidExpLookupCol: '[1]From Monthly Reporting'!$C$4:$C$7
Name PaidIndemLookupCol: '[1]From Monthly Reporting'!$E$4:$E$7
Name PaidStateCol: '[1]From Monthly Reporting'!$A$4:$A$7
Name PremStateCol: '[1]From Reinsurance Report'!$A$2:$A$4
Name RsvLookupCol_Exp: '[1]From Monthly Reporting'!$E$12:$E$15
Name RsvLookupCol_Loss: '[1]From Monthly Reporting'!$D$12:$D$15
Name RsvStateCol: '[1]From Monthly Reporting'!$A$12:$A$15
Name TreatyName: '[1]SetUp & Macro'!$F$8
Name UPRLookupCol: '[1]From Reinsurance Report'!$F$2:$F$4
Name WPLookupCol: '[1]From Reinsurance Report'!$B$2:$B$4

Sheet Instructions
A2: Monthly Reporting Package - Blue Tabs
A4: These should be filled out on a monthly basis
A6: Please only input data in the yellow shaded "input" areas. All other fields contain formulas that will automatically fill in once "input" areas are completed.
A8: The "MTHLY-State" sheets will feed into the "MTHLY-TOTAL" sheet. The only fields on the "MTHLY-TOTAL" sheet that should be filled are the "Polices in Force" field.
A10: The "Cash Settlement" sheet calculates from the "MTHLY-TOTAL" sheet. The "Ending Balance Due SNIC" shows the amount due to USIC for the reported month.
A13: Year- End Reporting Package - Yellow Tabs
A15: These should only be filled out when requested at year end
A17: Please input your data in the PINK highlighted cells only.
A19: Please provide a separate workbook for each company (SNIC, NSIC or USIC) if applicable and each treaty (contract) period.
A21: All data provided for the accounting months must reconcile to previous monthly exhibits. If you find any errors/differences, you must provide revised exhibits for the applicable reporting period(s).

Sheet Expenses Def.
A2: EXTRACTED FROM NAIC INSTRUCTION
B4: Expenses Definition
A8: The loss adjustment expenses used to be divided into "allocated" and "unallocated," which were terms that were
A9: never clearly defined. Effective January 1, 1998, a detailed definition of these expenses was adopted. The distinction
A10: is now between "defense & Cost Containment" and "Adjusting & Other." The loss adjustment expenses are separated
A11: with the intent of identifying the "Defense & Cost Containment" expenses as those, which are correlated with the loss
A12: amounts, and the "Adjusting & Other" as those expenses, which are correlated with claim, count or are general loss
A13: adjusting expenses. It is the character of the expenses that is most important, not whether the expenses were internal
A14: or external to the insurer.
A17: Defense & Cost Containment expenses include defense, litigation and cost containment expenses, whether internal or
A18: external. "Defense" means defense by the insurer in a contentious situation, whether a first party or a third party claim. The
A19: fees charged for insurer employees should include overhead, just as an outside firm's charges would include. The expenses
A20: exclude expenses incurred in the determination of coverage. These expenses include the following items:
A22: 1 | B22: Surveillance expenses;
A23: 2 | B23: Fixed amounts for cost containment expenses;
A24: 3 | B24: Litigation management expenses;
A25: 4 | B25: Loss adjustment expenses for participation in voluntary and involuntary market pools if reported by accident year;
A26: 5 | B26: Fees or salaries for appraisers, private investigators, hearing representatives, reinspectors and fraud investigators,
B27: if working in defense of a claim, and fees or salaries for rehabilitation nurses, if such cost is not included in losses;
A28: 6 | B28: Attorney fees incurred owing to a duty to defend, even when other coverage does not exist; and
A29: 7 | B29: The cost of engaging experts.
A31: Adjusting & Other expenses are those expenses other than those above and which have been assigned to the "Loss Adjustment
A32: Expense" group in the Underwriting and Investment Exhibit – Part 4 – Expenses. These expenses include the following items:
A34: 1 | B34: Fees of adjusters and settling agents (but not if engaged in a contentious defense);
A35: 2 | B35: Loss adjustment expenses for participation in voluntary and involuntary market pools if reported by calendar year;
A36: 3 | B36: Attorney fees incurred in the determination of coverage, including litigation between the insurer and the policyholder;
A37: 4 | B37: Fees or salaries for appraisers, private investigators, hearing representatives, reinspectors and fraud investigators,
B38: if working in the capacity of an adjuster.
A41: The foregoing list is not intended to be all-inclusive. We are relying on the insurers to use reasonable judgment in particular
A42: situations.
A44: The "Defense & Cost Containment" expenses should be assigned to the accident year in which the associated losses were
A45: assigned. The "Adjusting & Other" expenses can be assigned in any justifiable way among the accident years. The preferred
A46: way is to apportion these expenses in proportion to the number of claims reported, closed, or outstanding each year.

Sheet Cash Settlement
A1: PRODUCER: FUTURISTIC UNDERWRITERS LLC. | D1: Input area | F1: Input area | O1: Q/S | P1: 1
A2: COMPANY: SOUTHLAKE SPECIALTY INSURANCE COMPANY | O2: CF | P2: 0.05
O3: Comm | P3: 0.29
O4: Comm | P4: 0.29
A5: TREATY YEAR : 5/1/2020 | O5: BB | P5: 0.004
O6: ULAE | P6: 0.07
O7: XOL | P7: 0
B8: 100% QUOTA SHARE | O8: LR Cap | P8: 0.02
B9: FOR THE MONTH OF | C9: 46142
D11: (2)
D12: REINSURERS | L12: (3)
C13: (1) | D13: AMOUNT | L13: STATE NAT'L
C14: TOTAL | D14: SSIC | E14: ISMIE | F14: Ambridge Re | G14: Liberty Mutual Re | L14: AMOUNT
C15: 100 % | D15: 1 | E15: 0 | F15: 0 | G15: 0 | L15: =+C15-D15-E15-F15-G15-H15-I15-J15-K15 -> 0
A16: 1. | B16: QUOTA SHARE PREMIUMS WRITTEN | D16: =+C16*D15 -> 0 | E16: =+C16*E15 -> 0 | F16: =+C16*F15 -> 0 | G16: =+C16*G15 -> 0 | H16: =+C16*H15 -> 0 | I16: =+C16*I15 -> 0 | J16: =+C16*J15 -> 0 | K16: =+C16*K15 -> 0 | L16: =+C16-D16-E16-F16-G16-H16-I16-J16-K16 -> 0
A17: 2. | B17: POLICY FEES: | C17: ='MTHLY-TOTAL'!E13 -> 0 | D17: =+C17*$D$15 -> 0 | E17: =+C17*$E$15 -> 0 | F17: =+C17*$F$15 -> 0 | G17: =+C17*$G$15 -> 0 | H17: =+C17*$H$15 -> 0 | I17: =+C17*$I$15 -> 0 | J17: =+C17*$J$15 -> 0 | K17: =+C17*$K$15 -> 0 | L17: =+C17-D17-E17-F17-G17-H17-I17-J17-K17 -> 0
A18: 3. | B18: NET PREMIUMS INCLUDING POLICY FEES | C18: =+C16+C17 -> 0 | D18: =+D16+D17 -> 0 | E18: =+E16+E17 -> 0 | F18: =+F16+F17 -> 0 | G18: =+G16+G17 -> 0 | H18: =+H16+H17 -> 0 | I18: =+I16+I17 -> 0 | J18: =+J16+J17 -> 0 | ... L18: =+L16+L17 -> 0
A20: 4. | B20: COLLECTED PREMIUMS | C20: ='MTHLY-TOTAL'!E14 -> -12464.16 | D20: =+C20*D$15 -> -12464.16 | E20: =+C20*E$15 -> 0 | F20: =+C20*F$15 -> 0 | G20: =+C20*G$15 -> 0 | H20: =+C20*H$15 -> 0 | I20: =+C20*I$15 -> 0 | J20: =+C20*J$15 -> 0 | K20: =+C20*K$15 -> 0 | L20: =+C20-D20-E20-F20-G20-H20-I20-J20-K20 -> 0
A21: 5. | B21: POLICY FEES: | C21: ='MTHLY-TOTAL'!E15 -> 0 | D21: =+C21*D$15 -> 0 | E21: =+C21*E$15 -> 0 | F21: =+C21*F$15 -> 0 | G21: =+C21*G$15 -> 0 | H21: =+C21*H$15 -> 0 | I21: =+C21*I$15 -> 0 | J21: =+C21*J$15 -> 0 | K21: =+C21*K$15 -> 0 | L21: =+C21-D21-E21-F21-G21-H21-I21-J21-K21 -> 0
A22: 6. | B22: NET COLLECTED PREMIUMS INCLUDING POLICY FEES | C22: =C20+C21 -> -12464.16 | D22: =D20+D21 -> -12464.16 | E22: =E20+E21 -> 0 | F22: =F20+F21 -> 0 | G22: =G20+G21 -> 0 | H22: =H20+H21 -> 0 | I22: =I20+I21 -> 0 | J22: =J20+J21 -> 0 | ... L22: =L20+L21 -> 0
A24: 7. | B24: LESS: COMMISSION DUE | C24: =D24+E24+F24+G24+H24+I24+J24+K24 -> -3614.6064 | D24: =D20*P3 -> -3614.6064 | E24: =E20*P3 -> 0 | F24: =F20*P3 -> 0 | G24: =G20*P3 -> 0 | H24: =H20*P3 -> 0 | I24: =I20*P3 -> 0 | J24: =J20*P3 -> 0 | K24: =K20*P3 -> 0 | L24: =C24-D24-E24-F24-G24-H24-I24-J24-K24 -> 0
B25: LESS: POLICY FEES | C25: =+C21 -> 0 | D25: =+D21 -> 0 | E25: =+E21 -> 0 | F25: =+F21 -> 0 | G25: =+G21 -> 0 | H25: =+H21 -> 0 | I25: =+I21 -> 0 | J25: =+J21 -> 0 | ... L25: =+L21 -> 0
B26: TOTAL COMMISSION DUE | C26: =SUM(C23:C25) -> -3614.6064 | D26: =SUM(D23:D25) -> -3614.6064 | E26: =SUM(E23:E25) -> 0 | F26: =SUM(F23:F25) -> 0 | G26: =SUM(G23:G25) -> 0 | H26: =SUM(H23:H25) -> 0 | I26: =SUM(I23:I25) -> 0 | J26: =SUM(J23:J25) -> 0 | ... L26: =SUM(L23:L25) -> 0
A28: 8. | B28: LESS: LOSS FUNDING | C28: 0 | D28: =+C28*$D$15 -> 0 | E28: =+C28*$E$15 -> 0 | F28: =+C28*$F$15 -> 0 | G28: =+C28*$G$15 -> 0 | H28: =+C28*$H$15 -> 0 | I28: =+C28*$I$15 -> 0 | J28: =+C28*$J$15 -> 0 | K28: =+C28*$K$15 -> 0 | L28: =+C28-D28-E28-F28-G28-H28-I28-J28-K28 -> 0
B29: LESS: LOSSES PAID (net of salvage & subro) | C29: ='MTHLY-TOTAL'!E19 -> 207475.83 | D29: =+C29*$D$15 -> 207475.83 | E29: =+C29*$E$15 -> 0 | F29: =+C29*$F$15 -> 0 | G29: =+C29*$G$15 -> 0 | H29: =+C29*$H$15 -> 0 | I29: =+C29*$I$15 -> 0 | J29: =+C29*$J$15 -> 0 | K29: =+C29*$K$15 -> 0 | L29: =+C29-D29-E29-F29-G29-H29-I29-J29-K29 -> 0
B30: LESS: UNALLOCATED LOSS ADJUSTMENT EXPENSE | C30: ='MTHLY-TOTAL'!C29 -> 0 | D30: =+C30*$D$15 -> 0 | E30: =+C30*$E$15 -> 0 | F30: =+C30*$F$15 -> 0 | G30: =+C30*$G$15 -> 0 | H30: =+C30*$H$15 -> 0 | I30: =+C30*$I$15 -> 0 | J30: =+C30*$J$15 -> 0 | K30: =+C30*$K$15 -> 0 | L30: =+C30-D30-E30-F30-G30-H30-I30-J30-K30 -> 0
B31: LESS: DEFENSE AND COST CONTAINMENT EXPENSE PAID (DCC) | C31: ='MTHLY-TOTAL'!E20 -> 0 | D31: =+C31*$D$15 -> 0 | E31: =+C31*$E$15 -> 0 | F31: =+C31*$F$15 -> 0 | G31: =+C31*$G$15 -> 0 | H31: =+C31*$H$15 -> 0 | I31: =+C31*$I$15 -> 0 | J31: =+C31*$J$15 -> 0 | K31: =+C31*$K$15 -> 0 | L31: =+C31-D31-E31-F31-G31-H31-I31-J31-K31 -> 0
B32: LESS: ADJUSTING & OTHER EXPENSE PAID (A&O) | C32: ='MTHLY-TOTAL'!E21 -> -872.4912 | D32: =+$C32*D15 -> -872.4912 | E32: =+$C32*E15 -> 0 | F32: =+$C32*F15 -> 0 | G32: =+$C32*G15 -> 0 | H32: =+C32*$H$15 -> 0 | I32: =+C32*$I$15 -> 0 | J32: =+C32*$J$15 -> 0 | K32: =+C32*$K$15 -> 0 | L32: =+C32-D32-E32-F32-G32-H32-I32-J32-K32 -> 0
B33: TOTAL LOSSES PAID | C33: =SUM(C28:C32) -> 206603.34 | D33: =SUM(D28:D32) -> 206603.34 | E33: =SUM(E28:E32) -> 0 | F33: =SUM(F28:F32) -> 0 | G33: =SUM(G28:G32) -> 0 | H33: =SUM(H28:H32) -> 0 | I33: =SUM(I28:I32) -> 0 | J33: =SUM(J28:J32) -> 0 | ... L33: =SUM(L28:L32) -> 0
B35: SUBTOTAL DUE | C35: =C22-C26-C33 -> -215452.89 | D35: =D22-D26-D33 -> -215452.89 | E35: =E22-E26-E33 -> 0 | F35: =F22-F26-F33 -> 0 | G35: =G22-G26-G33 -> 0 | H35: =H22-H26-H33 -> 0 | I35: =I22-I26-I33 -> 0 | J35: =J22-J26-J33 -> 0 | ... L35: =L22-L26-L33 -> 0
A37: 9. | B37: CEDING FEE DUE | L37: =C22*$P$2 -> -623.208 | M37: **
A38: 10. | B38: BOARDS & BUREAUS DUE | D38: =-L38 -> 0 | L38: =+C18*$P$5 -> 0
A39: 11. | B39: XOL FEES DUE | L39: =+C18*$P$7 -> 0
A40: 12. | B40: LR Cap | D40: =-L40 -> 0 | L40: =+C18*(P8) -> 0
B41: TOTAL TAXES & FEES DUE | L41: =SUM(L37:L40) -> -623.208
B44: TOTAL BALANCE DUE REINSURERS | C44: ……………………. | D44: =D35+D38+D39+D40 -> -215452.89 | E44: =+E35+E41 -> 0 | F44: =+F35+F41 -> 0 | G44: =+G35+G41 -> 0 | H44: =+H35+H41 -> 0 | I44: =+I35+I41 -> 0 | J44: =+J35+J41 -> 0 | K44: =+K35+K41 -> 0
B45: TOTAL BALANCE DUE SSIC | C45: …………………………………………… | L45: =+L35+L41 -> -623.208
B47: Beginning Balance Due TO/(FROM) SSIC: | C47: carry from last month | L47: 0
B49: Less: Amounts Paid TO/(FROM) SSIC | L49: 0
B51: Ending Balance Due TO/(FROM) SSIC: | L51: =+L45+L49 -> -623.208
B56: UNEARNED PREMIUM | C56: ='MTHLY-TOTAL'!E24 -> 889754.56 | D56: =+C56*$D$15 -> 889754.56 | E56: =+C56*$E$15 -> 0 | F56: =+C56*$F$15 -> 0 | G56: =+C56*$G$15 -> 0 | H56: =+C56*$H$15 -> 0 | I56: =+C56*$I$15 -> 0 | J56: =+C56*$J$15 -> 0 | K56: =+C56*$K$15 -> 0
B58: OUTSTANDING LOSS RESERVES | C58: ='MTHLY-TOTAL'!E26 -> 54333 | D58: =+C58*$D$15 -> 54333 | E58: =+C58*$E$15 -> 0 | F58: =+C58*$F$15 -> 0 | G58: =+C58*$G$15 -> 0 | H58: =+C58*$H$15 -> 0 | I58: =+C58*$I$15 -> 0 | J58: =+C58*$J$15 -> 0 | K58: =+C58*$K$15 -> 0
B59: OUTSTANDING LAE RESERVES | C59: ='MTHLY-TOTAL'!E27 -> 14195 | D59: =+C59*$D$15 -> 14195 | E59: =+C59*$E$15 -> 0 | F59: =+C59*$F$15 -> 0 | G59: =+C59*$G$15 -> 0 | H59: =+C59*$H$15 -> 0 | I59: =+C59*$I$15 -> 0 | J59: =+C59*$J$15 -> 0 | K59: =+C59*$K$15 -> 0
B60: OUTSTANDING ULAE RESERVES | C60: =+'MTHLY-TOTAL'!E28 -> 0 | D60: =+C60*$D$15 -> 0 | E60: =+C60*$E$15 -> 0 | F60: =+C60*$F$15 -> 0 | G60: =+C60*$G$15 -> 0 | H60: =+C60*$H$15 -> 0 | I60: =+C60*$I$15 -> 0 | J60: =+C60*$J$15 -> 0 | K60: =+C60*$K$15 -> 0
B62: ** Min. Ceding Fee: $125,000 for each 6 month period.

Sheet MTHLY-TOTAL
A1: =+'Cash Settlement'!A2 -> COMPANY: SOUTHLAKE SPECIALTY INSURANCE COMPANY
A2: =+'Cash Settlement'!A1 -> PRODUCER: FUTURISTIC UNDERWRITERS LLC. | D2: Input area
A3: EXHIBIT OF PREMIUMS AND LOSSES
A4: =+'Cash Settlement'!B9 -> FOR THE MONTH OF | C4: ='Cash Settlement'!C9 -> 46142
A6: TOTAL PROGRAM BY LINE OF BUSINESS
A8: STATE All States
B9: 9 | C9: 19.4 | D9: 21.2
A10: ='Cash Settlement'!A5 -> TREATY YEAR : 5/1/2020 | B10: Comm'l Auto | C10: Other Comm'l | D10: Comm'l Auto | E10: TOTALS
B11: Inland Marine | C11: Auto Liab | D11: Phys. Damage
A12: Premiums Written | B12: =SUM('MTHLY-AL:MTHLY-WY'!B14) -> 0 | C12: =SUM('MTHLY-AL:MTHLY-WY'!C14) -> 0 | D12: =SUM('MTHLY-AL:MTHLY-WY'!D14) -> -12464.16 | E12: =SUM(B12:D12) -> -12464.16
A13: Policy Fees Written | B13: =SUM('MTHLY-AL:MTHLY-WY'!B15) -> 0 | C13: =SUM('MTHLY-AL:MTHLY-WY'!C15) -> 0 | D13: =SUM('MTHLY-AL:MTHLY-WY'!D15) -> 0 | E13: =SUM(B13:D13) -> 0
A14: Premiums Collected | B14: =SUM('MTHLY-AL:MTHLY-WY'!B16) -> 0 | C14: =SUM('MTHLY-AL:MTHLY-WY'!C16) -> 0 | D14: =SUM('MTHLY-AL:MTHLY-WY'!D16) -> -12464.16 | E14: =SUM(B14:D14) -> -12464.16
A15: Policy Fees Collected | B15: =SUM('MTHLY-AL:MTHLY-WY'!B17) -> 0 | C15: =SUM('MTHLY-AL:MTHLY-WY'!C17) -> 0 | D15: =SUM('MTHLY-AL:MTHLY-WY'!D17) -> 0 | E15: =SUM(B15:D15) -> 0
A16: Front/Ceding Fees | B16: =ROUND(SUM(B12:B13)*'Cash Settlement'!$P$2,2) -> 0 | C16: =ROUND(SUM(C12:C13)*'Cash Settlement'!$P$2,2) -> 0 | D16: =ROUND(SUM(D12:D13)*'Cash Settlement'!$P$2,2) -> -623.21 | E16: =SUM(B16:D16) -> -623.21
A17: Premium Taxes | B17: =SUM('MTHLY-AL:MTHLY-WY'!B18) -> 0 | C17: =SUM('MTHLY-AL:MTHLY-WY'!C18) -> 0 | D17: =SUM('MTHLY-AL:MTHLY-WY'!D18) -> 0 | E17: =SUM(B17:D17) -> 0
A18: Boards & Bureau | B18: =ROUND((B12+B13)*'Cash Settlement'!$P$5,2) -> 0 | C18: =ROUND((C12+C13)*'Cash Settlement'!$P$5,2) -> 0 | D18: =ROUND((D12+D13)*'Cash Settlement'!$P$5,2) -> -49.86 | E18: =SUM(B18:D18) -> -49.86
A19: Losses Paid (Net of Salvage & Subrogation) | B19: =SUM('MTHLY-AL:MTHLY-WY'!B19) -> 0 | C19: =SUM('MTHLY-AL:MTHLY-WY'!C19) -> 0 | D19: =SUM('MTHLY-AL:MTHLY-WY'!D19) -> 207475.83 | E19: =SUM(B19:D19) -> 207475.83
A20: Defense & Cost Containment Expenses Paid - (ALAE) | B20: =SUM('MTHLY-AL:MTHLY-WY'!B20) -> 0 | C20: =SUM('MTHLY-AL:MTHLY-WY'!C20) -> 0 | D20: =SUM('MTHLY-AL:MTHLY-WY'!D20) -> 0 | E20: =SUM(B20:D20) -> 0
A21: Adjusting & Other Expenses Paid - (ULAE-TPA Fees) | B21: =SUM('MTHLY-AL:MTHLY-WY'!B21) -> 0 | C21: =SUM('MTHLY-AL:MTHLY-WY'!C21) -> 0 | D21: =SUM('MTHLY-AL:MTHLY-WY'!D21) -> -872.4912 | E21: =SUM(B21:D21) -> -872.4912
A22: Premium Earned - YTD | B22: =SUM('MTHLY-AL:MTHLY-WY'!B22) -> 0 | C22: =SUM('MTHLY-AL:MTHLY-WY'!C22) -> 0 | D22: =SUM('MTHLY-AL:MTHLY-WY'!D22) -> 1170452 | E22: =SUM(B22:D22) -> 1170452
A23: Policy Fees Earned - YTD | B23: =SUM('MTHLY-AL:MTHLY-WY'!B23) -> 0 | C23: =SUM('MTHLY-AL:MTHLY-WY'!C23) -> 0 | D23: =SUM('MTHLY-AL:MTHLY-WY'!D23) -> 0 | E23: =SUM(B23:D23) -> 0
A24: Unearned Premium Reserves | B24: =SUM('MTHLY-AL:MTHLY-WY'!B24) -> 0 | C24: =SUM('MTHLY-AL:MTHLY-WY'!C24) -> 0 | D24: =SUM('MTHLY-AL:MTHLY-WY'!D24) -> 889754.56 | E24: =SUM(B24:D24) -> 889754.56
A25: NUMBER OF POLICIES IN FORCE | B25: 0 | C25: 0 | D25: ='Policies In force'!E61 -> 283 | E25: =D25 -> 283
A26: Direct Losses Unpaid | B26: =SUM('MTHLY-AL:MTHLY-WY'!B25) -> 0 | C26: =SUM('MTHLY-AL:MTHLY-WY'!C25) -> 0 | D26: =SUM('MTHLY-AL:MTHLY-WY'!D25) -> 54333 | E26: =SUM(B26:D26) -> 54333
A27: Defense & Cost Containment Unpaid - (ALAE) | B27: =SUM('MTHLY-AL:MTHLY-WY'!B26) -> 0 | C27: =SUM('MTHLY-AL:MTHLY-WY'!C26) -> 0 | D27: =SUM('MTHLY-AL:MTHLY-WY'!D26) -> 14195 | E27: =SUM(B27:D27) -> 14195
A28: Adjusting & Other Unpaid - (ULAE-TPA Fees) | B28: =SUM('MTHLY-AL:MTHLY-WY'!B27) -> 0 | C28: =SUM('MTHLY-AL:MTHLY-WY'!C27) -> 0 | D28: =SUM('MTHLY-AL:MTHLY-WY'!D27) -> 0 | E28: =SUM(B28:D28) -> 0
B29: =SUM('MTHLY-AL:MTHLY-WY'!B28) -> 0 | C29: =SUM('MTHLY-AL:MTHLY-WY'!C28) -> 0 | D29: =SUM('MTHLY-AL:MTHLY-WY'!D28) -> 0 | E29: =SUM(B29:D29) -> 0
A31: Submitted by: ______________

Sheet MTHLY-AL
A1: =+'Cash Settlement'!A2 -> COMPANY: SOUTHLAKE SPECIALTY INSURANCE COMPANY
A2: =+'Cash Settlement'!A1 -> PRODUCER: FUTURISTIC UNDERWRITERS LLC. | D2: Input area
A3: EXHIBIT OF PREMIUMS AND LOSSES
A4: FOR THE MONTH OF | C4: =+'Cash Settlement'!C9 -> 46142
A6: BY LINE, BY STATE
B11: 19.3 | C11: 19.4 | D11: 21.2
A12: =+'MTHLY-TOTAL'!A10 -> TREATY YEAR : 5/1/2020 | B12: Comm'l Auto | C12: Other Comm'l | D12: Comm'l Auto | E12: TOTALS
B13: No-Fault | C13: Auto Liab | D13: Phys. Damage
A14: Premiums Written | B14: 0 | C14: 0 | D14: 0 | E14: =SUM(B14:D14) -> 0
A15: Policy Fees Written | B15: 0 | C15: 0 | D15: 0 | E15: =SUM(B15:D15) -> 0
A16: Premiums Collected | B16: 0 | C16: 0 | D16: 0 | E16: =SUM(B16:D16) -> 0
A17: Policy Fees Collected | B17: 0 | C17: 0 | D17: 0 | E17: =SUM(B17:D17) -> 0
A18: Premium Taxes | B18: =(B14+B15)*'Tax Rates'!$B$7 -> 0 | C18: =(C14+C15)*'Tax Rates'!$B$7 -> 0 | D18: =(D14+D15)*'Tax Rates'!$B$7 -> 0 | E18: =SUM(B18:D18) -> 0
A19: Losses Paid (Net of Salvage & Subrogation) | B19: 0 | C19: 0 | D19: 0 | E19: =SUM(B19:D19) -> 0
A20: Defense & Cost Containment Expenses Paid | B20: 0 | C20: 0 | D20: 0 | E20: =SUM(B20:D20) -> 0
A21: Adjusting & Other Expenses Paid | B21: 0 | C21: 0 | D21: 0 | E21: =SUM(B21:D21) -> 0
A22: Premium Earned - YTD | B22: 0 | C22: 0 | D22: 0 | E22: =SUM(B22:D22) -> 0
A23: Policy Fees Earned - YTD | B23: 0 | C23: 0 | D23: 0 | E23: =SUM(B23:D23) -> 0
A24: Unearned Premium Reserves | B24: 0 | C24: 0 | D24: 0 | E24: =SUM(B24:D24) -> 0
A25: Direct Losses Unpaid | B25: 0 | C25: 0 | D25: 0 | E25: =SUM(B25:D25) -> 0
A26: Defense & Cost Containment Unpaid | B26: 0 | C26: 0 | D26: 0 | E26: =SUM(B26:D26) -> 0
A27: Adjusting & Other Unpaid | B27: 0 | C27: 0 | D27: 0 | E27: =SUM(B27:D27) -> 0
A29: ='MTHLY-TOTAL'!A31 -> Submitted by: ______________

Sheet MTHLY-AK
A1: =+'Cash Settlement'!A2 -> COMPANY: SOUTHLAKE SPECIALTY INSURANCE COMPANY
A2: =+'Cash Settlement'!A1 -> PRODUCER: FUTURISTIC UNDERWRITERS LLC. | D2: Input area
A3: EXHIBIT OF PREMIUMS AND LOSSES
A4: FOR THE MONTH OF | C4: =+'Cash Settlement'!C9 -> 46142
A6: BY LINE, BY STATE
B11: 19.3 | C11: 19.4 | D11: 21.2
A12: =+'MTHLY-TOTAL'!A10 -> TREATY YEAR : 5/1/2020 | B12: Comm'l Auto | C12: Other Comm'l | D12: Comm'l Auto | E12: TOTALS
B13: No-Fault | C13: Auto Liab | D13: Phys. Damage
A14: Premiums Written | B14: 0 | C14: 0 | D14: 0 | E14: =SUM(B14:D14) -> 0
A15: Policy Fees Written | B15: 0 | C15: 0 | D15: 0 | E15: =SUM(B15:D15) -> 0
A16: Premiums Collected | B16: 0 | C16: 0 | D16: 0 | E16: =SUM(B16:D16) -> 0
A17: Policy Fees Collected | B17: 0 | C17: 0 | D17: 0 | E17: =SUM(B17:D17) -> 0
A18: Premium Taxes | B18: =(B14+B15)*'Tax Rates'!$B$8 -> 0 | C18: =(C14+C15)*'Tax Rates'!$B$8 -> 0 | D18: =(D14+D15)*'Tax Rates'!$B$8 -> 0 | E18: =SUM(B18:D18) -> 0
A19: Losses Paid (Net of Salvage & Subrogation) | B19: 0 | C19: 0 | D19: 0 | E19: =SUM(B19:D19) -> 0
A20: Defense & Cost Containment Expenses Paid | B20: 0 | C20: 0 | D20: 0 | E20: =SUM(B20:D20) -> 0
A21: Adjusting & Other Expenses Paid | B21: 0 | C21: 0 | D21: 0 | E21: =SUM(B21:D21) -> 0
A22: Premium Earned - YTD | B22: 0 | C22: 0 | D22: 0 | E22: =SUM(B22:D22) -> 0
A23: Policy Fees Earned - YTD | B23: 0 | C23: 0 | D23: 0 | E23: =SUM(B23:D23) -> 0
A24: Unearned Premium Reserves | B24: 0 | C24: 0 | D24: 0 | E24: =SUM(B24:D24) -> 0
A25: Direct Losses Unpaid | B25: 0 | C25: 0 | D25: 0 | E25: =SUM(B25:D25) -> 0
A26: Defense & Cost Containment Unpaid | B26: 0 | C26: 0 | D26: 0 | E26: =SUM(B26:D26) -> 0
A27: Adjusting & Other Unpaid | B27: 0 | C27: 0 | D27: 0 | E27: =SUM(B27:D27) -> 0
A29: ='MTHLY-TOTAL'!A31 -> Submitted by: ______________

Sheet MTHLY-AR
A1: =+'Cash Settlement'!A2 -> COMPANY: SOUTHLAKE SPECIALTY INSURANCE COMPANY
A2: =+'Cash Settlement'!A1 -> PRODUCER: FUTURISTIC UNDERWRITERS LLC. | D2: Input area
A3: EXHIBIT OF PREMIUMS AND LOSSES
A4: FOR THE MONTH OF | C4: =+'Cash Settlement'!C9 -> 46142
A6: BY LINE, BY STATE
B11: 19.3 | C11: 19.4 | D11: 21.2
A12: =+'MTHLY-TOTAL'!A10 -> TREATY YEAR : 5/1/2020 | B12: Comm'l Auto | C12: Other Comm'l | D12: Comm'l Auto | E12: TOTALS
B13: No-Fault | C13: Auto Liab | D13: Phys. Damage
A14: Premiums Written | B14: 0 | C14: 0 | D14: 0 | E14: =SUM(B14:D14) -> 0
A15: Policy Fees Written | B15: 0 | C15: 0 | D15: 0 | E15: =SUM(B15:D15) -> 0
A16: Premiums Collected | B16: 0 | C16: 0 | D16: 0 | E16: =SUM(B16:D16) -> 0
A17: Policy Fees Collected | B17: 0 | C17: 0 | D17: 0 | E17: =SUM(B17:D17) -> 0
A18: Premium Taxes | B18: =(B14+B15)*'Tax Rates'!$B$10 -> 0 | C18: =(C14+C15)*'Tax Rates'!$B$10 -> 0 | D18: =(D14+D15)*'Tax Rates'!$B$10 -> 0 | E18: =SUM(B18:D18) -> 0
A19: Losses Paid (Net of Salvage & Subrogation) | B19: 0 | C19: 0 | D19: 0 | E19: =SUM(B19:D19) -> 0
A20: Defense & Cost Containment Expenses Paid | B20: 0 | C20: 0 | D20: 0 | E20: =SUM(B20:D20) -> 0
A21: Adjusting & Other Expenses Paid | B21: 0 | C21: 0 | D21: 0 | E21: =SUM(B21:D21) -> 0
A22: Premium Earned - YTD | B22: 0 | C22: 0 | D22: 0 | E22: =SUM(B22:D22) -> 0
A23: Policy Fees Earned - YTD | B23: 0 | C23: 0 | D23: 0 | E23: =SUM(B23:D23) -> 0
A24: Unearned Premium Reserves | B24: 0 | C24: 0 | D24: 0 | E24: =SUM(B24:D24) -> 0
A25: Direct Losses Unpaid | B25: 0 | C25: 0 | D25: 0 | E25: =SUM(B25:D25) -> 0
A26: Defense & Cost Containment Unpaid | B26: 0 | C26: 0 | D26: 0 | E26: =SUM(B26:D26) -> 0
A27: Adjusting & Other Unpaid | B27: 0 | C27: 0 | D27: 0 | E27: =SUM(B27:D27) -> 0
A29: ='MTHLY-TOTAL'!A31 -> Submitted by: ______________

Sheet MTHLY-AZ
A1: =+'Cash Settlement'!A2 -> COMPANY: SOUTHLAKE SPECIALTY INSURANCE COMPANY
A2: =+'Cash Settlement'!A1 -> PRODUCER: FUTURISTIC UNDERWRITERS LLC. | D2: Input area
A3: EXHIBIT OF PREMIUMS AND LOSSES
A4: FOR THE MONTH OF | C4: =+'Cash Settlement'!C9 -> 46142
A6: BY LINE, BY STATE
B11: 9 | C11: 19.4 | D11: 21.2
A12: =+'MTHLY-TOTAL'!A10 -> TREATY YEAR : 5/1/2020 | B12: Comm'l Auto | C12: Other Comm'l | D12: Comm'l Auto | E12: TOTALS
B13: Inland Marine | C13: Auto Liab | D13: Phys. Damage
A14: Premiums Written | B14: 0 | C14: 0 | D14: 0 | E14: =SUM(B14:D14) -> 0
A15: Policy Fees Written | B15: 0 | C15: 0 | D15: 0 | E15: =SUM(B15:D15) -> 0
A16: Premiums Collected | B16: 0 | C16: 0 | D16: 0 | E16: =SUM(B16:D16) -> 0
A17: Policy Fees Collected | B17: 0 | C17: 0 | D17: 0 | E17: =SUM(B17:D17) -> 0
A18: Premium Taxes | B18: =(B14+B15)*'Tax Rates'!$B$9 -> 0 | C18: =(C14+C15)*'Tax Rates'!$B$9 -> 0 | E18: =SUM(B18:D18) -> 0
A19: Losses Paid (Net of Salvage & Subrogation) | B19: 0 | C19: 0 | D19: 0 | E19: =SUM(B19:D19) -> 0
A20: Defense & Cost Containment Expenses Paid - (ALAE) | B20: 0 | C20: 0 | D20: 0 | E20: =SUM(B20:D20) -> 0
A21: Adjusting & Other Expenses Paid - (ULAE-TPA Fees) | B21: 0 | C21: 0 | D21: 0 | E21: =SUM(B21:D21) -> 0
A22: Premium Earned - YTD | B22: 0 | C22: 0 | D22: 27205.81 | E22: =SUM(B22:D22) -> 27205.81
A23: Policy Fees Earned - YTD | B23: 0 | C23: 0 | D23: 0 | E23: =SUM(B23:D23) -> 0
A24: Unearned Premium Reserves | B24: 0 | C24: 0 | D24: 21692.96 | E24: =SUM(B24:D24) -> 21692.96
A25: Direct Losses Unpaid | B25: 0 | C25: 0 | D25: 0 | E25: =SUM(B25:D25) -> 0
A26: Defense & Cost Containment Unpaid -- (ALAE) | B26: 0 | C26: 0 | D26: 0 | E26: =SUM(B26:D26) -> 0
A27: Adjusting & Other Unpaid - (ULAE-TPA Fees) | B27: 0 | C27: 0 | D27: 0 | E27: =SUM(B27:D27) -> 0
B28: 0 | C28: 0 | D28: 0 | E28: =SUM(B28:D28) -> 0
A30: ='MTHLY-TOTAL'!A31 -> Submitted by: ______________

Sheet MTHLY-CA
A1: =+'Cash Settlement'!A2 -> COMPANY: SOUTHLAKE SPECIALTY INSURANCE COMPANY
A2: =+'Cash Settlement'!A1 -> PRODUCER: FUTURISTIC UNDERWRITERS LLC. | D2: Input area
A3: EXHIBIT OF PREMIUMS AND LOSSES
A4: FOR THE MONTH OF | C4: =+'Cash Settlement'!C9 -> 46142
A6: BY LINE, BY STATE
B11: 9 | C11: 19.4 | D11: 21.2
A12: =+'MTHLY-TOTAL'!A10 -> TREATY YEAR : 5/1/2020 | B12: Comm'l Auto | C12: Other Comm'l | D12: Comm'l Auto | E12: TOTALS
B13: Inland Marine | C13: Auto Liab | D13: Phys. Damage
A14: Premiums Written | B14: 0 | C14: 0 | D14: -10318.74 | E14: =SUM(B14:D14) -> -10318.74
A15: Policy Fees Written | B15: 0 | C15: 0 | D15: 0 | E15: =SUM(B15:D15) -> 0
A16: Premiums Collected | B16: 0 | C16: 0 | D16: -10318.74 | E16: =SUM(B16:D16) -> -10318.74
A17: Policy Fees Collected | B17: 0 | C17: 0 | D17: 0 | E17: =SUM(B17:D17) -> 0
A18: Premium Taxes | B18: =(B14+B15)*'Tax Rates'!$B$11 -> 0 | C18: =(C14+C15)*'Tax Rates'!$B$11 -> 0 | E18: =SUM(B18:D18) -> 0
A19: Losses Paid (Net of Salvage & Subrogation) | B19: 0 | C19: 0 | D19: 80975.83 | E19: =SUM(B19:D19) -> 80975.83
A20: Defense & Cost Containment Expenses Paid - (ALAE) | B20: 0 | C20: 0 | D20: 0 | E20: =SUM(B20:D20) -> 0
A21: Adjusting & Other Expenses Paid - (ULAE-TPA Fees) | B21: 0 | C21: 0 | D21: -722.3118 | E21: =SUM(B21:D21) -> -722.3118
A22: Premium Earned - YTD | B22: 0 | C22: 0 | D22: 708172.81 | E22: =SUM(B22:D22) -> 708172.81
A23: Policy Fees Earned - YTD | B23: 0 | C23: 0 | D23: 0 | E23: =SUM(B23:D23) -> 0
A24: Unearned Premium Reserves | B24: 0 | C24: 0 | D24: 510480.07 | E24: =SUM(B24:D24) -> 510480.07
A25: Direct Losses Unpaid | B25: 0 | C25: 0 | D25: 17500 | E25: =SUM(B25:D25) -> 17500
A26: Defense & Cost Containment Unpaid - (ALAE) | B26: 0 | C26: 0 | D26: 5000 | E26: =SUM(B26:D26) -> 5000
A27: Adjusting & Other Unpaid - (ULAE-TPA Fees) | B27: 0 | C27: 0 | D27: 0 | E27: =SUM(B27:D27) -> 0
B28: 0 | C28: 0 | D28: 0 | E28: =SUM(B28:D28) -> 0
A30: ='MTHLY-TOTAL'!A31 -> Submitted by: ______________

Sheet MTHLY-CO
A1: =+'Cash Settlement'!A2 -> COMPANY: SOUTHLAKE SPECIALTY INSURANCE COMPANY
A2: =+'Cash Settlement'!A1 -> PRODUCER: FUTURISTIC UNDERWRITERS LLC. | D2: Input area
A3: EXHIBIT OF PREMIUMS AND LOSSES
A4: FOR THE MONTH OF | C4: =+'Cash Settlement'!C9 -> 46142
A6: BY LINE, BY STATE
B11: 19.3 | C11: 19.4 | D11: 21.2
A12: =+'MTHLY-TOTAL'!A10 -> TREATY YEAR : 5/1/2020 | B12: Comm'l Auto | C12: Other Comm'l | D12: Comm'l Auto | E12: TOTALS
B13: No-Fault | C13: Auto Liab | D13: Phys. Damage
A14: Premiums Written | B14: 0 | C14: 0 | D14: 0 | E14: =SUM(B14:D14) -> 0
A15: Policy Fees Written | B15: 0 | C15: 0 | D15: 0 | E15: =SUM(B15:D15) -> 0
A16: Premiums Collected | B16: 0 | C16: 0 | D16: 0 | E16: =SUM(B16:D16) -> 0
A17: Policy Fees Collected | B17: 0 | C17: 0 | D17: 0 | E17: =SUM(B17:D17) -> 0
A18: Premium Taxes | B18: =(B14+B15)*'Tax Rates'!$B$12 -> 0 | C18: =(C14+C15)*'Tax Rates'!$B$12 -> 0 | D18: =(D14+D15)*'Tax Rates'!$B$12 -> 0 | E18: =SUM(B18:D18) -> 0
A19: Losses Paid (Net of Salvage & Subrogation) | B19: 0 | C19: 0 | D19: 0 | E19: =SUM(B19:D19) -> 0
A20: Defense & Cost Containment Expenses Paid | B20: 0 | C20: 0 | D20: 0 | E20: =SUM(B20:D20) -> 0
A21: Adjusting & Other Expenses Paid | B21: 0 | C21: 0 | D21: 0 | E21: =SUM(B21:D21) -> 0
A22: Premium Earned - YTD | B22: 0 | C22: 0 | D22: 0 | E22: =SUM(B22:D22) -> 0
A23: Policy Fees Earned - YTD | B23: 0 | C23: 0 | D23: 0 | E23: =SUM(B23:D23) -> 0
A24: Unearned Premium Reserves | B24: 0 | C24: 0 | D24: 0 | E24: =SUM(B24:D24) -> 0
A25: Direct Losses Unpaid | B25: 0 | C25: 0 | D25: 0 | E25: =SUM(B25:D25) -> 0
A26: Defense & Cost Containment Unpaid | B26: 0 | C26: 0 | D26: 0 | E26: =SUM(B26:D26) -> 0
A27: Adjusting & Other Unpaid | B27: 0 | C27: 0 | D27: 0 | E27: =SUM(B27:D27) -> 0
A29: ='MTHLY-TOTAL'!A31 -> Submitted by: ______________

Sheet MTHLY-CT
A1: =+'Cash Settlement'!A2 -> COMPANY: SOUTHLAKE SPECIALTY INSURANCE COMPANY
A2: =+'Cash Settlement'!A1 -> PRODUCER: FUTURISTIC UNDERWRITERS LLC. | D2: Input area
A3: EXHIBIT OF PREMIUMS AND LOSSES
A4: FOR THE MONTH OF | C4: =+'Cash Settlement'!C9 -> 46142
A6: BY LINE, BY STATE
B11: 19.3 | C11: 19.4 | D11: 21.2
A12: =+'MTHLY-TOTAL'!A10 -> TREATY YEAR : 5/1/2020 | B12: Comm'l Auto | C12: Other Comm'l | D12: Comm'l Auto | E12: TOTALS
B13: No-Fault | C13: Auto Liab | D13: Phys. Damage
A14: Premiums Written | B14: 0 | C14: 0 | D14: 0 | E14: =SUM(B14:D14) -> 0
A15: Policy Fees Written | B15: 0 | C15: 0 | D15: 0 | E15: =SUM(B15:D15) -> 0
A16: Premiums Collected | B16: 0 | C16: 0 | D16: 0 | E16: =SUM(B16:D16) -> 0
A17: Policy Fees Collected | B17: 0 | C17: 0 | D17: 0 | E17: =SUM(B17:D17) -> 0
A18: Premium Taxes | B18: =(B14+B15)*'Tax Rates'!$B$13 -> 0 | C18: =(C14+C15)*'Tax Rates'!$B$13 -> 0 | D18: =(D14+D15)*'Tax Rates'!$B$13 -> 0 | E18: =SUM(B18:D18) -> 0
A19: Losses Paid (Net of Salvage & Subrogation) | B19: 0 | C19: 0 | D19: 0 | E19: =SUM(B19:D19) -> 0
A20: Defense & Cost Containment Expenses Paid | B20: 0 | C20: 0 | D20: 0 | E20: =SUM(B20:D20) -> 0
A21: Adjusting & Other Expenses Paid | B21: 0 | C21: 0 | D21: 0 | E21: =SUM(B21:D21) -> 0
A22: Premium Earned - YTD | B22: 0 | C22: 0 | D22: 0 | E22: =SUM(B22:D22) -> 0
A23: Policy Fees Earned - YTD | B23: 0 | C23: 0 | D23: 0 | E23: =SUM(B23:D23) -> 0
A24: Unearned Premium Reserves | B24: 0 | C24: 0 | D24: 0 | E24: =SUM(B24:D24) -> 0
A25: Direct Losses Unpaid | B25: 0 | C25: 0 | D25: 0 | E25: =SUM(B25:D25) -> 0
A26: Defense & Cost Containment Unpaid | B26: 0 | C26: 0 | D26: 0 | E26: =SUM(B26:D26) -> 0
A27: Adjusting & Other Unpaid | B27: 0 | C27: 0 | D27: 0 | E27: =SUM(B27:D27) -> 0
A29: ='MTHLY-TOTAL'!A31 -> Submitted by: ______________

Sheet MTHLY-DE
A1: =+'Cash Settlement'!A2 -> COMPANY: SOUTHLAKE SPECIALTY INSURANCE COMPANY
A2: =+'Cash Settlement'!A1 -> PRODUCER: FUTURISTIC UNDERWRITERS LLC. | D2: Input area
A3: EXHIBIT OF PREMIUMS AND LOSSES
A4: FOR THE MONTH OF | C4: =+'Cash Settlement'!C9 -> 46142
A6: BY LINE, BY STATE
B11: 19.3 | C11: 19.4 | D11: 21.2
A12: =+'MTHLY-TOTAL'!A10 -> TREATY YEAR : 5/1/2020 | B12: Comm'l Auto | C12: Other Comm'l | D12: Comm'l Auto | E12: TOTALS
B13: No-Fault | C13: Auto Liab | D13: Phys. Damage
A14: Premiums Written | B14: 0 | C14: 0 | D14: 0 | E14: =SUM(B14:D14) -> 0
A15: Policy Fees Written | B15: 0 | C15: 0 | D15: 0 | E15: =SUM(B15:D15) -> 0
A16: Premiums Collected | B16: 0 | C16: 0 | D16: 0 | E16: =SUM(B16:D16) -> 0
A17: Policy Fees Collected | B17: 0 | C17: 0 | D17: 0 | E17: =SUM(B17:D17) -> 0
A18: Premium Taxes | B18: =(B14+B15)*'Tax Rates'!$B$14 -> 0 | C18: =(C14+C15)*'Tax Rates'!$B$14 -> 0 | D18: =(D14+D15)*'Tax Rates'!$B$14 -> 0 | E18: =SUM(B18:D18) -> 0
A19: Losses Paid (Net of Salvage & Subrogation) | B19: 0 | C19: 0 | D19: 0 | E19: =SUM(B19:D19) -> 0
A20: Defense & Cost Containment Expenses Paid | B20: 0 | C20: 0 | D20: 0 | E20: =SUM(B20:D20) -> 0
A21: Adjusting & Other Expenses Paid | B21: 0 | C21: 0 | D21: 0 | E21: =SUM(B21:D21) -> 0
A22: Premium Earned - YTD | B22: 0 | C22: 0 | D22: 0 | E22: =SUM(B22:D22) -> 0
A23: Policy Fees Earned - YTD | B23: 0 | C23: 0 | D23: 0 | E23: =SUM(B23:D23) -> 0
A24: Unearned Premium Reserves | B24: 0 | C24: 0 | D24: 0 | E24: =SUM(B24:D24) -> 0
A25: Direct Losses Unpaid | B25: 0 | C25: 0 | D25: 0 | E25: =SUM(B25:D25) -> 0
A26: Defense & Cost Containment Unpaid | B26: 0 | C26: 0 | D26: 0 | E26: =SUM(B26:D26) -> 0
A27: Adjusting & Other Unpaid | B27: 0 | C27: 0 | D27: 0 | E27: =SUM(B27:D27) -> 0
A29: ='MTHLY-TOTAL'!A31 -> Submitted by: ______________

Sheet MTHLY-DC
A1: =+'Cash Settlement'!A2 -> COMPANY: SOUTHLAKE SPECIALTY INSURANCE COMPANY
A2: =+'Cash Settlement'!A1 -> PRODUCER: FUTURISTIC UNDERWRITERS LLC. | D2: Input area
A3: EXHIBIT OF PREMIUMS AND LOSSES
A4: FOR THE MONTH OF | C4: =+'Cash Settlement'!C9 -> 46142
A6: BY LINE, BY STATE
B11: 19.3 | C11: 19.4 | D11: 21.2
A12: =+'MTHLY-TOTAL'!A10 -> TREATY YEAR : 5/1/2020 | B12: Comm'l Auto | C12: Other Comm'l | D12: Comm'l Auto | E12: TOTALS
B13: No-Fault | C13: Auto Liab | D13: Phys. Damage
A14: Premiums Written | B14: 0 | C14: 0 | D14: 0 | E14: =SUM(B14:D14) -> 0
A15: Policy Fees Written | B15: 0 | C15: 0 | D15: 0 | E15: =SUM(B15:D15) -> 0
A16: Premiums Collected | B16: 0 | C16: 0 | D16: 0 | E16: =SUM(B16:D16) -> 0
A17: Policy Fees Collected | B17: 0 | C17: 0 | D17: 0 | E17: =SUM(B17:D17) -> 0
A18: Premium Taxes | B18: =(B14+B15)*'Tax Rates'!$B$15 -> 0 | C18: =(C14+C15)*'Tax Rates'!$B$15 -> 0 | D18: =(D14+D15)*'Tax Rates'!$B$15 -> 0 | E18: =SUM(B18:D18) -> 0
A19: Losses Paid (Net of Salvage & Subrogation) | B19: 0 | C19: 0 | D19: 0 | E19: =SUM(B19:D19) -> 0
A20: Defense & Cost Containment Expenses Paid | B20: 0 | C20: 0 | D20: 0 | E20: =SUM(B20:D20) -> 0
A21: Adjusting & Other Expenses Paid | B21: 0 | C21: 0 | D21: 0 | E21: =SUM(B21:D21) -> 0
A22: Premium Earned - YTD | B22: 0 | C22: 0 | D22: 0 | E22: =SUM(B22:D22) -> 0
A23: Policy Fees Earned - YTD | B23: 0 | C23: 0 | D23: 0 | E23: =SUM(B23:D23) -> 0
A24: Unearned Premium Reserves | B24: 0 | C24: 0 | D24: 0 | E24: =SUM(B24:D24) -> 0
A25: Direct Losses Unpaid | B25: 0 | C25: 0 | D25: 0 | E25: =SUM(B25:D25) -> 0
A26: Defense & Cost Containment Unpaid | B26: 0 | C26: 0 | D26: 0 | E26: =SUM(B26:D26) -> 0
A27: Adjusting & Other Unpaid | B27: 0 | C27: 0 | D27: 0 | E27: =SUM(B27:D27) -> 0
A29: ='MTHLY-TOTAL'!A31 -> Submitted by: ______________

Sheet MTHLY-FL
A1: =+'Cash Settlement'!A2 -> COMPANY: SOUTHLAKE SPECIALTY INSURANCE COMPANY
A2: =+'Cash Settlement'!A1 -> PRODUCER: FUTURISTIC UNDERWRITERS LLC. | D2: Input area
A3: EXHIBIT OF PREMIUMS AND LOSSES
A4: FOR THE MONTH OF | C4: =+'Cash Settlement'!C9 -> 46142
A6: BY LINE, BY STATE
B11: 19.3 | C11: 19.4 | D11: 21.2
A12: =+'MTHLY-TOTAL'!A10 -> TREATY YEAR : 5/1/2020 | B12: Comm'l Auto | C12: Other Comm'l | D12: Comm'l Auto | E12: TOTALS
B13: No-Fault | C13: Auto Liab | D13: Phys. Damage
A14: Premiums Written | B14: 0 | C14: 0 | D14: 0 | E14: =SUM(B14:D14) -> 0
A15: Policy Fees Written | B15: 0 | C15: 0 | D15: 0 | E15: =SUM(B15:D15) -> 0
A16: Premiums Collected | B16: 0 | C16: 0 | D16: 0 | E16: =SUM(B16:D16) -> 0
A17: Policy Fees Collected | B17: 0 | C17: 0 | D17: 0 | E17: =SUM(B17:D17) -> 0
A18: Premium Taxes | B18: =(B14+B15)*'Tax Rates'!$B$16 -> 0 | C18: =(C14+C15)*'Tax Rates'!$B$16 -> 0 | D18: =(D14+D15)*'Tax Rates'!$B$16 -> 0 | E18: =SUM(B18:D18) -> 0
A19: Losses Paid (Net of Salvage & Subrogation) | B19: 0 | C19: 0 | D19: 0 | E19: =SUM(B19:D19) -> 0
A20: Defense & Cost Containment Expenses Paid | B20: 0 | C20: 0 | D20: 0 | E20: =SUM(B20:D20) -> 0
A21: Adjusting & Other Expenses Paid | B21: 0 | C21: 0 | D21: 0 | E21: =SUM(B21:D21) -> 0
A22: Premium Earned - YTD | B22: 0 | C22: 0 | D22: 0 | E22: =SUM(B22:D22) -> 0
A23: Policy Fees Earned - YTD | B23: 0 | C23: 0 | D23: 0 | E23: =SUM(B23:D23) -> 0
A24: Unearned Premium Reserves | B24: 0 | C24: 0 | D24: 0 | E24: =SUM(B24:D24) -> 0
A25: Direct Losses Unpaid | B25: 0 | C25: 0 | D25: 0 | E25: =SUM(B25:D25) -> 0
A26: Defense & Cost Containment Unpaid | B26: 0 | C26: 0 | D26: 0 | E26: =SUM(B26:D26) -> 0
A27: Adjusting & Other Unpaid | B27: 0 | C27: 0 | D27: 0 | E27: =SUM(B27:D27) -> 0
A29: ='MTHLY-TOTAL'!A31 -> Submitted by: ______________

Sheet MTHLY-GA
A1: =+'Cash Settlement'!A2 -> COMPANY: SOUTHLAKE SPECIALTY INSURANCE COMPANY
A2: =+'Cash Settlement'!A1 -> PRODUCER: FUTURISTIC UNDERWRITERS LLC. | D2: Input area
A3: EXHIBIT OF PREMIUMS AND LOSSES
A4: FOR THE MONTH OF | C4: =+'Cash Settlement'!C9 -> 46142
A6: BY LINE, BY STATE
B11: 9 | C11: 19.4 | D11: 21.2
A12: =+'MTHLY-TOTAL'!A10 -> TREATY YEAR : 5/1/2020 | B12: Comm'l Auto | C12: Other Comm'l | D12: Comm'l Auto | E12: TOTALS
B13: Inland Marine | C13: Auto Liab | D13: Phys. Damage
A14: Premiums Written | B14: 0 | C14: 0 | D14: -1261.77 | E14: =SUM(B14:D14) -> -1261.77
A15: Policy Fees Written | B15: 0 | C15: 0 | D15: 0 | E15: =SUM(B15:D15) -> 0
A16: Premiums Collected | B16: 0 | C16: 0 | D16: -1261.77 | E16: =SUM(B16:D16) -> -1261.77
A17: Policy Fees Collected | B17: 0 | C17: 0 | D17: 0 | E17: =SUM(B17:D17) -> 0
A18: Premium Taxes | B18: =(B14+B15)*'Tax Rates'!$B$17 -> 0 | C18: =(C14+C15)*'Tax Rates'!$B$17 -> 0 | E18: =SUM(B18:D18) -> 0
A19: Losses Paid (Net of Salvage & Subrogation) | B19: 0 | C19: 0 | D19: 0 | E19: =SUM(B19:D19) -> 0
A20: Defense & Cost Containment Expenses Paid | B20: 0 | C20: 0 | D20: 0 | E20: =SUM(B20:D20) -> 0
A21: Adjusting & Other Expenses Paid | B21: 0 | C21: 0 | D21: -88.3239 | E21: =SUM(B21:D21) -> -88.3239
A22: Premium Earned - YTD | B22: 0 | C22: 0 | D22: 5669.34 | E22: =SUM(B22:D22) -> 5669.34
A23: Policy Fees Earned - YTD | B23: 0 | C23: 0 | D23: 0 | E23: =SUM(B23:D23) -> 0
A24: Unearned Premium Reserves | B24: 0 | C24: 0 | D24: 3466.11 | E24: =SUM(B24:D24) -> 3466.11
A25: Direct Losses Unpaid | B25: 0 | C25: 0 | D25: 0 | E25: =SUM(B25:D25) -> 0
A26: Defense & Cost Containment Unpaid | B26: 0 | C26: 0 | D26: 0 | E26: =SUM(B26:D26) -> 0
A27: Adjusting & Other Unpaid | B27: 0 | C27: 0 | D27: 0 | E27: =SUM(B27:D27) -> 0
A29: ='MTHLY-TOTAL'!A31 -> Submitted by: ______________

Sheet MTHLY-HI
A1: =+'Cash Settlement'!A2 -> COMPANY: SOUTHLAKE SPECIALTY INSURANCE COMPANY
A2: =+'Cash Settlement'!A1 -> PRODUCER: FUTURISTIC UNDERWRITERS LLC. | D2: Input area
A3: EXHIBIT OF PREMIUMS AND LOSSES
A4: FOR THE MONTH OF | C4: =+'Cash Settlement'!C9 -> 46142
A6: BY LINE, BY STATE
B11: 19.3 | C11: 19.4 | D11: 21.2
A12: =+'MTHLY-TOTAL'!A10 -> TREATY YEAR : 5/1/2020 | B12: Comm'l Auto | C12: Other Comm'l | D12: Comm'l Auto | E12: TOTALS
B13: No-Fault | C13: Auto Liab | D13: Phys. Damage
A14: Premiums Written | B14: 0 | C14: 0 | D14: 0 | E14: =SUM(B14:D14) -> 0
A15: Policy Fees Written | B15: 0 | C15: 0 | D15: 0 | E15: =SUM(B15:D15) -> 0
A16: Premiums Collected | B16: 0 | C16: 0 | D16: 0 | E16: =SUM(B16:D16) -> 0
A17: Policy Fees Collected | B17: 0 | C17: 0 | D17: 0 | E17: =SUM(B17:D17) -> 0
A18: Premium Taxes | B18: =(B14+B15)*'Tax Rates'!$B$18 -> 0 | C18: =(C14+C15)*'Tax Rates'!$B$18 -> 0 | D18: =(D14+D15)*'Tax Rates'!$B$18 -> 0 | E18: =SUM(B18:D18) -> 0
A19: Losses Paid (Net of Salvage & Subrogation) | B19: 0 | C19: 0 | D19: 0 | E19: =SUM(B19:D19) -> 0
A20: Defense & Cost Containment Expenses Paid | B20: 0 | C20: 0 | D20: 0 | E20: =SUM(B20:D20) -> 0
A21: Adjusting & Other Expenses Paid | B21: 0 | C21: 0 | D21: 0 | E21: =SUM(B21:D21) -> 0
A22: Premium Earned - YTD | B22: 0 | C22: 0 | D22: 0 | E22: =SUM(B22:D22) -> 0
A23: Policy Fees Earned - YTD | B23: 0 | C23: 0 | D23: 0 | E23: =SUM(B23:D23) -> 0
A24: Unearned Premium Reserves | B24: 0 | C24: 0 | D24: 0 | E24: =SUM(B24:D24) -> 0
A25: Direct Losses Unpaid | B25: 0 | C25: 0 | D25: 0 | E25: =SUM(B25:D25) -> 0
A26: Defense & Cost Containment Unpaid | B26: 0 | C26: 0 | D26: 0 | E26: =SUM(B26:D26) -> 0
A27: Adjusting & Other Unpaid | B27: 0 | C27: 0 | D27: 0 | E27: =SUM(B27:D27) -> 0
A29: ='MTHLY-TOTAL'!A31 -> Submitted by: ______________

Sheet MTHLY-IA
A1: =+'Cash Settlement'!A2 -> COMPANY: SOUTHLAKE SPECIALTY INSURANCE COMPANY
A2: =+'Cash Settlement'!A1 -> PRODUCER: FUTURISTIC UNDERWRITERS LLC. | D2: Input area
A3: EXHIBIT OF PREMIUMS AND LOSSES
A4: FOR THE MONTH OF | C4: =+'Cash Settlement'!C9 -> 46142
A6: BY LINE, BY STATE
B11: 19.3 | C11: 19.4 | D11: 21.2
A12: =+'MTHLY-TOTAL'!A10 -> TREATY YEAR : 5/1/2020 | B12: Comm'l Auto | C12: Other Comm'l | D12: Comm'l Auto | E12: TOTALS
B13: No-Fault | C13: Auto Liab | D13: Phys. Damage
A14: Premiums Written | B14: 0 | C14: 0 | D14: 0 | E14: =SUM(B14:D14) -> 0
A15: Policy Fees Written | B15: 0 | C15: 0 | D15: 0 | E15: =SUM(B15:D15) -> 0
A16: Premiums Collected | B16: 0 | C16: 0 | D16: 0 | E16: =SUM(B16:D16) -> 0
A17: Policy Fees Collected | B17: 0 | C17: 0 | D17: 0 | E17: =SUM(B17:D17) -> 0
A18: Premium Taxes | B18: =(B14+B15)*'Tax Rates'!$B$22 -> 0 | C18: =(C14+C15)*'Tax Rates'!$B$22 -> 0 | E18: =SUM(B18:D18) -> 0
A19: Losses Paid (Net of Salvage & Subrogation) | B19: 0 | C19: 0 | D19: 0 | E19: =SUM(B19:D19) -> 0
A20: Defense & Cost Containment Expenses Paid | B20: 0 | C20: 0 | D20: 0 | E20: =SUM(B20:D20) -> 0
A21: Adjusting & Other Expenses Paid | B21: 0 | C21: 0 | D21: 0 | E21: =SUM(B21:D21) -> 0
A22: Premium Earned - YTD | B22: 0 | C22: 0 | D22: 2347.66 | E22: =SUM(B22:D22) -> 2347.66
A23: Policy Fees Earned - YTD | B23: 0 | C23: 0 | D23: 0 | E23: =SUM(B23:D23) -> 0
A24: Unearned Premium Reserves | B24: 0 | C24: 0 | D24: 3006.98 | E24: =SUM(B24:D24) -> 3006.98
A25: Direct Losses Unpaid | B25: 0 | C25: 0 | D25: 0 | E25: =SUM(B25:D25) -> 0
A26: Defense & Cost Containment Unpaid | B26: 0 | C26: 0 | D26: 0 | E26: =SUM(B26:D26) -> 0
A27: Adjusting & Other Unpaid | B27: 0 | C27: 0 | D27: 0 | E27: =SUM(B27:D27) -> 0
A29: ='MTHLY-TOTAL'!A31 -> Submitted by: ______________

Sheet MTHLY-IL
A1: =+'Cash Settlement'!A2 -> COMPANY: SOUTHLAKE SPECIALTY INSURANCE COMPANY
A2: =+'Cash Settlement'!A1 -> PRODUCER: FUTURISTIC UNDERWRITERS LLC. | D2: Input area
A3: EXHIBIT OF PREMIUMS AND LOSSES
A4: FOR THE MONTH OF | C4: June-25
A6: BY LINE, BY STATE | C6: CA
B11: 19.3 | C11: 19.4 | D11: 21.2
A12: =+'MTHLY-TOTAL'!A10 -> TREATY YEAR : 5/1/2020 | B12: Comm'l Auto | C12: Other Comm'l | D12: Comm'l Auto | E12: TOTALS
B13: No-Fault | C13: Auto Liab | D13: Phys. Damage
A14: Premiums Written | B14: 0 | C14: 0 | D14: 0 | E14: =SUM(B14:D14) -> 0
A15: Policy Fees Written | B15: 0 | C15: 0 | D15: 0 | E15: =SUM(B15:D15) -> 0
A16: Premiums Collected | B16: 0 | C16: 0 | D16: 0 | E16: =SUM(B16:D16) -> 0
A17: Policy Fees Collected | B17: 0 | D17: 0 | E17: =SUM(B17:D17) -> 0
A18: Premium Taxes | B18: =(B14+B15)*'Tax Rates'!$B$20 -> 0 | D18: =(D14+D15)*'Tax Rates'!$B$20 -> 0 | E18: =SUM(B18:D18) -> 0
A19: Losses Paid (Net of Salvage & Subrogation) | B19: 0 | C19: 0 | D19: 0 | E19: =SUM(B19:D19) -> 0
A20: Defense & Cost Containment Expenses Paid | B20: 0 | C20: 0 | D20: 0 | E20: =SUM(B20:D20) -> 0
A21: Adjusting & Other Expenses Paid (ULAE) | B21: 0 | C21: 0 | D21: 0 | E21: =SUM(B21:D21) -> 0
A22: Premium Earned - YTD | B22: 0 | C22: 0 | D22: 0 | E22: =SUM(B22:D22) -> 0
A23: Policy Fees Earned - YTD | B23: 0 | C23: 0 | D23: 0 | E23: =SUM(B23:D23) -> 0
A24: Unearned Premium Reserves | B24: 0 | C24: 0 | D24: 0 | E24: =SUM(B24:D24) -> 0
A25: Direct Losses Unpaid | B25: 0 | C25: 0 | D25: 0 | E25: =SUM(B25:D25) -> 0
A26: Defense & Cost Containment Unpaid | B26: 0 | C26: 0 | D26: 0 | E26: =SUM(B26:D26) -> 0
A27: Adjusting & Other Unpaid | B27: 0 | D27: 0 | E27: =SUM(B27:D27) -> 0
C28: 0
A29: ='MTHLY-TOTAL'!A31 -> Submitted by: ______________

Sheet MTHLY-ID
A1: =+'Cash Settlement'!A2 -> COMPANY: SOUTHLAKE SPECIALTY INSURANCE COMPANY
A2: =+'Cash Settlement'!A1 -> PRODUCER: FUTURISTIC UNDERWRITERS LLC. | D2: Input area
A3: EXHIBIT OF PREMIUMS AND LOSSES
A4: FOR THE MONTH OF | C4: =+'Cash Settlement'!C9 -> 46142
A6: BY LINE, BY STATE
B11: 19.3 | C11: 19.4 | D11: 21.2
A12: =+'MTHLY-TOTAL'!A10 -> TREATY YEAR : 5/1/2020 | B12: Comm'l Auto | C12: Other Comm'l | D12: Comm'l Auto | E12: TOTALS
B13: No-Fault | C13: Auto Liab | D13: Phys. Damage
A14: Premiums Written | B14: 0 | C14: 0 | D14: 0 | E14: =SUM(B14:D14) -> 0
A15: Policy Fees Written | B15: 0 | C15: 0 | D15: 0 | E15: =SUM(B15:D15) -> 0
A16: Premiums Collected | B16: 0 | C16: 0 | D16: 0 | E16: =SUM(B16:D16) -> 0
A17: Policy Fees Collected | B17: 0 | C17: 0 | D17: 0 | E17: =SUM(B17:D17) -> 0
A18: Premium Taxes | B18: =(B14+B15)*'Tax Rates'!$B$19 -> 0 | C18: =(C14+C15)*'Tax Rates'!$B$19 -> 0 | D18: =(D14+D15)*'Tax Rates'!$B$19 -> 0 | E18: =SUM(B18:D18) -> 0
A19: Losses Paid (Net of Salvage & Subrogation) | B19: 0 | C19: 0 | D19: 0 | E19: =SUM(B19:D19) -> 0
A20: Defense & Cost Containment Expenses Paid | B20: 0 | C20: 0 | D20: 0 | E20: =SUM(B20:D20) -> 0
A21: Adjusting & Other Expenses Paid | B21: 0 | C21: 0 | D21: 0 | E21: =SUM(B21:D21) -> 0
A22: Premium Earned - YTD | B22: 0 | C22: 0 | D22: 0 | E22: =SUM(B22:D22) -> 0
A23: Policy Fees Earned - YTD | B23: 0 | C23: 0 | D23: 0 | E23: =SUM(B23:D23) -> 0
A24: Unearned Premium Reserves | B24: 0 | C24: 0 | D24: 0 | E24: =SUM(B24:D24) -> 0
A25: Direct Losses Unpaid | B25: 0 | C25: 0 | D25: 0 | E25: =SUM(B25:D25) -> 0
A26: Defense & Cost Containment Unpaid | B26: 0 | C26: 0 | D26: 0 | E26: =SUM(B26:D26) -> 0
A27: Adjusting & Other Unpaid | B27: 0 | C27: 0 | D27: 0 | E27: =SUM(B27:D27) -> 0
A29: ='MTHLY-TOTAL'!A31 -> Submitted by: ______________

Sheet MTHLY-IN
A1: =+'Cash Settlement'!A2 -> COMPANY: SOUTHLAKE SPECIALTY INSURANCE COMPANY
A2: =+'Cash Settlement'!A1 -> PRODUCER: FUTURISTIC UNDERWRITERS LLC. | D2: Input area
A3: EXHIBIT OF PREMIUMS AND LOSSES
A4: FOR THE MONTH OF | C4: =+'Cash Settlement'!C9 -> 46142
A6: BY LINE, BY STATE
B11: 9 | C11: 19.4 | D11: 21.2
A12: =+'MTHLY-TOTAL'!A10 -> TREATY YEAR : 5/1/2020 | B12: Comm'l Auto | C12: Other Comm'l | D12: Comm'l Auto | E12: TOTALS
B13: Inland Marine | C13: Auto Liab | D13: Phys. Damage
A14: Premiums Written | B14: 0 | C14: 0 | D14: 0 | E14: =SUM(B14:D14) -> 0
A15: Policy Fees Written | B15: 0 | C15: 0 | D15: 0 | E15: =SUM(B15:D15) -> 0
A16: Premiums Collected | B16: 0 | C16: 0 | D16: 0 | E16: =SUM(B16:D16) -> 0
A17: Policy Fees Collected | B17: 0 | C17: 0 | D17: 0 | E17: =SUM(B17:D17) -> 0
A18: Premium Taxes | B18: =(B14+B15)*'Tax Rates'!$B$21 -> 0 | C18: =(C14+C15)*'Tax Rates'!$B$21 -> 0 | E18: =SUM(B18:D18) -> 0
A19: Losses Paid (Net of Salvage & Subrogation) | B19: 0 | C19: 0 | D19: 57500 | E19: =SUM(B19:D19) -> 57500
A20: Defense & Cost Containment Expenses Paid | B20: 0 | C20: 0 | D20: 0 | E20: =SUM(B20:D20) -> 0
A21: Adjusting & Other Expenses Paid | B21: 0 | C21: 0 | D21: 0 | E21: =SUM(B21:D21) -> 0
A22: Premium Earned - YTD | B22: 0 | C22: 0 | D22: 21781.15 | E22: =SUM(B22:D22) -> 21781.15
A23: Policy Fees Earned - YTD | B23: 0 | C23: 0 | D23: 0 | E23: =SUM(B23:D23) -> 0
A24: Unearned Premium Reserves | B24: 0 | C24: 0 | D24: 25663.96 | E24: =SUM(B24:D24) -> 25663.96
A25: Direct Losses Unpaid | B25: 0 | C25: 0 | D25: 0 | E25: =SUM(B25:D25) -> 0
A26: Defense & Cost Containment Unpaid | B26: 0 | C26: 0 | D26: 0 | E26: =SUM(B26:D26) -> 0
A27: Adjusting & Other Unpaid | B27: 0 | C27: 0 | D27: 0 | E27: =SUM(B27:D27) -> 0
A29: ='MTHLY-TOTAL'!A31 -> Submitted by: ______________

Sheet MTHLY-KS
A1: =+'Cash Settlement'!A2 -> COMPANY: SOUTHLAKE SPECIALTY INSURANCE COMPANY
A2: =+'Cash Settlement'!A1 -> PRODUCER: FUTURISTIC UNDERWRITERS LLC. | D2: Input area
A3: EXHIBIT OF PREMIUMS AND LOSSES
A4: FOR THE MONTH OF | C4: =+'Cash Settlement'!C9 -> 46142
A6: BY LINE, BY STATE
B11: 19.3 | C11: 19.4 | D11: 21.2
A12: =+'MTHLY-TOTAL'!A10 -> TREATY YEAR : 5/1/2020 | B12: Comm'l Auto | C12: Other Comm'l | D12: Comm'l Auto | E12: TOTALS
B13: No-Fault | C13: Auto Liab | D13: Phys. Damage
A14: Premiums Written | B14: 0 | C14: 0 | D14: 0 | E14: =SUM(B14:D14) -> 0
A15: Policy Fees Written | B15: 0 | C15: 0 | D15: 0 | E15: =SUM(B15:D15) -> 0
A16: Premiums Collected | B16: 0 | C16: 0 | D16: 0 | E16: =SUM(B16:D16) -> 0
A17: Policy Fees Collected | B17: 0 | C17: 0 | D17: 0 | E17: =SUM(B17:D17) -> 0
A18: Premium Taxes | B18: =(B14+B15)*'Tax Rates'!$B$23 -> 0 | C18: =(C14+C15)*'Tax Rates'!$B$23 -> 0 | D18: =(D14+D15)*'Tax Rates'!$B$23 -> 0 | E18: =SUM(B18:D18) -> 0
A19: Losses Paid (Net of Salvage & Subrogation) | B19: 0 | C19: 0 | D19: 0 | E19: =SUM(B19:D19) -> 0
A20: Defense & Cost Containment Expenses Paid | B20: 0 | C20: 0 | D20: 0 | E20: =SUM(B20:D20) -> 0
A21: Adjusting & Other Expenses Paid | B21: 0 | C21: 0 | D21: 0 | E21: =SUM(B21:D21) -> 0
A22: Premium Earned - YTD | B22: 0 | C22: 0 | D22: 0 | E22: =SUM(B22:D22) -> 0
A23: Policy Fees Earned - YTD | B23: 0 | C23: 0 | D23: 0 | E23: =SUM(B23:D23) -> 0
A24: Unearned Premium Reserves | B24: 0 | C24: 0 | D24: 0 | E24: =SUM(B24:D24) -> 0
A25: Direct Losses Unpaid | B25: 0 | C25: 0 | D25: 0 | E25: =SUM(B25:D25) -> 0
A26: Defense & Cost Containment Unpaid | B26: 0 | C26: 0 | D26: 0 | E26: =SUM(B26:D26) -> 0
A27: Adjusting & Other Unpaid | B27: 0 | C27: 0 | D27: 0 | E27: =SUM(B27:D27) -> 0
A29: ='MTHLY-TOTAL'!A31 -> Submitted by: ______________

Sheet MTHLY-KY
A1: =+'Cash Settlement'!A2 -> COMPANY: SOUTHLAKE SPECIALTY INSURANCE COMPANY
A2: =+'Cash Settlement'!A1 -> PRODUCER: FUTURISTIC UNDERWRITERS LLC. | D2: Input area
A3: EXHIBIT OF PREMIUMS AND LOSSES
A4: FOR THE MONTH OF | C4: =+'Cash Settlement'!C9 -> 46142
A6: BY LINE, BY STATE
B11: 19.3 | C11: 19.4 | D11: 21.2
A12: =+'MTHLY-TOTAL'!A10 -> TREATY YEAR : 5/1/2020 | B12: Comm'l Auto | C12: Other Comm'l | D12: Comm'l Auto | E12: TOTALS
B13: No-Fault | C13: Auto Liab | D13: Phys. Damage
A14: Premiums Written | B14: 0 | C14: 0 | D14: 0 | E14: =SUM(B14:D14) -> 0
A15: Policy Fees Written | B15: 0 | C15: 0 | D15: 0 | E15: =SUM(B15:D15) -> 0
A16: Premiums Collected | B16: 0 | C16: 0 | D16: 0 | E16: =SUM(B16:D16) -> 0
A17: Policy Fees Collected | B17: 0 | C17: 0 | D17: 0 | E17: =SUM(B17:D17) -> 0
A18: Premium Taxes | B18: =(B14+B15)*'Tax Rates'!$B$24 -> 0 | C18: =(C14+C15)*'Tax Rates'!$B$24 -> 0 | D18: =(D14+D15)*'Tax Rates'!$B$24 -> 0 | E18: =SUM(B18:D18) -> 0
A19: Losses Paid (Net of Salvage & Subrogation) | B19: 0 | C19: 0 | D19: 0 | E19: =SUM(B19:D19) -> 0
A20: Defense & Cost Containment Expenses Paid | B20: 0 | C20: 0 | D20: 0 | E20: =SUM(B20:D20) -> 0
A21: Adjusting & Other Expenses Paid | B21: 0 | C21: 0 | D21: 0 | E21: =SUM(B21:D21) -> 0
A22: Premium Earned - YTD | B22: 0 | C22: 0 | D22: 0 | E22: =SUM(B22:D22) -> 0
A23: Policy Fees Earned - YTD | B23: 0 | C23: 0 | D23: 0 | E23: =SUM(B23:D23) -> 0
A24: Unearned Premium Reserves | B24: 0 | C24: 0 | D24: 0 | E24: =SUM(B24:D24) -> 0
A25: Direct Losses Unpaid | B25: 0 | C25: 0 | D25: 0 | E25: =SUM(B25:D25) -> 0
A26: Defense & Cost Containment Unpaid | B26: 0 | C26: 0 | D26: 0 | E26: =SUM(B26:D26) -> 0
A27: Adjusting & Other Unpaid | B27: 0 | C27: 0 | D27: 0 | E27: =SUM(B27:D27) -> 0
A29: ='MTHLY-TOTAL'!A31 -> Submitted by: ______________

Sheet MTHLY-LA
A1: =+'Cash Settlement'!A2 -> COMPANY: SOUTHLAKE SPECIALTY INSURANCE COMPANY
A2: =+'Cash Settlement'!A1 -> PRODUCER: FUTURISTIC UNDERWRITERS LLC. | D2: Input area
A3: EXHIBIT OF PREMIUMS AND LOSSES
A4: FOR THE MONTH OF | C4: =+'Cash Settlement'!C9 -> 46142
A6: BY LINE, BY STATE
B11: 19.3 | C11: 19.4 | D11: 21.2
A12: =+'MTHLY-TOTAL'!A10 -> TREATY YEAR : 5/1/2020 | B12: Comm'l Auto | C12: Other Comm'l | D12: Comm'l Auto | E12: TOTALS
B13: No-Fault | C13: Auto Liab | D13: Phys. Damage
A14: Premiums Written | B14: 0 | C14: 0 | D14: 0 | E14: =SUM(B14:D14) -> 0
A15: Policy Fees Written | B15: 0 | C15: 0 | D15: 0 | E15: =SUM(B15:D15) -> 0
A16: Premiums Collected | B16: 0 | C16: 0 | D16: 0 | E16: =SUM(B16:D16) -> 0
A17: Policy Fees Collected | B17: 0 | C17: 0 | D17: 0 | E17: =SUM(B17:D17) -> 0
A18: Premium Taxes | B18: =(B14+B15)*'Tax Rates'!$B$25 -> 0 | C18: =(C14+C15)*'Tax Rates'!$B$25 -> 0 | D18: =(D14+D15)*'Tax Rates'!$B$25 -> 0 | E18: =SUM(B18:D18) -> 0
A19: Losses Paid (Net of Salvage & Subrogation) | B19: 0 | C19: 0 | D19: 0 | E19: =SUM(B19:D19) -> 0
A20: Defense & Cost Containment Expenses Paid | B20: 0 | C20: 0 | D20: 0 | E20: =SUM(B20:D20) -> 0
A21: Adjusting & Other Expenses Paid | B21: 0 | C21: 0 | D21: 0 | E21: =SUM(B21:D21) -> 0
A22: Premium Earned - YTD | B22: 0 | C22: 0 | D22: 0 | E22: =SUM(B22:D22) -> 0
A23: Policy Fees Earned - YTD | B23: 0 | C23: 0 | D23: 0 | E23: =SUM(B23:D23) -> 0
A24: Unearned Premium Reserves | B24: 0 | C24: 0 | D24: 0 | E24: =SUM(B24:D24) -> 0
A25: Direct Losses Unpaid | B25: 0 | C25: 0 | D25: 0 | E25: =SUM(B25:D25) -> 0
A26: Defense & Cost Containment Unpaid | B26: 0 | C26: 0 | D26: 0 | E26: =SUM(B26:D26) -> 0
A27: Adjusting & Other Unpaid | B27: 0 | C27: 0 | D27: 0 | E27: =SUM(B27:D27) -> 0
A29: ='MTHLY-TOTAL'!A31 -> Submitted by: ______________

Sheet MTHLY-MA
A1: =+'Cash Settlement'!A2 -> COMPANY: SOUTHLAKE SPECIALTY INSURANCE COMPANY
A2: =+'Cash Settlement'!A1 -> PRODUCER: FUTURISTIC UNDERWRITERS LLC. | D2: Input area
A3: EXHIBIT OF PREMIUMS AND LOSSES
A4: FOR THE MONTH OF | C4: =+'Cash Settlement'!C9 -> 46142
A6: BY LINE, BY STATE
B11: 19.3 | C11: 19.4 | D11: 21.2
A12: =+'MTHLY-TOTAL'!A10 -> TREATY YEAR : 5/1/2020 | B12: Comm'l Auto | C12: Other Comm'l | D12: Comm'l Auto | E12: TOTALS
B13: No-Fault | C13: Auto Liab | D13: Phys. Damage
A14: Premiums Written | B14: 0 | C14: 0 | D14: 0 | E14: =SUM(B14:D14) -> 0
A15: Policy Fees Written | B15: 0 | C15: 0 | D15: 0 | E15: =SUM(B15:D15) -> 0
A16: Premiums Collected | B16: 0 | C16: 0 | D16: 0 | E16: =SUM(B16:D16) -> 0
A17: Policy Fees Collected | B17: 0 | C17: 0 | D17: 0 | E17: =SUM(B17:D17) -> 0
A18: Premium Taxes | B18: =(B14+B15)*'Tax Rates'!$B$28 -> 0 | C18: =(C14+C15)*'Tax Rates'!$B$28 -> 0 | D18: =(D14+D15)*'Tax Rates'!$B$28 -> 0 | E18: =SUM(B18:D18) -> 0
A19: Losses Paid (Net of Salvage & Subrogation) | B19: 0 | C19: 0 | D19: 0 | E19: =SUM(B19:D19) -> 0
A20: Defense & Cost Containment Expenses Paid | B20: 0 | C20: 0 | D20: 0 | E20: =SUM(B20:D20) -> 0
A21: Adjusting & Other Expenses Paid | B21: 0 | C21: 0 | D21: 0 | E21: =SUM(B21:D21) -> 0
A22: Premium Earned - YTD | B22: 0 | C22: 0 | D22: 0 | E22: =SUM(B22:D22) -> 0
A23: Policy Fees Earned - YTD | B23: 0 | C23: 0 | D23: 0 | E23: =SUM(B23:D23) -> 0
A24: Unearned Premium Reserves | B24: 0 | C24: 0 | D24: 0 | E24: =SUM(B24:D24) -> 0
A25: Direct Losses Unpaid | B25: 0 | C25: 0 | D25: 0 | E25: =SUM(B25:D25) -> 0
A26: Defense & Cost Containment Unpaid | B26: 0 | C26: 0 | D26: 0 | E26: =SUM(B26:D26) -> 0
A27: Adjusting & Other Unpaid | B27: 0 | C27: 0 | D27: 0 | E27: =SUM(B27:D27) -> 0
A29: ='MTHLY-TOTAL'!A31 -> Submitted by: ______________

Sheet MTHLY-MD
A1: =+'Cash Settlement'!A2 -> COMPANY: SOUTHLAKE SPECIALTY INSURANCE COMPANY
A2: =+'Cash Settlement'!A1 -> PRODUCER: FUTURISTIC UNDERWRITERS LLC. | D2: Input area
A3: EXHIBIT OF PREMIUMS AND LOSSES
A4: FOR THE MONTH OF | C4: =+'Cash Settlement'!C9 -> 46142
A6: BY LINE, BY STATE
B11: 19.3 | C11: 19.4 | D11: 21.2
A12: =+'MTHLY-TOTAL'!A10 -> TREATY YEAR : 5/1/2020 | B12: Comm'l Auto | C12: Other Comm'l | D12: Comm'l Auto | E12: TOTALS
B13: No-Fault | C13: Auto Liab | D13: Phys. Damage
A14: Premiums Written | B14: 0 | C14: 0 | D14: 0 | E14: =SUM(B14:D14) -> 0
A15: Policy Fees Written | B15: 0 | C15: 0 | D15: 0 | E15: =SUM(B15:D15) -> 0
A16: Premiums Collected | B16: 0 | C16: 0 | D16: 0 | E16: =SUM(B16:D16) -> 0
A17: Policy Fees Collected | B17: 0 | C17: 0 | D17: 0 | E17: =SUM(B17:D17) -> 0
A18: Premium Taxes | B18: =(B14+B15)*'Tax Rates'!$B$27 -> 0 | C18: =(C14+C15)*'Tax Rates'!$B$27 -> 0 | D18: =(D14+D15)*'Tax Rates'!$B$27 -> 0 | E18: =SUM(B18:D18) -> 0
A19: Losses Paid (Net of Salvage & Subrogation) | B19: 0 | C19: 0 | D19: 0 | E19: =SUM(B19:D19) -> 0
A20: Defense & Cost Containment Expenses Paid | B20: 0 | C20: 0 | D20: 0 | E20: =SUM(B20:D20) -> 0
A21: Adjusting & Other Expenses Paid | B21: 0 | C21: 0 | D21: 0 | E21: =SUM(B21:D21) -> 0
A22: Premium Earned - YTD | B22: 0 | C22: 0 | D22: 0 | E22: =SUM(B22:D22) -> 0
A23: Policy Fees Earned - YTD | B23: 0 | C23: 0 | D23: 0 | E23: =SUM(B23:D23) -> 0
A24: Unearned Premium Reserves | B24: 0 | C24: 0 | D24: 0 | E24: =SUM(B24:D24) -> 0
A25: Direct Losses Unpaid | B25: 0 | C25: 0 | D25: 0 | E25: =SUM(B25:D25) -> 0
A26: Defense & Cost Containment Unpaid | B26: 0 | C26: 0 | D26: 0 | E26: =SUM(B26:D26) -> 0
A27: Adjusting & Other Unpaid | B27: 0 | C27: 0 | D27: 0 | E27: =SUM(B27:D27) -> 0
A29: ='MTHLY-TOTAL'!A31 -> Submitted by: ______________

Sheet MTHLY-ME
A1: =+'Cash Settlement'!A2 -> COMPANY: SOUTHLAKE SPECIALTY INSURANCE COMPANY
A2: =+'Cash Settlement'!A1 -> PRODUCER: FUTURISTIC UNDERWRITERS LLC. | D2: Input area
A3: EXHIBIT OF PREMIUMS AND LOSSES
A4: FOR THE MONTH OF | C4: =+'Cash Settlement'!C9 -> 46142
A6: BY LINE, BY STATE
B11: 19.3 | C11: 19.4 | D11: 21.2
A12: =+'MTHLY-TOTAL'!A10 -> TREATY YEAR : 5/1/2020 | B12: Comm'l Auto | C12: Other Comm'l | D12: Comm'l Auto | E12: TOTALS
B13: No-Fault | C13: Auto Liab | D13: Phys. Damage
A14: Premiums Written | B14: 0 | C14: 0 | D14: 0 | E14: =SUM(B14:D14) -> 0
A15: Policy Fees Written | B15: 0 | C15: 0 | D15: 0 | E15: =SUM(B15:D15) -> 0
A16: Premiums Collected | B16: 0 | C16: 0 | D16: 0 | E16: =SUM(B16:D16) -> 0
A17: Policy Fees Collected | B17: 0 | C17: 0 | D17: 0 | E17: =SUM(B17:D17) -> 0
A18: Premium Taxes | B18: =(B14+B15)*'Tax Rates'!$B$26 -> 0 | C18: =(C14+C15)*'Tax Rates'!$B$26 -> 0 | D18: =(D14+D15)*'Tax Rates'!$B$26 -> 0 | E18: =SUM(B18:D18) -> 0
A19: Losses Paid (Net of Salvage & Subrogation) | B19: 0 | C19: 0 | D19: 0 | E19: =SUM(B19:D19) -> 0
A20: Defense & Cost Containment Expenses Paid | B20: 0 | C20: 0 | D20: 0 | E20: =SUM(B20:D20) -> 0
A21: Adjusting & Other Expenses Paid | B21: 0 | C21: 0 | D21: 0 | E21: =SUM(B21:D21) -> 0
A22: Premium Earned - YTD | B22: 0 | C22: 0 | D22: 0 | E22: =SUM(B22:D22) -> 0
A23: Policy Fees Earned - YTD | B23: 0 | C23: 0 | D23: 0 | E23: =SUM(B23:D23) -> 0
A24: Unearned Premium Reserves | B24: 0 | C24: 0 | D24: 0 | E24: =SUM(B24:D24) -> 0
A25: Direct Losses Unpaid | B25: 0 | C25: 0 | D25: 0 | E25: =SUM(B25:D25) -> 0
A26: Defense & Cost Containment Unpaid | B26: 0 | C26: 0 | D26: 0 | E26: =SUM(B26:D26) -> 0
A27: Adjusting & Other Unpaid | B27: 0 | C27: 0 | D27: 0 | E27: =SUM(B27:D27) -> 0
A29: ='MTHLY-TOTAL'!A31 -> Submitted by: ______________

Sheet MTHLY-MI
A1: =+'Cash Settlement'!A2 -> COMPANY: SOUTHLAKE SPECIALTY INSURANCE COMPANY
A2: =+'Cash Settlement'!A1 -> PRODUCER: FUTURISTIC UNDERWRITERS LLC. | D2: Input area
A3: EXHIBIT OF PREMIUMS AND LOSSES
A4: FOR THE MONTH OF | C4: =+'Cash Settlement'!C9 -> 46142
A6: BY LINE, BY STATE
B11: 9 | C11: 19.4 | D11: 21.2
A12: =+'MTHLY-TOTAL'!A10 -> TREATY YEAR : 5/1/2020 | B12: Comm'l Auto | C12: Other Comm'l | D12: Comm'l Auto | E12: TOTALS
B13: Inland Marine | C13: Auto Liab | D13: Phys. Damage
A14: Premiums Written | B14: 0 | C14: 0 | D14: 0 | E14: =SUM(B14:D14) -> 0
A15: Policy Fees Written | B15: 0 | C15: 0 | D15: 0 | E15: =SUM(B15:D15) -> 0
A16: Premiums Collected | B16: 0 | C16: 0 | D16: 0 | E16: =SUM(B16:D16) -> 0
A17: Policy Fees Collected | B17: 0 | C17: 0 | D17: 0 | E17: =SUM(B17:D17) -> 0
A18: Premium Taxes | B18: =(B14+B15)*'Tax Rates'!$B$29 -> 0 | C18: =(C14+C15)*'Tax Rates'!$B$29 -> 0 | E18: =SUM(B18:D18) -> 0
A19: Losses Paid (Net of Salvage & Subrogation) | B19: 0 | C19: 0 | D19: 0 | E19: =SUM(B19:D19) -> 0
A20: Defense & Cost Containment Expenses Paid | B20: 0 | C20: 0 | D20: 0 | E20: =SUM(B20:D20) -> 0
A21: Adjusting & Other Expenses Paid | B21: 0 | C21: 0 | D21: 0 | E21: =SUM(B21:D21) -> 0
A22: Premium Earned - YTD | B22: 0 | C22: 0 | D22: 18270.37 | E22: =SUM(B22:D22) -> 18270.37
A23: Policy Fees Earned - YTD | B23: 0 | C23: 0 | D23: 0 | E23: =SUM(B23:D23) -> 0
A24: Unearned Premium Reserves | B24: 0 | C24: 0 | D24: 2775.66 | E24: =SUM(B24:D24) -> 2775.66
A25: Direct Losses Unpaid | B25: 0 | C25: 0 | D25: 0 | E25: =SUM(B25:D25) -> 0
A26: Defense & Cost Containment Unpaid | B26: 0 | C26: 0 | D26: 0 | E26: =SUM(B26:D26) -> 0
A27: Adjusting & Other Unpaid | B27: 0 | C27: 0 | D27: 0 | E27: =SUM(B27:D27) -> 0
A29: ='MTHLY-TOTAL'!A31 -> Submitted by: ______________

Sheet MTHLY-MN
A1: =+'Cash Settlement'!A2 -> COMPANY: SOUTHLAKE SPECIALTY INSURANCE COMPANY
A2: =+'Cash Settlement'!A1 -> PRODUCER: FUTURISTIC UNDERWRITERS LLC. | D2: Input area
A3: EXHIBIT OF PREMIUMS AND LOSSES
A4: FOR THE MONTH OF | C4: =+'Cash Settlement'!C9 -> 46142
A6: BY LINE, BY STATE
B11: 19.3 | C11: 19.4 | D11: 21.2
A12: =+'MTHLY-TOTAL'!A10 -> TREATY YEAR : 5/1/2020 | B12: Comm'l Auto | C12: Other Comm'l | D12: Comm'l Auto | E12: TOTALS
B13: No-Fault | C13: Auto Liab | D13: Phys. Damage
A14: Premiums Written | B14: 0 | C14: 0 | D14: 0 | E14: =SUM(B14:D14) -> 0
A15: Policy Fees Written | B15: 0 | C15: 0 | D15: 0 | E15: =SUM(B15:D15) -> 0
A16: Premiums Collected | B16: 0 | C16: 0 | D16: 0 | E16: =SUM(B16:D16) -> 0
A17: Policy Fees Collected | B17: 0 | C17: 0 | D17: 0 | E17: =SUM(B17:D17) -> 0
A18: Premium Taxes | B18: =(B14+B15)*'Tax Rates'!$B$30 -> 0 | C18: =(C14+C15)*'Tax Rates'!$B$30 -> 0 | E18: =SUM(B18:D18) -> 0
A19: Losses Paid (Net of Salvage & Subrogation) | B19: 0 | C19: 0 | D19: 0 | E19: =SUM(B19:D19) -> 0
A20: Defense & Cost Containment Expenses Paid | B20: 0 | C20: 0 | D20: 0 | E20: =SUM(B20:D20) -> 0
A21: Adjusting & Other Expenses Paid | B21: 0 | C21: 0 | D21: 0 | E21: =SUM(B21:D21) -> 0
A22: Premium Earned - YTD | B22: 0 | C22: 0 | D22: 16329.93 | E22: =SUM(B22:D22) -> 16329.93
A23: Policy Fees Earned - YTD | B23: 0 | C23: 0 | D23: 0 | E23: =SUM(B23:D23) -> 0
A24: Unearned Premium Reserves | B24: 0 | C24: 0 | D24: 12758.8 | E24: =SUM(B24:D24) -> 12758.8
A25: Direct Losses Unpaid | B25: 0 | C25: 0 | D25: 0 | E25: =SUM(B25:D25) -> 0
A26: Defense & Cost Containment Unpaid | B26: 0 | C26: 0 | D26: 0 | E26: =SUM(B26:D26) -> 0
A27: Adjusting & Other Unpaid | B27: 0 | C27: 0 | D27: 0 | E27: =SUM(B27:D27) -> 0
A29: ='MTHLY-TOTAL'!A31 -> Submitted by: ______________

Sheet MTHLY-MO
A1: =+'Cash Settlement'!A2 -> COMPANY: SOUTHLAKE SPECIALTY INSURANCE COMPANY
A2: =+'Cash Settlement'!A1 -> PRODUCER: FUTURISTIC UNDERWRITERS LLC. | D2: Input area
A3: EXHIBIT OF PREMIUMS AND LOSSES
A4: FOR THE MONTH OF | C4: =+'Cash Settlement'!C9 -> 46142
A6: BY LINE, BY STATE
B11: 19.3 | C11: 19.4 | D11: 21.2
A12: =+'MTHLY-TOTAL'!A10 -> TREATY YEAR : 5/1/2020 | B12: Comm'l Auto | C12: Other Comm'l | D12: Comm'l Auto | E12: TOTALS
B13: No-Fault | C13: Auto Liab | D13: Phys. Damage
A14: Premiums Written | B14: 0 | C14: 0 | D14: 0 | E14: =SUM(B14:D14) -> 0
A15: Policy Fees Written | B15: 0 | C15: 0 | D15: 0 | E15: =SUM(B15:D15) -> 0
A16: Premiums Collected | B16: 0 | C16: 0 | D16: 0 | E16: =SUM(B16:D16) -> 0
A17: Policy Fees Collected | B17: 0 | C17: 0 | D17: 0 | E17: =SUM(B17:D17) -> 0
A18: Premium Taxes | B18: =(B14+B15)*'Tax Rates'!$B$32 -> 0 | C18: =(C14+C15)*'Tax Rates'!$B$32 -> 0 | E18: =SUM(B18:D18) -> 0
A19: Losses Paid (Net of Salvage & Subrogation) | B19: 0 | C19: 0 | D19: 0 | E19: =SUM(B19:D19) -> 0
A20: Defense & Cost Containment Expenses Paid | B20: 0 | C20: 0 | D20: 0 | E20: =SUM(B20:D20) -> 0
A21: Adjusting & Other Expenses Paid | B21: 0 | C21: 0 | D21: 0 | E21: =SUM(B21:D21) -> 0
A22: Premium Earned - YTD | B22: 0 | C22: 0 | D22: 21815.8 | E22: =SUM(B22:D22) -> 21815.8
A23: Policy Fees Earned - YTD | B23: 0 | C23: 0 | D23: 0 | E23: =SUM(B23:D23) -> 0
A24: Unearned Premium Reserves | B24: 0 | C24: 0 | D24: 21189.47 | E24: =SUM(B24:D24) -> 21189.47
A25: Direct Losses Unpaid | B25: 0 | C25: 0 | D25: 0 | E25: =SUM(B25:D25) -> 0
A26: Defense & Cost Containment Unpaid | B26: 0 | C26: 0 | D26: 0 | E26: =SUM(B26:D26) -> 0
A27: Adjusting & Other Unpaid | B27: 0 | C27: 0 | D27: 0 | E27: =SUM(B27:D27) -> 0
A29: ='MTHLY-TOTAL'!A31 -> Submitted by: ______________

Sheet MTHLY-MS
A1: =+'Cash Settlement'!A2 -> COMPANY: SOUTHLAKE SPECIALTY INSURANCE COMPANY
A2: =+'Cash Settlement'!A1 -> PRODUCER: FUTURISTIC UNDERWRITERS LLC. | D2: Input area
A3: EXHIBIT OF PREMIUMS AND LOSSES
A4: FOR THE MONTH OF | C4: =+'Cash Settlement'!C9 -> 46142
A6: BY LINE, BY STATE
B11: 19.3 | C11: 19.4 | D11: 21.2
A12: =+'MTHLY-TOTAL'!A10 -> TREATY YEAR : 5/1/2020 | B12: Comm'l Auto | C12: Other Comm'l | D12: Comm'l Auto | E12: TOTALS
B13: No-Fault | C13: Auto Liab | D13: Phys. Damage
A14: Premiums Written | B14: 0 | C14: 0 | D14: 0 | E14: =SUM(B14:D14) -> 0
A15: Policy Fees Written | B15: 0 | C15: 0 | D15: 0 | E15: =SUM(B15:D15) -> 0
A16: Premiums Collected | B16: 0 | C16: 0 | D16: 0 | E16: =SUM(B16:D16) -> 0
A17: Policy Fees Collected | B17: 0 | C17: 0 | D17: 0 | E17: =SUM(B17:D17) -> 0
A18: Premium Taxes | B18: =(B14+B15)*'Tax Rates'!$B$31 -> 0 | C18: =(C14+C15)*'Tax Rates'!$B$31 -> 0 | D18: =(D14+D15)*'Tax Rates'!$B$31 -> 0 | E18: =SUM(B18:D18) -> 0
A19: Losses Paid (Net of Salvage & Subrogation) | B19: 0 | C19: 0 | D19: 0 | E19: =SUM(B19:D19) -> 0
A20: Defense & Cost Containment Expenses Paid | B20: 0 | C20: 0 | D20: 0 | E20: =SUM(B20:D20) -> 0
A21: Adjusting & Other Expenses Paid | B21: 0 | C21: 0 | D21: 0 | E21: =SUM(B21:D21) -> 0
A22: Premium Earned - YTD | B22: 0 | C22: 0 | D22: 0 | E22: =SUM(B22:D22) -> 0
A23: Policy Fees Earned - YTD | B23: 0 | C23: 0 | D23: 0 | E23: =SUM(B23:D23) -> 0
A24: Unearned Premium Reserves | B24: 0 | C24: 0 | D24: 0 | E24: =SUM(B24:D24) -> 0
A25: Direct Losses Unpaid | B25: 0 | C25: 0 | D25: 0 | E25: =SUM(B25:D25) -> 0
A26: Defense & Cost Containment Unpaid | B26: 0 | C26: 0 | D26: 0 | E26: =SUM(B26:D26) -> 0
A27: Adjusting & Other Unpaid | B27: 0 | C27: 0 | D27: 0 | E27: =SUM(B27:D27) -> 0
A29: ='MTHLY-TOTAL'!A31 -> Submitted by: ______________

Sheet MTHLY-MT
A1: =+'Cash Settlement'!A2 -> COMPANY: SOUTHLAKE SPECIALTY INSURANCE COMPANY
A2: =+'Cash Settlement'!A1 -> PRODUCER: FUTURISTIC UNDERWRITERS LLC. | D2: Input area
A3: EXHIBIT OF PREMIUMS AND LOSSES
A4: FOR THE MONTH OF | C4: =+'Cash Settlement'!C9 -> 46142
A6: BY LINE, BY STATE
B11: 19.3 | C11: 19.4 | D11: 21.2
A12: =+'MTHLY-TOTAL'!A10 -> TREATY YEAR : 5/1/2020 | B12: Comm'l Auto | C12: Other Comm'l | D12: Comm'l Auto | E12: TOTALS
B13: No-Fault | C13: Auto Liab | D13: Phys. Damage
A14: Premiums Written | B14: 0 | C14: 0 | D14: 0 | E14: =SUM(B14:D14) -> 0
A15: Policy Fees Written | B15: 0 | C15: 0 | D15: 0 | E15: =SUM(B15:D15) -> 0
A16: Premiums Collected | B16: 0 | C16: 0 | D16: 0 | E16: =SUM(B16:D16) -> 0
A17: Policy Fees Collected | B17: 0 | C17: 0 | D17: 0 | E17: =SUM(B17:D17) -> 0
A18: Premium Taxes | B18: =(B14+B15)*'Tax Rates'!$B$33 -> 0 | C18: =(C14+C15)*'Tax Rates'!$B$33 -> 0 | D18: =(D14+D15)*'Tax Rates'!$B$33 -> 0 | E18: =SUM(B18:D18) -> 0
A19: Losses Paid (Net of Salvage & Subrogation) | B19: 0 | C19: 0 | D19: 0 | E19: =SUM(B19:D19) -> 0
A20: Defense & Cost Containment Expenses Paid | B20: 0 | C20: 0 | D20: 0 | E20: =SUM(B20:D20) -> 0
A21: Adjusting & Other Expenses Paid | B21: 0 | C21: 0 | D21: 0 | E21: =SUM(B21:D21) -> 0
A22: Premium Earned - YTD | B22: 0 | C22: 0 | D22: 0 | E22: =SUM(B22:D22) -> 0
A23: Policy Fees Earned - YTD | B23: 0 | C23: 0 | D23: 0 | E23: =SUM(B23:D23) -> 0
A24: Unearned Premium Reserves | B24: 0 | C24: 0 | D24: 0 | E24: =SUM(B24:D24) -> 0
A25: Direct Losses Unpaid | B25: 0 | C25: 0 | D25: 0 | E25: =SUM(B25:D25) -> 0
A26: Defense & Cost Containment Unpaid | B26: 0 | C26: 0 | D26: 0 | E26: =SUM(B26:D26) -> 0
A27: Adjusting & Other Unpaid | B27: 0 | C27: 0 | D27: 0 | E27: =SUM(B27:D27) -> 0
A29: ='MTHLY-TOTAL'!A31 -> Submitted by: ______________

Sheet MTHLY-NC
A1: =+'Cash Settlement'!A2 -> COMPANY: SOUTHLAKE SPECIALTY INSURANCE COMPANY
A2: =+'Cash Settlement'!A1 -> PRODUCER: FUTURISTIC UNDERWRITERS LLC. | D2: Input area
A3: EXHIBIT OF PREMIUMS AND LOSSES
A4: FOR THE MONTH OF | C4: =+'Cash Settlement'!C9 -> 46142
A6: BY LINE, BY STATE
B11: 19.3 | C11: 19.4 | D11: 21.2
A12: =+'MTHLY-TOTAL'!A10 -> TREATY YEAR : 5/1/2020 | B12: Comm'l Auto | C12: Other Comm'l | D12: Comm'l Auto | E12: TOTALS
B13: No-Fault | C13: Auto Liab | D13: Phys. Damage
A14: Premiums Written | B14: 0 | C14: 0 | D14: 0 | E14: =SUM(B14:D14) -> 0
A15: Policy Fees Written | B15: 0 | C15: 0 | D15: 0 | E15: =SUM(B15:D15) -> 0
A16: Premiums Collected | B16: 0 | C16: 0 | D16: 0 | E16: =SUM(B16:D16) -> 0
A17: Policy Fees Collected | B17: 0 | C17: 0 | D17: 0 | E17: =SUM(B17:D17) -> 0
A18: Premium Taxes | B18: =(B14+B15)*'Tax Rates'!$B$40 -> 0 | C18: =(C14+C15)*'Tax Rates'!$B$40 -> 0 | D18: =(D14+D15)*'Tax Rates'!$B$40 -> 0 | E18: =SUM(B18:D18) -> 0
A19: Losses Paid (Net of Salvage & Subrogation) | B19: 0 | C19: 0 | D19: 0 | E19: =SUM(B19:D19) -> 0
A20: Defense & Cost Containment Expenses Paid | B20: 0 | C20: 0 | D20: 0 | E20: =SUM(B20:D20) -> 0
A21: Adjusting & Other Expenses Paid | B21: 0 | C21: 0 | D21: 0 | E21: =SUM(B21:D21) -> 0
A22: Premium Earned - YTD | B22: 0 | C22: 0 | D22: 0 | E22: =SUM(B22:D22) -> 0
A23: Policy Fees Earned - YTD | B23: 0 | C23: 0 | D23: 0 | E23: =SUM(B23:D23) -> 0
A24: Unearned Premium Reserves | B24: 0 | C24: 0 | D24: 0 | E24: =SUM(B24:D24) -> 0
A25: Direct Losses Unpaid | B25: 0 | C25: 0 | D25: 0 | E25: =SUM(B25:D25) -> 0
A26: Defense & Cost Containment Unpaid | B26: 0 | C26: 0 | D26: 0 | E26: =SUM(B26:D26) -> 0
A27: Adjusting & Other Unpaid | B27: 0 | C27: 0 | D27: 0 | E27: =SUM(B27:D27) -> 0
A29: ='MTHLY-TOTAL'!A31 -> Submitted by: ______________

Sheet MTHLY-ND
A1: =+'Cash Settlement'!A2 -> COMPANY: SOUTHLAKE SPECIALTY INSURANCE COMPANY
A2: =+'Cash Settlement'!A1 -> PRODUCER: FUTURISTIC UNDERWRITERS LLC. | D2: Input area
A3: EXHIBIT OF PREMIUMS AND LOSSES
A4: FOR THE MONTH OF | C4: =+'Cash Settlement'!C9 -> 46142
A6: BY LINE, BY STATE
B11: 19.3 | C11: 19.4 | D11: 21.2
A12: =+'MTHLY-TOTAL'!A10 -> TREATY YEAR : 5/1/2020 | B12: Comm'l Auto | C12: Other Comm'l | D12: Comm'l Auto | E12: TOTALS
B13: No-Fault | C13: Auto Liab | D13: Phys. Damage
A14: Premiums Written | B14: 0 | C14: 0 | D14: 0 | E14: =SUM(B14:D14) -> 0
A15: Policy Fees Written | B15: 0 | C15: 0 | D15: 0 | E15: =SUM(B15:D15) -> 0
A16: Premiums Collected | B16: 0 | C16: 0 | D16: 0 | E16: =SUM(B16:D16) -> 0
A17: Policy Fees Collected | B17: 0 | C17: 0 | D17: 0 | E17: =SUM(B17:D17) -> 0
A18: Premium Taxes | B18: =(B14+B15)*'Tax Rates'!$B$41 -> 0 | C18: =(C14+C15)*'Tax Rates'!$B$41 -> 0 | D18: =(D14+D15)*'Tax Rates'!$B$41 -> 0 | E18: =SUM(B18:D18) -> 0
A19: Losses Paid (Net of Salvage & Subrogation) | B19: 0 | C19: 0 | D19: 0 | E19: =SUM(B19:D19) -> 0
A20: Defense & Cost Containment Expenses Paid | B20: 0 | C20: 0 | D20: 0 | E20: =SUM(B20:D20) -> 0
A21: Adjusting & Other Expenses Paid | B21: 0 | C21: 0 | D21: 0 | E21: =SUM(B21:D21) -> 0
A22: Premium Earned - YTD | B22: 0 | C22: 0 | D22: 0 | E22: =SUM(B22:D22) -> 0
A23: Policy Fees Earned - YTD | B23: 0 | C23: 0 | D23: 0 | E23: =SUM(B23:D23) -> 0
A24: Unearned Premium Reserves | B24: 0 | C24: 0 | D24: 0 | E24: =SUM(B24:D24) -> 0
A25: Direct Losses Unpaid | B25: 0 | C25: 0 | D25: 0 | E25: =SUM(B25:D25) -> 0
A26: Defense & Cost Containment Unpaid | B26: 0 | C26: 0 | D26: 0 | E26: =SUM(B26:D26) -> 0
A27: Adjusting & Other Unpaid | B27: 0 | C27: 0 | D27: 0 | E27: =SUM(B27:D27) -> 0
A29: ='MTHLY-TOTAL'!A31 -> Submitted by: ______________

Sheet MTHLY-NH
A1: =+'Cash Settlement'!A2 -> COMPANY: SOUTHLAKE SPECIALTY INSURANCE COMPANY
A2: =+'Cash Settlement'!A1 -> PRODUCER: FUTURISTIC UNDERWRITERS LLC. | D2: Input area
A3: EXHIBIT OF PREMIUMS AND LOSSES
A4: FOR THE MONTH OF | C4: =+'Cash Settlement'!C9 -> 46142
A6: BY LINE, BY STATE
B11: 19.3 | C11: 19.4 | D11: 21.2
A12: =+'MTHLY-TOTAL'!A10 -> TREATY YEAR : 5/1/2020 | B12: Comm'l Auto | C12: Other Comm'l | D12: Comm'l Auto | E12: TOTALS
B13: No-Fault | C13: Auto Liab | D13: Phys. Damage
A14: Premiums Written | B14: 0 | C14: 0 | D14: 0 | E14: =SUM(B14:D14) -> 0
A15: Policy Fees Written | B15: 0 | C15: 0 | D15: 0 | E15: =SUM(B15:D15) -> 0
A16: Premiums Collected | B16: 0 | C16: 0 | D16: 0 | E16: =SUM(B16:D16) -> 0
A17: Policy Fees Collected | B17: 0 | C17: 0 | D17: 0 | E17: =SUM(B17:D17) -> 0
A18: Premium Taxes | B18: =(B14+B15)*'Tax Rates'!$B$36 -> 0 | C18: =(C14+C15)*'Tax Rates'!$B$36 -> 0 | D18: =(D14+D15)*'Tax Rates'!$B$36 -> 0 | E18: =SUM(B18:D18) -> 0
A19: Losses Paid (Net of Salvage & Subrogation) | B19: 0 | C19: 0 | D19: 0 | E19: =SUM(B19:D19) -> 0
A20: Defense & Cost Containment Expenses Paid | B20: 0 | C20: 0 | D20: 0 | E20: =SUM(B20:D20) -> 0
A21: Adjusting & Other Expenses Paid | B21: 0 | C21: 0 | D21: 0 | E21: =SUM(B21:D21) -> 0
A22: Premium Earned - YTD | B22: 0 | C22: 0 | D22: 0 | E22: =SUM(B22:D22) -> 0
A23: Policy Fees Earned - YTD | B23: 0 | C23: 0 | D23: 0 | E23: =SUM(B23:D23) -> 0
A24: Unearned Premium Reserves | B24: 0 | C24: 0 | D24: 0 | E24: =SUM(B24:D24) -> 0
A25: Direct Losses Unpaid | B25: 0 | C25: 0 | D25: 0 | E25: =SUM(B25:D25) -> 0
A26: Defense & Cost Containment Unpaid | B26: 0 | C26: 0 | D26: 0 | E26: =SUM(B26:D26) -> 0
A27: Adjusting & Other Unpaid | B27: 0 | C27: 0 | D27: 0 | E27: =SUM(B27:D27) -> 0
A29: ='MTHLY-TOTAL'!A31 -> Submitted by: ______________

Sheet MTHLY-NJ
A1: =+'Cash Settlement'!A2 -> COMPANY: SOUTHLAKE SPECIALTY INSURANCE COMPANY
A2: =+'Cash Settlement'!A1 -> PRODUCER: FUTURISTIC UNDERWRITERS LLC. | D2: Input area
A3: EXHIBIT OF PREMIUMS AND LOSSES
A4: FOR THE MONTH OF | C4: =+'Cash Settlement'!C9 -> 46142
A6: BY LINE, BY STATE
B11: 9 | C11: 19.4 | D11: 21.2
A12: =+'MTHLY-TOTAL'!A10 -> TREATY YEAR : 5/1/2020 | B12: Comm'l Auto | C12: Other Comm'l | D12: Comm'l Auto | E12: TOTALS
B13: Inland Marine | C13: Auto Liab | D13: Phys. Damage
A14: Premiums Written | B14: 0 | C14: 0 | D14: 0 | E14: =SUM(B14:D14) -> 0
A15: Policy Fees Written | B15: 0 | C15: 0 | D15: 0 | E15: =SUM(B15:D15) -> 0
A16: Premiums Collected | B16: 0 | C16: 0 | D16: 0 | E16: =SUM(B16:D16) -> 0
A17: Policy Fees Collected | B17: 0 | C17: 0 | D17: 0 | E17: =SUM(B17:D17) -> 0
A18: Premium Taxes | B18: =(B14+B15)*'Tax Rates'!$B$37 -> 0 | C18: =(C14+C15)*'Tax Rates'!$B$37 -> 0 | E18: =SUM(B18:D18) -> 0
A19: Losses Paid (Net of Salvage & Subrogation) | B19: 0 | C19: 0 | D19: 0 | E19: =SUM(B19:D19) -> 0
A20: Defense & Cost Containment Expenses Paid | B20: 0 | C20: 0 | D20: 0 | E20: =SUM(B20:D20) -> 0
A21: Adjusting & Other Expenses Paid | B21: 0 | C21: 0 | D21: 0 | E21: =SUM(B21:D21) -> 0
A22: Premium Earned - YTD | B22: 0 | C22: 0 | D22: 66446.82 | E22: =SUM(B22:D22) -> 66446.82
A23: Policy Fees Earned - YTD | B23: 0 | C23: 0 | D23: 0 | E23: =SUM(B23:D23) -> 0
A24: Unearned Premium Reserves | B24: 0 | C24: 0 | D24: 49223.95 | E24: =SUM(B24:D24) -> 49223.95
A25: Direct Losses Unpaid | B25: 0 | C25: 0 | D25: 0 | E25: =SUM(B25:D25) -> 0
A26: Defense & Cost Containment Unpaid | B26: 0 | C26: 0 | D26: 0 | E26: =SUM(B26:D26) -> 0
A27: Adjusting & Other Unpaid | B27: 0 | C27: 0 | D27: 0 | E27: =SUM(B27:D27) -> 0
A29: ='MTHLY-TOTAL'!A31 -> Submitted by: ______________

Sheet MTHLY-NM
A1: =+'Cash Settlement'!A2 -> COMPANY: SOUTHLAKE SPECIALTY INSURANCE COMPANY
A2: =+'Cash Settlement'!A1 -> PRODUCER: FUTURISTIC UNDERWRITERS LLC. | D2: Input area
A3: EXHIBIT OF PREMIUMS AND LOSSES
A4: FOR THE MONTH OF | C4: =+'Cash Settlement'!C9 -> 46142
A6: BY LINE, BY STATE
B11: 19.3 | C11: 19.4 | D11: 21.2
A12: =+'MTHLY-TOTAL'!A10 -> TREATY YEAR : 5/1/2020 | B12: Comm'l Auto | C12: Other Comm'l | D12: Comm'l Auto | E12: TOTALS
B13: No-Fault | C13: Auto Liab | D13: Phys. Damage
A14: Premiums Written | B14: 0 | C14: 0 | D14: 0 | E14: =SUM(B14:D14) -> 0
A15: Policy Fees Written | B15: 0 | C15: 0 | D15: 0 | E15: =SUM(B15:D15) -> 0
A16: Premiums Collected | B16: 0 | C16: 0 | D16: 0 | E16: =SUM(B16:D16) -> 0
A17: Policy Fees Collected | B17: 0 | C17: 0 | D17: 0 | E17: =SUM(B17:D17) -> 0
A18: Premium Taxes | B18: =(B14+B15)*'Tax Rates'!$B$38 -> 0 | C18: =(C14+C15)*'Tax Rates'!$B$38 -> 0 | D18: =(D14+D15)*'Tax Rates'!$B$38 -> 0 | E18: =SUM(B18:D18) -> 0
A19: Losses Paid (Net of Salvage & Subrogation) | B19: 0 | C19: 0 | D19: 0 | E19: =SUM(B19:D19) -> 0
A20: Defense & Cost Containment Expenses Paid | B20: 0 | C20: 0 | D20: 0 | E20: =SUM(B20:D20) -> 0
A21: Adjusting & Other Expenses Paid | B21: 0 | C21: 0 | D21: 0 | E21: =SUM(B21:D21) -> 0
A22: Premium Earned - YTD | B22: 0 | C22: 0 | D22: 0 | E22: =SUM(B22:D22) -> 0
A23: Policy Fees Earned - YTD | B23: 0 | C23: 0 | D23: 0 | E23: =SUM(B23:D23) -> 0
A24: Unearned Premium Reserves | B24: 0 | C24: 0 | D24: 0 | E24: =SUM(B24:D24) -> 0
A25: Direct Losses Unpaid | B25: 0 | C25: 0 | D25: 0 | E25: =SUM(B25:D25) -> 0
A26: Defense & Cost Containment Unpaid | B26: 0 | C26: 0 | D26: 0 | E26: =SUM(B26:D26) -> 0
A27: Adjusting & Other Unpaid | B27: 0 | C27: 0 | D27: 0 | E27: =SUM(B27:D27) -> 0
A29: ='MTHLY-TOTAL'!A31 -> Submitted by: ______________

Sheet MTHLY-NE
A1: =+'Cash Settlement'!A2 -> COMPANY: SOUTHLAKE SPECIALTY INSURANCE COMPANY
A2: =+'Cash Settlement'!A1 -> PRODUCER: FUTURISTIC UNDERWRITERS LLC. | D2: Input area
A3: EXHIBIT OF PREMIUMS AND LOSSES
A4: FOR THE MONTH OF | C4: =+'Cash Settlement'!C9 -> 46142
A6: BY LINE, BY STATE
B11: 19.3 | C11: 19.4 | D11: 21.2
A12: =+'MTHLY-TOTAL'!A10 -> TREATY YEAR : 5/1/2020 | B12: Comm'l Auto | C12: Other Comm'l | D12: Comm'l Auto | E12: TOTALS
B13: No-Fault | C13: Auto Liab | D13: Phys. Damage
A14: Premiums Written | B14: 0 | C14: 0 | D14: 0 | E14: =SUM(B14:D14) -> 0
A15: Policy Fees Written | B15: 0 | C15: 0 | D15: 0 | E15: =SUM(B15:D15) -> 0
A16: Premiums Collected | B16: 0 | C16: 0 | D16: 0 | E16: =SUM(B16:D16) -> 0
A17: Policy Fees Collected | B17: 0 | C17: 0 | D17: 0 | E17: =SUM(B17:D17) -> 0
A18: Premium Taxes | B18: =(B14+B15)*'Tax Rates'!$B$34 -> 0 | C18: =(C14+C15)*'Tax Rates'!$B$34 -> 0 | D18: =(D14+D15)*'Tax Rates'!$B$34 -> 0 | E18: =SUM(B18:D18) -> 0
A19: Losses Paid (Net of Salvage & Subrogation) | B19: 0 | C19: 0 | D19: 0 | E19: =SUM(B19:D19) -> 0
A20: Defense & Cost Containment Expenses Paid | B20: 0 | C20: 0 | D20: 0 | E20: =SUM(B20:D20) -> 0
A21: Adjusting & Other Expenses Paid | B21: 0 | C21: 0 | D21: 0 | E21: =SUM(B21:D21) -> 0
A22: Premium Earned - YTD | B22: 0 | C22: 0 | D22: 0 | E22: =SUM(B22:D22) -> 0
A23: Policy Fees Earned - YTD | B23: 0 | C23: 0 | D23: 0 | E23: =SUM(B23:D23) -> 0
A24: Unearned Premium Reserves | B24: 0 | C24: 0 | D24: 0 | E24: =SUM(B24:D24) -> 0
A25: Direct Losses Unpaid | B25: 0 | C25: 0 | D25: 0 | E25: =SUM(B25:D25) -> 0
A26: Defense & Cost Containment Unpaid | B26: 0 | C26: 0 | D26: 0 | E26: =SUM(B26:D26) -> 0
A27: Adjusting & Other Unpaid | B27: 0 | C27: 0 | D27: 0 | E27: =SUM(B27:D27) -> 0
A29: ='MTHLY-TOTAL'!A31 -> Submitted by: ______________

Sheet MTHLY-NV
A1: =+'Cash Settlement'!A2 -> COMPANY: SOUTHLAKE SPECIALTY INSURANCE COMPANY
A2: =+'Cash Settlement'!A1 -> PRODUCER: FUTURISTIC UNDERWRITERS LLC. | D2: Input area
A3: EXHIBIT OF PREMIUMS AND LOSSES
A4: FOR THE MONTH OF | C4: =+'Cash Settlement'!C9 -> 46142
A6: BY LINE, BY STATE
B11: 19.3 | C11: 19.4 | D11: 21.2
A12: =+'MTHLY-TOTAL'!A10 -> TREATY YEAR : 5/1/2020 | B12: Comm'l Auto | C12: Other Comm'l | D12: Comm'l Auto | E12: TOTALS
B13: No-Fault | C13: Auto Liab | D13: Phys. Damage
A14: Premiums Written | B14: 0 | C14: 0 | D14: 0 | E14: =SUM(B14:D14) -> 0
A15: Policy Fees Written | B15: 0 | C15: 0 | D15: 0 | E15: =SUM(B15:D15) -> 0
A16: Premiums Collected | B16: 0 | C16: 0 | D16: 0 | E16: =SUM(B16:D16) -> 0
A17: Policy Fees Collected | B17: 0 | C17: 0 | D17: 0 | E17: =SUM(B17:D17) -> 0
A18: Premium Taxes | B18: =(B14+B15)*'Tax Rates'!$B$35 -> 0 | C18: =(C14+C15)*'Tax Rates'!$B$35 -> 0 | D18: =(D14+D15)*'Tax Rates'!$B$35 -> 0 | E18: =SUM(B18:D18) -> 0
A19: Losses Paid (Net of Salvage & Subrogation) | B19: 0 | C19: 0 | D19: 0 | E19: =SUM(B19:D19) -> 0
A20: Defense & Cost Containment Expenses Paid | B20: 0 | C20: 0 | D20: 0 | E20: =SUM(B20:D20) -> 0
A21: Adjusting & Other Expenses Paid | B21: 0 | C21: 0 | D21: 0 | E21: =SUM(B21:D21) -> 0
A22: Premium Earned - YTD | B22: 0 | C22: 0 | D22: 0 | E22: =SUM(B22:D22) -> 0
A23: Policy Fees Earned - YTD | B23: 0 | C23: 0 | D23: 0 | E23: =SUM(B23:D23) -> 0
A24: Unearned Premium Reserves | B24: 0 | C24: 0 | D24: 0 | E24: =SUM(B24:D24) -> 0
A25: Direct Losses Unpaid | B25: 0 | C25: 0 | D25: 0 | E25: =SUM(B25:D25) -> 0
A26: Defense & Cost Containment Unpaid | B26: 0 | C26: 0 | D26: 0 | E26: =SUM(B26:D26) -> 0
A27: Adjusting & Other Unpaid | B27: 0 | C27: 0 | D27: 0 | E27: =SUM(B27:D27) -> 0
A29: ='MTHLY-TOTAL'!A31 -> Submitted by: ______________

Sheet MTHLY-NY
A1: =+'Cash Settlement'!A2 -> COMPANY: SOUTHLAKE SPECIALTY INSURANCE COMPANY
A2: =+'Cash Settlement'!A1 -> PRODUCER: FUTURISTIC UNDERWRITERS LLC. | D2: Input area
A3: EXHIBIT OF PREMIUMS AND LOSSES
A4: FOR THE MONTH OF | C4: =+'Cash Settlement'!C9 -> 46142
A6: BY LINE, BY STATE
B11: 19.3 | C11: 19.4 | D11: 21.2
A12: =+'MTHLY-TOTAL'!A10 -> TREATY YEAR : 5/1/2020 | B12: Comm'l Auto | C12: Other Comm'l | D12: Comm'l Auto | E12: TOTALS
B13: No-Fault | C13: Auto Liab | D13: Phys. Damage
A14: Premiums Written | B14: 0 | C14: 0 | D14: 0 | E14: =SUM(B14:D14) -> 0
A15: Policy Fees Written | B15: 0 | C15: 0 | D15: 0 | E15: =SUM(B15:D15) -> 0
A16: Premiums Collected | B16: 0 | C16: 0 | D16: 0 | E16: =SUM(B16:D16) -> 0
A17: Policy Fees Collected | B17: 0 | C17: 0 | D17: 0 | E17: =SUM(B17:D17) -> 0
A18: Premium Taxes | B18: =(B14+B15)*'Tax Rates'!$B$39 -> 0 | C18: =(C14+C15)*'Tax Rates'!$B$39 -> 0 | D18: =(D14+D15)*'Tax Rates'!$B$39 -> 0 | E18: =SUM(B18:D18) -> 0
A19: Losses Paid (Net of Salvage & Subrogation) | B19: 0 | C19: 0 | D19: 0 | E19: =SUM(B19:D19) -> 0
A20: Defense & Cost Containment Expenses Paid | B20: 0 | C20: 0 | D20: 0 | E20: =SUM(B20:D20) -> 0
A21: Adjusting & Other Expenses Paid | B21: 0 | C21: 0 | D21: 0 | E21: =SUM(B21:D21) -> 0
A22: Premium Earned - YTD | B22: 0 | C22: 0 | D22: 0 | E22: =SUM(B22:D22) -> 0
A23: Policy Fees Earned - YTD | B23: 0 | C23: 0 | D23: 0 | E23: =SUM(B23:D23) -> 0
A24: Unearned Premium Reserves | B24: 0 | C24: 0 | D24: 0 | E24: =SUM(B24:D24) -> 0
A25: Direct Losses Unpaid | B25: 0 | C25: 0 | D25: 0 | E25: =SUM(B25:D25) -> 0
A26: Defense & Cost Containment Unpaid | B26: 0 | C26: 0 | D26: 0 | E26: =SUM(B26:D26) -> 0
A27: Adjusting & Other Unpaid | B27: 0 | C27: 0 | D27: 0 | E27: =SUM(B27:D27) -> 0
A29: ='MTHLY-TOTAL'!A31 -> Submitted by: ______________

Sheet MTHLY-OH
A1: =+'Cash Settlement'!A2 -> COMPANY: SOUTHLAKE SPECIALTY INSURANCE COMPANY
A2: =+'Cash Settlement'!A1 -> PRODUCER: FUTURISTIC UNDERWRITERS LLC. | D2: Input area
A3: EXHIBIT OF PREMIUMS AND LOSSES
A4: FOR THE MONTH OF | C4: =+'Cash Settlement'!C9 -> 46142
A6: BY LINE, BY STATE
B11: 19.3 | C11: 19.4 | D11: 21.2
A12: =+'MTHLY-TOTAL'!A10 -> TREATY YEAR : 5/1/2020 | B12: Comm'l Auto | C12: Other Comm'l | D12: Comm'l Auto | E12: TOTALS
B13: No-Fault | C13: Auto Liab | D13: Phys. Damage
A14: Premiums Written | B14: 0 | C14: 0 | D14: 0 | E14: =SUM(B14:D14) -> 0
A15: Policy Fees Written | B15: 0 | C15: 0 | D15: 0 | E15: =SUM(B15:D15) -> 0
A16: Premiums Collected | B16: 0 | C16: 0 | D16: 0 | E16: =SUM(B16:D16) -> 0
A17: Policy Fees Collected | B17: 0 | C17: 0 | D17: 0 | E17: =SUM(B17:D17) -> 0
A18: Premium Taxes | B18: =(B14+B15)*'Tax Rates'!$B$42 -> 0 | C18: =(C14+C15)*'Tax Rates'!$B$42 -> 0 | E18: =SUM(B18:D18) -> 0
A19: Losses Paid (Net of Salvage & Subrogation) | B19: 0 | C19: 0 | D19: 0 | E19: =SUM(B19:D19) -> 0
A20: Defense & Cost Containment Expenses Paid | B20: 0 | C20: 0 | D20: 0 | E20: =SUM(B20:D20) -> 0
A21: Adjusting & Other Expenses Paid | B21: 0 | C21: 0 | D21: 0 | E21: =SUM(B21:D21) -> 0
A22: Premium Earned - YTD | B22: 0 | C22: 0 | D22: 8271.53 | E22: =SUM(B22:D22) -> 8271.53
A23: Policy Fees Earned - YTD | B23: 0 | C23: 0 | D23: 0 | E23: =SUM(B23:D23) -> 0
A24: Unearned Premium Reserves | B24: 0 | C24: 0 | D24: 9398.55 | E24: =SUM(B24:D24) -> 9398.55
A25: Direct Losses Unpaid | B25: 0 | C25: 0 | D25: 0 | E25: =SUM(B25:D25) -> 0
A26: Defense & Cost Containment Unpaid | B26: 0 | C26: 0 | D26: 0 | E26: =SUM(B26:D26) -> 0
A27: Adjusting & Other Unpaid | B27: 0 | C27: 0 | D27: 0 | E27: =SUM(B27:D27) -> 0
A29: ='MTHLY-TOTAL'!A31 -> Submitted by: ______________

Sheet MTHLY-OK
A1: =+'Cash Settlement'!A2 -> COMPANY: SOUTHLAKE SPECIALTY INSURANCE COMPANY
A2: =+'Cash Settlement'!A1 -> PRODUCER: FUTURISTIC UNDERWRITERS LLC. | D2: Input area
A3: EXHIBIT OF PREMIUMS AND LOSSES
A4: FOR THE MONTH OF | C4: =+'Cash Settlement'!C9 -> 46142
A6: BY LINE, BY STATE
B11: 19.3 | C11: 19.4 | D11: 21.2
A12: =+'MTHLY-TOTAL'!A10 -> TREATY YEAR : 5/1/2020 | B12: Comm'l Auto | C12: Other Comm'l | D12: Comm'l Auto | E12: TOTALS
B13: No-Fault | C13: Auto Liab | D13: Phys. Damage
A14: Premiums Written | B14: 0 | C14: 0 | D14: 0 | E14: =SUM(B14:D14) -> 0
A15: Policy Fees Written | B15: 0 | C15: 0 | D15: 0 | E15: =SUM(B15:D15) -> 0
A16: Premiums Collected | B16: 0 | C16: 0 | D16: 0 | E16: =SUM(B16:D16) -> 0
A17: Policy Fees Collected | B17: 0 | C17: 0 | D17: 0 | E17: =SUM(B17:D17) -> 0
A18: Premium Taxes | B18: =(B14+B15)*'Tax Rates'!$B$43 -> 0 | C18: =(C14+C15)*'Tax Rates'!$B$43 -> 0 | E18: =SUM(B18:D18) -> 0
A19: Losses Paid (Net of Salvage & Subrogation) | B19: 0 | C19: 0 | D19: 0 | E19: =SUM(B19:D19) -> 0
A20: Defense & Cost Containment Expenses Paid | B20: 0 | C20: 0 | D20: 0 | E20: =SUM(B20:D20) -> 0
A21: Adjusting & Other Expenses Paid | B21: 0 | C21: 0 | D21: 0 | E21: =SUM(B21:D21) -> 0
A22: Premium Earned - YTD | B22: 0 | C22: 0 | D22: 0 | E22: =SUM(B22:D22) -> 0
A23: Policy Fees Earned - YTD | B23: 0 | C23: 0 | D23: 0 | E23: =SUM(B23:D23) -> 0
A24: Unearned Premium Reserves | B24: 0 | C24: 0 | D24: 0 | E24: =SUM(B24:D24) -> 0
A25: Direct Losses Unpaid | B25: 0 | C25: 0 | D25: 0 | E25: =SUM(B25:D25) -> 0
A26: Defense & Cost Containment Unpaid | B26: 0 | C26: 0 | D26: 0 | E26: =SUM(B26:D26) -> 0
A27: Adjusting & Other Unpaid | B27: 0 | C27: 0 | D27: 0 | E27: =SUM(B27:D27) -> 0
A29: ='MTHLY-TOTAL'!A31 -> Submitted by: ______________

Sheet MTHLY-OR
A1: =+'Cash Settlement'!A2 -> COMPANY: SOUTHLAKE SPECIALTY INSURANCE COMPANY
A2: =+'Cash Settlement'!A1 -> PRODUCER: FUTURISTIC UNDERWRITERS LLC. | D2: Input area
A3: EXHIBIT OF PREMIUMS AND LOSSES
A4: FOR THE MONTH OF | C4: =+'Cash Settlement'!C9 -> 46142
A6: BY LINE, BY STATE
B11: 19.3 | C11: 19.4 | D11: 21.2
A12: =+'MTHLY-TOTAL'!A10 -> TREATY YEAR : 5/1/2020 | B12: Comm'l Auto | C12: Other Comm'l | D12: Comm'l Auto | E12: TOTALS
B13: No-Fault | C13: Auto Liab | D13: Phys. Damage
A14: Premiums Written | B14: 0 | C14: 0 | D14: 0 | E14: =SUM(B14:D14) -> 0
A15: Policy Fees Written | B15: 0 | C15: 0 | D15: 0 | E15: =SUM(B15:D15) -> 0
A16: Premiums Collected | B16: 0 | C16: 0 | D16: 0 | E16: =SUM(B16:D16) -> 0
A17: Policy Fees Collected | B17: 0 | C17: 0 | D17: 0 | E17: =SUM(B17:D17) -> 0
A18: Premium Taxes | B18: =(B14+B15)*'Tax Rates'!$B$44 -> 0 | C18: =(C14+C15)*'Tax Rates'!$B$44 -> 0 | E18: =SUM(B18:D18) -> 0
A19: Losses Paid (Net of Salvage & Subrogation) | B19: 0 | C19: 0 | D19: 0 | E19: =SUM(B19:D19) -> 0
A20: Defense & Cost Containment Expenses Paid | B20: 0 | C20: 0 | D20: 0 | E20: =SUM(B20:D20) -> 0
A21: Adjusting & Other Expenses Paid | B21: 0 | C21: 0 | D21: 0 | E21: =SUM(B21:D21) -> 0
A22: Premium Earned - YTD | B22: 0 | C22: 0 | D22: 1217.63 | E22: =SUM(B22:D22) -> 1217.63
A23: Policy Fees Earned - YTD | B23: 0 | C23: 0 | D23: 0 | E23: =SUM(B23:D23) -> 0
A24: Unearned Premium Reserves | B24: 0 | C24: 0 | D24: 1438.87 | E24: =SUM(B24:D24) -> 1438.87
A25: Direct Losses Unpaid | B25: 0 | C25: 0 | D25: 0 | E25: =SUM(B25:D25) -> 0
A26: Defense & Cost Containment Unpaid | B26: 0 | C26: 0 | D26: 0 | E26: =SUM(B26:D26) -> 0
A27: Adjusting & Other Unpaid | B27: 0 | C27: 0 | D27: 0 | E27: =SUM(B27:D27) -> 0
A29: ='MTHLY-TOTAL'!A31 -> Submitted by: ______________

Sheet MTHLY-PA
A1: =+'Cash Settlement'!A2 -> COMPANY: SOUTHLAKE SPECIALTY INSURANCE COMPANY
A2: =+'Cash Settlement'!A1 -> PRODUCER: FUTURISTIC UNDERWRITERS LLC. | D2: Input area
A3: EXHIBIT OF PREMIUMS AND LOSSES
A4: FOR THE MONTH OF | C4: =+'Cash Settlement'!C9 -> 46142
A6: BY LINE, BY STATE
B11: 19.3 | C11: 19.4 | D11: 21.2
A12: =+'MTHLY-TOTAL'!A10 -> TREATY YEAR : 5/1/2020 | B12: Comm'l Auto | C12: Other Comm'l | D12: Comm'l Auto | E12: TOTALS
B13: No-Fault | C13: Auto Liab | D13: Phys. Damage
A14: Premiums Written | B14: 0 | C14: 0 | D14: 0 | E14: =SUM(B14:D14) -> 0
A15: Policy Fees Written | B15: 0 | C15: 0 | D15: 0 | E15: =SUM(B15:D15) -> 0
A16: Premiums Collected | B16: 0 | C16: 0 | D16: 0 | E16: =SUM(B16:D16) -> 0
A17: Policy Fees Collected | B17: 0 | C17: 0 | D17: 0 | E17: =SUM(B17:D17) -> 0
A18: Premium Taxes | B18: =(B14+B15)*'Tax Rates'!$B$45 -> 0 | C18: =(C14+C15)*'Tax Rates'!$B$45 -> 0 | E18: =SUM(B18:D18) -> 0
A19: Losses Paid (Net of Salvage & Subrogation) | B19: 0 | C19: 0 | D19: 0 | E19: =SUM(B19:D19) -> 0
A20: Defense & Cost Containment Expenses Paid | B20: 0 | C20: 0 | D20: 0 | E20: =SUM(B20:D20) -> 0
A21: Adjusting & Other Expenses Paid | B21: 0 | C21: 0 | D21: 0 | E21: =SUM(B21:D21) -> 0
A22: Premium Earned - YTD | B22: 0 | C22: 0 | D22: 52533.41 | E22: =SUM(B22:D22) -> 52533.41
A23: Policy Fees Earned - YTD | B23: 0 | C23: 0 | D23: 0 | E23: =SUM(B23:D23) -> 0
A24: Unearned Premium Reserves | B24: 0 | C24: 0 | D24: 49151.32 | E24: =SUM(B24:D24) -> 49151.32
A25: Direct Losses Unpaid | B25: 0 | C25: 0 | D25: 0 | E25: =SUM(B25:D25) -> 0
A26: Defense & Cost Containment Unpaid | B26: 0 | C26: 0 | D26: 0 | E26: =SUM(B26:D26) -> 0
A27: Adjusting & Other Unpaid | B27: 0 | C27: 0 | D27: 0 | E27: =SUM(B27:D27) -> 0
A29: ='MTHLY-TOTAL'!A31 -> Submitted by: ______________

Sheet MTHLY-RI
A1: =+'Cash Settlement'!A2 -> COMPANY: SOUTHLAKE SPECIALTY INSURANCE COMPANY
A2: =+'Cash Settlement'!A1 -> PRODUCER: FUTURISTIC UNDERWRITERS LLC. | D2: Input area
A3: EXHIBIT OF PREMIUMS AND LOSSES
A4: FOR THE MONTH OF | C4: =+'Cash Settlement'!C9 -> 46142
A6: BY LINE, BY STATE
B11: 19.3 | C11: 19.4 | D11: 21.2
A12: =+'MTHLY-TOTAL'!A10 -> TREATY YEAR : 5/1/2020 | B12: Comm'l Auto | C12: Other Comm'l | D12: Comm'l Auto | E12: TOTALS
B13: No-Fault | C13: Auto Liab | D13: Phys. Damage
A14: Premiums Written | B14: 0 | C14: 0 | D14: 0 | E14: =SUM(B14:D14) -> 0
A15: Policy Fees Written | B15: 0 | C15: 0 | D15: 0 | E15: =SUM(B15:D15) -> 0
A16: Premiums Collected | B16: 0 | C16: 0 | D16: 0 | E16: =SUM(B16:D16) -> 0
A17: Policy Fees Collected | B17: 0 | C17: 0 | D17: 0 | E17: =SUM(B17:D17) -> 0
A18: Premium Taxes | B18: =(B14+B15)*'Tax Rates'!$B$46 -> 0 | C18: =(C14+C15)*'Tax Rates'!$B$46 -> 0 | D18: =(D14+D15)*'Tax Rates'!$B$46 -> 0 | E18: =SUM(B18:D18) -> 0
A19: Losses Paid (Net of Salvage & Subrogation) | B19: 0 | C19: 0 | D19: 0 | E19: =SUM(B19:D19) -> 0
A20: Defense & Cost Containment Expenses Paid | B20: 0 | C20: 0 | D20: 0 | E20: =SUM(B20:D20) -> 0
A21: Adjusting & Other Expenses Paid | B21: 0 | C21: 0 | D21: 0 | E21: =SUM(B21:D21) -> 0
A22: Premium Earned - YTD | B22: 0 | C22: 0 | D22: 0 | E22: =SUM(B22:D22) -> 0
A23: Policy Fees Earned - YTD | B23: 0 | C23: 0 | D23: 0 | E23: =SUM(B23:D23) -> 0
A24: Unearned Premium Reserves | B24: 0 | C24: 0 | D24: 0 | E24: =SUM(B24:D24) -> 0
A25: Direct Losses Unpaid | B25: 0 | C25: 0 | D25: 0 | E25: =SUM(B25:D25) -> 0
A26: Defense & Cost Containment Unpaid | B26: 0 | C26: 0 | D26: 0 | E26: =SUM(B26:D26) -> 0
A27: Adjusting & Other Unpaid | B27: 0 | C27: 0 | D27: 0 | E27: =SUM(B27:D27) -> 0
A29: ='MTHLY-TOTAL'!A31 -> Submitted by: ______________

Sheet MTHLY-SC
A1: =+'Cash Settlement'!A2 -> COMPANY: SOUTHLAKE SPECIALTY INSURANCE COMPANY
A2: =+'Cash Settlement'!A1 -> PRODUCER: FUTURISTIC UNDERWRITERS LLC. | D2: Input area
A3: EXHIBIT OF PREMIUMS AND LOSSES
A4: FOR THE MONTH OF | C4: =+'Cash Settlement'!C9 -> 46142
A6: BY LINE, BY STATE
B11: 19.3 | C11: 19.4 | D11: 21.2
A12: =+'MTHLY-TOTAL'!A10 -> TREATY YEAR : 5/1/2020 | B12: Comm'l Auto | C12: Other Comm'l | D12: Comm'l Auto | E12: TOTALS
B13: No-Fault | C13: Auto Liab | D13: Phys. Damage
A14: Premiums Written | B14: 0 | C14: 0 | D14: 0 | E14: =SUM(B14:D14) -> 0
A15: Policy Fees Written | B15: 0 | C15: 0 | D15: 0 | E15: =SUM(B15:D15) -> 0
A16: Premiums Collected | B16: 0 | C16: 0 | D16: 0 | E16: =SUM(B16:D16) -> 0
A17: Policy Fees Collected | B17: 0 | C17: 0 | D17: 0 | E17: =SUM(B17:D17) -> 0
A18: Premium Taxes | B18: =(B14+B15)*'Tax Rates'!$B$47 -> 0 | C18: =(C14+C15)*'Tax Rates'!$B$47 -> 0 | D18: =(D14+D15)*'Tax Rates'!$B$47 -> 0 | E18: =SUM(B18:D18) -> 0
A19: Losses Paid (Net of Salvage & Subrogation) | B19: 0 | C19: 0 | D19: 0 | E19: =SUM(B19:D19) -> 0
A20: Defense & Cost Containment Expenses Paid | B20: 0 | C20: 0 | D20: 0 | E20: =SUM(B20:D20) -> 0
A21: Adjusting & Other Expenses Paid | B21: 0 | C21: 0 | D21: 0 | E21: =SUM(B21:D21) -> 0
A22: Premium Earned - YTD | B22: 0 | C22: 0 | D22: 0 | E22: =SUM(B22:D22) -> 0
A23: Policy Fees Earned - YTD | B23: 0 | C23: 0 | D23: 0 | E23: =SUM(B23:D23) -> 0
A24: Unearned Premium Reserves | B24: 0 | C24: 0 | D24: 0 | E24: =SUM(B24:D24) -> 0
A25: Direct Losses Unpaid | B25: 0 | C25: 0 | D25: 0 | E25: =SUM(B25:D25) -> 0
A26: Defense & Cost Containment Unpaid | B26: 0 | C26: 0 | D26: 0 | E26: =SUM(B26:D26) -> 0
A27: Adjusting & Other Unpaid | B27: 0 | C27: 0 | D27: 0 | E27: =SUM(B27:D27) -> 0
A29: ='MTHLY-TOTAL'!A31 -> Submitted by: ______________

Sheet MTHLY-SD
A1: =+'Cash Settlement'!A2 -> COMPANY: SOUTHLAKE SPECIALTY INSURANCE COMPANY
A2: =+'Cash Settlement'!A1 -> PRODUCER: FUTURISTIC UNDERWRITERS LLC. | D2: Input area
A3: EXHIBIT OF PREMIUMS AND LOSSES
A4: FOR THE MONTH OF | C4: =+'Cash Settlement'!C9 -> 46142
A6: BY LINE, BY STATE
B11: 19.3 | C11: 19.4 | D11: 21.2
A12: =+'MTHLY-TOTAL'!A10 -> TREATY YEAR : 5/1/2020 | B12: Comm'l Auto | C12: Other Comm'l | D12: Comm'l Auto | E12: TOTALS
B13: No-Fault | C13: Auto Liab | D13: Phys. Damage
A14: Premiums Written | B14: 0 | C14: 0 | D14: 0 | E14: =SUM(B14:D14) -> 0
A15: Policy Fees Written | B15: 0 | C15: 0 | D15: 0 | E15: =SUM(B15:D15) -> 0
A16: Premiums Collected | B16: 0 | C16: 0 | D16: 0 | E16: =SUM(B16:D16) -> 0
A17: Policy Fees Collected | B17: 0 | C17: 0 | D17: 0 | E17: =SUM(B17:D17) -> 0
A18: Premium Taxes | B18: =(B14+B15)*'Tax Rates'!$B$48 -> 0 | C18: =(C14+C15)*'Tax Rates'!$B$48 -> 0 | D18: =(D14+D15)*'Tax Rates'!$B$48 -> 0 | E18: =SUM(B18:D18) -> 0
A19: Losses Paid (Net of Salvage & Subrogation) | B19: 0 | C19: 0 | D19: 0 | E19: =SUM(B19:D19) -> 0
A20: Defense & Cost Containment Expenses Paid | B20: 0 | C20: 0 | D20: 0 | E20: =SUM(B20:D20) -> 0
A21: Adjusting & Other Expenses Paid | B21: 0 | C21: 0 | D21: 0 | E21: =SUM(B21:D21) -> 0
A22: Premium Earned - YTD | B22: 0 | C22: 0 | D22: 0 | E22: =SUM(B22:D22) -> 0
A23: Policy Fees Earned - YTD | B23: 0 | C23: 0 | D23: 0 | E23: =SUM(B23:D23) -> 0
A24: Unearned Premium Reserves | B24: 0 | C24: 0 | D24: 0 | E24: =SUM(B24:D24) -> 0
A25: Direct Losses Unpaid | B25: 0 | C25: 0 | D25: 0 | E25: =SUM(B25:D25) -> 0
A26: Defense & Cost Containment Unpaid | B26: 0 | C26: 0 | D26: 0 | E26: =SUM(B26:D26) -> 0
A27: Adjusting & Other Unpaid | B27: 0 | C27: 0 | D27: 0 | E27: =SUM(B27:D27) -> 0
A29: ='MTHLY-TOTAL'!A31 -> Submitted by: ______________

Sheet MTHLY-TN
A1: =+'Cash Settlement'!A2 -> COMPANY: SOUTHLAKE SPECIALTY INSURANCE COMPANY
A2: =+'Cash Settlement'!A1 -> PRODUCER: FUTURISTIC UNDERWRITERS LLC. | D2: Input area
A3: EXHIBIT OF PREMIUMS AND LOSSES
A4: FOR THE MONTH OF | C4: =+'Cash Settlement'!C9 -> 46142
A6: BY LINE, BY STATE
B11: 19.3 | C11: 19.4 | D11: 21.2
A12: =+'MTHLY-TOTAL'!A10 -> TREATY YEAR : 5/1/2020 | B12: Comm'l Auto | C12: Other Comm'l | D12: Comm'l Auto | E12: TOTALS
B13: No-Fault | C13: Auto Liab | D13: Phys. Damage
A14: Premiums Written | B14: 0 | C14: 0 | D14: 0 | E14: =SUM(B14:D14) -> 0
A15: Policy Fees Written | B15: 0 | C15: 0 | D15: 0 | E15: =SUM(B15:D15) -> 0
A16: Premiums Collected | B16: 0 | C16: 0 | D16: 0 | E16: =SUM(B16:D16) -> 0
A17: Policy Fees Collected | B17: 0 | C17: 0 | D17: 0 | E17: =SUM(B17:D17) -> 0
A18: Premium Taxes | B18: =(B14+B15)*'Tax Rates'!$B$49 -> 0 | C18: =(C14+C15)*'Tax Rates'!$B$49 -> 0 | D18: =(D14+D15)*'Tax Rates'!$B$49 -> 0 | E18: =SUM(B18:D18) -> 0
A19: Losses Paid (Net of Salvage & Subrogation) | B19: 0 | C19: 0 | D19: 0 | E19: =SUM(B19:D19) -> 0
A20: Defense & Cost Containment Expenses Paid | B20: 0 | C20: 0 | D20: 0 | E20: =SUM(B20:D20) -> 0
A21: Adjusting & Other Expenses Paid | B21: 0 | C21: 0 | D21: 0 | E21: =SUM(B21:D21) -> 0
A22: Premium Earned - YTD | B22: 0 | C22: 0 | D22: 0 | E22: =SUM(B22:D22) -> 0
A23: Policy Fees Earned - YTD | B23: 0 | C23: 0 | D23: 0 | E23: =SUM(B23:D23) -> 0
A24: Unearned Premium Reserves | B24: 0 | C24: 0 | D24: 0 | E24: =SUM(B24:D24) -> 0
A25: Direct Losses Unpaid | B25: 0 | C25: 0 | D25: 0 | E25: =SUM(B25:D25) -> 0
A26: Defense & Cost Containment Unpaid | B26: 0 | C26: 0 | D26: 0 | E26: =SUM(B26:D26) -> 0
A27: Adjusting & Other Unpaid | B27: 0 | C27: 0 | D27: 0 | E27: =SUM(B27:D27) -> 0
A29: ='MTHLY-TOTAL'!A31 -> Submitted by: ______________

Sheet MTHLY-TX
A1: =+'Cash Settlement'!A2 -> COMPANY: SOUTHLAKE SPECIALTY INSURANCE COMPANY
A2: =+'Cash Settlement'!A1 -> PRODUCER: FUTURISTIC UNDERWRITERS LLC. | D2: Input area
A3: EXHIBIT OF PREMIUMS AND LOSSES
A4: FOR THE MONTH OF | C4: September-25
A6: BY LINE, BY STATE | C6: TX
B11: 9 | C11: 19.4 | D11: 21.2
A12: =+'MTHLY-TOTAL'!A10 -> TREATY YEAR : 5/1/2020 | B12: Comm'l Auto | C12: Other Comm'l | D12: Comm'l Auto | E12: TOTALS
B13: Inland Marine | C13: Auto Liab | D13: Phys. Damage
A14: Premiums Written | B14: 0 | C14: 0 | D14: 2202.3 | E14: =SUM(B14:D14) -> 2202.3
A15: Policy Fees Written | B15: 0 | D15: 0 | E15: =SUM(B15:D15) -> 0
A16: Premiums Collected | B16: 0 | C16: 0 | D16: 2202.3 | E16: =SUM(B16:D16) -> 2202.3
A17: Policy Fees Collected | B17: 0 | C17: 0 | D17: 0 | E17: =SUM(B17:D17) -> 0
A18: Premium Taxes | B18: =(B14+B15)*'Tax Rates'!$B$50 -> 0 | E18: =SUM(B18:D18) -> 0
A19: Losses Paid (Net of Salvage & Subrogation) | B19: 0 | C19: 0 | D19: 69000 | E19: =SUM(B19:D19) -> 69000
A20: Defense & Cost Containment Expenses Paid | B20: 0 | C20: 0 | D20: 0 | E20: =SUM(B20:D20) -> 0
A21: Adjusting & Other Expenses Paid | B21: 0 | C21: 0 | D21: 154.161 | E21: =SUM(B21:D21) -> 154.161
A22: Premium Earned - YTD | B22: 0 | C22: 0 | D22: 169293.16 | E22: =SUM(B22:D22) -> 169293.16
A23: Policy Fees Earned - YTD | B23: 0 | D23: 0 | E23: =SUM(B23:D23) -> 0
A24: Unearned Premium Reserves | B24: 0 | C24: 0 | D24: 142071.06 | E24: =SUM(B24:D24) -> 142071.06
A25: Direct Losses Unpaid | B25: 0 | C25: 0 | D25: 5000 | E25: =SUM(B25:D25) -> 5000
A26: Defense & Cost Containment Unpaid | B26: 0 | C26: 0 | D26: 4195 | E26: =SUM(B26:D26) -> 4195
A27: Adjusting & Other Unpaid | B27: 0 | C27: 0 | D27: 0 | E27: =SUM(B27:D27) -> 0
A29: ='MTHLY-TOTAL'!A31 -> Submitted by: ______________

Sheet MTHLY-UT
A1: =+'Cash Settlement'!A2 -> COMPANY: SOUTHLAKE SPECIALTY INSURANCE COMPANY
A2: =+'Cash Settlement'!A1 -> PRODUCER: FUTURISTIC UNDERWRITERS LLC. | D2: Input area
A3: EXHIBIT OF PREMIUMS AND LOSSES
A4: FOR THE MONTH OF | C4: =+'Cash Settlement'!C9 -> 46142
A6: BY LINE, BY STATE
B11: 19.3 | C11: 19.4 | D11: 21.2
A12: =+'MTHLY-TOTAL'!A10 -> TREATY YEAR : 5/1/2020 | B12: Comm'l Auto | C12: Other Comm'l | D12: Comm'l Auto | E12: TOTALS
B13: No-Fault | C13: Auto Liab | D13: Phys. Damage
A14: Premiums Written | B14: 0 | C14: 0 | D14: 0 | E14: =SUM(B14:D14) -> 0
A15: Policy Fees Written | B15: 0 | C15: 0 | D15: 0 | E15: =SUM(B15:D15) -> 0
A16: Premiums Collected | B16: 0 | C16: 0 | D16: 0 | E16: =SUM(B16:D16) -> 0
A17: Policy Fees Collected | B17: 0 | C17: 0 | D17: 0 | E17: =SUM(B17:D17) -> 0
A18: Premium Taxes | B18: =(B14+B15)*'Tax Rates'!$B$51 -> 0 | C18: =(C14+C15)*'Tax Rates'!$B$51 -> 0 | D18: =(D14+D15)*'Tax Rates'!$B$51 -> 0 | E18: =SUM(B18:D18) -> 0
A19: Losses Paid (Net of Salvage & Subrogation) | B19: 0 | C19: 0 | D19: 0 | E19: =SUM(B19:D19) -> 0
A20: Defense & Cost Containment Expenses Paid | B20: 0 | C20: 0 | D20: 0 | E20: =SUM(B20:D20) -> 0
A21: Adjusting & Other Expenses Paid | B21: 0 | C21: 0 | D21: 0 | E21: =SUM(B21:D21) -> 0
A22: Premium Earned - YTD | B22: 0 | C22: 0 | D22: 0 | E22: =SUM(B22:D22) -> 0
A23: Policy Fees Earned - YTD | B23: 0 | C23: 0 | D23: 0 | E23: =SUM(B23:D23) -> 0
A24: Unearned Premium Reserves | B24: 0 | C24: 0 | D24: 0 | E24: =SUM(B24:D24) -> 0
A25: Direct Losses Unpaid | B25: 0 | C25: 0 | D25: 0 | E25: =SUM(B25:D25) -> 0
A26: Defense & Cost Containment Unpaid | B26: 0 | C26: 0 | D26: 0 | E26: =SUM(B26:D26) -> 0
A27: Adjusting & Other Unpaid | B27: 0 | C27: 0 | D27: 0 | E27: =SUM(B27:D27) -> 0
A29: ='MTHLY-TOTAL'!A31 -> Submitted by: ______________

Sheet MTHLY-VA
A1: =+'Cash Settlement'!A2 -> COMPANY: SOUTHLAKE SPECIALTY INSURANCE COMPANY
A2: =+'Cash Settlement'!A1 -> PRODUCER: FUTURISTIC UNDERWRITERS LLC. | D2: Input area
A3: EXHIBIT OF PREMIUMS AND LOSSES
A4: FOR THE MONTH OF | C4: =+'Cash Settlement'!C9 -> 46142
A6: BY LINE, BY STATE
B11: 19.3 | C11: 19.4 | D11: 21.2
A12: =+'MTHLY-TOTAL'!A10 -> TREATY YEAR : 5/1/2020 | B12: Comm'l Auto | C12: Other Comm'l | D12: Comm'l Auto | E12: TOTALS
B13: No-Fault | C13: Auto Liab | D13: Phys. Damage
A14: Premiums Written | B14: 0 | C14: 0 | D14: -1574.95 | E14: =SUM(B14:D14) -> -1574.95
A15: Policy Fees Written | B15: 0 | C15: 0 | D15: 0 | E15: =SUM(B15:D15) -> 0
A16: Premiums Collected | B16: 0 | C16: 0 | D16: -1574.95 | E16: =SUM(B16:D16) -> -1574.95
A17: Policy Fees Collected | B17: 0 | C17: 0 | D17: 0 | E17: =SUM(B17:D17) -> 0
A18: Premium Taxes | B18: =(B14+B15)*'Tax Rates'!$B$53 -> 0 | C18: =(C14+C15)*'Tax Rates'!$B$53 -> 0 | E18: =SUM(B18:D18) -> 0
A19: Losses Paid (Net of Salvage & Subrogation) | B19: 0 | C19: 0 | D19: 0 | E19: =SUM(B19:D19) -> 0
A20: Defense & Cost Containment Expenses Paid | B20: 0 | C20: 0 | D20: 0 | E20: =SUM(B20:D20) -> 0
A21: Adjusting & Other Expenses Paid | B21: 0 | C21: 0 | D21: -110.2465 | E21: =SUM(B21:D21) -> -110.2465
A22: Premium Earned - YTD | B22: 0 | C22: 0 | D22: 44001.62 | E22: =SUM(B22:D22) -> 44001.62
A23: Policy Fees Earned - YTD | B23: 0 | C23: 0 | D23: 0 | E23: =SUM(B23:D23) -> 0
A24: Unearned Premium Reserves | B24: 0 | C24: 0 | D24: 34011.53 | E24: =SUM(B24:D24) -> 34011.53
A25: Direct Losses Unpaid | B25: 0 | C25: 0 | D25: 21833 | E25: =SUM(B25:D25) -> 21833
A26: Defense & Cost Containment Unpaid | B26: 0 | C26: 0 | D26: 2500 | E26: =SUM(B26:D26) -> 2500
A27: Adjusting & Other Unpaid | B27: 0 | C27: 0 | D27: 0 | E27: =SUM(B27:D27) -> 0
A29: ='MTHLY-TOTAL'!A31 -> Submitted by: ______________

Sheet MTHLY-VT
A1: =+'Cash Settlement'!A2 -> COMPANY: SOUTHLAKE SPECIALTY INSURANCE COMPANY
A2: =+'Cash Settlement'!A1 -> PRODUCER: FUTURISTIC UNDERWRITERS LLC. | D2: Input area
A3: EXHIBIT OF PREMIUMS AND LOSSES
A4: FOR THE MONTH OF | C4: =+'Cash Settlement'!C9 -> 46142
A6: BY LINE, BY STATE
B11: 19.3 | C11: 19.4 | D11: 21.2
A12: =+'MTHLY-TOTAL'!A10 -> TREATY YEAR : 5/1/2020 | B12: Comm'l Auto | C12: Other Comm'l | D12: Comm'l Auto | E12: TOTALS
B13: No-Fault | C13: Auto Liab | D13: Phys. Damage
A14: Premiums Written | B14: 0 | C14: 0 | D14: 0 | E14: =SUM(B14:D14) -> 0
A15: Policy Fees Written | B15: 0 | C15: 0 | D15: 0 | E15: =SUM(B15:D15) -> 0
A16: Premiums Collected | B16: 0 | C16: 0 | D16: 0 | E16: =SUM(B16:D16) -> 0
A17: Policy Fees Collected | B17: 0 | C17: 0 | D17: 0 | E17: =SUM(B17:D17) -> 0
A18: Premium Taxes | B18: =(B14+B15)*'Tax Rates'!$B$52 -> 0 | C18: =(C14+C15)*'Tax Rates'!$B$52 -> 0 | D18: =(D14+D15)*'Tax Rates'!$B$52 -> 0 | E18: =SUM(B18:D18) -> 0
A19: Losses Paid (Net of Salvage & Subrogation) | B19: 0 | C19: 0 | D19: 0 | E19: =SUM(B19:D19) -> 0
A20: Defense & Cost Containment Expenses Paid | B20: 0 | C20: 0 | D20: 0 | E20: =SUM(B20:D20) -> 0
A21: Adjusting & Other Expenses Paid | B21: 0 | C21: 0 | D21: 0 | E21: =SUM(B21:D21) -> 0
A22: Premium Earned - YTD | B22: 0 | C22: 0 | D22: 0 | E22: =SUM(B22:D22) -> 0
A23: Policy Fees Earned - YTD | B23: 0 | C23: 0 | D23: 0 | E23: =SUM(B23:D23) -> 0
A24: Unearned Premium Reserves | B24: 0 | C24: 0 | D24: 0 | E24: =SUM(B24:D24) -> 0
A25: Direct Losses Unpaid | B25: 0 | C25: 0 | D25: 0 | E25: =SUM(B25:D25) -> 0
A26: Defense & Cost Containment Unpaid | B26: 0 | C26: 0 | D26: 0 | E26: =SUM(B26:D26) -> 0
A27: Adjusting & Other Unpaid | B27: 0 | C27: 0 | D27: 0 | E27: =SUM(B27:D27) -> 0
A29: ='MTHLY-TOTAL'!A31 -> Submitted by: ______________

Sheet MTHLY-WA
A1: =+'Cash Settlement'!A2 -> COMPANY: SOUTHLAKE SPECIALTY INSURANCE COMPANY
A2: =+'Cash Settlement'!A1 -> PRODUCER: FUTURISTIC UNDERWRITERS LLC. | D2: Input area
A3: EXHIBIT OF PREMIUMS AND LOSSES
A4: FOR THE MONTH OF | C4: =+'Cash Settlement'!C9 -> 46142
A6: BY LINE, BY STATE
B11: 19.3 | C11: 19.4 | D11: 21.2
A12: =+'MTHLY-TOTAL'!A10 -> TREATY YEAR : 5/1/2020 | B12: Comm'l Auto | C12: Other Comm'l | D12: Comm'l Auto | E12: TOTALS
B13: No-Fault | C13: Auto Liab | D13: Phys. Damage
A14: Premiums Written | B14: 0 | C14: 0 | D14: -1511 | E14: =SUM(B14:D14) -> -1511
A15: Policy Fees Written | B15: 0 | C15: 0 | D15: 0 | E15: =SUM(B15:D15) -> 0
A16: Premiums Collected | B16: 0 | C16: 0 | D16: -1511 | E16: =SUM(B16:D16) -> -1511
A17: Policy Fees Collected | B17: 0 | C17: 0 | D17: 0 | E17: =SUM(B17:D17) -> 0
A18: Premium Taxes | B18: =(B14+B15)*'Tax Rates'!$B$54 -> 0 | C18: =(C14+C15)*'Tax Rates'!$B$54 -> 0 | E18: =SUM(B18:D18) -> 0
A19: Losses Paid (Net of Salvage & Subrogation) | B19: 0 | C19: 0 | D19: 0 | E19: =SUM(B19:D19) -> 0
A20: Defense & Cost Containment Expenses Paid | B20: 0 | C20: 0 | D20: 0 | E20: =SUM(B20:D20) -> 0
A21: Adjusting & Other Expenses Paid | B21: 0 | C21: 0 | D21: -105.77 | E21: =SUM(B21:D21) -> -105.77
A22: Premium Earned - YTD | B22: 0 | C22: 0 | D22: 7094.95 | E22: =SUM(B22:D22) -> 7094.95
A23: Policy Fees Earned - YTD | B23: 0 | C23: 0 | D23: 0 | E23: =SUM(B23:D23) -> 0
A24: Unearned Premium Reserves | B24: 0 | C24: 0 | D24: 3425.27 | E24: =SUM(B24:D24) -> 3425.27
A25: Direct Losses Unpaid | B25: 0 | C25: 0 | D25: 10000 | E25: =SUM(B25:D25) -> 10000
A26: Defense & Cost Containment Unpaid | B26: 0 | C26: 0 | D26: 2500 | E26: =SUM(B26:D26) -> 2500
A27: Adjusting & Other Unpaid | B27: 0 | C27: 0 | D27: 0 | E27: =SUM(B27:D27) -> 0
A29: ='MTHLY-TOTAL'!A31 -> Submitted by: ______________

Sheet MTHLY-WI
A1: =+'Cash Settlement'!A2 -> COMPANY: SOUTHLAKE SPECIALTY INSURANCE COMPANY
A2: =+'Cash Settlement'!A1 -> PRODUCER: FUTURISTIC UNDERWRITERS LLC. | D2: Input area
A3: EXHIBIT OF PREMIUMS AND LOSSES
A4: FOR THE MONTH OF | C4: =+'Cash Settlement'!C9 -> 46142
A6: BY LINE, BY STATE
B11: 19.3 | C11: 19.4 | D11: 21.2
A12: =+'MTHLY-TOTAL'!A10 -> TREATY YEAR : 5/1/2020 | B12: Comm'l Auto | C12: Other Comm'l | D12: Comm'l Auto | E12: TOTALS
B13: No-Fault | C13: Auto Liab | D13: Phys. Damage
A14: Premiums Written | B14: 0 | C14: 0 | D14: 0 | E14: =SUM(B14:D14) -> 0
A15: Policy Fees Written | B15: 0 | C15: 0 | D15: 0 | E15: =SUM(B15:D15) -> 0
A16: Premiums Collected | B16: 0 | C16: 0 | D16: 0 | E16: =SUM(B16:D16) -> 0
A17: Policy Fees Collected | B17: 0 | C17: 0 | D17: 0 | E17: =SUM(B17:D17) -> 0
A18: Premium Taxes | B18: =(B14+B15)*'Tax Rates'!$B$56 -> 0 | C18: =(C14+C15)*'Tax Rates'!$B$56 -> 0 | E18: =SUM(B18:D18) -> 0
A19: Losses Paid (Net of Salvage & Subrogation) | B19: 0 | C19: 0 | D19: 0 | E19: =SUM(B19:D19) -> 0
A20: Defense & Cost Containment Expenses Paid | B20: 0 | C20: 0 | D20: 0 | E20: =SUM(B20:D20) -> 0
A21: Adjusting & Other Expenses Paid | B21: 0 | C21: 0 | D21: 0 | E21: =SUM(B21:D21) -> 0
A22: Premium Earned - YTD | B22: 0 | C22: 0 | D22: 0 | E22: =SUM(B22:D22) -> 0
A23: Policy Fees Earned - YTD | B23: 0 | C23: 0 | D23: 0 | E23: =SUM(B23:D23) -> 0
A24: Unearned Premium Reserves | B24: 0 | C24: 0 | D24: 0 | E24: =SUM(B24:D24) -> 0
A25: Direct Losses Unpaid | B25: 0 | C25: 0 | D25: 0 | E25: =SUM(B25:D25) -> 0
A26: Defense & Cost Containment Unpaid | B26: 0 | C26: 0 | D26: 0 | E26: =SUM(B26:D26) -> 0
A27: Adjusting & Other Unpaid | B27: 0 | C27: 0 | D27: 0 | E27: =SUM(B27:D27) -> 0
A29: ='MTHLY-TOTAL'!A31 -> Submitted by: ______________

Sheet MTHLY-WV
A1: =+'Cash Settlement'!A2 -> COMPANY: SOUTHLAKE SPECIALTY INSURANCE COMPANY
A2: =+'Cash Settlement'!A1 -> PRODUCER: FUTURISTIC UNDERWRITERS LLC. | D2: Input area
A3: EXHIBIT OF PREMIUMS AND LOSSES
A4: FOR THE MONTH OF | C4: =+'Cash Settlement'!C9 -> 46142
A6: BY LINE, BY STATE
B11: 19.3 | C11: 19.4 | D11: 21.2
A12: =+'MTHLY-TOTAL'!A10 -> TREATY YEAR : 5/1/2020 | B12: Comm'l Auto | C12: Other Comm'l | D12: Comm'l Auto | E12: TOTALS
B13: No-Fault | C13: Auto Liab | D13: Phys. Damage
A14: Premiums Written | B14: 0 | C14: 0 | D14: 0 | E14: =SUM(B14:D14) -> 0
A15: Policy Fees Written | B15: 0 | C15: 0 | D15: 0 | E15: =SUM(B15:D15) -> 0
A16: Premiums Collected | B16: 0 | C16: 0 | D16: 0 | E16: =SUM(B16:D16) -> 0
A17: Policy Fees Collected | B17: 0 | C17: 0 | D17: 0 | E17: =SUM(B17:D17) -> 0
A18: Premium Taxes | B18: =(B14+B15)*'Tax Rates'!$B$55 -> 0 | C18: =(C14+C15)*'Tax Rates'!$B$55 -> 0 | D18: =(D14+D15)*'Tax Rates'!$B$55 -> 0 | E18: =SUM(B18:D18) -> 0
A19: Losses Paid (Net of Salvage & Subrogation) | B19: 0 | C19: 0 | D19: 0 | E19: =SUM(B19:D19) -> 0
A20: Defense & Cost Containment Expenses Paid | B20: 0 | C20: 0 | D20: 0 | E20: =SUM(B20:D20) -> 0
A21: Adjusting & Other Expenses Paid | B21: 0 | C21: 0 | D21: 0 | E21: =SUM(B21:D21) -> 0
A22: Premium Earned - YTD | B22: 0 | C22: 0 | D22: 0 | E22: =SUM(B22:D22) -> 0
A23: Policy Fees Earned - YTD | B23: 0 | C23: 0 | D23: 0 | E23: =SUM(B23:D23) -> 0
A24: Unearned Premium Reserves | B24: 0 | C24: 0 | D24: 0 | E24: =SUM(B24:D24) -> 0
A25: Direct Losses Unpaid | B25: 0 | C25: 0 | D25: 0 | E25: =SUM(B25:D25) -> 0
A26: Defense & Cost Containment Unpaid | B26: 0 | C26: 0 | D26: 0 | E26: =SUM(B26:D26) -> 0
A27: Adjusting & Other Unpaid | B27: 0 | C27: 0 | D27: 0 | E27: =SUM(B27:D27) -> 0
A29: ='MTHLY-TOTAL'!A31 -> Submitted by: ______________

Sheet MTHLY-WY
A1: =+'Cash Settlement'!A2 -> COMPANY: SOUTHLAKE SPECIALTY INSURANCE COMPANY
A2: =+'Cash Settlement'!A1 -> PRODUCER: FUTURISTIC UNDERWRITERS LLC. | D2: Input area
A3: EXHIBIT OF PREMIUMS AND LOSSES
A4: FOR THE MONTH OF | C4: =+'Cash Settlement'!C9 -> 46142
A6: BY LINE, BY STATE
B11: 19.3 | C11: 19.4 | D11: 21.2
A12: =+'MTHLY-TOTAL'!A10 -> TREATY YEAR : 5/1/2020 | B12: Comm'l Auto | C12: Other Comm'l | D12: Comm'l Auto | E12: TOTALS
B13: No-Fault | C13: Auto Liab | D13: Phys. Damage
A14: Premiums Written | B14: 0 | C14: 0 | D14: 0 | E14: =SUM(B14:D14) -> 0
A15: Policy Fees Written | B15: 0 | C15: 0 | D15: 0 | E15: =SUM(B15:D15) -> 0
A16: Premiums Collected | B16: 0 | C16: 0 | D16: 0 | E16: =SUM(B16:D16) -> 0
A17: Policy Fees Collected | B17: 0 | C17: 0 | D17: 0 | E17: =SUM(B17:D17) -> 0
A18: Premium Taxes | B18: =(B14+B15)*'Tax Rates'!$B$57 -> 0 | C18: =(C14+C15)*'Tax Rates'!$B$57 -> 0 | D18: =(D14+D15)*'Tax Rates'!$B$57 -> 0 | E18: =SUM(B18:D18) -> 0
A19: Losses Paid (Net of Salvage & Subrogation) | B19: 0 | C19: 0 | D19: 0 | E19: =SUM(B19:D19) -> 0
A20: Defense & Cost Containment Expenses Paid | B20: 0 | C20: 0 | D20: 0 | E20: =SUM(B20:D20) -> 0
A21: Adjusting & Other Expenses Paid | B21: 0 | C21: 0 | D21: 0 | E21: =SUM(B21:D21) -> 0
A22: Premium Earned - YTD | B22: 0 | C22: 0 | D22: 0 | E22: =SUM(B22:D22) -> 0
A23: Policy Fees Earned - YTD | B23: 0 | C23: 0 | D23: 0 | E23: =SUM(B23:D23) -> 0
A24: Unearned Premium Reserves | B24: 0 | C24: 0 | D24: 0 | E24: =SUM(B24:D24) -> 0
A25: Direct Losses Unpaid | B25: 0 | C25: 0 | D25: 0 | E25: =SUM(B25:D25) -> 0
A26: Defense & Cost Containment Unpaid | B26: 0 | C26: 0 | D26: 0 | E26: =SUM(B26:D26) -> 0
A27: Adjusting & Other Unpaid | B27: 0 | C27: 0 | D27: 0 | E27: =SUM(B27:D27) -> 0
A29: ='MTHLY-TOTAL'!A31 -> Submitted by: ______________

Sheet Policies In force
A1: ='Paids --yr end'!A1 -> NTA - 1/1/2013
A2: Policies in force at 11/30/2013 | E2: INPUT AREA
A3: ='Paids --yr end'!A3 -> Line of Business (Annual Statement Lines)
A4: =Premiums!A4 -> STATE NATIONAL INSURANCE COMPANY
B5: *Note: Because some polices may have more than one line of coverage, please KEY in the total number of policies in column E (DO NOT create a formula in col E to sum the row)
A10: STATE | B10: =Premiums!B7 -> 19.3 | C10: =Premiums!C7 -> 19.4 | D10: =Premiums!D7 -> 21.2 | E10: TOTAL*
A11: Alabama | B11: 0 | C11: 0 | D11: 0 | E11: =C11+D11 -> 0
A12: Alaska | B12: 0 | C12: 0 | D12: 0 | E12: =C12+D12 -> 0
A13: Arizona | B13: 0 | C13: 0 | D13: 6 | E13: =C13+D13 -> 6
A14: Arkansas | B14: 0 | C14: 0 | D14: 0 | E14: =C14+D14 -> 0
A15: California | B15: 0 | C15: 0 | D15: 219 | E15: =C15+D15 -> 219
A16: Colorado | B16: 0 | C16: 0 | D16: 0 | E16: =C16+D16 -> 0
A17: Connecticut | B17: 0 | C17: 0 | D17: 0 | E17: =C17+D17 -> 0
A18: Delaware | B18: 0 | C18: 0 | D18: 0 | E18: =C18+D18 -> 0
A19: Florida | B19: 0 | C19: 0 | D19: 0 | E19: =C19+D19 -> 0
A20: Georgia | B20: 0 | C20: 0 | D20: 3 | E20: =C20+D20 -> 3
A21: Hawaii | B21: 0 | C21: 0 | D21: 0 | E21: =C21+D21 -> 0
A22: Idaho | B22: 0 | C22: 0 | D22: 0 | E22: =C22+D22 -> 0
... A60: Wyoming | B60: 0 | C60: 0 | D60: 0 | E60: =C60+D60 -> 0
C61: =SUM(C11:C60) -> 0 | D61: =SUM(D11:D60) -> 283 | E61: =SUM(E11:E60) -> 283

Sheet Tax Rates
A1: STATE PREMIUM TAX RATES FOR 2012
B4: State Tax
A5: STATE | B5: Rates
A7: ALABAMA | B7: 0.04906
A8: ALASKA | B8: 0.027
A9: ARIZONA | B9: 0.02375
A10: ARKANSAS | B10: 0.03
A11: CALIFORNIA | B11: 0.0235
A12: COLORADO | B12: 0.02
A13: CONNECTICUT | B13: 0.0175
A14: DELAWARE | B14: 0.02
A15: DISTRICT OF COLUMBIA | B15: 0.0174
A16: FLORIDA | B16: 0.01804
A17: GEORGIA | B17: 0.04987
A18: HAWAII | B18: 0.04265
... A57: WYOMING | B57: 0.0174
A61: Source: Premium Pro State Rates Schedule and various state tax return
A62: For purpose of retaliatory tax use TX 2002 Actual Tax Rate of 1.793%

Sheet Premiums
A1: NTA - 1/1/2013
A2: Premiums
A3: Line of Business (Annual Statement Lines) | B3: 2013
A4: STATE NATIONAL INSURANCE COMPANY | C4: INPUT AREA
A7: Premium Written | B7: 19.3 | C7: 19.4 | D7: 21.2 | E7: Total
A8: Reported by Sample Dec. 2012-Nov. 2013 | B8: 0 | C8: 0 | D8: 0 | E8: =SUM(B8:D8) -> 0
A10: Unearned Premium
A11: Reported by Sample @ 11/30/13 | B11: 0 | C11: 0 | D11: 0 | E11: =SUM(B11:D11) -> 0
A14: TOTAL PER PASS
B15: =B7 -> 19.3 | C15: =C7 -> 19.4 | D15: =D7 -> 21.2 | E15: Total
A16: Premium Written | B16: 0 | C16: 0 | D16: 0 | E16: =SUM(B16:D16) -> 0
A18: Unearned Premium | B18: 0 | C18: 0 | D18: 0 | E18: =SUM(B18:D18) -> 0
A21: DIFFERENCES
B22: =B7 -> 19.3 | C22: =C7 -> 19.4 | D22: =D7 -> 21.2 | E22: Total
A23: Premium Written | B23: =B16-B8 -> 0 | C23: =C16-C8 -> 0 | D23: =D16-D8 -> 0 | E23: =SUM(B23:D23) -> 0
A25: Unearned Premium | B25: =+B18-B11 -> 0 | C25: =+C18-C11 -> 0 | D25: =+D18-D11 -> 0 | E25: =SUM(B25:D25) -> 0
A28: RECONCILIATION
A29: Premium Written
A30: 12/2011 Accrual Reversal | B30: 0 | C30: 0 | D30: 0 | E30: =SUM(B30:D30) -> 0
A31: 12/2012 Accrual | B31: 0 | C31: 0 | D31: 0 | E31: =SUM(B31:D31) -> 0
A32: Corrections | B32: 0 | C32: 0 | D32: 0 | E32: =SUM(B32:D32) -> 0
B33: =SUM(B30:B32) -> 0 | C33: =SUM(C30:C32) -> 0 | D33: =SUM(D30:D32) -> 0 | E33: =SUM(B33:D33) -> 0
A35: Unearned Premium
A36: 12/2012 Accrual | B36: 0 | C36: 0 | D36: 0 | E36: =SUM(B36:D36) -> 0

Sheet Paids --yr end
A1: =+Premiums!A1 -> NTA - 1/1/2013
A2: Paid By Accident Year | C2: =Premiums!B3 -> 2013 | E2: INPUT AREA
A3: Line of Business (Annual Statement Lines)
A4: =Premiums!A4 -> STATE NATIONAL INSURANCE COMPANY
A6: LOB
A8: 2018 | B8: Accident | C8: Losses | D8: ALAE | E8: ULAE | F8: Salvage/Subro
B9: Year | C9: Paid | D9: Paid | E9: Paid | F9: Received
A11: =Premiums!$B$7 -> 19.3 | B11: =A8 -> 2018 | C11: 0 | D11: 0 | E11: 0 | F11: 0
A12: =Premiums!$C$7 -> 19.4 | B12: =B11 -> 2018 | C12: 0 | D12: 0 | E12: 0 | F12: 0
A13: =Premiums!$D$7 -> 21.2 | B13: =B12 -> 2018 | C13: 0 | D13: 0 | E13: 0 | F13: 0
B15: Total | C15: =SUM(C11:C13) -> 0 | D15: =SUM(D11:D13) -> 0 | E15: =SUM(E11:E13) -> 0 | F15: =SUM(F11:F13) -> 0
A17: 2017 | B17: Accident | C17: Losses | D17: ALAE | E17: ULAE | F17: Salvage/Subro
B18: Year | C18: Paid | D18: Paid | E18: Paid | F18: Received
A20: =Premiums!$B$7 -> 19.3 | B20: =A17 -> 2017 | C20: 0 | D20: 0 | E20: 0 | F20: 0
A21: =Premiums!$C$7 -> 19.4 | B21: =B20 -> 2017 | C21: 0 | D21: 0 | E21: 0 | F21: 0
A22: =Premiums!$D$7 -> 21.2 | B22: =B21 -> 2017 | C22: 0 | D22: 0 | E22: 0 | F22: 0
B24: Total | C24: =SUM(C20:C22) -> 0 | D24: =SUM(D20:D22) -> 0 | E24: =SUM(E20:E22) -> 0 | F24: =SUM(F20:F22) -> 0
A26: 2016 | B26: Accident | C26: Losses | D26: ALAE | E26: ULAE | F26: Salvage/Subro
B27: Year | C27: Paid | D27: Paid | E27: Paid | F27: Received
A29: =Premiums!$B$7 -> 19.3 | B29: =A26 -> 2016 | C29: 0 | D29: 0 | E29: 0 | F29: 0
A30: =Premiums!$C$7 -> 19.4 | B30: =B29 -> 2016 | C30: 0 | D30: 0 | E30: 0 | F30: 0
A31: =Premiums!$D$7 -> 21.2 | B31: =B30 -> 2016 | C31: 0 | D31: 0 | E31: 0 | F31: 0
B33: Total | C33: =SUM(C29:C31) -> 0 | D33: =SUM(D29:D31) -> 0 | E33: =SUM(E29:E31) -> 0 | F33: =SUM(F29:F31) -> 0
A35: 2015 | B35: Accident | C35: Losses | D35: ALAE | E35: ULAE | F35: Salvage/Subro
B36: Year | C36: Paid | D36: Paid | E36: Paid | F36: Received
A38: =Premiums!$B$7 -> 19.3 | B38: =A35 -> 2015 | C38: 0 | D38: 0 | E38: 0 | F38: 0
A39: =Premiums!$C$7 -> 19.4 | B39: =B38 -> 2015 | C39: 0 | D39: 0 | E39: 0 | F39: 0
A40: =Premiums!$D$7 -> 21.2 | B40: =B39 -> 2015 | C40: 0 | D40: 0 | E40: 0 | F40: 0
B42: Total | C42: =SUM(C38:C40) -> 0 | D42: =SUM(D38:D40) -> 0 | E42: =SUM(E38:E40) -> 0 | F42: =SUM(F38:F40) -> 0
A44: 2014 | B44: Accident | C44: Losses | D44: ALAE | E44: ULAE | F44: Salvage/Subro
B45: Year | C45: Paid | D45: Paid | E45: Paid | F45: Received
A47: =Premiums!$B$7 -> 19.3 | B47: =A44 -> 2014 | C47: 0 | D47: 0 | E47: 0 | F47: 0
A48: =Premiums!$C$7 -> 19.4 | B48: =B47 -> 2014 | C48: 0 | D48: 0 | E48: 0 | F48: 0
A49: =Premiums!$D$7 -> 21.2 | B49: =B48 -> 2014 | C49: 0 | D49: 0 | E49: 0 | F49: 0
B51: Total | C51: =SUM(C47:C49) -> 0 | D51: =SUM(D47:D49) -> 0 | E51: =SUM(E47:E49) -> 0 | F51: =SUM(F47:F49) -> 0
A53: 2013 | B53: Accident | C53: Losses | D53: ALAE | E53: ULAE | F53: Salvage/Subro
B54: Year | C54: Paid | D54: Paid | E54: Paid | F54: Received
A56: =Premiums!$B$7 -> 19.3 | B56: =A53 -> 2013 | C56: 0 | D56: 0 | E56: 0 | F56: 0
A57: =Premiums!$C$7 -> 19.4 | B57: =B56 -> 2013 | C57: 0 | D57: 0 | E57: 0 | F57: 0
A58: =Premiums!$D$7 -> 21.2 | B58: =B57 -> 2013 | C58: 0 | D58: 0 | E58: 0 | F58: 0
B60: Total | C60: =SUM(C56:C58) -> 0 | D60: =SUM(D56:D58) -> 0 | E60: =SUM(E56:E58) -> 0 | F60: =SUM(F56:F58) -> 0
A62: 2013 | B62: Accident | C62: Losses | D62: ALAE | E62: ULAE | F62: Salvage/Subro
B63: Year | C63: Paid | D63: Paid | E63: Paid | F63: Received
A65: =Premiums!$B$7 -> 19.3 | B65: =A62 -> 2013 | C65: 0 | D65: 0 | E65: 0 | F65: 0
A66: =Premiums!$C$7 -> 19.4 | B66: =B65 -> 2013 | C66: 0 | D66: 0 | E66: 0 | F66: 0
A67: =Premiums!$D$7 -> 21.2 | B67: =B66 -> 2013 | C67: 0 | D67: 0 | E67: 0 | F67: 0
B69: Total | C69: =SUM(C65:C67) -> 0 | D69: =SUM(D65:D67) -> 0 | E69: =SUM(E65:E67) -> 0 | F69: =SUM(F65:F67) -> 0
B72: All Accident Years | C72: Losses | D72: ALAE | E72: ULAE | F72: Salvage/Subro
B73: Total - Per program | C73: Paid | D73: Paid | E73: Paid | F73: Received
A75: =Premiums!$B$7 -> 19.3 | C75: =C11+C20+C29+C38+C47+C56+C65 -> 0 | D75: =D11+D20+D29+D38+D47+D56+D65 -> 0 | E75: =E11+E20+E29+E38+E47+E56+E65 -> 0 | F75: =F11+F20+F29+F38+F47+F56+F65 -> 0
A76: =Premiums!$C$7 -> 19.4 | C76: =C12+C21+C30+C39+C48+C57+C66 -> 0 | D76: =D12+D21+D30+D39+D48+D57+D66 -> 0 | E76: =E12+E21+E30+E39+E48+E57+E66 -> 0 | F76: =F12+F21+F30+F39+F48+F57+F66 -> 0
A77: =Premiums!$D$7 -> 21.2 | C77: =C13+C22+C31+C40+C49+C58+C67 -> 0 | D77: =D13+D22+D31+D40+D49+D58+D67 -> 0 | E77: =E13+E22+E31+E40+E49+E58+E67 -> 0 | F77: =F13+F22+F31+F40+F49+F58+F67 -> 0
B79: Total | C79: =SUM(C75:C77) -> 0 | D79: =SUM(D75:D77) -> 0 | E79: =SUM(E75:E77) -> 0 | F79: =SUM(F75:F77) -> 0
C82: Losses | D82: ALAE | E82: ULAE | F82: Salvage/Subro
B83: Total - Per PASS | C83: Paid | D83: Paid | E83: Paid | F83: Received
A85: =Premiums!$B$7 -> 19.3 | C85: 0 | D85: 0 | E85: 0 | F85: N/A
A86: =Premiums!$C$7 -> 19.4 | C86: 0 | D86: 0 | E86: 0 | F86: N/A
A87: =Premiums!$D$7 -> 21.2 | C87: 0 | D87: 0 | E87: 0 | F87: N/A
B89: Total | C89: =SUM(C85:C87) -> 0 | D89: =SUM(D85:D87) -> 0 | E89: =SUM(E85:E87) -> 0 | F89: N/A
C92: Losses | D92: ALAE | E92: ULAE | F92: Salvage/Subro
B93: DIFFERENCES | C93: Paid | D93: Paid | E93: Paid | F93: Received
A95: =Premiums!$B$7 -> 19.3 | C95: =C75-C85 -> 0 | D95: =D75-D85 -> 0 | E95: =E75-E85 -> 0 | F95: N/A
A96: =Premiums!$C$7 -> 19.4 | C96: =C76-C86 -> 0 | D96: =D76-D86 -> 0 | E96: =E76-E86 -> 0 | F96: N/A
A97: =Premiums!$D$7 -> 21.2 | C97: =C77-C87 -> 0 | D97: =D77-D87 -> 0 | E97: =E77-E87 -> 0 | F97: N/A
B99: Total | C99: =SUM(C95:C97) -> 0 | D99: =SUM(D95:D97) -> 0 | E99: =SUM(E95:E97) -> 0 | F99: N/A
A105: RECONCILIATION
C106: Losses | D106: ALAE | E106: ULAE | F106: Salvage/Subro
B107: =Premiums!A30 -> 12/2011 Accrual Reversal | C107: Paid | D107: Paid | E107: Paid | F107: Received
A109: =Premiums!$B$7 -> 19.3 | C109: 0 | D109: 0 | E109: 0 | F109: N/A
A110: =Premiums!$C$7 -> 19.4 | C110: 0 | D110: 0 | E110: 0 | F110: N/A
A111: =Premiums!$D$7 -> 21.2 | C111: 0 | D111: 0 | E111: 0 | F111: N/A
B113: Total | C113: =SUM(C109:C111) -> 0 | D113: =SUM(D109:D111) -> 0 | E113: =SUM(E109:E111) -> 0 | F113: N/A
C116: Losses | D116: ALAE | E116: ULAE | F116: Salvage/Subro
B117: =Premiums!A31 -> 12/2012 Accrual | C117: Paid | D117: Paid | E117: Paid | F117: Received
A119: =Premiums!$B$7 -> 19.3 | C119: 0 | D119: 0 | E119: 0 | F119: N/A
A120: =Premiums!$C$7 -> 19.4 | C120: 0 | D120: 0 | E120: 0 | F120: N/A
A121: =Premiums!$D$7 -> 21.2 | C121: 0 | D121: 0 | E121: 0 | F121: N/A
B123: Total | C123: =SUM(C119:C121) -> 0 | D123: =SUM(D119:D121) -> 0 | E123: =SUM(E119:E121) -> 0 | F123: N/A
C126: Losses | D126: ALAE | E126: ULAE | F126: Salvage/Subro
B127: Corrections | C127: Paid | D127: Paid | E127: Paid | F127: Received
A129: =Premiums!$B$7 -> 19.3 | C129: 0 | D129: 0 | E129: 0 | F129: N/A
A130: =Premiums!$C$7 -> 19.4 | C130: 0 | D130: 0 | E130: 0 | F130: N/A
A131: =Premiums!$D$7 -> 21.2 | C131: 0 | D131: 0 | E131: 0 | F131: N/A
B133: Total | C133: =SUM(C129:C131) -> 0 | D133: =SUM(D129:D131) -> 0 | E133: =SUM(E129:E131) -> 0 | F133: N/A
C136: Losses | D136: ALAE | E136: ULAE | F136: Salvage/Subro
B137: TOTAL | C137: Paid | D137: Paid | E137: Paid | F137: Received
A139: =Premiums!$B$7 -> 19.3 | C139: =+C129+C119+C109 -> 0 | D139: =+D129+D119+D109 -> 0 | E139: =+E129+E119+E109 -> 0 | F139: N/A
A140: =Premiums!$C$7 -> 19.4 | C140: =+C130+C120+C110 -> 0 | D140: =+D130+D120+D110 -> 0 | E140: =+E130+E120+E110 -> 0 | F140: N/A
A141: =Premiums!$D$7 -> 21.2 | C141: =+C131+C121+C111 -> 0 | D141: =+D131+D121+D111 -> 0 | E141: =+E131+E121+E111 -> 0 | F141: N/A
B143: Total | C143: =SUM(C139:C141) -> 0 | D143: =SUM(D139:D141) -> 0 | E143: =SUM(E139:E141) -> 0 | F143: N/A
A146: Diffrences | C146: Losses | D146: ALAE | E146: ULAE | F146: Salvage/Subro
B147: TOTAL | C147: Paid | D147: Paid | E147: Paid | F147: Received
A149: =Premiums!$B$7 -> 19.3 | C149: =C95+C139 -> 0 | D149: =D95+D139 -> 0 | E149: =E95+E139 -> 0 | F149: N/A
A150: =Premiums!$C$7 -> 19.4 | C150: =C96+C140 -> 0 | D150: =D96+D140 -> 0 | E150: =E96+E140 -> 0 | F150: N/A
A151: =Premiums!$D$7 -> 21.2 | C151: =C97+C141 -> 0 | D151: =D97+D141 -> 0 | E151: =E97+E141 -> 0 | F151: N/A
B153: Total | C153: =SUM(C149:C151) -> 0 | D153: =SUM(D149:D151) -> 0 | E153: =SUM(E149:E151) -> 0 | F153: N/A

Sheet Reserves --yr end
A1: ='Paids --yr end'!A1 -> NTA - 1/1/2013
A2: Reserves by Accident Year | C2: ='Paids --yr end'!C2 -> 2013 | E2: INPUT AREA
A3: ='Paids --yr end'!A3 -> Line of Business (Annual Statement Lines)
A4: =Premiums!A4 -> STATE NATIONAL INSURANCE COMPANY
A6: LOB
A8: 2018 | B8: Accident | C8: O/S Loss | D8: O/S ALAE | E8: O/S ULAE | F8: Salvage/Subro
B9: Year | C9: Reserve | D9: Reserve | E9: Reserve | F9: Reserve/Anticipated
A11: =Premiums!$B$7 -> 19.3 | B11: =A8 -> 2018 | C11: 0 | D11: 0 | E11: 0 | F11: 0
A12: =Premiums!$C$7 -> 19.4 | B12: =B11 -> 2018 | C12: 0 | D12: 0 | E12: 0 | F12: 0
A13: =Premiums!$D$7 -> 21.2 | B13: =B12 -> 2018 | C13: 0 | D13: 0 | E13: 0 | F13: 0
B15: Total | C15: =SUM(C11:C13) -> 0 | D15: =SUM(D11:D13) -> 0 | E15: =SUM(E11:E13) -> 0 | F15: =SUM(F11:F13) -> 0
A17: 2017 | B17: Accident | C17: O/S Loss | D17: O/S ALAE | E17: O/S ULAE | F17: Salvage/Subro
B18: Year | C18: Reserve | D18: Reserve | E18: Reserve | F18: Reserve/Anticipated
A20: =Premiums!$B$7 -> 19.3 | B20: =A17 -> 2017 | C20: 0 | D20: 0 | E20: 0 | F20: 0
A21: =Premiums!$C$7 -> 19.4 | B21: =B20 -> 2017 | C21: 0 | D21: 0 | E21: 0 | F21: 0
A22: =Premiums!$D$7 -> 21.2 | B22: =B21 -> 2017 | C22: 0 | D22: 0 | E22: 0 | F22: 0
B24: Total | C24: =SUM(C20:C22) -> 0 | D24: =SUM(D20:D22) -> 0 | E24: =SUM(E20:E22) -> 0 | F24: =SUM(F20:F22) -> 0
A26: 2016 | B26: Accident | C26: O/S Loss | D26: O/S ALAE | E26: O/S ULAE | F26: Salvage/Subro
B27: Year | C27: Reserve | D27: Reserve | E27: Reserve | F27: Reserve/Anticipated
A29: =Premiums!$B$7 -> 19.3 | B29: =A26 -> 2016 | C29: 0 | D29: 0 | E29: 0 | F29: 0
A30: =Premiums!$C$7 -> 19.4 | B30: =B29 -> 2016 | C30: 0 | D30: 0 | E30: 0 | F30: 0
A31: =Premiums!$D$7 -> 21.2 | B31: =B30 -> 2016 | C31: 0 | D31: 0 | E31: 0 | F31: 0
B33: Total | C33: =SUM(C29:C31) -> 0 | D33: =SUM(D29:D31) -> 0 | E33: =SUM(E29:E31) -> 0 | F33: =SUM(F29:F31) -> 0
A35: 2015 | B35: Accident | C35: O/S Loss | D35: O/S ALAE | E35: O/S ULAE | F35: Salvage/Subro
B36: Year | C36: Reserve | D36: Reserve | E36: Reserve | F36: Reserve/Anticipated
A38: =Premiums!$B$7 -> 19.3 | B38: =A35 -> 2015 | C38: 0 | D38: 0 | E38: 0 | F38: 0
A39: =Premiums!$C$7 -> 19.4 | B39: =B38 -> 2015 | C39: 0 | D39: 0 | E39: 0 | F39: 0
A40: =Premiums!$D$7 -> 21.2 | B40: =B39 -> 2015 | C40: 0 | D40: 0 | E40: 0 | F40: 0
B42: Total | C42: =SUM(C38:C40) -> 0 | D42: =SUM(D38:D40) -> 0 | E42: =SUM(E38:E40) -> 0 | F42: =SUM(F38:F40) -> 0
A44: 2014 | B44: Accident | C44: O/S Loss | D44: O/S ALAE | E44: O/S ULAE | F44: Salvage/Subro
B45: Year | C45: Reserve | D45: Reserve | E45: Reserve | F45: Reserve/Anticipated
A47: =Premiums!$B$7 -> 19.3 | B47: =A44 -> 2014 | C47: 0 | D47: 0 | E47: 0 | F47: 0
A48: =Premiums!$C$7 -> 19.4 | B48: =B47 -> 2014 | C48: 0 | D48: 0 | E48: 0 | F48: 0
A49: =Premiums!$D$7 -> 21.2 | B49: =B48 -> 2014 | C49: 0 | D49: 0 | E49: 0 | F49: 0
B51: Total | C51: =SUM(C47:C49) -> 0 | D51: =SUM(D47:D49) -> 0 | E51: =SUM(E47:E49) -> 0 | F51: =SUM(F47:F49) -> 0
A53: 2013 | B53: Accident | C53: O/S Loss | D53: O/S ALAE | E53: O/S ULAE | F53: Salvage/Subro
B54: Year | C54: Reserve | D54: Reserve | E54: Reserve | F54: Reserve/Anticipated
A56: =Premiums!$B$7 -> 19.3 | B56: =A53 -> 2013 | C56: 0 | D56: 0 | E56: 0 | F56: 0
A57: =Premiums!$C$7 -> 19.4 | B57: =B56 -> 2013 | C57: 0 | D57: 0 | E57: 0 | F57: 0
A58: =Premiums!$D$7 -> 21.2 | B58: =B57 -> 2013 | C58: 0 | D58: 0 | E58: 0 | F58: 0
B60: Total | C60: =SUM(C56:C58) -> 0 | D60: =SUM(D56:D58) -> 0 | E60: =SUM(E56:E58) -> 0 | F60: =SUM(F56:F58) -> 0
A62: 2013 | B62: Accident | C62: O/S Loss | D62: O/S ALAE | E62: O/S ULAE | F62: Salvage/Subro
B63: Year | C63: Reserve | D63: Reserve | E63: Reserve | F63: Reserve/Anticipated
A65: =Premiums!$B$7 -> 19.3 | B65: =A62 -> 2013 | C65: 0 | D65: 0 | E65: 0 | F65: 0
A66: =Premiums!$C$7 -> 19.4 | B66: =B65 -> 2013 | C66: 0 | D66: 0 | E66: 0 | F66: 0
A67: =Premiums!$D$7 -> 21.2 | B67: =B66 -> 2013 | C67: 0 | D67: 0 | E67: 0 | F67: 0
B69: Total | C69: =SUM(C65:C67) -> 0 | D69: =SUM(D65:D67) -> 0 | E69: =SUM(E65:E67) -> 0 | F69: =SUM(F65:F67) -> 0
B72: All Accident Years | C72: O/S Loss | D72: O/S ALAE | E72: O/S ULAE | F72: Salvage/Subro
B73: Total - Per program | C73: Reserve | D73: Reserve | E73: Reserve | F73: Reserve/Anticipated
A75: =Premiums!$B$7 -> 19.3 | C75: =C11+C20+C29+C38+C47+C56+C65 -> 0 | D75: =D11+D20+D29+D38+D47+D56+D65 -> 0 | E75: =E11+E20+E29+E38+E47+E56+E65 -> 0 | F75: =F11+F20+F29+F38+F47+F56+F65 -> 0
A76: =Premiums!$C$7 -> 19.4 | C76: =C12+C21+C30+C39+C48+C57+C66 -> 0 | D76: =D12+D21+D30+D39+D48+D57+D66 -> 0 | E76: =E12+E21+E30+E39+E48+E57+E66 -> 0 | F76: =F12+F21+F30+F39+F48+F57+F66 -> 0
A77: =Premiums!$D$7 -> 21.2 | C77: =C13+C22+C31+C40+C49+C58+C67 -> 0 | D77: =D13+D22+D31+D40+D49+D58+D67 -> 0 | E77: =E13+E22+E31+E40+E49+E58+E67 -> 0 | F77: =F13+F22+F31+F40+F49+F58+F67 -> 0
B79: Total | C79: =SUM(C75:C77) -> 0 | D79: =SUM(D75:D77) -> 0 | E79: =SUM(E75:E77) -> 0 | F79: =SUM(F75:F77) -> 0
C82: O/S Loss | D82: O/S ALAE | E82: O/S ULAE | F82: Salvage/Subro
B83: Total - Per PASS | C83: Reserve | D83: Reserve | E83: Reserve | F83: Reserve/Anticipated
A85: =Premiums!$B$7 -> 19.3 | C85: 0 | D85: 0 | E85: 0 | F85: N/A
A86: =Premiums!$C$7 -> 19.4 | C86: 0 | D86: 0 | E86: 0 | F86: N/A
A87: =Premiums!$D$7 -> 21.2 | C87: 0 | D87: 0 | E87: 0 | F87: N/A
B89: Total | C89: =SUM(C85:C87) -> 0 | D89: =SUM(D85:D87) -> 0 | E89: =SUM(E85:E87) -> 0 | F89: N/A
C92: O/S Loss | D92: O/S ALAE | E92: O/S ULAE | F92: Salvage/Subro
B93: DIFFERENCES | C93: Reserve | D93: Reserve | E93: Reserve | F93: Reserve/Anticipated
A95: =Premiums!$B$7 -> 19.3 | C95: =C75-C85 -> 0 | D95: =D75-D85 -> 0 | E95: =E75-E85 -> 0 | F95: N/A
A96: =Premiums!$C$7 -> 19.4 | C96: =C76-C86 -> 0 | D96: =D76-D86 -> 0 | E96: =E76-E86 -> 0 | F96: N/A
A97: =Premiums!$D$7 -> 21.2 | C97: =C77-C87 -> 0 | D97: =D77-D87 -> 0 | E97: =E77-E87 -> 0 | F97: N/A
B99: Total | C99: =SUM(C95:C97) -> 0 | D99: =SUM(D95:D97) -> 0 | E99: =SUM(E95:E97) -> 0 | F99: N/A
A106: RECONCILIATION
C107: O/S Loss | D107: O/S ALAE | E107: O/S ULAE | F107: Salvage/Subro
B108: 12/2011 Accrual | C108: Reserve | D108: Reserve | E108: Reserve | F108: Reserve/Anticipated
A110: =Premiums!$B$7 -> 19.3 | C110: 0 | D110: 0 | E110: 0 | F110: N/A
A111: =Premiums!$C$7 -> 19.4 | C111: 0 | D111: 0 | E111: 0 | F111: N/A
A112: =Premiums!$D$7 -> 21.2 | C112: 0 | D112: 0 | E112: 0 | F112: N/A
B114: Total | C114: =SUM(C110:C112) -> 0 | D114: =SUM(D110:D112) -> 0 | E114: =SUM(E110:E112) -> 0 | F114: N/A

Sheet Claim Count Format--yr end
A1: ='Paids --yr end'!A1 -> NTA - 1/1/2013
A2: Claim Count by Accident Year | C2: ='Paids --yr end'!C2 -> 2013 | E2: INPUT AREA
A3: ='Paids --yr end'!A3 -> Line of Business (Annual Statement Lines)
A4: =Premiums!A4 -> STATE NATIONAL INSURANCE COMPANY
A6: LOB
C7: Outstanding / open claims | E7: Claims | F7: Claims | G7: Outstanding / open claims
A8: 2018 | B8: Accident | C8: =C18 -> at 11-30-2011 | D8: Claims | E8: Closed | F8: Closed | G8: =G18 -> at 11-30-2012
B9: Year | C9: (beg of period) | D9: reported | E9: With Pay | F9: Without Pay | G9: (end of period)
A11: =Premiums!$B$7 -> 19.3 | B11: =A8 -> 2018 | C11: 0 | D11: 0 | E11: 0 | F11: 0 | G11: =SUM(C11+D11)-SUM(E11+F11) -> 0
A12: =Premiums!$C$7 -> 19.4 | B12: =B11 -> 2018 | C12: 0 | D12: 0 | E12: 0 | F12: 0 | G12: =SUM(C12+D12)-SUM(E12+F12) -> 0
A13: =Premiums!$D$7 -> 21.2 | B13: =B12 -> 2018 | C13: 0 | D13: 0 | E13: 0 | F13: 0 | G13: =SUM(C13+D13)-SUM(E13+F13) -> 0
B15: Total | C15: =SUM(C11:C13) -> 0 | D15: =SUM(D11:D13) -> 0 | E15: =SUM(E11:E13) -> 0 | F15: =SUM(F11:F13) -> 0 | G15: =SUM(G11:G13) -> 0
C17: Outstanding / open claims | E17: Claims | F17: Claims | G17: Outstanding / open claims
A18: 2017 | B18: Accident | C18: =C28 -> at 11-30-2011 | D18: Claims | E18: Closed | F18: Closed | G18: =G28 -> at 11-30-2012
B19: Year | C19: (beg of period) | D19: reported | E19: With Pay | F19: Without Pay | G19: (end of period)
A21: =Premiums!$B$7 -> 19.3 | B21: =A18 -> 2017 | C21: 0 | D21: 0 | E21: 0 | F21: 0 | G21: =SUM(C21+D21)-SUM(E21+F21) -> 0
A22: =Premiums!$C$7 -> 19.4 | B22: =B21 -> 2017 | C22: 0 | D22: 0 | E22: 0 | F22: 0 | G22: =SUM(C22+D22)-SUM(E22+F22) -> 0
A23: =Premiums!$D$7 -> 21.2 | B23: =B22 -> 2017 | C23: 0 | D23: 0 | E23: 0 | F23: 0 | G23: =SUM(C23+D23)-SUM(E23+F23) -> 0
B25: Total | C25: =SUM(C21:C23) -> 0 | D25: =SUM(D21:D23) -> 0 | E25: =SUM(E21:E23) -> 0 | F25: =SUM(F21:F23) -> 0 | G25: =SUM(G21:G23) -> 0
C27: Outstanding / open claims | E27: Claims | F27: Claims | G27: Outstanding / open claims
A28: 2016 | B28: Accident | C28: =C38 -> at 11-30-2011 | D28: Claims | E28: Closed | F28: Closed | G28: =G38 -> at 11-30-2012
B29: Year | C29: (beg of period) | D29: reported | E29: With Pay | F29: Without Pay | G29: (end of period)
A31: =Premiums!$B$7 -> 19.3 | B31: =A28 -> 2016 | C31: 0 | D31: 0 | E31: 0 | F31: 0 | G31: =SUM(C31+D31)-SUM(E31+F31) -> 0
A32: =Premiums!$C$7 -> 19.4 | B32: =B31 -> 2016 | C32: 0 | D32: 0 | E32: 0 | F32: 0 | G32: =SUM(C32+D32)-SUM(E32+F32) -> 0
A33: =Premiums!$D$7 -> 21.2 | B33: =B32 -> 2016 | C33: 0 | D33: 0 | E33: 0 | F33: 0 | G33: =SUM(C33+D33)-SUM(E33+F33) -> 0
B35: Total | C35: =SUM(C31:C33) -> 0 | D35: =SUM(D31:D33) -> 0 | E35: =SUM(E31:E33) -> 0 | F35: =SUM(F31:F33) -> 0 | G35: =SUM(G31:G33) -> 0
C37: Outstanding / open claims | E37: Claims | F37: Claims | G37: Outstanding / open claims
A38: 2015 | B38: Accident | C38: =C48 -> at 11-30-2011 | D38: Claims | E38: Closed | F38: Closed | G38: =G48 -> at 11-30-2012
B39: Year | C39: (beg of period) | D39: reported | E39: With Pay | F39: Without Pay | G39: (end of period)
A41: =Premiums!$B$7 -> 19.3 | B41: =A38 -> 2015 | C41: 0 | D41: 0 | E41: 0 | F41: 0 | G41: =SUM(C41+D41)-SUM(E41+F41) -> 0
A42: =Premiums!$C$7 -> 19.4 | B42: =B41 -> 2015 | C42: 0 | D42: 0 | E42: 0 | F42: 0 | G42: =SUM(C42+D42)-SUM(E42+F42) -> 0
A43: =Premiums!$D$7 -> 21.2 | B43: =B42 -> 2015 | C43: 0 | D43: 0 | E43: 0 | F43: 0 | G43: =SUM(C43+D43)-SUM(E43+F43) -> 0
B45: Total | C45: =SUM(C41:C43) -> 0 | D45: =SUM(D41:D43) -> 0 | E45: =SUM(E41:E43) -> 0 | F45: =SUM(F41:F43) -> 0 | G45: =SUM(G41:G43) -> 0
C47: Outstanding / open claims | E47: Claims | F47: Claims | G47: Outstanding / open claims
A48: 2014 | B48: Accident | C48: =C58 -> at 11-30-2011 | D48: Claims | E48: Closed | F48: Closed | G48: =G58 -> at 11-30-2012
B49: Year | C49: (beg of period) | D49: reported | E49: With Pay | F49: Without Pay | G49: (end of period)
A51: =Premiums!$B$7 -> 19.3 | B51: =A48 -> 2014 | C51: 0 | D51: 0 | E51: 0 | F51: 0 | G51: =SUM(C51+D51)-SUM(E51+F51) -> 0
A52: =Premiums!$C$7 -> 19.4 | B52: =B51 -> 2014 | C52: 0 | D52: 0 | E52: 0 | F52: 0 | G52: =SUM(C52+D52)-SUM(E52+F52) -> 0
A53: =Premiums!$D$7 -> 21.2 | B53: =B52 -> 2014 | C53: 0 | D53: 0 | E53: 0 | F53: 0 | G53: =SUM(C53+D53)-SUM(E53+F53) -> 0
B55: Total | C55: =SUM(C51:C53) -> 0 | D55: =SUM(D51:D53) -> 0 | E55: =SUM(E51:E53) -> 0 | F55: =SUM(F51:F53) -> 0 | G55: =SUM(G51:G53) -> 0
C57: Outstanding / open claims | E57: Claims | F57: Claims | G57: Outstanding / open claims
A58: 2013 | B58: Accident | C58: =C68 -> at 11-30-2011 | D58: Claims | E58: Closed | F58: Closed | G58: =G68 -> at 11-30-2012
B59: Year | C59: (beg of period) | D59: reported | E59: With Pay | F59: Without Pay | G59: (end of period)
A61: =Premiums!$B$7 -> 19.3 | B61: =A58 -> 2013 | C61: 0 | D61: 0 | E61: 0 | F61: 0 | G61: =SUM(C61+D61)-SUM(E61+F61) -> 0
A62: =Premiums!$C$7 -> 19.4 | B62: =B61 -> 2013 | C62: 0 | D62: 0 | E62: 0 | F62: 0 | G62: =SUM(C62+D62)-SUM(E62+F62) -> 0
A63: =Premiums!$D$7 -> 21.2 | B63: =B62 -> 2013 | C63: 0 | D63: 0 | E63: 0 | F63: 0 | G63: =SUM(C63+D63)-SUM(E63+F63) -> 0
B65: Total | C65: =SUM(C61:C63) -> 0 | D65: =SUM(D61:D63) -> 0 | E65: =SUM(E61:E63) -> 0 | F65: =SUM(F61:F63) -> 0 | G65: =SUM(G61:G63) -> 0
C67: Outstanding / open claims | E67: Claims | F67: Claims | G67: Outstanding / open claims
A68: 2013 | B68: Accident | C68: =C79 -> at 11-30-2011 | D68: Claims | E68: Closed | F68: Closed | G68: =G79 -> at 11-30-2012
B69: Year | C69: (beg of period) | D69: reported | E69: With Pay | F69: Without Pay | G69: (end of period)
A71: =Premiums!$B$7 -> 19.3 | B71: =A68 -> 2013 | C71: 0 | D71: 0 | E71: 0 | F71: 0 | G71: =SUM(C71+D71)-SUM(E71+F71) -> 0
A72: =Premiums!$C$7 -> 19.4 | B72: =B71 -> 2013 | C72: 0 | D72: 0 | E72: 0 | F72: 0 | G72: =SUM(C72+D72)-SUM(E72+F72) -> 0
A73: =Premiums!$D$7 -> 21.2 | B73: =B72 -> 2013 | C73: 0 | D73: 0 | E73: 0 | F73: 0 | G73: =SUM(C73+D73)-SUM(E73+F73) -> 0
B75: Total | C75: =SUM(C71:C73) -> 0 | D75: =SUM(D71:D73) -> 0 | E75: =SUM(E71:E73) -> 0 | F75: =SUM(F71:F73) -> 0 | G75: =SUM(G71:G73) -> 0
C78: Outstanding / open claims | E78: Claims | F78: Claims | G78: Outstanding / open claims
B79: All Accident Years | C79: at 11-30-2011 | D79: Claims | E79: Closed | F79: Closed | G79: at 11-30-2012
B80: Total - Per program | C80: (beg of period) | D80: reported | E80: With Pay | F80: Without Pay | G80: (end of period)
A82: =Premiums!$B$7 -> 19.3 | C82: =C11+C21+C31+C41+C51+C61+C71 -> 0 | D82: =D11+D21+D31+D41+D51+D61+D71 -> 0 | E82: =E11+E21+E31+E41+E51+E61+E71 -> 0 | F82: =F11+F21+F31+F41+F51+F61+F71 -> 0 | G82: =G11+G21+G31+G41+G51+G61+G71 -> 0
A83: =Premiums!$C$7 -> 19.4 | C83: =C12+C22+C32+C42+C52+C62+C72 -> 0 | D83: =D12+D22+D32+D42+D52+D62+D72 -> 0 | E83: =E12+E22+E32+E42+E52+E62+E72 -> 0 | F83: =F12+F22+F32+F42+F52+F62+F72 -> 0 | G83: =G12+G22+G32+G42+G52+G62+G72 -> 0
A84: =Premiums!$D$7 -> 21.2 | C84: =C13+C23+C33+C43+C53+C63+C73 -> 0 | D84: =D13+D23+D33+D43+D53+D63+D73 -> 0 | E84: =E13+E23+E33+E43+E53+E63+E73 -> 0 | F84: =F13+F23+F33+F43+F53+F63+F73 -> 0 | G84: =G13+G23+G33+G43+G53+G63+G73 -> 0
B86: Total | C86: =SUM(C82:C85) -> 0 | D86: =SUM(D82:D85) -> 0 | E86: =SUM(E82:E85) -> 0 | F86: =SUM(F82:F85) -> 0 | G86: =SUM(G82:G85) -> 0
