Workbook

Sheet Starlight APD
A1: Southlake Specialty Insurance Company
C2: 2025 | P2: 2026
C3: ITD | P3: YTD | Q3: ITD | R3: System | T3: Summary
B4: FUT Starlight APD DRP T2 - Total | C4: Totals | D4: Jan-26 | E4: Feb-26 | F4: Mar-26 | G4: Apr-26 | H4: May-26 | I4: Jun-26 | J4: Jul-26 | K4: Aug-26 | L4: Sep-26 | M4: Oct-26 | N4: Nov-26 | O4: Dec-26 | P4: Totals | Q4: Totals | R4: Reports | S4: Variance | T4: Account Description | U4: Comp | V4: Account | W4: CC | X4: MGA | Y4: LOB | Z4: ST | AA4: EXT | AB4: Sub | AC4: Description | AD4: Jan-26 | AE4: Feb-26 | AF4: Mar-26 | AG4: Apr-26 | AH4: May-26 | AI4: Jun-26 | AJ4: Jul-26 | AK4: Aug-26 | AL4: Sep-26 | AM4: Oct-26 | AN4: Nov-26 | AO4: Dec-26 | AP4: Totals
T5: Uncollected Premium Direct | U5: 100 | V5: 120100 | W5: 00 | X5: 2002 | Y5: 000212 | Z5: 00 | AA5: 0000 | AC5: FUT Starlight T2 APD DRP | AD5: =SUM(AL:WY!AE5) -> -4003.16 | AE5: =SUM(AL:WY!AP5) -> -32023.47 | AF5: =SUM(AL:WY!BA5) -> -8507.36 | AG5: =SUM(AL:WY!BL5) -> 0 | AH5: =SUM(AL:WY!BW5) -> 0 | AI5: =SUM(AL:WY!CH5) -> 0 | AJ5: =SUM(AL:WY!CS5) -> 0 | AK5: =SUM(AL:WY!DD5) -> 0 | AL5: =SUM(AL:WY!DO5) -> 0 | AM5: =SUM(AL:WY!DZ5) -> 0 | AN5: =SUM(AL:WY!EK5) -> 0 | AO5: =SUM(AL:WY!EV5) -> 0 | AP5: =SUM(AD5:AO5) -> -44533.99
A6: a. | B6: Premiums Written | C6: =SUM(AL:WY!C6) -> 2135589.9 | D6: =SUM(AL:WY!D6) -> -4003.16 | E6: =SUM(AL:WY!E6) -> -32023.47 | F6: =SUM(AL:WY!F6) -> -8507.36 | G6: =SUM(AL:WY!G6) -> 0 | H6: =SUM(AL:WY!H6) -> 0 | I6: =SUM(AL:WY!I6) -> 0 | J6: =SUM(AL:WY!J6) -> 0 | ... O6: =SUM(AL:WY!O6) -> 0 | P6: =SUM(D6:O6) -> -44533.99 | Q6: =+C6+P6 -> 2091055.9 | R6: =SUM(AL:WY!R6) -> 2072670.7 | S6: =Q6-R6 -> 18385.17 | T6: Direct Premium Written | U6: 100 | V6: 400100 | W6: 00 | X6: 2002 | Y6: 000212 | Z6: CA | AA6: 0000 | AC6: FUT Starlight T2 APD DRP | AD6: =SUM(AL:WY!AE6) -> 4003.16 | AE6: =SUM(AL:WY!AP6) -> 32023.47 | AF6: =SUM(AL:WY!BA6) -> 8507.36 | AG6: =SUM(AL:WY!BL6) -> 0 | AH6: =SUM(AL:WY!BW6) -> 0 | AI6: =SUM(AL:WY!CH6) -> 0 | AJ6: =SUM(AL:WY!CS6) -> 0 | AK6: =SUM(AL:WY!DD6) -> 0 | AL6: =SUM(AL:WY!DO6) -> 0 | AM6: =SUM(AL:WY!DZ6) -> 0 | AN6: =SUM(AL:WY!EK6) -> 0 | AO6: =SUM(AL:WY!EV6) -> 0 | AP6: =SUM(AD6:AO6) -> 44533.99
B7: Change in UEP | C7: =SUM(AL:WY!C7) -> -1641729.9 | D7: =SUM(AL:WY!D7) -> 182408.02 | E7: =SUM(AL:WY!E7) -> 208703.25 | F7: =SUM(AL:WY!F7) -> 182754.37 | G7: =SUM(AL:WY!G7) -> 0 | H7: =SUM(AL:WY!H7) -> 0 | I7: =SUM(AL:WY!I7) -> 0 | J7: =SUM(AL:WY!J7) -> 0 | ... O7: =SUM(AL:WY!O7) -> 0 | P7: =SUM(D7:O7) -> 573865.64 | Q7: =+C7+P7 -> -1067864.3 | R7: =SUM(AL:WY!R7) -> -1067864.3 | S7: =Q7-R7 -> 0 | T7: Change in Unearned Premium Direct | U7: 100 | V7: 411100 | W7: 00 | X7: 2002 | Y7: 000212 | Z7: CA | AA7: 0000 | AC7: FUT Starlight T2 APD DRP | AD7: =SUM(AL:WY!AE7) -> -182408.02 | AE7: =SUM(AL:WY!AP7) -> -208703.25 | AF7: =SUM(AL:WY!BA7) -> -182754.37 | AG7: =SUM(AL:WY!BL7) -> 0 | AH7: =SUM(AL:WY!BW7) -> 0 | AI7: =SUM(AL:WY!CH7) -> 0 | AJ7: =SUM(AL:WY!CS7) -> 0 | AK7: =SUM(AL:WY!DD7) -> 0 | AL7: =SUM(AL:WY!DO7) -> 0 | AM7: =SUM(AL:WY!DZ7) -> 0 | AN7: =SUM(AL:WY!EK7) -> 0 | AO7: =SUM(AL:WY!EV7) -> 0 | AP7: =SUM(AD7:AO7) -> -573865.64
B8: Premiums Earned | C8: =SUM(C6:C7) -> 493859.97 | D8: =SUM(D6:D7) -> 178404.86 | E8: =SUM(E6:E7) -> 176679.78 | F8: =SUM(F6:F7) -> 174247.01 | G8: =SUM(G6:G7) -> 0 | H8: =SUM(H6:H7) -> 0 | I8: =SUM(I6:I7) -> 0 | J8: =SUM(J6:J7) -> 0 | ... S8: =SUM(S6:S7) -> 18385.17 | T8: Unearned Premium Direct | U8: 100 | V8: 230100 | W8: 00 | X8: 2002 | Y8: 000212 | Z8: CA | AA8: 0000 | AC8: FUT Starlight T2 APD DRP | AD8: =SUM(AL:WY!AE8) -> 182408.02 | AE8: =SUM(AL:WY!AP8) -> 208703.25 | AF8: =SUM(AL:WY!BA8) -> 182754.37 | AG8: =SUM(AL:WY!BL8) -> 0 | AH8: =SUM(AL:WY!BW8) -> 0 | AI8: =SUM(AL:WY!CH8) -> 0 | AJ8: =SUM(AL:WY!CS8) -> 0 | AK8: =SUM(AL:WY!DD8) -> 0 | AL8: =SUM(AL:WY!DO8) -> 0 | AM8: =SUM(AL:WY!DZ8) -> 0 | AN8: =SUM(AL:WY!EK8) -> 0 | AO8: =SUM(AL:WY!EV8) -> 0 | AP8: =SUM(AD8:AO8) -> 573865.64
T9: Ceded Premium Written | U9: 100 | V9: 400300 | W9: 00 | X9: 2002 | Y9: 000212 | Z9: 00 | AA9: 0000 | AC9: FUT Starlight T2 APD DRP | AD9: =SUM(AL:WY!AE9) -> -4003.16 | AE9: =SUM(AL:WY!AP9) -> -32023.47 | AF9: =SUM(AL:WY!BA9) -> -8507.36 | AG9: =SUM(AL:WY!BL9) -> 0 | AH9: =SUM(AL:WY!BW9) -> 0 | AI9: =SUM(AL:WY!CH9) -> 0 | AJ9: =SUM(AL:WY!CS9) -> 0 | AK9: =SUM(AL:WY!DD9) -> 0 | AL9: =SUM(AL:WY!DO9) -> 0 | AM9: =SUM(AL:WY!DZ9) -> 0 | AN9: =SUM(AL:WY!EK9) -> 0 | AO9: =SUM(AL:WY!EV9) -> 0 | AP9: =SUM(AD9:AO9) -> -44533.99
B10: Less: | T10: Ceded Reinsurance Premiums Payable | U10: 100 | V10: 243100 | W10: 00 | X10: 2002 | Y10: 000212 | Z10: 00 | AA10: 0000 | AC10: FUT Starlight T2 APD DRP | AD10: =SUM(AL:WY!AE10) -> 4003.16 | AE10: =SUM(AL:WY!AP10) -> 32023.47 | AF10: =SUM(AL:WY!BA10) -> 8507.36 | AG10: =SUM(AL:WY!BL10) -> 0 | AH10: =SUM(AL:WY!BW10) -> 0 | AI10: =SUM(AL:WY!CH10) -> 0 | AJ10: =SUM(AL:WY!CS10) -> 0 | AK10: =SUM(AL:WY!DD10) -> 0 | AL10: =SUM(AL:WY!DO10) -> 0 | AM10: =SUM(AL:WY!DZ10) -> 0 | AN10: =SUM(AL:WY!EK10) -> 0 | AO10: =SUM(AL:WY!EV10) -> 0 | AP10: =SUM(AD10:AO10) -> 44533.99
A11: b. | B11: Ceding Commissions at 29% | C11: =SUM(AL:WY!C11) -> 619321.06 | D11: =SUM(AL:WY!D11) -> -1160.9164 | E11: =SUM(AL:WY!E11) -> -9286.8063 | F11: =SUM(AL:WY!F11) -> -2467.1344 | G11: =SUM(AL:WY!G11) -> 0 | H11: =SUM(AL:WY!H11) -> 0 | I11: =SUM(AL:WY!I11) -> 0 | J11: =SUM(AL:WY!J11) -> 0 | ... O11: =SUM(AL:WY!O11) -> 0 | P11: =SUM(D11:O11) -> -12914.857 | Q11: =+C11+P11 -> 606406.21 | T11: Unearned Premium Ceded | U11: 100 | V11: 230300 | W11: 00 | X11: 2002 | Y11: 000212 | Z11: 00 | AA11: 0000 | AC11: FUT Starlight T2 APD DRP | AD11: =SUM(AL:WY!AE11) -> -182408.02 | AE11: =SUM(AL:WY!AP11) -> -208703.25 | AF11: =SUM(AL:WY!BA11) -> -182754.37 | AG11: =SUM(AL:WY!BL11) -> 0 | AH11: =SUM(AL:WY!BW11) -> 0 | AI11: =SUM(AL:WY!CH11) -> 0 | AJ11: =SUM(AL:WY!CS11) -> 0 | AK11: =SUM(AL:WY!DD11) -> 0 | AL11: =SUM(AL:WY!DO11) -> 0 | AM11: =SUM(AL:WY!DZ11) -> 0 | AN11: =SUM(AL:WY!EK11) -> 0 | AO11: =SUM(AL:WY!EV11) -> 0 | AP11: =SUM(AD11:AO11) -> -573865.64
B12: Ceding Commissions on UEP | C12: =SUM(AL:WY!C12) -> 0 | D12: =SUM(AL:WY!D12) -> 0 | E12: =SUM(AL:WY!E12) -> 0 | F12: =SUM(AL:WY!F12) -> 0 | G12: =SUM(AL:WY!G12) -> 0 | H12: =SUM(AL:WY!H12) -> 0 | I12: =SUM(AL:WY!I12) -> 0 | J12: =SUM(AL:WY!J12) -> 0 | ... O12: =SUM(AL:WY!O12) -> 0 | P12: =SUM(D12:O12) -> 0 | Q12: =+C12+P12 -> 0 | T12: Change in Unearned Premium Ceded | U12: 100 | V12: 411300 | W12: 00 | X12: 2002 | Y12: 000212 | Z12: 00 | AA12: 0000 | AC12: FUT Starlight T2 APD DRP | AD12: =SUM(AL:WY!AE12) -> 182408.02 | AE12: =SUM(AL:WY!AP12) -> 208703.25 | AF12: =SUM(AL:WY!BA12) -> 182754.37 | AG12: =SUM(AL:WY!BL12) -> 0 | AH12: =SUM(AL:WY!BW12) -> 0 | AI12: =SUM(AL:WY!CH12) -> 0 | AJ12: =SUM(AL:WY!CS12) -> 0 | AK12: =SUM(AL:WY!DD12) -> 0 | AL12: =SUM(AL:WY!DO12) -> 0 | AM12: =SUM(AL:WY!DZ12) -> 0 | AN12: =SUM(AL:WY!EK12) -> 0 | AO12: =SUM(AL:WY!EV12) -> 0 | AP12: =SUM(AD12:AO12) -> 573865.64
B13: Ceding Commissions Earned | C13: =SUM(C11:C12) -> 619321.06 | D13: =SUM(D11:D12) -> -1160.9164 | E13: =SUM(E11:E12) -> -9286.8063 | F13: =SUM(F11:F12) -> -2467.1344 | G13: =SUM(G11:G12) -> 0 | H13: =SUM(H11:H12) -> 0 | I13: =SUM(I11:I12) -> 0 | J13: =SUM(J11:J12) -> 0 | ... Q13: =SUM(Q11:Q12) -> 606406.21 | T13: Commissions Direct | U13: 100 | V13: 500100 | W13: 00 | X13: 2002 | Y13: 000212 | Z13: CA | AA13: 0000 | AC13: FUT Starlight T2 APD DRP | AD13: =SUM(AL:WY!AE13) -> -1160.9164 | AE13: =SUM(AL:WY!AP13) -> -9286.8063 | AF13: =SUM(AL:WY!BA13) -> -2467.1344 | AG13: =SUM(AL:WY!BL13) -> 0 | AH13: =SUM(AL:WY!BW13) -> 0 | AI13: =SUM(AL:WY!CH13) -> 0 | AJ13: =SUM(AL:WY!CS13) -> 0 | AK13: =SUM(AL:WY!DD13) -> 0 | AL13: =SUM(AL:WY!DO13) -> 0 | AM13: =SUM(AL:WY!DZ13) -> 0 | AN13: =SUM(AL:WY!EK13) -> 0 | AO13: =SUM(AL:WY!EV13) -> 0 | AP13: =SUM(AD13:AO13) -> -12914.857
D14: =+D6-D11 -> -2842.2436 | E14: =+E6-E11 -> -22736.664 | F14: =+F6-F11 -> -6040.2256 | G14: =+G6-G11 -> 0 | H14: =+H6-H11 -> 0 | I14: =+I6-I11 -> 0 | J14: =+J6-J11 -> 0 | K14: =+K6-K11 -> 0 | ... O14: =+O6-O11 -> 0 | T14: Uncollected Premium Direct | U14: 100 | V14: 120100 | W14: 00 | X14: 2002 | Y14: 000212 | Z14: 00 | AA14: 0000 | AC14: FUT Starlight T2 APD DRP | AD14: =SUM(AL:WY!AE14) -> 1160.9164 | AE14: =SUM(AL:WY!AP14) -> 9286.8063 | AF14: =SUM(AL:WY!BA14) -> 2467.1344 | AG14: =SUM(AL:WY!BL14) -> 0 | AH14: =SUM(AL:WY!BW14) -> 0 | AI14: =SUM(AL:WY!CH14) -> 0 | AJ14: =SUM(AL:WY!CS14) -> 0 | AK14: =SUM(AL:WY!DD14) -> 0 | AL14: =SUM(AL:WY!DO14) -> 0 | AM14: =SUM(AL:WY!DZ14) -> 0 | AN14: =SUM(AL:WY!EK14) -> 0 | AO14: =SUM(AL:WY!EV14) -> 0 | AP14: =SUM(AD14:AO14) -> 12914.857
A15: c. | B15: Losses Paid (net of salvage & subro) | C15: =SUM(AL:WY!C15) -> 21210.31 | D15: =SUM(AL:WY!D15) -> 12500 | E15: =SUM(AL:WY!E15) -> 21996.52 | F15: =SUM(AL:WY!F15) -> 103850.88 | G15: =SUM(AL:WY!G15) -> 0 | H15: =SUM(AL:WY!H15) -> 0 | I15: =SUM(AL:WY!I15) -> 0 | J15: =SUM(AL:WY!J15) -> 0 | ... O15: =SUM(AL:WY!O15) -> 0 | P15: =SUM(D15:O15) -> 138347.4 | Q15: =+C15+P15 -> 159557.71 | R15: =SUM(AL:WY!R15) -> 159557.71 | S15: =Q15-R15 -> 0 | T15: Ceded Reinsurance Premiums Payable | U15: 100 | V15: 243100 | W15: 00 | X15: 2002 | Y15: 000212 | Z15: 00 | AA15: 0000 | AC15: FUT Starlight T2 APD DRP | AD15: =SUM(AL:WY!AE15) -> -1160.9164 | AE15: =SUM(AL:WY!AP15) -> -9286.8063 | AF15: =SUM(AL:WY!BA15) -> -2467.1344 | AG15: =SUM(AL:WY!BL15) -> 0 | AH15: =SUM(AL:WY!BW15) -> 0 | AI15: =SUM(AL:WY!CH15) -> 0 | AJ15: =SUM(AL:WY!CS15) -> 0 | AK15: =SUM(AL:WY!DD15) -> 0 | AL15: =SUM(AL:WY!DO15) -> 0 | AM15: =SUM(AL:WY!DZ15) -> 0 | AN15: =SUM(AL:WY!EK15) -> 0 | AO15: =SUM(AL:WY!EV15) -> 0 | AP15: =SUM(AD15:AO15) -> -12914.857
B16: Change in Loss Reserves | C16: =SUM(AL:WY!C16) -> 25000 | D16: =SUM(AL:WY!D16) -> 60564 | E16: =SUM(AL:WY!E16) -> 13600.51 | F16: =SUM(AL:WY!F16) -> 152500 | G16: =SUM(AL:WY!G16) -> 0 | H16: =SUM(AL:WY!H16) -> 0 | I16: =SUM(AL:WY!I16) -> 0 | J16: =SUM(AL:WY!J16) -> 0 | ... O16: =SUM(AL:WY!O16) -> 0 | P16: =SUM(D16:O16) -> 226664.51 | Q16: =+C16+P16 -> 251664.51 | T16: Commissions Ceded | U16: 100 | V16: 500300 | W16: 00 | X16: 2002 | Y16: 000212 | Z16: CA | AA16: 0000 | AC16: FUT Starlight T2 APD DRP | AD16: =SUM(AL:WY!AE16) -> 1160.9164 | AE16: =SUM(AL:WY!AP16) -> 9286.8063 | AF16: =SUM(AL:WY!BA16) -> 2467.1344 | AG16: =SUM(AL:WY!BL16) -> 0 | AH16: =SUM(AL:WY!BW16) -> 0 | AI16: =SUM(AL:WY!CH16) -> 0 | AJ16: =SUM(AL:WY!CS16) -> 0 | AK16: =SUM(AL:WY!DD16) -> 0 | AL16: =SUM(AL:WY!DO16) -> 0 | AM16: =SUM(AL:WY!DZ16) -> 0 | AN16: =SUM(AL:WY!EK16) -> 0 | AO16: =SUM(AL:WY!EV16) -> 0 | AP16: =SUM(AD16:AO16) -> 12914.857
B17: Change in Loss IBNR Reserves | C17: =SUM(AL:WY!C17) -> 233314.43 | D17: =SUM(AL:WY!D17) -> 27913.151 | E17: =SUM(AL:WY!E17) -> 64403.725 | F17: =SUM(AL:WY!F17) -> -157727.07 | G17: =SUM(AL:WY!G17) -> 0 | H17: =SUM(AL:WY!H17) -> 0 | I17: =SUM(AL:WY!I17) -> 0 | J17: =SUM(AL:WY!J17) -> 0 | ... O17: =SUM(AL:WY!O17) -> 0 | P17: =SUM(D17:O17) -> -65410.196 | Q17: =+C17+P17 -> 167904.24 | T17: Direct Losses paid | U17: 100 | V17: 600100 | W17: 00 | X17: 2002 | Y17: 000212 | Z17: CA | AA17: 0000 | AC17: FUT Starlight T2 APD DRP | AD17: =SUM(AL:WY!AE17) -> 12500 | AE17: =SUM(AL:WY!AP17) -> 21996.52 | AF17: =SUM(AL:WY!BA17) -> 103850.88 | AG17: =SUM(AL:WY!BL17) -> 0 | AH17: =SUM(AL:WY!BW17) -> 0 | AI17: =SUM(AL:WY!CH17) -> 0 | AJ17: =SUM(AL:WY!CS17) -> 0 | AK17: =SUM(AL:WY!DD17) -> 0 | AL17: =SUM(AL:WY!DO17) -> 0 | AM17: =SUM(AL:WY!DZ17) -> 0 | AN17: =SUM(AL:WY!EK17) -> 0 | AO17: =SUM(AL:WY!EV17) -> 0 | AP17: =SUM(AD17:AO17) -> 138347.4
B18: Losses Incurred | C18: =SUM(C15:C17) -> 279524.74 | D18: =SUM(D15:D17) -> 100977.15 | E18: =SUM(E15:E17) -> 100000.76 | F18: =SUM(F15:F17) -> 98623.808 | G18: =SUM(G15:G17) -> 0 | H18: =SUM(H15:H17) -> 0 | I18: =SUM(I15:I17) -> 0 | J18: =SUM(J15:J17) -> 0 | ... Q18: =SUM(Q15:Q17) -> 579126.46 | T18: Payable to MGA | U18: 100 | V18: 264400 | W18: 00 | X18: 2002 | Y18: 000212 | Z18: 00 | AA18: 0000 | AC18: FUT Starlight T2 APD DRP | AD18: =SUM(AL:WY!AE18) -> -12500 | AE18: =SUM(AL:WY!AP18) -> -21996.52 | AF18: =SUM(AL:WY!BA18) -> -103850.88 | AG18: =SUM(AL:WY!BL18) -> 0 | AH18: =SUM(AL:WY!BW18) -> 0 | AI18: =SUM(AL:WY!CH18) -> 0 | AJ18: =SUM(AL:WY!CS18) -> 0 | AK18: =SUM(AL:WY!DD18) -> 0 | AL18: =SUM(AL:WY!DO18) -> 0 | AM18: =SUM(AL:WY!DZ18) -> 0 | AN18: =SUM(AL:WY!EK18) -> 0 | AO18: =SUM(AL:WY!EV18) -> 0 | AP18: =SUM(AD18:AO18) -> -138347.4
T19: Amounts recoverable from reinsurers | U19: 100 | V19: 125100 | W19: 00 | X19: 2002 | Y19: 000212 | Z19: 00 | AA19: 0000 | AC19: FUT Starlight T2 APD DRP | AD19: =SUM(AL:WY!AE19) -> 12500 | AE19: =SUM(AL:WY!AP19) -> 21996.52 | AF19: =SUM(AL:WY!BA19) -> 103850.88 | AG19: =SUM(AL:WY!BL19) -> 0 | AH19: =SUM(AL:WY!BW19) -> 0 | AI19: =SUM(AL:WY!CH19) -> 0 | AJ19: =SUM(AL:WY!CS19) -> 0 | AK19: =SUM(AL:WY!DD19) -> 0 | AL19: =SUM(AL:WY!DO19) -> 0 | AM19: =SUM(AL:WY!DZ19) -> 0 | AN19: =SUM(AL:WY!EK19) -> 0 | AO19: =SUM(AL:WY!EV19) -> 0 | AP19: =SUM(AD19:AO19) -> 138347.4
A20: d. | B20: Defense and Cost Containment Expense Paid (DCC) | C20: =SUM(AL:WY!C20) -> 0 | D20: =SUM(AL:WY!D20) -> 0 | E20: =SUM(AL:WY!E20) -> 0 | F20: =SUM(AL:WY!F20) -> 0 | G20: =SUM(AL:WY!G20) -> 0 | H20: =SUM(AL:WY!H20) -> 0 | I20: =SUM(AL:WY!I20) -> 0 | J20: =SUM(AL:WY!J20) -> 0 | ... O20: =SUM(AL:WY!O20) -> 0 | P20: =SUM(D20:O20) -> 0 | Q20: =+C20+P20 -> 0 | S20: =Q20-R20 -> 0 | T20: Ceded Losses Paid | U20: 100 | V20: 600300 | W20: 00 | X20: 2002 | Y20: 000212 | Z20: 00 | AA20: 0000 | AC20: FUT Starlight T2 APD DRP | AD20: =SUM(AL:WY!AE20) -> -12500 | AE20: =SUM(AL:WY!AP20) -> -21996.52 | AF20: =SUM(AL:WY!BA20) -> -103850.88 | AG20: =SUM(AL:WY!BL20) -> 0 | AH20: =SUM(AL:WY!BW20) -> 0 | AI20: =SUM(AL:WY!CH20) -> 0 | AJ20: =SUM(AL:WY!CS20) -> 0 | AK20: =SUM(AL:WY!DD20) -> 0 | AL20: =SUM(AL:WY!DO20) -> 0 | AM20: =SUM(AL:WY!DZ20) -> 0 | AN20: =SUM(AL:WY!EK20) -> 0 | AO20: =SUM(AL:WY!EV20) -> 0 | AP20: =SUM(AD20:AO20) -> -138347.4
B21: Change in DCC Reserves | C21: =SUM(AL:WY!C21) -> 0 | D21: =SUM(AL:WY!D21) -> 0 | E21: =SUM(AL:WY!E21) -> 0 | F21: =SUM(AL:WY!F21) -> 0 | G21: =SUM(AL:WY!G21) -> 0 | H21: =SUM(AL:WY!H21) -> 0 | I21: =SUM(AL:WY!I21) -> 0 | J21: =SUM(AL:WY!J21) -> 0 | ... O21: =SUM(AL:WY!O21) -> 0 | P21: =SUM(D21:O21) -> 0 | Q21: =+C21+P21 -> 0 | T21: Change in Case Loss Reserves - Direct | U21: 100 | V21: 550100 | W21: 00 | X21: 2002 | Y21: 000212 | Z21: CA | AA21: 0000 | AC21: FUT Starlight T2 APD DRP | AD21: =SUM(AL:WY!AE21) -> 60564 | AE21: =SUM(AL:WY!AP21) -> 13600.51 | AF21: =SUM(AL:WY!BA21) -> 152500 | AG21: =SUM(AL:WY!BL21) -> 0 | AH21: =SUM(AL:WY!BW21) -> 0 | AI21: =SUM(AL:WY!CH21) -> 0 | AJ21: =SUM(AL:WY!CS21) -> 0 | AK21: =SUM(AL:WY!DD21) -> 0 | AL21: =SUM(AL:WY!DO21) -> 0 | AM21: =SUM(AL:WY!DZ21) -> 0 | AN21: =SUM(AL:WY!EK21) -> 0 | AO21: =SUM(AL:WY!EV21) -> 0 | AP21: =SUM(AD21:AO21) -> 226664.51
B22: Change in DCC IBNR Reserves | C22: =SUM(AL:WY!C22) -> 0 | D22: =SUM(AL:WY!D22) -> 0 | E22: =SUM(AL:WY!E22) -> 0 | F22: =SUM(AL:WY!F22) -> 0 | G22: =SUM(AL:WY!G22) -> 0 | H22: =SUM(AL:WY!H22) -> 0 | I22: =SUM(AL:WY!I22) -> 0 | J22: =SUM(AL:WY!J22) -> 0 | ... O22: =SUM(AL:WY!O22) -> 0 | P22: =SUM(D22:O22) -> 0 | Q22: =+C22+P22 -> 0 | T22: Case Loss Reserves - Direct | U22: 100 | V22: 200100 | W22: 00 | X22: 2002 | Y22: 000212 | Z22: CA | AA22: 0000 | AC22: FUT Starlight T2 APD DRP | AD22: =SUM(AL:WY!AE22) -> -60564 | AE22: =SUM(AL:WY!AP22) -> -13600.51 | AF22: =SUM(AL:WY!BA22) -> -152500 | AG22: =SUM(AL:WY!BL22) -> 0 | AH22: =SUM(AL:WY!BW22) -> 0 | AI22: =SUM(AL:WY!CH22) -> 0 | AJ22: =SUM(AL:WY!CS22) -> 0 | AK22: =SUM(AL:WY!DD22) -> 0 | AL22: =SUM(AL:WY!DO22) -> 0 | AM22: =SUM(AL:WY!DZ22) -> 0 | AN22: =SUM(AL:WY!EK22) -> 0 | AO22: =SUM(AL:WY!EV22) -> 0 | AP22: =SUM(AD22:AO22) -> -226664.51
A23: e. | B23: Adjusting & Other Expense Paid (AOE) | C23: =SUM(AL:WY!C23) -> 867.5 | D23: =SUM(AL:WY!D23) -> 0 | E23: =SUM(AL:WY!E23) -> 2167.4 | F23: =SUM(AL:WY!F23) -> 2127.5 | G23: =SUM(AL:WY!G23) -> 0 | H23: =SUM(AL:WY!H23) -> 0 | I23: =SUM(AL:WY!I23) -> 0 | J23: =SUM(AL:WY!J23) -> 0 | ... O23: =SUM(AL:WY!O23) -> 0 | P23: =SUM(D23:O23) -> 4294.9 | Q23: =+C23+P23 -> 5162.4 | R23: =SUM(AL:WY!R23) -> 5162.4 | S23: =Q23-R23 -> 0 | T23: Case Loss Reserves - Ceded | U23: 100 | V23: 200300 | W23: 00 | X23: 2002 | Y23: 000212 | Z23: 00 | AA23: 0000 | AC23: FUT Starlight T2 APD DRP | AD23: =SUM(AL:WY!AE23) -> 60564 | AE23: =SUM(AL:WY!AP23) -> 13600.51 | AF23: =SUM(AL:WY!BA23) -> 152500 | AG23: =SUM(AL:WY!BL23) -> 0 | AH23: =SUM(AL:WY!BW23) -> 0 | AI23: =SUM(AL:WY!CH23) -> 0 | AJ23: =SUM(AL:WY!CS23) -> 0 | AK23: =SUM(AL:WY!DD23) -> 0 | AL23: =SUM(AL:WY!DO23) -> 0 | AM23: =SUM(AL:WY!DZ23) -> 0 | AN23: =SUM(AL:WY!EK23) -> 0 | AO23: =SUM(AL:WY!EV23) -> 0 | AP23: =SUM(AD23:AO23) -> 226664.51
B24: Change in AOE Reserves | C24: =SUM(AL:WY!C24) -> 12500 | D24: =SUM(AL:WY!D24) -> 5000 | E24: =SUM(AL:WY!E24) -> 3692.6 | F24: =SUM(AL:WY!F24) -> -5597.6 | G24: =SUM(AL:WY!G24) -> 0 | H24: =SUM(AL:WY!H24) -> 0 | I24: =SUM(AL:WY!I24) -> 0 | J24: =SUM(AL:WY!J24) -> 0 | ... O24: =SUM(AL:WY!O24) -> 0 | P24: =SUM(D24:O24) -> 3095 | Q24: =+C24+P24 -> 15595 | T24: Change in Case Loss Reserves - Ceded | U24: 100 | V24: 550300 | W24: 00 | X24: 2002 | Y24: 000212 | Z24: 00 | AA24: 0000 | AC24: FUT Starlight T2 APD DRP | AD24: =SUM(AL:WY!AE24) -> -60564 | AE24: =SUM(AL:WY!AP24) -> -13600.51 | AF24: =SUM(AL:WY!BA24) -> -152500 | AG24: =SUM(AL:WY!BL24) -> 0 | AH24: =SUM(AL:WY!BW24) -> 0 | AI24: =SUM(AL:WY!CH24) -> 0 | AJ24: =SUM(AL:WY!CS24) -> 0 | AK24: =SUM(AL:WY!DD24) -> 0 | AL24: =SUM(AL:WY!DO24) -> 0 | AM24: =SUM(AL:WY!DZ24) -> 0 | AN24: =SUM(AL:WY!EK24) -> 0 | AO24: =SUM(AL:WY!EV24) -> 0 | AP24: =SUM(AD24:AO24) -> -226664.51
B25: Change in AOE IBNR Reserves | C25: =SUM(AL:WY!C25) -> 52809.736 | D25: =SUM(AL:WY!D25) -> 18906.251 | E25: =SUM(AL:WY!E25) -> 17815.091 | F25: =SUM(AL:WY!F25) -> 26819.199 | G25: =SUM(AL:WY!G25) -> 0 | H25: =SUM(AL:WY!H25) -> 0 | I25: =SUM(AL:WY!I25) -> 0 | J25: =SUM(AL:WY!J25) -> 0 | ... O25: =SUM(AL:WY!O25) -> 0 | P25: =SUM(D25:O25) -> 63540.541 | Q25: =+C25+P25 -> 116350.28 | T25: Change in IBNR Loss Reserves - Direct | U25: 100 | V25: 550400 | W25: 00 | X25: 2002 | Y25: 000212 | Z25: CA | AA25: 0000 | AC25: FUT Starlight T2 APD DRP | AD25: =SUM(AL:WY!AE25) -> 27913.151 | AE25: =SUM(AL:WY!AP25) -> 64403.725 | AF25: =SUM(AL:WY!BA25) -> -157727.07 | AG25: =SUM(AL:WY!BL25) -> 0 | AH25: =SUM(AL:WY!BW25) -> 0 | AI25: =SUM(AL:WY!CH25) -> 0 | AJ25: =SUM(AL:WY!CS25) -> 0 | AK25: =SUM(AL:WY!DD25) -> 0 | AL25: =SUM(AL:WY!DO25) -> 0 | AM25: =SUM(AL:WY!DZ25) -> 0 | AN25: =SUM(AL:WY!EK25) -> 0 | AO25: =SUM(AL:WY!EV25) -> 0 | AP25: =SUM(AD25:AO25) -> -65410.196
A26: f. | B26: Unallocated Loss Adjustment Expense at 7% | C26: =SUM(AL:WY!C26) -> 149491.29 | D26: =SUM(AL:WY!D26) -> -280.2212 | E26: =SUM(AL:WY!E26) -> -2241.6429 | F26: =SUM(AL:WY!F26) -> -595.5152 | G26: =SUM(AL:WY!G26) -> 0 | H26: =SUM(AL:WY!H26) -> 0 | I26: =SUM(AL:WY!I26) -> 0 | J26: =SUM(AL:WY!J26) -> 0 | ... O26: =SUM(AL:WY!O26) -> 0 | P26: =SUM(D26:O26) -> -3117.3793 | Q26: =+C26+P26 -> 146373.91 | T26: IBNR Loss Reserves - Direct | U26: 100 | V26: 200400 | W26: 00 | X26: 2002 | Y26: 000212 | Z26: CA | AA26: 0000 | AC26: FUT Starlight T2 APD DRP | AD26: =SUM(AL:WY!AE26) -> -27913.151 | AE26: =SUM(AL:WY!AP26) -> -64403.725 | AF26: =SUM(AL:WY!BA26) -> 157727.07 | AG26: =SUM(AL:WY!BL26) -> 0 | AH26: =SUM(AL:WY!BW26) -> 0 | AI26: =SUM(AL:WY!CH26) -> 0 | AJ26: =SUM(AL:WY!CS26) -> 0 | AK26: =SUM(AL:WY!DD26) -> 0 | AL26: =SUM(AL:WY!DO26) -> 0 | AM26: =SUM(AL:WY!DZ26) -> 0 | AN26: =SUM(AL:WY!EK26) -> 0 | AO26: =SUM(AL:WY!EV26) -> 0 | AP26: =SUM(AD26:AO26) -> 65410.196
B27: Change in ULAE IBNR Reserves | C27: =SUM(AL:WY!C27) -> 1229.0722 | D27: =SUM(AL:WY!D27) -> 290.97575 | E27: =SUM(AL:WY!E27) -> 356.0199 | F27: =SUM(AL:WY!F27) -> -407.38536 | G27: =SUM(AL:WY!G27) -> 0 | H27: =SUM(AL:WY!H27) -> 0 | I27: =SUM(AL:WY!I27) -> 0 | J27: =SUM(AL:WY!J27) -> 0 | ... O27: =SUM(AL:WY!O27) -> 0 | P27: =SUM(D27:O27) -> 239.61029 | Q27: =+C27+P27 -> 1468.6825 | T27: IBNR Loss Reserves - Ceded | U27: 100 | V27: 200600 | W27: 00 | X27: 2002 | Y27: 000212 | Z27: 00 | AA27: 0000 | AC27: FUT Starlight T2 APD DRP | AD27: =SUM(AL:WY!AE27) -> 27913.151 | AE27: =SUM(AL:WY!AP27) -> 64403.725 | AF27: =SUM(AL:WY!BA27) -> -157727.07 | AG27: =SUM(AL:WY!BL27) -> 0 | AH27: =SUM(AL:WY!BW27) -> 0 | AI27: =SUM(AL:WY!CH27) -> 0 | AJ27: =SUM(AL:WY!CS27) -> 0 | AK27: =SUM(AL:WY!DD27) -> 0 | AL27: =SUM(AL:WY!DO27) -> 0 | AM27: =SUM(AL:WY!DZ27) -> 0 | AN27: =SUM(AL:WY!EK27) -> 0 | AO27: =SUM(AL:WY!EV27) -> 0 | AP27: =SUM(AD27:AO27) -> -65410.196
B28: Loss Adjustment Expenses Incurred | C28: =SUM(C20:C27) -> 216897.6 | D28: =SUM(D20:D27) -> 23917.006 | E28: =SUM(E20:E27) -> 21789.468 | F28: =SUM(F20:F27) -> 22346.199 | G28: =SUM(G20:G27) -> 0 | H28: =SUM(H20:H27) -> 0 | I28: =SUM(I20:I27) -> 0 | J28: =SUM(J20:J27) -> 0 | ... Q28: =SUM(Q20:Q27) -> 284950.27 | T28: Change in IBNR Loss Reserves - Ceded | U28: 100 | V28: 550600 | W28: 00 | X28: 2002 | Y28: 000212 | Z28: 00 | AA28: 0000 | AC28: FUT Starlight T2 APD DRP | AD28: =SUM(AL:WY!AE28) -> -27913.151 | AE28: =SUM(AL:WY!AP28) -> -64403.725 | AF28: =SUM(AL:WY!BA28) -> 157727.07 | AG28: =SUM(AL:WY!BL28) -> 0 | AH28: =SUM(AL:WY!BW28) -> 0 | AI28: =SUM(AL:WY!CH28) -> 0 | AJ28: =SUM(AL:WY!CS28) -> 0 | AK28: =SUM(AL:WY!DD28) -> 0 | AL28: =SUM(AL:WY!DO28) -> 0 | AM28: =SUM(AL:WY!DZ28) -> 0 | AN28: =SUM(AL:WY!EK28) -> 0 | AO28: =SUM(AL:WY!EV28) -> 0 | AP28: =SUM(AD28:AO28) -> 65410.196
D29: =+D15+D23+D26 -> 12219.779 | E29: =+E15+E23+E26 -> 21922.277 | F29: =+F15+F23+F26 -> 105382.86 | G29: =+G15+G23+G26 -> 0 | H29: =+H15+H23+H26 -> 0 | I29: =+I15+I23+I26 -> 0 | J29: =+J15+J23+J26 -> 0 | K29: =+K15+K23+K26 -> 0 | ... O29: =+O15+O23+O26 -> 0 | T29: Direct LAE DCC Paid | U29: 100 | V29: 601100 | W29: 00 | X29: 2002 | Y29: 000212 | Z29: CA | AA29: 0000 | AC29: FUT Starlight T2 APD DRP | AD29: =SUM(AL:WY!AE29) -> 0 | AE29: =SUM(AL:WY!AP29) -> 0 | AF29: =SUM(AL:WY!BA29) -> 0 | AG29: =SUM(AL:WY!BL29) -> 0 | AH29: =SUM(AL:WY!BW29) -> 0 | AI29: =SUM(AL:WY!CH29) -> 0 | AJ29: =SUM(AL:WY!CS29) -> 0 | AK29: =SUM(AL:WY!DD29) -> 0 | AL29: =SUM(AL:WY!DO29) -> 0 | AM29: =SUM(AL:WY!DZ29) -> 0 | AN29: =SUM(AL:WY!EK29) -> 0 | AO29: =SUM(AL:WY!EV29) -> 0 | AP29: =SUM(AD29:AO29) -> 0
A30: g. | B30: Boards & Bureaus / ISO Charge at .4% | C30: =SUM(AL:WY!C30) -> 8542.3595 | D30: =SUM(AL:WY!D30) -> -16.01264 | E30: =SUM(AL:WY!E30) -> -128.09388 | F30: =SUM(AL:WY!F30) -> -34.02944 | G30: =SUM(AL:WY!G30) -> 0 | H30: =SUM(AL:WY!H30) -> 0 | I30: =SUM(AL:WY!I30) -> 0 | J30: =SUM(AL:WY!J30) -> 0 | ... O30: =SUM(AL:WY!O30) -> 0 | P30: =SUM(D30:O30) -> -178.13596 | Q30: =+C30+P30 -> 8364.2235 | T30: Payable to MGA | U30: 100 | V30: 264400 | W30: 00 | X30: 2002 | Y30: 000212 | Z30: 00 | AA30: 0000 | AC30: FUT Starlight T2 APD DRP | AD30: =SUM(AL:WY!AE30) -> 0 | AE30: =SUM(AL:WY!AP30) -> 0 | AF30: =SUM(AL:WY!BA30) -> 0 | AG30: =SUM(AL:WY!BL30) -> 0 | AH30: =SUM(AL:WY!BW30) -> 0 | AI30: =SUM(AL:WY!CH30) -> 0 | AJ30: =SUM(AL:WY!CS30) -> 0 | AK30: =SUM(AL:WY!DD30) -> 0 | AL30: =SUM(AL:WY!DO30) -> 0 | AM30: =SUM(AL:WY!DZ30) -> 0 | AN30: =SUM(AL:WY!EK30) -> 0 | AO30: =SUM(AL:WY!EV30) -> 0 | AP30: =SUM(AD30:AO30) -> 0
B31: Boards & Bureaus / ISO Charge at .4% on UEP | C31: =SUM(AL:WY!C31) -> -6566.9196 | D31: =SUM(AL:WY!D31) -> 729.63208 | E31: =SUM(AL:WY!E31) -> 834.813 | F31: =SUM(AL:WY!F31) -> 731.01748 | G31: =SUM(AL:WY!G31) -> 0 | H31: =SUM(AL:WY!H31) -> 0 | I31: =SUM(AL:WY!I31) -> 0 | J31: =SUM(AL:WY!J31) -> 0 | ... O31: =SUM(AL:WY!O31) -> 0 | P31: =SUM(D31:O31) -> 2295.4626 | Q31: =+C31+P31 -> -4271.457 | T31: Amounts recoverable from reinsurers | U31: 100 | V31: 125100 | W31: 00 | X31: 2002 | Y31: 000212 | Z31: 00 | AA31: 0000 | AC31: FUT Starlight T2 APD DRP | AD31: =SUM(AL:WY!AE31) -> 0 | AE31: =SUM(AL:WY!AP31) -> 0 | AF31: =SUM(AL:WY!BA31) -> 0 | AG31: =SUM(AL:WY!BL31) -> 0 | AH31: =SUM(AL:WY!BW31) -> 0 | AI31: =SUM(AL:WY!CH31) -> 0 | AJ31: =SUM(AL:WY!CS31) -> 0 | AK31: =SUM(AL:WY!DD31) -> 0 | AL31: =SUM(AL:WY!DO31) -> 0 | AM31: =SUM(AL:WY!DZ31) -> 0 | AN31: =SUM(AL:WY!EK31) -> 0 | AO31: =SUM(AL:WY!EV31) -> 0 | AP31: =SUM(AD31:AO31) -> 0
A32: h. | B32: Loss Ratio Cap Charge at 0% | C32: =SUM(AL:WY!C32) -> 42711.797 | D32: =SUM(AL:WY!D32) -> -80.0632 | E32: =SUM(AL:WY!E32) -> -640.4694 | F32: =SUM(AL:WY!F32) -> -170.1472 | G32: =SUM(AL:WY!G32) -> 0 | H32: =SUM(AL:WY!H32) -> 0 | I32: =SUM(AL:WY!I32) -> 0 | J32: =SUM(AL:WY!J32) -> 0 | ... O32: =SUM(AL:WY!O32) -> 0 | P32: =SUM(D32:O32) -> -890.6798 | Q32: =+C32+P32 -> 41821.118 | T32: Ceded LAE DCC Paid | U32: 100 | V32: 601300 | W32: 00 | X32: 2002 | Y32: 000212 | Z32: 00 | AA32: 0000 | AC32: FUT Starlight T2 APD DRP | AD32: =SUM(AL:WY!AE32) -> 0 | AE32: =SUM(AL:WY!AP32) -> 0 | AF32: =SUM(AL:WY!BA32) -> 0 | AG32: =SUM(AL:WY!BL32) -> 0 | AH32: =SUM(AL:WY!BW32) -> 0 | AI32: =SUM(AL:WY!CH32) -> 0 | AJ32: =SUM(AL:WY!CS32) -> 0 | AK32: =SUM(AL:WY!DD32) -> 0 | AL32: =SUM(AL:WY!DO32) -> 0 | AM32: =SUM(AL:WY!DZ32) -> 0 | AN32: =SUM(AL:WY!EK32) -> 0 | AO32: =SUM(AL:WY!EV32) -> 0 | AP32: =SUM(AD32:AO32) -> 0
B33: Loss Ratio Cap on UEP | C33: =SUM(AL:WY!C33) -> -32834.598 | D33: =SUM(AL:WY!D33) -> 3648.1604 | E33: =SUM(AL:WY!E33) -> 4174.065 | F33: =SUM(AL:WY!F33) -> 3655.0874 | G33: =SUM(AL:WY!G33) -> 0 | H33: =SUM(AL:WY!H33) -> 0 | I33: =SUM(AL:WY!I33) -> 0 | J33: =SUM(AL:WY!J33) -> 0 | ... O33: =SUM(AL:WY!O33) -> 0 | P33: =SUM(D33:O33) -> 11477.313 | Q33: =+C33+P33 -> -21357.285 | T33: Change in LAE DCC Reserves - Direct | U33: 100 | V33: 557100 | W33: 00 | X33: 2002 | Y33: 000212 | Z33: CA | AA33: 0000 | AC33: FUT Starlight T2 APD DRP | AD33: =SUM(AL:WY!AE33) -> 0 | AE33: =SUM(AL:WY!AP33) -> 0 | AF33: =SUM(AL:WY!BA33) -> 0 | AG33: =SUM(AL:WY!BL33) -> 0 | AH33: =SUM(AL:WY!BW33) -> 0 | AI33: =SUM(AL:WY!CH33) -> 0 | AJ33: =SUM(AL:WY!CS33) -> 0 | AK33: =SUM(AL:WY!DD33) -> 0 | AL33: =SUM(AL:WY!DO33) -> 0 | AM33: =SUM(AL:WY!DZ33) -> 0 | AN33: =SUM(AL:WY!EK33) -> 0 | AO33: =SUM(AL:WY!EV33) -> 0 | AP33: =SUM(AD33:AO33) -> 0
B34: Other Expenses Incurred | C34: =SUM(C30:C33) -> 11852.639 | D34: =SUM(D30:D33) -> 4281.7166 | E34: =SUM(E30:E33) -> 4240.3147 | F34: =SUM(F30:F33) -> 4181.9282 | G34: =SUM(G30:G33) -> 0 | H34: =SUM(H30:H33) -> 0 | I34: =SUM(I30:I33) -> 0 | J34: =SUM(J30:J33) -> 0 | ... Q34: =SUM(Q30:Q33) -> 24556.599 | T34: LAE DCC Reserves - Direct | U34: 100 | V34: 207100 | W34: 00 | X34: 2002 | Y34: 000212 | Z34: CA | AA34: 0000 | AC34: FUT Starlight T2 APD DRP | AD34: =SUM(AL:WY!AE34) -> 0 | AE34: =SUM(AL:WY!AP34) -> 0 | AF34: =SUM(AL:WY!BA34) -> 0 | AG34: =SUM(AL:WY!BL34) -> 0 | AH34: =SUM(AL:WY!BW34) -> 0 | AI34: =SUM(AL:WY!CH34) -> 0 | AJ34: =SUM(AL:WY!CS34) -> 0 | AK34: =SUM(AL:WY!DD34) -> 0 | AL34: =SUM(AL:WY!DO34) -> 0 | AM34: =SUM(AL:WY!DZ34) -> 0 | AN34: =SUM(AL:WY!EK34) -> 0 | AO34: =SUM(AL:WY!EV34) -> 0 | AP34: =SUM(AD34:AO34) -> 0
T35: LAE DCC Reserves - Ceded | U35: 100 | V35: 207300 | W35: 00 | X35: 2002 | Y35: 000212 | Z35: 00 | AA35: 0000 | AC35: FUT Starlight T2 APD DRP | AD35: =SUM(AL:WY!AE35) -> 0 | AE35: =SUM(AL:WY!AP35) -> 0 | AF35: =SUM(AL:WY!BA35) -> 0 | AG35: =SUM(AL:WY!BL35) -> 0 | AH35: =SUM(AL:WY!BW35) -> 0 | AI35: =SUM(AL:WY!CH35) -> 0 | AJ35: =SUM(AL:WY!CS35) -> 0 | AK35: =SUM(AL:WY!DD35) -> 0 | AL35: =SUM(AL:WY!DO35) -> 0 | AM35: =SUM(AL:WY!DZ35) -> 0 | AN35: =SUM(AL:WY!EK35) -> 0 | AO35: =SUM(AL:WY!EV35) -> 0 | AP35: =SUM(AD35:AO35) -> 0
T36: Change in LAE DCC Reserves - Ceded | U36: 100 | V36: 557300 | W36: 00 | X36: 2002 | Y36: 000212 | Z36: 00 | AA36: 0000 | AC36: FUT Starlight T2 APD DRP | AD36: =SUM(AL:WY!AE36) -> 0 | AE36: =SUM(AL:WY!AP36) -> 0 | AF36: =SUM(AL:WY!BA36) -> 0 | AG36: =SUM(AL:WY!BL36) -> 0 | AH36: =SUM(AL:WY!BW36) -> 0 | AI36: =SUM(AL:WY!CH36) -> 0 | AJ36: =SUM(AL:WY!CS36) -> 0 | AK36: =SUM(AL:WY!DD36) -> 0 | AL36: =SUM(AL:WY!DO36) -> 0 | AM36: =SUM(AL:WY!DZ36) -> 0 | AN36: =SUM(AL:WY!EK36) -> 0 | AO36: =SUM(AL:WY!EV36) -> 0 | AP36: =SUM(AD36:AO36) -> 0
B37: Total Profit (Loss) | C37: =+C8-C13-C18-C28-C34 -> -633736.07 | D37: =+D8-D13-D18-D28-D34 -> 50389.903 | E37: =+E8-E13-E18-E28-E34 -> 59936.049 | F37: =+F8-F13-F18-F28-F34 -> 51562.21 | G37: =+G8-G13-G18-G28-G34 -> 0 | H37: =+H8-H13-H18-H28-H34 -> 0 | I37: =+I8-I13-I18-I28-I34 -> 0 | J37: =+J8-J13-J18-J28-J34 -> 0 | ... Q37: =+Q8-Q13-Q18-Q28-Q34 -> -471847.91 | T37: Change in IBNR DCC Reserves - Direct | U37: 100 | V37: 557400 | W37: 00 | X37: 2002 | Y37: 000212 | Z37: CA | AA37: 0000 | AC37: FUT Starlight T2 APD DRP | AD37: =SUM(AL:WY!AE37) -> 0 | AE37: =SUM(AL:WY!AP37) -> 0 | AF37: =SUM(AL:WY!BA37) -> 0 | AG37: =SUM(AL:WY!BL37) -> 0 | AH37: =SUM(AL:WY!BW37) -> 0 | AI37: =SUM(AL:WY!CH37) -> 0 | AJ37: =SUM(AL:WY!CS37) -> 0 | AK37: =SUM(AL:WY!DD37) -> 0 | AL37: =SUM(AL:WY!DO37) -> 0 | AM37: =SUM(AL:WY!DZ37) -> 0 | AN37: =SUM(AL:WY!EK37) -> 0 | AO37: =SUM(AL:WY!EV37) -> 0 | AP37: =SUM(AD37:AO37) -> 0
P38: =+P37-AL!P37-AR!P37-AZ!P37-CA!P37-CO!P37-CT!P37-DE!P37-FL!P37-GA!P37-HI!P37-ID!P37-IL!P37-IN!P37-KS!P37-LA!P37-MD!P37-MI!P37-MN!P37-MO!P37-MS!P37-NC!P37-NJ!P37-NE!P37-NV!P37-NY!P37-OH!P37-OK!P37-OR!P37-PA!P37-SC!P37-SD!P37-TN!P37-TX!P37-VA!P37-WA!P37-WI!P37-WY!P37 -> -842.70435 | Q38: =+Q37-AL!Q37-AR!Q37-AZ!Q37-CA!Q37-CO!Q37-CT!Q37-DE!Q37-FL!Q37-GA!Q37-HI!Q37-ID!Q37-IL!Q37-IN!Q37-KS!Q37-LA!Q37-MD!Q37-MI!Q37-MN!Q37-MO!Q37-MS!Q37-NC!Q37-NJ!Q37-NE!Q37-NV!Q37-NY!Q37-OH!Q37-OK!Q37-OR!Q37-PA!Q37-SC!Q37-SD!Q37-TN!Q37-TX!Q37-VA!Q37-WA!Q37-WI!Q37-WY!Q37 -> -1439.0681 | T38: IBNR DCC Reserves - Direct | U38: 100 | V38: 207400 | W38: 00 | X38: 2002 | Y38: 000212 | Z38: CA | AA38: 0000 | AC38: FUT Starlight T2 APD DRP | AD38: =SUM(AL:WY!AE38) -> 0 | AE38: =SUM(AL:WY!AP38) -> 0 | AF38: =SUM(AL:WY!BA38) -> 0 | AG38: =SUM(AL:WY!BL38) -> 0 | AH38: =SUM(AL:WY!BW38) -> 0 | AI38: =SUM(AL:WY!CH38) -> 0 | AJ38: =SUM(AL:WY!CS38) -> 0 | AK38: =SUM(AL:WY!DD38) -> 0 | AL38: =SUM(AL:WY!DO38) -> 0 | AM38: =SUM(AL:WY!DZ38) -> 0 | AN38: =SUM(AL:WY!EK38) -> 0 | AO38: =SUM(AL:WY!EV38) -> 0 | AP38: =SUM(AD38:AO38) -> 0
A39: i. | B39: Reinsurance Brokerage Fee | C39: =SUM(AL:WY!C39) -> 0 | D39: =SUM(AL:WY!D39) -> 0 | E39: =SUM(AL:WY!E39) -> 0 | F39: =SUM(AL:WY!F39) -> 0 | G39: =SUM(AL:WY!G39) -> 0 | H39: =SUM(AL:WY!H39) -> 0 | I39: =SUM(AL:WY!I39) -> 0 | J39: =SUM(AL:WY!J39) -> 0 | ... O39: =SUM(AL:WY!O39) -> 0 | P39: =SUM(D39:O39) -> 0 | Q39: =+C39+P39 -> 0 | T39: IBNR DCC Reserves - Ceded | U39: 100 | V39: 207600 | W39: 00 | X39: 2002 | Y39: 000212 | Z39: 00 | AA39: 0000 | AC39: FUT Starlight T2 APD DRP | AD39: =SUM(AL:WY!AE39) -> 0 | AE39: =SUM(AL:WY!AP39) -> 0 | AF39: =SUM(AL:WY!BA39) -> 0 | AG39: =SUM(AL:WY!BL39) -> 0 | AH39: =SUM(AL:WY!BW39) -> 0 | AI39: =SUM(AL:WY!CH39) -> 0 | AJ39: =SUM(AL:WY!CS39) -> 0 | AK39: =SUM(AL:WY!DD39) -> 0 | AL39: =SUM(AL:WY!DO39) -> 0 | AM39: =SUM(AL:WY!DZ39) -> 0 | AN39: =SUM(AL:WY!EK39) -> 0 | AO39: =SUM(AL:WY!EV39) -> 0 | AP39: =SUM(AD39:AO39) -> 0
T40: Change in IBNR DCC Reserves - Ceded | U40: 100 | V40: 557600 | W40: 00 | X40: 2002 | Y40: 000212 | Z40: 00 | AA40: 0000 | AC40: FUT Starlight T2 APD DRP | AD40: =SUM(AL:WY!AE40) -> 0 | AE40: =SUM(AL:WY!AP40) -> 0 | AF40: =SUM(AL:WY!BA40) -> 0 | AG40: =SUM(AL:WY!BL40) -> 0 | AH40: =SUM(AL:WY!BW40) -> 0 | AI40: =SUM(AL:WY!CH40) -> 0 | AJ40: =SUM(AL:WY!CS40) -> 0 | AK40: =SUM(AL:WY!DD40) -> 0 | AL40: =SUM(AL:WY!DO40) -> 0 | AM40: =SUM(AL:WY!DZ40) -> 0 | AN40: =SUM(AL:WY!EK40) -> 0 | AO40: =SUM(AL:WY!EV40) -> 0 | AP40: =SUM(AD40:AO40) -> 0
B41: Net Settlement due to/(from) Reinsurer | C41: =+C6-C11-C15-C20-C23-C26-C30-C32-C39 -> 1293445.5 | D41: =+D6-D11-D15-D20-D23-D26-D30-D32-D39 -> -14965.947 | E41: =+E6-E11-E15-E20-E23-E26-E30-E32-E39 -> -43890.378 | F41: =+F6-F11-F15-F20-F23-F26-F30-F32-F39 -> -111218.91 | G41: =+G6-G11-G15-G20-G23-G26-G30-G32-G39 -> 0 | H41: =+H6-H11-H15-H20-H23-H26-H30-H32-H39 -> 0 | I41: =+I6-I11-I15-I20-I23-I26-I30-I32-I39 -> 0 | J41: =+J6-J11-J15-J20-J23-J26-J30-J32-J39 -> 0 | ... Q41: =+Q6-Q11-Q15-Q20-Q23-Q26-Q30-Q32-Q39 -> 1123370.3 | T41: Direct LAE A&O Paid | U41: 100 | V41: 602100 | W41: 00 | X41: 2002 | Y41: 000212 | Z41: CA | AA41: 0000 | AC41: FUT Starlight T2 APD DRP | AD41: =SUM(AL:WY!AE41) -> 0 | AE41: =SUM(AL:WY!AP41) -> 2167.4 | AF41: =SUM(AL:WY!BA41) -> 2127.5 | AG41: =SUM(AL:WY!BL41) -> 0 | AH41: =SUM(AL:WY!BW41) -> 0 | AI41: =SUM(AL:WY!CH41) -> 0 | AJ41: =SUM(AL:WY!CS41) -> 0 | AK41: =SUM(AL:WY!DD41) -> 0 | AL41: =SUM(AL:WY!DO41) -> 0 | AM41: =SUM(AL:WY!DZ41) -> 0 | AN41: =SUM(AL:WY!EK41) -> 0 | AO41: =SUM(AL:WY!EV41) -> 0 | AP41: =SUM(AD41:AO41) -> 4294.9
P42: =+P41-AL!P41-AR!P41-AZ!P41-CA!P41-CO!P41-CT!P41-DE!P41-FL!P41-GA!P41-HI!P41-ID!P41-IL!P41-IN!P41-KS!P41-LA!P41-MD!P41-MI!P41-MN!P41-MO!P41-MS!P41-NC!P41-NJ!P41-NE!P41-NV!P41-NY!P41-OH!P41-OK!P41-OR!P41-PA!P41-SC!P41-SD!P41-TN!P41-TX!P41-VA!P41-WA!P41-WI!P41-WY!P41 -> 2066.4582 | Q42: =+Q41-AL!Q41-AR!Q41-AZ!Q41-CA!Q41-CO!Q41-CT!Q41-DE!Q41-FL!Q41-GA!Q41-HI!Q41-ID!Q41-IL!Q41-IN!Q41-KS!Q41-LA!Q41-MD!Q41-MI!Q41-MN!Q41-MO!Q41-MS!Q41-NC!Q41-NJ!Q41-NE!Q41-NV!Q41-NY!Q41-OH!Q41-OK!Q41-OR!Q41-PA!Q41-SC!Q41-SD!Q41-TN!Q41-TX!Q41-VA!Q41-WA!Q41-WI!Q41-WY!Q41 -> 3298.4582 | T42: Payable to MGA | U42: 100 | V42: 264400 | W42: 00 | X42: 2002 | Y42: 000212 | Z42: 00 | AA42: 0000 | AC42: FUT Starlight T2 APD DRP | AD42: =SUM(AL:WY!AE42) -> 0 | AE42: =SUM(AL:WY!AP42) -> -2167.4 | AF42: =SUM(AL:WY!BA42) -> -2127.5 | AG42: =SUM(AL:WY!BL42) -> 0 | AH42: =SUM(AL:WY!BW42) -> 0 | AI42: =SUM(AL:WY!CH42) -> 0 | AJ42: =SUM(AL:WY!CS42) -> 0 | AK42: =SUM(AL:WY!DD42) -> 0 | AL42: =SUM(AL:WY!DO42) -> 0 | AM42: =SUM(AL:WY!DZ42) -> 0 | AN42: =SUM(AL:WY!EK42) -> 0 | AO42: =SUM(AL:WY!EV42) -> 0 | AP42: =SUM(AD42:AO42) -> -4294.9
A43: j. | B43: Loss Funding | C43: =SUM(AL:WY!C43) -> 0 | D43: =SUM(AL:WY!D43) -> 0 | E43: =SUM(AL:WY!E43) -> 0 | F43: =SUM(AL:WY!F43) -> 0 | G43: =SUM(AL:WY!G43) -> 0 | H43: =SUM(AL:WY!H43) -> 0 | I43: =SUM(AL:WY!I43) -> 0 | J43: =SUM(AL:WY!J43) -> 0 | ... O43: =SUM(AL:WY!O43) -> 0 | P43: =SUM(D43:O43) -> 0 | Q43: =+C43+P43 -> 0 | T43: Amounts recoverable from reinsurers | U43: 100 | V43: 125100 | W43: 00 | X43: 2002 | Y43: 000212 | Z43: 00 | AA43: 0000 | AC43: FUT Starlight T2 APD DRP | AD43: =SUM(AL:WY!AE43) -> 0 | AE43: =SUM(AL:WY!AP43) -> 2167.4 | AF43: =SUM(AL:WY!BA43) -> 2127.5 | AG43: =SUM(AL:WY!BL43) -> 0 | AH43: =SUM(AL:WY!BW43) -> 0 | AI43: =SUM(AL:WY!CH43) -> 0 | AJ43: =SUM(AL:WY!CS43) -> 0 | AK43: =SUM(AL:WY!DD43) -> 0 | AL43: =SUM(AL:WY!DO43) -> 0 | AM43: =SUM(AL:WY!DZ43) -> 0 | AN43: =SUM(AL:WY!EK43) -> 0 | AO43: =SUM(AL:WY!EV43) -> 0 | AP43: =SUM(AD43:AO43) -> 4294.9
T44: Ceded LAE A&O Paid | U44: 100 | V44: 602300 | W44: 00 | X44: 2002 | Y44: 000212 | Z44: 00 | AA44: 0000 | AC44: FUT Starlight T2 APD DRP | AD44: =SUM(AL:WY!AE44) -> 0 | AE44: =SUM(AL:WY!AP44) -> -2167.4 | AF44: =SUM(AL:WY!BA44) -> -2127.5 | AG44: =SUM(AL:WY!BL44) -> 0 | AH44: =SUM(AL:WY!BW44) -> 0 | AI44: =SUM(AL:WY!CH44) -> 0 | AJ44: =SUM(AL:WY!CS44) -> 0 | AK44: =SUM(AL:WY!DD44) -> 0 | AL44: =SUM(AL:WY!DO44) -> 0 | AM44: =SUM(AL:WY!DZ44) -> 0 | AN44: =SUM(AL:WY!EK44) -> 0 | AO44: =SUM(AL:WY!EV44) -> 0 | AP44: =SUM(AD44:AO44) -> -4294.9
B45: Net Settlement due from NTA | C45: =+C6-C11-C15-C20-C23-C26-C43 -> 1344699.7 | D45: =+D6-D11-D15-D20-D23-D26-D43 -> -15062.022 | E45: =+E6-E11-E15-E20-E23-E26-E43 -> -44658.941 | F45: =+F6-F11-F15-F20-F23-F26-F43 -> -111423.09 | G45: =+G6-G11-G15-G20-G23-G26-G43 -> 0 | H45: =+H6-H11-H15-H20-H23-H26-H43 -> 0 | I45: =+I6-I11-I15-I20-I23-I26-I43 -> 0 | J45: =+J6-J11-J15-J20-J23-J26-J43 -> 0 | ... Q45: =+Q6-Q11-Q15-Q20-Q23-Q26-Q43 -> 1173555.7 | T45: Change in LAE A&O Reserves - Direct | U45: 100 | V45: 558100 | W45: 00 | X45: 2002 | Y45: 000212 | Z45: CA | AA45: 0000 | AC45: FUT Starlight T2 APD DRP | AD45: =SUM(AL:WY!AE45) -> 5000 | AE45: =SUM(AL:WY!AP45) -> 3692.6 | AF45: =SUM(AL:WY!BA45) -> -5597.6 | AG45: =SUM(AL:WY!BL45) -> 0 | AH45: =SUM(AL:WY!BW45) -> 0 | AI45: =SUM(AL:WY!CH45) -> 0 | AJ45: =SUM(AL:WY!CS45) -> 0 | AK45: =SUM(AL:WY!DD45) -> 0 | AL45: =SUM(AL:WY!DO45) -> 0 | AM45: =SUM(AL:WY!DZ45) -> 0 | AN45: =SUM(AL:WY!EK45) -> 0 | AO45: =SUM(AL:WY!EV45) -> 0 | AP45: =SUM(AD45:AO45) -> 3095
P46: =+P45-AL!P45-AR!P45-AZ!P45-CA!P45-CO!P45-CT!P45-DE!P45-FL!P45-GA!P45-HI!P45-ID!P45-IL!P45-IN!P45-KS!P45-LA!P45-MD!P45-MI!P45-MN!P45-MO!P45-MS!P45-NC!P45-NJ!P45-NE!P45-NV!P45-NY!P45-OH!P45-OK!P45-OR!P45-PA!P45-SC!P45-SD!P45-TN!P45-TX!P45-VA!P45-WA!P45-WI!P45-WY!P45 -> 2146.9696 | Q46: =+Q45-AL!Q45-AR!Q45-AZ!Q45-CA!Q45-CO!Q45-CT!Q45-DE!Q45-FL!Q45-GA!Q45-HI!Q45-ID!Q45-IL!Q45-IN!Q45-KS!Q45-LA!Q45-MD!Q45-MI!Q45-MN!Q45-MO!Q45-MS!Q45-NC!Q45-NJ!Q45-NE!Q45-NV!Q45-NY!Q45-OH!Q45-OK!Q45-OR!Q45-PA!Q45-SC!Q45-SD!Q45-TN!Q45-TX!Q45-VA!Q45-WA!Q45-WI!Q45-WY!Q45 -> 3426.9696 | T46: LAE A&O Reserves - Direct | U46: 100 | V46: 208100 | W46: 00 | X46: 2002 | Y46: 000212 | Z46: CA | AA46: 0000 | AC46: FUT Starlight T2 APD DRP | AD46: =SUM(AL:WY!AE46) -> -5000 | AE46: =SUM(AL:WY!AP46) -> -3692.6 | AF46: =SUM(AL:WY!BA46) -> 5597.6 | AG46: =SUM(AL:WY!BL46) -> 0 | AH46: =SUM(AL:WY!BW46) -> 0 | AI46: =SUM(AL:WY!CH46) -> 0 | AJ46: =SUM(AL:WY!CS46) -> 0 | AK46: =SUM(AL:WY!DD46) -> 0 | AL46: =SUM(AL:WY!DO46) -> 0 | AM46: =SUM(AL:WY!DZ46) -> 0 | AN46: =SUM(AL:WY!EK46) -> 0 | AO46: =SUM(AL:WY!EV46) -> 0 | AP46: =SUM(AD46:AO46) -> -3095
B47: Fronting Fee @ 5% (paid by separate wire from NTA) | C47: =SUM(AL:WY!C47) -> 106779.49 | D47: =SUM(AL:WY!D47) -> -200.158 | E47: =SUM(AL:WY!E47) -> -1601.1735 | F47: =SUM(AL:WY!F47) -> -425.368 | G47: =SUM(AL:WY!G47) -> 0 | H47: =SUM(AL:WY!H47) -> 0 | I47: =SUM(AL:WY!I47) -> 0 | J47: =SUM(AL:WY!J47) -> 0 | ... O47: =SUM(AL:WY!O47) -> 0 | P47: =SUM(D47:O47) -> -2226.6995 | Q47: =+C47+P47 -> 104552.79 | T47: LAE A&O Reserves - Ceded | U47: 100 | V47: 208300 | W47: 00 | X47: 2002 | Y47: 000212 | Z47: 00 | AA47: 0000 | AC47: FUT Starlight T2 APD DRP | AD47: =SUM(AL:WY!AE47) -> 5000 | AE47: =SUM(AL:WY!AP47) -> 3692.6 | AF47: =SUM(AL:WY!BA47) -> -5597.6 | AG47: =SUM(AL:WY!BL47) -> 0 | AH47: =SUM(AL:WY!BW47) -> 0 | AI47: =SUM(AL:WY!CH47) -> 0 | AJ47: =SUM(AL:WY!CS47) -> 0 | AK47: =SUM(AL:WY!DD47) -> 0 | AL47: =SUM(AL:WY!DO47) -> 0 | AM47: =SUM(AL:WY!DZ47) -> 0 | AN47: =SUM(AL:WY!EK47) -> 0 | AO47: =SUM(AL:WY!EV47) -> 0 | AP47: =SUM(AD47:AO47) -> 3095
B48: Fronting Fee on UEP | C48: =SUM(AL:WY!C48) -> -82086.495 | D48: =SUM(AL:WY!D48) -> 9120.401 | E48: =SUM(AL:WY!E48) -> 10435.163 | F48: =SUM(AL:WY!F48) -> 9137.7185 | G48: =SUM(AL:WY!G48) -> 0 | H48: =SUM(AL:WY!H48) -> 0 | I48: =SUM(AL:WY!I48) -> 0 | J48: =SUM(AL:WY!J48) -> 0 | ... O48: =SUM(AL:WY!O48) -> 0 | P48: =SUM(D48:O48) -> 28693.282 | Q48: =+C48+P48 -> -53393.213 | T48: Change in LAE A&O Reserves - Ceded | U48: 100 | V48: 558300 | W48: 00 | X48: 2002 | Y48: 000212 | Z48: 00 | AA48: 0000 | AC48: FUT Starlight T2 APD DRP | AD48: =SUM(AL:WY!AE48) -> -5000 | AE48: =SUM(AL:WY!AP48) -> -3692.6 | AF48: =SUM(AL:WY!BA48) -> 5597.6 | AG48: =SUM(AL:WY!BL48) -> 0 | AH48: =SUM(AL:WY!BW48) -> 0 | AI48: =SUM(AL:WY!CH48) -> 0 | AJ48: =SUM(AL:WY!CS48) -> 0 | AK48: =SUM(AL:WY!DD48) -> 0 | AL48: =SUM(AL:WY!DO48) -> 0 | AM48: =SUM(AL:WY!DZ48) -> 0 | AN48: =SUM(AL:WY!EK48) -> 0 | AO48: =SUM(AL:WY!EV48) -> 0 | AP48: =SUM(AD48:AO48) -> -3095
B49: Total Fees Earned - SSIC | C49: =+C34+C47+C48 -> 36545.638 | D49: =+D34+D47+D48 -> 13201.96 | E49: =+E34+E47+E48 -> 13074.304 | F49: =+F34+F47+F48 -> 12894.279 | G49: =+G34+G47+G48 -> 0 | H49: =+H34+H47+H48 -> 0 | I49: =+I34+I47+I48 -> 0 | J49: =+J34+J47+J48 -> 0 | ... Q49: =+Q34+Q47+Q48 -> 75716.18 | T49: Change in IBNR A&O Reserves - Direct | U49: 100 | V49: 558400 | W49: 00 | X49: 2002 | Y49: 000212 | Z49: CA | AA49: 0000 | AC49: FUT Starlight T2 APD DRP | AD49: =SUM(AL:WY!AE49) -> 18906.251 | AE49: =SUM(AL:WY!AP49) -> 17815.091 | AF49: =SUM(AL:WY!BA49) -> 26819.199 | AG49: =SUM(AL:WY!BL49) -> 0 | AH49: =SUM(AL:WY!BW49) -> 0 | AI49: =SUM(AL:WY!CH49) -> 0 | AJ49: =SUM(AL:WY!CS49) -> 0 | AK49: =SUM(AL:WY!DD49) -> 0 | AL49: =SUM(AL:WY!DO49) -> 0 | AM49: =SUM(AL:WY!DZ49) -> 0 | AN49: =SUM(AL:WY!EK49) -> 0 | AO49: =SUM(AL:WY!EV49) -> 0 | AP49: =SUM(AD49:AO49) -> 63540.541
P50: =+P49-AL!P49-AR!P49-AZ!P49-CA!P49-CO!P49-CT!P49-DE!P49-FL!P49-GA!P49-HI!P49-ID!P49-IL!P49-IN!P49-KS!P49-LA!P49-MD!P49-MI!P49-MN!P49-MO!P49-MS!P49-NC!P49-NJ!P49-NE!P49-NV!P49-NY!P49-OH!P49-OK!P49-OR!P49-PA!P49-SC!P49-SD!P49-TN!P49-TX!P49-VA!P49-WA!P49-WI!P49-WY!P49 -> 98.86696 | Q50: =+Q49-AL!Q49-AR!Q49-AZ!Q49-CA!Q49-CO!Q49-CT!Q49-DE!Q49-FL!Q49-GA!Q49-HI!Q49-ID!Q49-IL!Q49-IN!Q49-KS!Q49-LA!Q49-MD!Q49-MI!Q49-MN!Q49-MO!Q49-MS!Q49-NC!Q49-NJ!Q49-NE!Q49-NV!Q49-NY!Q49-OH!Q49-OK!Q49-OR!Q49-PA!Q49-SC!Q49-SD!Q49-TN!Q49-TX!Q49-VA!Q49-WA!Q49-WI!Q49-WY!Q49 -> 132.52142 | T50: IBNR A&O Reserves - Direct | U50: 100 | V50: 208400 | W50: 00 | X50: 2002 | Y50: 000212 | Z50: CA | AA50: 0000 | AC50: FUT Starlight T2 APD DRP | AD50: =SUM(AL:WY!AE50) -> -18906.251 | AE50: =SUM(AL:WY!AP50) -> -17815.091 | AF50: =SUM(AL:WY!BA50) -> -26819.199 | AG50: =SUM(AL:WY!BL50) -> 0 | AH50: =SUM(AL:WY!BW50) -> 0 | AI50: =SUM(AL:WY!CH50) -> 0 | AJ50: =SUM(AL:WY!CS50) -> 0 | AK50: =SUM(AL:WY!DD50) -> 0 | AL50: =SUM(AL:WY!DO50) -> 0 | AM50: =SUM(AL:WY!DZ50) -> 0 | AN50: =SUM(AL:WY!EK50) -> 0 | AO50: =SUM(AL:WY!EV50) -> 0 | AP50: =SUM(AD50:AO50) -> -63540.541
B51: Unearned Premium Reserve | C51: =SUM(AL:WY!C51) -> 1641729.9 | D51: =SUM(AL:WY!D51) -> 1459321.9 | E51: =SUM(AL:WY!E51) -> 1250618.6 | F51: =SUM(AL:WY!F51) -> 1067864.3 | G51: =SUM(AL:WY!G51) -> 0 | H51: =SUM(AL:WY!H51) -> 0 | I51: =SUM(AL:WY!I51) -> 0 | J51: =SUM(AL:WY!J51) -> 0 | ... O51: =SUM(AL:WY!O51) -> 0 | P51: =+F51 -> 1067864.3 | Q51: =SUM(AL:WY!Q51) -> 1067864.3 | R51: =SUM(AL:WY!R51) -> 1067864.3 | S51: =Q51-R51 -> 0 | T51: IBNR A&O Reserves - Ceded | U51: 100 | V51: 208600 | W51: 00 | X51: 2002 | Y51: 000212 | Z51: 00 | AA51: 0000 | AC51: FUT Starlight T2 APD DRP | AD51: =SUM(AL:WY!AE51) -> 18906.251 | AE51: =SUM(AL:WY!AP51) -> 17815.091 | AF51: =SUM(AL:WY!BA51) -> 26819.199 | AG51: =SUM(AL:WY!BL51) -> 0 | AH51: =SUM(AL:WY!BW51) -> 0 | AI51: =SUM(AL:WY!CH51) -> 0 | AJ51: =SUM(AL:WY!CS51) -> 0 | AK51: =SUM(AL:WY!DD51) -> 0 | AL51: =SUM(AL:WY!DO51) -> 0 | AM51: =SUM(AL:WY!DZ51) -> 0 | AN51: =SUM(AL:WY!EK51) -> 0 | AO51: =SUM(AL:WY!EV51) -> 0 | AP51: =SUM(AD51:AO51) -> 63540.541
B52: Loss Reserves | C52: =SUM(AL:WY!C52) -> 25000 | D52: =SUM(AL:WY!D52) -> 85564 | E52: =SUM(AL:WY!E52) -> 99164.51 | F52: =SUM(AL:WY!F52) -> 251664.51 | G52: =SUM(AL:WY!G52) -> 0 | H52: =SUM(AL:WY!H52) -> 0 | I52: =SUM(AL:WY!I52) -> 0 | J52: =SUM(AL:WY!J52) -> 0 | ... O52: =SUM(AL:WY!O52) -> 0 | P52: =+F52 -> 251664.51 | Q52: =SUM(AL:WY!Q52) -> 251664.51 | R52: =SUM(AL:WY!R52) -> 251664.51 | S52: =Q52-R52 -> 0 | T52: Change in IBNR A&O Reserves - Ceded | U52: 100 | V52: 558600 | W52: 00 | X52: 2002 | Y52: 000212 | Z52: 00 | AA52: 0000 | AC52: FUT Starlight T2 APD DRP | AD52: =SUM(AL:WY!AE52) -> -18906.251 | AE52: =SUM(AL:WY!AP52) -> -17815.091 | AF52: =SUM(AL:WY!BA52) -> -26819.199 | AG52: =SUM(AL:WY!BL52) -> 0 | AH52: =SUM(AL:WY!BW52) -> 0 | AI52: =SUM(AL:WY!CH52) -> 0 | AJ52: =SUM(AL:WY!CS52) -> 0 | AK52: =SUM(AL:WY!DD52) -> 0 | AL52: =SUM(AL:WY!DO52) -> 0 | AM52: =SUM(AL:WY!DZ52) -> 0 | AN52: =SUM(AL:WY!EK52) -> 0 | AO52: =SUM(AL:WY!EV52) -> 0 | AP52: =SUM(AD52:AO52) -> -63540.541
B53: Loss IBNR Reserves | C53: =SUM(AL:WY!C53) -> 233314.43 | D53: =SUM(AL:WY!D53) -> 261227.58 | E53: =SUM(AL:WY!E53) -> 325631.31 | F53: =SUM(AL:WY!F53) -> 167904.24 | G53: =SUM(AL:WY!G53) -> 0 | H53: =SUM(AL:WY!H53) -> 0 | I53: =SUM(AL:WY!I53) -> 0 | J53: =SUM(AL:WY!J53) -> 0 | ... O53: =SUM(AL:WY!O53) -> 0 | P53: =+P65-P15-P16+C53 -> 167904.24 | Q53: =SUM(AL:WY!Q53) -> 167904.24 | T53: Direct ULAE Paid | U53: 100 | V53: 603100 | W53: 00 | X53: 2002 | Y53: 000212 | Z53: CA | AA53: 0000 | AC53: FUT Starlight T2 APD DRP | AD53: =SUM(AL:WY!AE53) -> -280.2212 | AE53: =SUM(AL:WY!AP53) -> -2241.6429 | AF53: =SUM(AL:WY!BA53) -> -595.5152 | AG53: =SUM(AL:WY!BL53) -> 0 | AH53: =SUM(AL:WY!BW53) -> 0 | AI53: =SUM(AL:WY!CH53) -> 0 | AJ53: =SUM(AL:WY!CS53) -> 0 | AK53: =SUM(AL:WY!DD53) -> 0 | AL53: =SUM(AL:WY!DO53) -> 0 | AM53: =SUM(AL:WY!DZ53) -> 0 | AN53: =SUM(AL:WY!EK53) -> 0 | AO53: =SUM(AL:WY!EV53) -> 0 | AP53: =SUM(AD53:AO53) -> -3117.3793
B54: LAE Reserves - DCC | C54: =SUM(AL:WY!C54) -> 0 | D54: =SUM(AL:WY!D54) -> 0 | E54: =SUM(AL:WY!E54) -> 0 | F54: =SUM(AL:WY!F54) -> 0 | G54: =SUM(AL:WY!G54) -> 0 | H54: =SUM(AL:WY!H54) -> 0 | I54: =SUM(AL:WY!I54) -> 0 | J54: =SUM(AL:WY!J54) -> 0 | ... O54: =SUM(AL:WY!O54) -> 0 | P54: =+F54 -> 0 | Q54: =SUM(AL:WY!Q54) -> 0 | R54: =SUM(AL:WY!R54) -> 0 | S54: =Q54-R54 -> 0 | T54: Payable to MGA | U54: 100 | V54: 264400 | W54: 00 | X54: 2002 | Y54: 000212 | Z54: 00 | AA54: 0000 | AC54: FUT Starlight T2 APD DRP | AD54: =SUM(AL:WY!AE54) -> 280.2212 | AE54: =SUM(AL:WY!AP54) -> 2241.6429 | AF54: =SUM(AL:WY!BA54) -> 595.5152 | AG54: =SUM(AL:WY!BL54) -> 0 | AH54: =SUM(AL:WY!BW54) -> 0 | AI54: =SUM(AL:WY!CH54) -> 0 | AJ54: =SUM(AL:WY!CS54) -> 0 | AK54: =SUM(AL:WY!DD54) -> 0 | AL54: =SUM(AL:WY!DO54) -> 0 | AM54: =SUM(AL:WY!DZ54) -> 0 | AN54: =SUM(AL:WY!EK54) -> 0 | AO54: =SUM(AL:WY!EV54) -> 0 | AP54: =SUM(AD54:AO54) -> 3117.3793
B55: LAE IBNR Reserves - DCC | C55: =SUM(AL:WY!C55) -> 0 | D55: =SUM(AL:WY!D55) -> 0 | E55: =SUM(AL:WY!E55) -> 0 | F55: =SUM(AL:WY!F55) -> 0 | G55: =SUM(AL:WY!G55) -> 0 | H55: =SUM(AL:WY!H55) -> 0 | I55: =SUM(AL:WY!I55) -> 0 | J55: =SUM(AL:WY!J55) -> 0 | ... O55: =SUM(AL:WY!O55) -> 0 | P55: =+F55 -> 0 | Q55: =SUM(AL:WY!Q55) -> 0 | T55: Amounts recoverable from reinsurers | U55: 100 | V55: 125100 | W55: 00 | X55: 2002 | Y55: 000212 | Z55: 00 | AA55: 0000 | AC55: FUT Starlight T2 APD DRP | AD55: =SUM(AL:WY!AE55) -> -280.2212 | AE55: =SUM(AL:WY!AP55) -> -2241.6429 | AF55: =SUM(AL:WY!BA55) -> -595.5152 | AG55: =SUM(AL:WY!BL55) -> 0 | AH55: =SUM(AL:WY!BW55) -> 0 | AI55: =SUM(AL:WY!CH55) -> 0 | AJ55: =SUM(AL:WY!CS55) -> 0 | AK55: =SUM(AL:WY!DD55) -> 0 | AL55: =SUM(AL:WY!DO55) -> 0 | AM55: =SUM(AL:WY!DZ55) -> 0 | AN55: =SUM(AL:WY!EK55) -> 0 | AO55: =SUM(AL:WY!EV55) -> 0 | AP55: =SUM(AD55:AO55) -> -3117.3793
B56: LAE Reserves - AOE | C56: =SUM(AL:WY!C56) -> 12500 | D56: =SUM(AL:WY!D56) -> 17500 | E56: =SUM(AL:WY!E56) -> 21192.6 | F56: =SUM(AL:WY!F56) -> 15595 | G56: =SUM(AL:WY!G56) -> 0 | H56: =SUM(AL:WY!H56) -> 0 | I56: =SUM(AL:WY!I56) -> 0 | J56: =SUM(AL:WY!J56) -> 0 | ... O56: =SUM(AL:WY!O56) -> 0 | P56: =+F56 -> 15595 | Q56: =SUM(AL:WY!Q56) -> 15595 | R56: =SUM(AL:WY!R56) -> 15595 | S56: =Q56-R56 -> 0 | T56: Ceded ULAE Paid | U56: 100 | V56: 603300 | W56: 00 | X56: 2002 | Y56: 000212 | Z56: 00 | AA56: 0000 | AC56: FUT Starlight T2 APD DRP | AD56: =SUM(AL:WY!AE56) -> 280.2212 | AE56: =SUM(AL:WY!AP56) -> 2241.6429 | AF56: =SUM(AL:WY!BA56) -> 595.5152 | AG56: =SUM(AL:WY!BL56) -> 0 | AH56: =SUM(AL:WY!BW56) -> 0 | AI56: =SUM(AL:WY!CH56) -> 0 | AJ56: =SUM(AL:WY!CS56) -> 0 | AK56: =SUM(AL:WY!DD56) -> 0 | AL56: =SUM(AL:WY!DO56) -> 0 | AM56: =SUM(AL:WY!DZ56) -> 0 | AN56: =SUM(AL:WY!EK56) -> 0 | AO56: =SUM(AL:WY!EV56) -> 0 | AP56: =SUM(AD56:AO56) -> 3117.3793
B57: LAE IBNR Reserves - AOE | C57: =SUM(AL:WY!C57) -> 52809.736 | D57: =SUM(AL:WY!D57) -> 71715.987 | E57: =SUM(AL:WY!E57) -> 89531.078 | F57: =SUM(AL:WY!F57) -> 116350.28 | G57: =SUM(AL:WY!G57) -> 0 | H57: =SUM(AL:WY!H57) -> 0 | I57: =SUM(AL:WY!I57) -> 0 | J57: =SUM(AL:WY!J57) -> 0 | ... O57: =SUM(AL:WY!O57) -> 0 | P57: =+P67-P23-P24+C57 -> 116350.28 | Q57: =SUM(AL:WY!Q57) -> 116350.28 | T57: Change in IBNR ULAE Reserves - Direct | U57: 100 | V57: 559400 | W57: 00 | X57: 2002 | Y57: 000212 | Z57: CA | AA57: 0000 | AC57: FUT Starlight T2 APD DRP | AD57: =SUM(AL:WY!AE57) -> 290.97575 | AE57: =SUM(AL:WY!AP57) -> 356.0199 | AF57: =SUM(AL:WY!BA57) -> -407.38536 | AG57: =SUM(AL:WY!BL57) -> 0 | AH57: =SUM(AL:WY!BW57) -> 0 | AI57: =SUM(AL:WY!CH57) -> 0 | AJ57: =SUM(AL:WY!CS57) -> 0 | AK57: =SUM(AL:WY!DD57) -> 0 | AL57: =SUM(AL:WY!DO57) -> 0 | AM57: =SUM(AL:WY!DZ57) -> 0 | AN57: =SUM(AL:WY!EK57) -> 0 | AO57: =SUM(AL:WY!EV57) -> 0 | AP57: =SUM(AD57:AO57) -> 239.61029
B58: ULAE IBNR Reserves | C58: =SUM(AL:WY!C58) -> 1229.0722 | D58: =SUM(AL:WY!D58) -> 1520.0479 | E58: =SUM(AL:WY!E58) -> 1876.0678 | F58: =SUM(AL:WY!F58) -> 1468.6825 | G58: =SUM(AL:WY!G58) -> 0 | H58: =SUM(AL:WY!H58) -> 0 | I58: =SUM(AL:WY!I58) -> 0 | J58: =SUM(AL:WY!J58) -> 0 | ... O58: =SUM(AL:WY!O58) -> 0 | P58: =+F58 -> 1468.6825 | Q58: =SUM(AL:WY!Q58) -> 1468.6825 | T58: IBNR ULAE Reserves - Direct | U58: 100 | V58: 209400 | W58: 00 | X58: 2002 | Y58: 000212 | Z58: CA | AA58: 0000 | AC58: FUT Starlight T2 APD DRP | AD58: =SUM(AL:WY!AE58) -> -290.97575 | AE58: =SUM(AL:WY!AP58) -> -356.0199 | AF58: =SUM(AL:WY!BA58) -> 407.38536 | AG58: =SUM(AL:WY!BL58) -> 0 | AH58: =SUM(AL:WY!BW58) -> 0 | AI58: =SUM(AL:WY!CH58) -> 0 | AJ58: =SUM(AL:WY!CS58) -> 0 | AK58: =SUM(AL:WY!DD58) -> 0 | AL58: =SUM(AL:WY!DO58) -> 0 | AM58: =SUM(AL:WY!DZ58) -> 0 | AN58: =SUM(AL:WY!EK58) -> 0 | AO58: =SUM(AL:WY!EV58) -> 0 | AP58: =SUM(AD58:AO58) -> -239.61029
T59: IBNR ULAE Reserves - Ceded | U59: 100 | V59: 209600 | W59: 00 | X59: 2002 | Y59: 000212 | Z59: 00 | AA59: 0000 | AC59: FUT Starlight T2 APD DRP | AD59: =SUM(AL:WY!AE59) -> 290.97575 | AE59: =SUM(AL:WY!AP59) -> 356.0199 | AF59: =SUM(AL:WY!BA59) -> -407.38536 | AG59: =SUM(AL:WY!BL59) -> 0 | AH59: =SUM(AL:WY!BW59) -> 0 | AI59: =SUM(AL:WY!CH59) -> 0 | AJ59: =SUM(AL:WY!CS59) -> 0 | AK59: =SUM(AL:WY!DD59) -> 0 | AL59: =SUM(AL:WY!DO59) -> 0 | AM59: =SUM(AL:WY!DZ59) -> 0 | AN59: =SUM(AL:WY!EK59) -> 0 | AO59: =SUM(AL:WY!EV59) -> 0 | AP59: =SUM(AD59:AO59) -> 239.61029
B60: Loss Pick | C60: =+C18/C8 -> 0.566 | D60: =+D18/D8 -> 0.566 | E60: =+E18/E8 -> 0.566 | F60: =+F18/F8 -> 0.566 | G60: =+G18/G8 -> #DIV/0! | H60: =+H18/H8 -> #DIV/0! | I60: =+I18/I8 -> #DIV/0! | J60: =+J18/J8 -> #DIV/0! | ... Q60: =+Q18/Q8 -> 0.566 | T60: Change in IBNR ULAE Reserves - Ceded | U60: 100 | V60: 559600 | W60: 00 | X60: 2002 | Y60: 000212 | Z60: 00 | AA60: 0000 | AC60: FUT Starlight T2 APD DRP | AD60: =SUM(AL:WY!AE60) -> -290.97575 | AE60: =SUM(AL:WY!AP60) -> -356.0199 | AF60: =SUM(AL:WY!BA60) -> 407.38536 | AG60: =SUM(AL:WY!BL60) -> 0 | AH60: =SUM(AL:WY!BW60) -> 0 | AI60: =SUM(AL:WY!CH60) -> 0 | AJ60: =SUM(AL:WY!CS60) -> 0 | AK60: =SUM(AL:WY!DD60) -> 0 | AL60: =SUM(AL:WY!DO60) -> 0 | AM60: =SUM(AL:WY!DZ60) -> 0 | AN60: =SUM(AL:WY!EK60) -> 0 | AO60: =SUM(AL:WY!EV60) -> 0 | AP60: =SUM(AD60:AO60) -> -239.61029
B61: LAE - DCC | C61: =SUM(C20:C22)/C8 -> 0 | D61: =SUM(D20:D22)/D8 -> 0 | E61: =SUM(E20:E22)/E8 -> 0 | F61: =SUM(F20:F22)/F8 -> 0 | G61: =SUM(G20:G22)/G8 -> #DIV/0! | H61: =SUM(H20:H22)/H8 -> #DIV/0! | I61: =SUM(I20:I22)/I8 -> #DIV/0! | J61: =SUM(J20:J22)/J8 -> #DIV/0! | ... Q61: =SUM(Q20:Q22)/Q8 -> 0 | T61: Other amounts recoverable from reinsurers | U61: 100 | V61: 127100 | W61: 00 | X61: 2002 | Y61: 000212 | Z61: 00 | AA61: 0000 | AC61: FUT Starlight T2 APD DRP | AD61: =SUM(AL:WY!AE61) -> -16.01264 | AE61: =SUM(AL:WY!AP61) -> -128.09388 | AF61: =SUM(AL:WY!BA61) -> -34.02944 | AG61: =SUM(AL:WY!BL61) -> 0 | AH61: =SUM(AL:WY!BW61) -> 0 | AI61: =SUM(AL:WY!CH61) -> 0 | AJ61: =SUM(AL:WY!CS61) -> 0 | AK61: =SUM(AL:WY!DD61) -> 0 | AL61: =SUM(AL:WY!DO61) -> 0 | AM61: =SUM(AL:WY!DZ61) -> 0 | AN61: =SUM(AL:WY!EK61) -> 0 | AO61: =SUM(AL:WY!EV61) -> 0 | AP61: =SUM(AD61:AO61) -> -178.13596
B62: LAE - AOE | C62: =SUM(C23:C25)/C8 -> 0.134 | D62: =SUM(D23:D25)/D8 -> 0.134 | E62: =SUM(E23:E25)/E8 -> 0.134 | F62: =SUM(F23:F25)/F8 -> 0.134 | G62: =SUM(G23:G25)/G8 -> #DIV/0! | H62: =SUM(H23:H25)/H8 -> #DIV/0! | I62: =SUM(I23:I25)/I8 -> #DIV/0! | J62: =SUM(J23:J25)/J8 -> #DIV/0! | ... Q62: =SUM(Q23:Q25)/Q8 -> 0.134 | T62: Commissions Ceded | U62: 100 | V62: 500300 | W62: 00 | X62: 2002 | Y62: 000212 | Z62: 00 | AA62: 0000 | AC62: FUT Starlight T2 APD DRP | AD62: =SUM(AL:WY!AE62) -> 16.01264 | AE62: =SUM(AL:WY!AP62) -> 128.09388 | AF62: =SUM(AL:WY!BA62) -> 34.02944 | AG62: =SUM(AL:WY!BL62) -> 0 | AH62: =SUM(AL:WY!BW62) -> 0 | AI62: =SUM(AL:WY!CH62) -> 0 | AJ62: =SUM(AL:WY!CS62) -> 0 | AK62: =SUM(AL:WY!DD62) -> 0 | AL62: =SUM(AL:WY!DO62) -> 0 | AM62: =SUM(AL:WY!DZ62) -> 0 | AN62: =SUM(AL:WY!EK62) -> 0 | AO62: =SUM(AL:WY!EV62) -> 0 | AP62: =SUM(AD62:AO62) -> 178.13596
B63: Total Loss Pick | C63: =SUM(C60:C62) -> 0.7 | D63: =SUM(D60:D62) -> 0.7 | E63: =SUM(E60:E62) -> 0.7 | F63: =SUM(F60:F62) -> 0.7 | G63: =SUM(G60:G62) -> #DIV/0! | H63: =SUM(H60:H62) -> #DIV/0! | I63: =SUM(I60:I62) -> #DIV/0! | J63: =SUM(J60:J62) -> #DIV/0! | ... Q63: =SUM(Q60:Q62) -> 0.7 | T63: Commissions Ceded | U63: 100 | V63: 500300 | W63: 00 | X63: 2002 | Y63: 000212 | Z63: 00 | AA63: 0000 | AC63: FUT Starlight T2 APD DRP | AD63: =SUM(AL:WY!AE63) -> -729.63208 | AE63: =SUM(AL:WY!AP63) -> -834.813 | AF63: =SUM(AL:WY!BA63) -> -731.01748 | AG63: =SUM(AL:WY!BL63) -> 0 | AH63: =SUM(AL:WY!BW63) -> 0 | AI63: =SUM(AL:WY!CH63) -> 0 | AJ63: =SUM(AL:WY!CS63) -> 0 | AK63: =SUM(AL:WY!DD63) -> 0 | AL63: =SUM(AL:WY!DO63) -> 0 | AM63: =SUM(AL:WY!DZ63) -> 0 | AN63: =SUM(AL:WY!EK63) -> 0 | AO63: =SUM(AL:WY!EV63) -> 0 | AP63: =SUM(AD63:AO63) -> -2295.4626
T64: Deferred Ceding Commissions | U64: 100 | V64: 243200 | W64: 00 | X64: 2002 | Y64: 000212 | Z64: 00 | AA64: 0000 | AC64: FUT Starlight T2 APD DRP | AD64: =SUM(AL:WY!AE64) -> 729.63208 | AE64: =SUM(AL:WY!AP64) -> 834.813 | AF64: =SUM(AL:WY!BA64) -> 731.01748 | AG64: =SUM(AL:WY!BL64) -> 0 | AH64: =SUM(AL:WY!BW64) -> 0 | AI64: =SUM(AL:WY!CH64) -> 0 | AJ64: =SUM(AL:WY!CS64) -> 0 | AK64: =SUM(AL:WY!DD64) -> 0 | AL64: =SUM(AL:WY!DO64) -> 0 | AM64: =SUM(AL:WY!DZ64) -> 0 | AN64: =SUM(AL:WY!EK64) -> 0 | AO64: =SUM(AL:WY!EV64) -> 0 | AP64: =SUM(AD64:AO64) -> 2295.4626
B65: Ultimate Loss | C65: =C$8*C60 -> 279524.74 | D65: =D$8*D60 -> 100977.15 | E65: =E$8*E60 -> 100000.76 | F65: =F$8*F60 -> 98623.808 | G65: =G$8*G60 -> #DIV/0! | H65: =H$8*H60 -> #DIV/0! | I65: =I$8*I60 -> #DIV/0! | J65: =J$8*J60 -> #DIV/0! | ... P65: =P$8*P60 -> 299601.71 | Q65: =+Q8*Q60 -> 579126.46 | R65: =+AL!Q65+CA!Q65+AR!Q65+AZ!Q65+CO!Q65+CT!Q65+DE!Q65+FL!Q65+GA!Q65+HI!Q65+ID!Q65+IL!Q65+IN!Q65+KS!Q65+LA!Q65+MD!Q65+MI!Q65+MN!Q65+MO!Q65+MS!Q65+NC!Q65+NJ!Q65+NE!Q65+NV!Q65+NY!Q65+OH!Q65+OK!Q65+OR!Q65+PA!Q65+SC!Q65+SD!Q65+TN!Q65+TX!Q65+VA!Q65+WA!Q65+WI!Q65+WY!Q65-Q65 -> #DIV/0! | T65: Ceded Reinsurance Premiums Payable | U65: 100 | V65: 243100 | W65: 00 | X65: 2002 | Y65: 000212 | Z65: 00 | AA65: 0000 | AC65: FUT Starlight T2 APD DRP | AD65: =SUM(AL:WY!AE65) -> -80.0632 | AE65: =SUM(AL:WY!AP65) -> -640.4694 | AF65: =SUM(AL:WY!BA65) -> -170.1472 | AG65: =SUM(AL:WY!BL65) -> 0 | AH65: =SUM(AL:WY!BW65) -> 0 | AI65: =SUM(AL:WY!CH65) -> 0 | AJ65: =SUM(AL:WY!CS65) -> 0 | AK65: =SUM(AL:WY!DD65) -> 0 | AL65: =SUM(AL:WY!DO65) -> 0 | AM65: =SUM(AL:WY!DZ65) -> 0 | AN65: =SUM(AL:WY!EK65) -> 0 | AO65: =SUM(AL:WY!EV65) -> 0 | AP65: =SUM(AD65:AO65) -> -890.6798
B66: Ultimate LAE - DCC | C66: =C$8*C61 -> 0 | D66: =D$8*D61 -> 0 | E66: =E$8*E61 -> 0 | F66: =F$8*F61 -> 0 | G66: =G$8*G61 -> #DIV/0! | H66: =H$8*H61 -> #DIV/0! | I66: =I$8*I61 -> #DIV/0! | J66: =J$8*J61 -> #DIV/0! | ... P66: =P$8*P61 -> 0 | Q66: =+C66+P66 -> 0 | R66: =+AL!Q66+CA!Q66+AR!Q66+AZ!Q66+CO!Q66+CT!Q66+DE!Q66+FL!Q66+GA!Q66+HI!Q66+ID!Q66+IL!Q66+IN!Q66+KS!Q66+LA!Q66+MD!Q66+MI!Q66+MN!Q66+MO!Q66+MS!Q66+NC!Q66+NJ!Q66+NE!Q66+NV!Q66+NY!Q66+OH!Q66+OK!Q66+OR!Q66+PA!Q66+SC!Q66+SD!Q66+TN!Q66+TX!Q66+VA!Q66+WA!Q66+WI!Q66+WY!Q66-Q66 -> 0 | T66: Commissions Ceded | U66: 100 | V66: 500300 | W66: 00 | X66: 2002 | Y66: 000212 | Z66: 00 | AA66: 0000 | AC66: FUT Starlight T2 APD DRP | AD66: =SUM(AL:WY!AE66) -> 80.0632 | AE66: =SUM(AL:WY!AP66) -> 640.4694 | AF66: =SUM(AL:WY!BA66) -> 170.1472 | AG66: =SUM(AL:WY!BL66) -> 0 | AH66: =SUM(AL:WY!BW66) -> 0 | AI66: =SUM(AL:WY!CH66) -> 0 | AJ66: =SUM(AL:WY!CS66) -> 0 | AK66: =SUM(AL:WY!DD66) -> 0 | AL66: =SUM(AL:WY!DO66) -> 0 | AM66: =SUM(AL:WY!DZ66) -> 0 | AN66: =SUM(AL:WY!EK66) -> 0 | AO66: =SUM(AL:WY!EV66) -> 0 | AP66: =SUM(AD66:AO66) -> 890.6798
B67: Ultimate LAE - AOE | C67: =C$8*C62 -> 66177.236 | D67: =D$8*D62 -> 23906.251 | E67: =E$8*E62 -> 23675.091 | F67: =F$8*F62 -> 23349.099 | G67: =G$8*G62 -> #DIV/0! | H67: =H$8*H62 -> #DIV/0! | I67: =I$8*I62 -> #DIV/0! | J67: =J$8*J62 -> #DIV/0! | ... P67: =P$8*P62 -> 70930.441 | Q67: =+Q8*Q62 -> 137107.68 | R67: =+AL!Q67+CA!Q67+AR!Q67+AZ!Q67+CO!Q67+CT!Q67+DE!Q67+FL!Q67+GA!Q67+HI!Q67+ID!Q67+IL!Q67+IN!Q67+KS!Q67+LA!Q67+MD!Q67+MI!Q67+MN!Q67+MO!Q67+MS!Q67+NC!Q67+NJ!Q67+NE!Q67+NV!Q67+NY!Q67+OH!Q67+OK!Q67+OR!Q67+PA!Q67+SC!Q67+SD!Q67+TN!Q67+TX!Q67+VA!Q67+WA!Q67+WI!Q67+WY!Q67-Q67 -> #DIV/0! | T67: Commissions Ceded | U67: 100 | V67: 500300 | W67: 00 | X67: 2002 | Y67: 000212 | Z67: 00 | AA67: 0000 | AC67: FUT Starlight T2 APD DRP | AD67: =SUM(AL:WY!AE67) -> -3648.1604 | AE67: =SUM(AL:WY!AP67) -> -4174.065 | AF67: =SUM(AL:WY!BA67) -> -3655.0874 | AG67: =SUM(AL:WY!BL67) -> 0 | AH67: =SUM(AL:WY!BW67) -> 0 | AI67: =SUM(AL:WY!CH67) -> 0 | AJ67: =SUM(AL:WY!CS67) -> 0 | AK67: =SUM(AL:WY!DD67) -> 0 | AL67: =SUM(AL:WY!DO67) -> 0 | AM67: =SUM(AL:WY!DZ67) -> 0 | AN67: =SUM(AL:WY!EK67) -> 0 | AO67: =SUM(AL:WY!EV67) -> 0 | AP67: =SUM(AD67:AO67) -> -11477.313
B68: Ultimate ULAE | C68: =C26+C27 -> 150720.36 | D68: =D26+D27 -> 10.754554 | E68: =E26+E27 -> -1885.623 | F68: =F26+F27 -> -1002.9006 | G68: =G26+G27 -> 0 | H68: =H26+H27 -> 0 | I68: =I26+I27 -> 0 | J68: =J26+J27 -> 0 | ... O68: =O26+O27 -> 0 | P68: =SUM(D68:O68) -> -2877.769 | Q68: =+C68+P68 -> 147842.59 | R68: =SUM(AL:WY!Q68)-'Starlight APD'!Q68 -> 0 | T68: Deferred Ceding Commissions | U68: 100 | V68: 243200 | W68: 00 | X68: 2002 | Y68: 000212 | Z68: 00 | AA68: 0000 | AC68: FUT Starlight T2 APD DRP | AD68: =SUM(AL:WY!AE68) -> 3648.1604 | AE68: =SUM(AL:WY!AP68) -> 4174.065 | AF68: =SUM(AL:WY!BA68) -> 3655.0874 | AG68: =SUM(AL:WY!BL68) -> 0 | AH68: =SUM(AL:WY!BW68) -> 0 | AI68: =SUM(AL:WY!CH68) -> 0 | AJ68: =SUM(AL:WY!CS68) -> 0 | AK68: =SUM(AL:WY!DD68) -> 0 | AL68: =SUM(AL:WY!DO68) -> 0 | AM68: =SUM(AL:WY!DZ68) -> 0 | AN68: =SUM(AL:WY!EK68) -> 0 | AO68: =SUM(AL:WY!EV68) -> 0 | AP68: =SUM(AD68:AO68) -> 11477.313
C69: =SUM(C65:C68) -> 496422.34 | D69: =SUM(D65:D68) -> 124894.16 | E69: =SUM(E65:E68) -> 121790.22 | F69: =SUM(F65:F68) -> 120970.01 | G69: =SUM(G65:G68) -> #DIV/0! | H69: =SUM(H65:H68) -> #DIV/0! | I69: =SUM(I65:I68) -> #DIV/0! | J69: =SUM(J65:J68) -> #DIV/0! | ... Q69: =SUM(Q65:Q68) -> 864076.73 | R69: =+AL!Q69+CA!Q69+AR!Q69+AZ!Q69+CO!Q69+CT!Q69+DE!Q69+FL!Q69+GA!Q69+HI!Q69+ID!Q69+IL!Q69+IN!Q69+KS!Q69+LA!Q69+MD!Q69+MI!Q69+MN!Q69+MO!Q69+MS!Q69+NC!Q69+NJ!Q69+NE!Q69+NV!Q69+NY!Q69+OH!Q69+OK!Q69+OR!Q69+PA!Q69+SC!Q69+SD!Q69+TN!Q69+TX!Q69+VA!Q69+WA!Q69+WI!Q69+WY!Q69-Q69 -> #DIV/0! | T69: Receivable from MGA | U69: 100 | V69: 160400 | W69: 00 | X69: 2002 | Y69: 000212 | Z69: 00 | AA69: 0000 | AC69: FUT Starlight T2 APD DRP | AD69: =SUM(AL:WY!AE69) -> -200.158 | AE69: =SUM(AL:WY!AP69) -> -1601.1735 | AF69: =SUM(AL:WY!BA69) -> -425.368 | AG69: =SUM(AL:WY!BL69) -> 0 | AH69: =SUM(AL:WY!BW69) -> 0 | AI69: =SUM(AL:WY!CH69) -> 0 | AJ69: =SUM(AL:WY!CS69) -> 0 | AK69: =SUM(AL:WY!DD69) -> 0 | AL69: =SUM(AL:WY!DO69) -> 0 | AM69: =SUM(AL:WY!DZ69) -> 0 | AN69: =SUM(AL:WY!EK69) -> 0 | AO69: =SUM(AL:WY!EV69) -> 0 | AP69: =SUM(AD69:AO69) -> -2226.6995
C70: =+C18+C28-C69 -> 0 | D70: =+D18+D28-D69 -> 0 | E70: =+E18+E28-E69 -> 0 | F70: =+F18+F28-F69 -> 0 | G70: =+G18+G28-G69 -> #DIV/0! | H70: =+H18+H28-H69 -> #DIV/0! | I70: =+I18+I28-I69 -> #DIV/0! | J70: =+J18+J28-J69 -> #DIV/0! | ... Q70: =+Q18+Q28-Q69 -> 0 | T70: Fronting Fees | U70: 100 | V70: 500110 | W70: 00 | X70: 2002 | Y70: 000212 | Z70: CA | AA70: 0000 | AC70: FUT Starlight T2 APD DRP | AD70: =SUM(AL:WY!AE70) -> 200.158 | AE70: =SUM(AL:WY!AP70) -> 1601.1735 | AF70: =SUM(AL:WY!BA70) -> 425.368 | AG70: =SUM(AL:WY!BL70) -> 0 | AH70: =SUM(AL:WY!BW70) -> 0 | AI70: =SUM(AL:WY!CH70) -> 0 | AJ70: =SUM(AL:WY!CS70) -> 0 | AK70: =SUM(AL:WY!DD70) -> 0 | AL70: =SUM(AL:WY!DO70) -> 0 | AM70: =SUM(AL:WY!DZ70) -> 0 | AN70: =SUM(AL:WY!EK70) -> 0 | AO70: =SUM(AL:WY!EV70) -> 0 | AP70: =SUM(AD70:AO70) -> 2226.6995
B71: Loss & LAE Reserves (including IBNR) | C71: =SUM(C52:C58) -> 324853.24 | D71: =SUM(D52:D58) -> 437527.62 | E71: =SUM(E52:E58) -> 537395.56 | F71: =SUM(F52:F58) -> 552982.71 | G71: =SUM(G52:G58) -> 0 | H71: =SUM(H52:H58) -> 0 | I71: =SUM(I52:I58) -> 0 | J71: =SUM(J52:J58) -> 0 | ... Q71: =SUM(Q52:Q58) -> 552982.71 | T71: Fronting Fees | U71: 100 | V71: 500110 | W71: 00 | X71: 2002 | Y71: 000212 | Z71: CA | AA71: 0000 | AC71: FUT Starlight T2 APD DRP | AD71: =SUM(AL:WY!AE71) -> -9120.401 | AE71: =SUM(AL:WY!AP71) -> -10435.163 | AF71: =SUM(AL:WY!BA71) -> -9137.7185 | AG71: =SUM(AL:WY!BL71) -> 0 | AH71: =SUM(AL:WY!BW71) -> 0 | AI71: =SUM(AL:WY!CH71) -> 0 | AJ71: =SUM(AL:WY!CS71) -> 0 | AK71: =SUM(AL:WY!DD71) -> 0 | AL71: =SUM(AL:WY!DO71) -> 0 | AM71: =SUM(AL:WY!DZ71) -> 0 | AN71: =SUM(AL:WY!EK71) -> 0 | AO71: =SUM(AL:WY!EV71) -> 0 | AP71: =SUM(AD71:AO71) -> -28693.282
B72: Required Collateral at 115% | C72: =+C71*1.15 -> 373581.23 | D72: =+D71*1.15 -> 503156.76 | E72: =+E71*1.15 -> 618004.9 | F72: =+F71*1.15 -> 635930.11 | G72: =+G71*1.15 -> 0 | H72: =+H71*1.15 -> 0 | I72: =+I71*1.15 -> 0 | J72: =+J71*1.15 -> 0 | ... Q72: =+Q71*1.15 -> 635930.11 | T72: Deferred Ceding Commissions | U72: 100 | V72: 243200 | W72: 00 | X72: 2002 | Y72: 000212 | Z72: 00 | AA72: 0000 | AC72: FUT Starlight T2 APD DRP | AD72: =SUM(AL:WY!AE72) -> 9120.401 | AE72: =SUM(AL:WY!AP72) -> 10435.163 | AF72: =SUM(AL:WY!BA72) -> 9137.7185 | AG72: =SUM(AL:WY!BL72) -> 0 | AH72: =SUM(AL:WY!BW72) -> 0 | AI72: =SUM(AL:WY!CH72) -> 0 | AJ72: =SUM(AL:WY!CS72) -> 0 | AK72: =SUM(AL:WY!DD72) -> 0 | AL72: =SUM(AL:WY!DO72) -> 0 | AM72: =SUM(AL:WY!DZ72) -> 0 | AN72: =SUM(AL:WY!EK72) -> 0 | AO72: =SUM(AL:WY!EV72) -> 0 | AP72: =SUM(AD72:AO72) -> 28693.282
P73: =+P72-AL!P72-AR!P72-AZ!P72-CA!P72-CO!P72-CT!P72-DE!P72-FL!P72-GA!P72-HI!P72-ID!P72-IL!P72-IN!P72-KS!P72-LA!P72-MD!P72-MI!P72-MN!P72-MO!P72-MS!P72-NC!P72-NJ!P72-NE!P72-NV!P72-NY!P72-OH!P72-OK!P72-OR!P72-PA!P72-SC!P72-SD!P72-TN!P72-TX!P72-VA!P72-WA!P72-WI!P72-WY!P72 -> 1448.135 | Q73: =+Q72-AL!Q72-AR!Q72-AZ!Q72-CA!Q72-CO!Q72-CT!Q72-DE!Q72-FL!Q72-GA!Q72-HI!Q72-ID!Q72-IL!Q72-IN!Q72-KS!Q72-LA!Q72-MD!Q72-MI!Q72-MN!Q72-MO!Q72-MS!Q72-NC!Q72-NJ!Q72-NE!Q72-NV!Q72-NY!Q72-OH!Q72-OK!Q72-OR!Q72-PA!Q72-SC!Q72-SD!Q72-TN!Q72-TX!Q72-VA!Q72-WA!Q72-WI!Q72-WY!Q72 -> 1448.135 | AD73: =SUM(AD5:AD72) -> 0 | AE73: =SUM(AE5:AE72) -> 0 | AF73: =SUM(AF5:AF72) -> 0 | AG73: =SUM(AG5:AG72) -> 0 | AH73: =SUM(AH5:AH72) -> 0 | AI73: =SUM(AI5:AI72) -> 0 | AJ73: =SUM(AJ5:AJ72) -> 0 | AK73: =SUM(AK5:AK72) -> 0 | ... AP73: =SUM(AP5:AP72) -> 0
O75: =+O53+O57 -> 0 | P75: =+P53+P57 -> 284254.51 | Q75: =+Q53+Q57 -> 284254.51 | AD75: Debit total | AE75: Debit total | AF75: Debit total | AG75: Debit total | AH75: Debit total | AI75: Debit total | AJ75: Debit total | AK75: Debit total | AL75: Debit total | AM75: Debit total | AN75: Debit total | AO75: Debit total
AC76: JE Control Totals | AD76: =SUM(AL:WY!AE76) -> 1013842.4 | AE76: =SUM(AL:WY!AP76) -> 1042015.5 | AF76: =SUM(AL:WY!BA76) -> 1536415.4 | AG76: =SUM(AL:WY!BL76) -> 0 | AH76: =SUM(AL:WY!BW76) -> 0 | AI76: =SUM(AL:WY!CH76) -> 0 | AJ76: =SUM(AL:WY!CS76) -> 0 | AK76: =SUM(AL:WY!DD76) -> 0 | AL76: =SUM(AL:WY!DO76) -> 0 | AM76: =SUM(AL:WY!DZ76) -> 0 | AN76: =SUM(AL:WY!EK76) -> 0 | AO76: =SUM(AL:WY!EV76) -> 0
AD77: Credit total | AE77: Credit total | AF77: Credit total | AG77: Credit total | AH77: Credit total | AI77: Credit total | AJ77: Credit total | AK77: Credit total | AL77: Credit total | AM77: Credit total | AN77: Credit total | AO77: Credit total
AC78: JE Control Totals | AD78: =SUM(AL:WY!AE78) -> -1013842.4 | AE78: =SUM(AL:WY!AP78) -> -1042015.5 | AF78: =SUM(AL:WY!BA78) -> -1536415.4 | AG78: =SUM(AL:WY!BL78) -> 0 | AH78: =SUM(AL:WY!BW78) -> 0 | AI78: =SUM(AL:WY!CH78) -> 0 | AJ78: =SUM(AL:WY!CS78) -> 0 | AK78: =SUM(AL:WY!DD78) -> 0 | AL78: =SUM(AL:WY!DO78) -> 0 | AM78: =SUM(AL:WY!DZ78) -> 0 | AN78: =SUM(AL:WY!EK78) -> 0 | AO78: =SUM(AL:WY!EV78) -> 0
AC79: Journal Number | AD79: 5985 | AE79: 6034 | AF79: 6056
AC80: Posted Date | AD80: 46156 | AE80: 46156 | AF80: 46157

Sheet AL
A1: Southlake Specialty Insurance Company
C2: 2025 | P2: 2026
C3: ITD | P3: YTD | Q3: ITD | R3: System
B4: Starlight APD - AL | C4: Totals | D4: Jan-26 | E4: Feb-26 | F4: Mar-26 | G4: Apr-26 | H4: May-26 | I4: Jun-26 | J4: Jul-26 | K4: Aug-26 | L4: Sep-26 | M4: Oct-26 | N4: Nov-26 | O4: Dec-26 | P4: Totals | Q4: Totals | R4: Reports | S4: Variance | U4: Jan-26 Journal Entries | V4: Comp | W4: Account | X4: CC | Y4: MGA | Z4: LOB | AA4: ST | AB4: EXT | AC4: Sub | AD4: Description | AE4: DR / (CR) | AF4: Feb-26 Journal Entries | AG4: Comp | AH4: Account | AI4: CC | AJ4: MGA | AK4: LOB | AL4: ST | AM4: EXT | AN4: Sub | AO4: Description | AP4: DR / (CR) | AQ4: Mar-26 Journal Entries | AR4: Comp | AS4: Account | AT4: CC | AU4: MGA | AV4: LOB | AW4: ST | AX4: EXT | AY4: Sub | AZ4: Description | BA4: DR / (CR) | BB4: Apr-26 Journal Entries | BC4: Comp | BD4: Account | BE4: CC | BF4: MGA | BG4: LOB | BH4: ST | BI4: EXT | BJ4: Sub | BK4: Description | BL4: DR / (CR) | BM4: May-26 Journal Entries | BN4: Comp | BO4: Account | BP4: CC | BQ4: MGA | BR4: LOB | BS4: ST | BT4: EXT | BU4: Sub | BV4: Description | BW4: DR / (CR) | BX4: Jun-26 Journal Entries | BY4: Comp | BZ4: Account | CA4: CC | CB4: MGA | CC4: LOB | CD4: ST | CE4: EXT | CF4: Sub | CG4: Description | CH4: DR / (CR) | CI4: Jul-26 Journal Entries | CJ4: Comp | CK4: Account | CL4: CC | CM4: MGA | CN4: LOB | CO4: ST | CP4: EXT | CQ4: Sub | CR4: Description | CS4: DR / (CR) | CT4: Aug-26 Journal Entries | CU4: Comp | CV4: Account | CW4: CC | CX4: MGA | CY4: LOB | CZ4: ST | DA4: EXT | DB4: Sub | DC4: Description | DD4: DR / (CR) | DE4: Sep-26 Journal Entries | DF4: Comp | DG4: Account | DH4: CC | DI4: MGA | DJ4: LOB | DK4: ST | DL4: EXT | DM4: Sub | DN4: Description | DO4: DR / (CR) | DP4: Oct-26 Journal Entries | DQ4: Comp | DR4: Account | DS4: CC | DT4: MGA | DU4: LOB | DV4: ST | DW4: EXT | DX4: Sub | DY4: Description | DZ4: DR / (CR) | EA4: Nov-26 Journal Entries | EB4: Comp | EC4: Account | ED4: CC | EE4: MGA | EF4: LOB | EG4: ST | EH4: EXT | EI4: Sub | EJ4: Description | EK4: DR / (CR) | EL4: Dec-26 Journal Entries | EM4: Comp | EN4: Account | EO4: CC | EP4: MGA | EQ4: LOB | ER4: ST | ES4: EXT | ET4: Sub | EU4: Description | EV4: DR / (CR)
U5: Uncollected Premium Direct | V5: 100 | W5: 120100 | X5: 00 | Y5: 2002 | Z5: 000212 | AA5: 00 | AB5: 0000 | AD5: FUT Starlight T2 APD DRP | AE5: =+D6 -> 0 | AF5: Uncollected Premium Direct | AG5: 100 | AH5: 120100 | AI5: 00 | AJ5: 2002 | AK5: 000212 | AL5: 00 | AM5: 0000 | AO5: FUT Starlight T2 APD DRP | AP5: =+E6 -> 0 | AQ5: Uncollected Premium Direct | AR5: 100 | AS5: 120100 | AT5: 00 | AU5: 2002 | AV5: 000212 | AW5: 00 | AX5: 0000 | AZ5: FUT Starlight T2 APD DRP | BA5: =+F6 -> 0 | BB5: Uncollected Premium Direct | BC5: 100 | BD5: 120100 | BE5: 00 | BF5: 2002 | BG5: 000212 | BH5: 00 | BI5: 0000 | BK5: FUT Starlight T2 APD DRP | BL5: =+G6 -> 0 | BM5: Uncollected Premium Direct | BN5: 100 | BO5: 120100 | BP5: 00 | BQ5: 2002 | BR5: 000212 | BS5: 00 | BT5: 0000 | BV5: FUT Starlight T2 APD DRP | BW5: =+H6 -> 0 | BX5: Uncollected Premium Direct | BY5: 100 | BZ5: 120100 | CA5: 00 | CB5: 2002 | CC5: 000212 | CD5: 00 | CE5: 0000 | CG5: FUT Starlight T2 APD DRP | CH5: =+I6 -> 0 | CI5: Uncollected Premium Direct | CJ5: 100 | CK5: 120100 | CL5: 00 | CM5: 2002 | CN5: 000212 | CO5: 00 | CP5: 0000 | CR5: FUT Starlight T2 APD DRP | CS5: =+J6 -> 0 | CT5: Uncollected Premium Direct | CU5: 100 | CV5: 120100 | CW5: 00 | CX5: 2002 | CY5: 000212 | CZ5: 00 | DA5: 0000 | DC5: FUT Starlight T2 APD DRP | DD5: =+K6 -> 0 | DE5: Uncollected Premium Direct | DF5: 100 | DG5: 120100 | DH5: 00 | DI5: 2002 | DJ5: 000212 | DK5: 00 | DL5: 0000 | DN5: FUT Starlight T2 APD DRP | DO5: =+L6 -> 0 | DP5: Uncollected Premium Direct | DQ5: 100 | DR5: 120100 | DS5: 00 | DT5: 2002 | DU5: 000212 | DV5: 00 | DW5: 0000 | DY5: FUT Starlight T2 APD DRP | DZ5: =+M6 -> 0 | EA5: Uncollected Premium Direct | EB5: 100 | EC5: 120100 | ED5: 00 | EE5: 2002 | EF5: 000212 | EG5: 00 | EH5: 0000 | EJ5: FUT Starlight T2 APD DRP | EK5: =+N6 -> 0 | EL5: Uncollected Premium Direct | EM5: 100 | EN5: 120100 | EO5: 00 | EP5: 2002 | EQ5: 000212 | ER5: 00 | ES5: 0000 | EU5: FUT Starlight T2 APD DRP | EV5: =+O6 -> 0
A6: a. | B6: Premiums Written | C6: 0 | D6: 0 | P6: =SUM(D6:O6) -> 0 | Q6: =+C6+P6 -> 0 | R6: =Q6 -> 0 | S6: =Q6-R6 -> 0 | U6: Direct Premium Written | V6: 100 | W6: 400100 | X6: 00 | Y6: 2002 | Z6: 000212 | AA6: {=RIGHT(CELL("filename",A1),LEN(CELL("filename",A1))-FIND("]",CELL("filename",A1)))} -> #VALUE! | AB6: 0000 | AD6: FUT Starlight T2 APD DRP | AE6: =-D6 -> 0 | AF6: Direct Premium Written | AG6: 100 | AH6: 400100 | AI6: 00 | AJ6: 2002 | AK6: 000212 | AL6: {=RIGHT(CELL("filename",A1),LEN(CELL("filename",A1))-FIND("]",CELL("filename",A1)))} -> #VALUE! | AM6: 0000 | AO6: FUT Starlight T2 APD DRP | AP6: =-E6 -> 0 | AQ6: Direct Premium Written | AR6: 100 | AS6: 400100 | AT6: 00 | AU6: 2002 | AV6: 000212 | AW6: {=RIGHT(CELL("filename",A1),LEN(CELL("filename",A1))-FIND("]",CELL("filename",A1)))} -> #VALUE! | AX6: 0000 | AZ6: FUT Starlight T2 APD DRP | BA6: =-F6 -> 0 | BB6: Direct Premium Written | BC6: 100 | BD6: 400100 | BE6: 00 | BF6: 2002 | BG6: 000212 | BH6: {=RIGHT(CELL("filename",A1),LEN(CELL("filename",A1))-FIND("]",CELL("filename",A1)))} -> #VALUE! | BI6: 0000 | BK6: FUT Starlight T2 APD DRP | BL6: =-G6 -> 0 | BM6: Direct Premium Written | BN6: 100 | BO6: 400100 | BP6: 00 | BQ6: 2002 | BR6: 000212 | BS6: {=RIGHT(CELL("filename",A1),LEN(CELL("filename",A1))-FIND("]",CELL("filename",A1)))} -> #VALUE! | BT6: 0000 | BV6: FUT Starlight T2 APD DRP | BW6: =-H6 -> 0 | BX6: Direct Premium Written | BY6: 100 | BZ6: 400100 | CA6: 00 | CB6: 2002 | CC6: 000212 | CD6: {=RIGHT(CELL("filename",A1),LEN(CELL("filename",A1))-FIND("]",CELL("filename",A1)))} -> #VALUE! | CE6: 0000 | CG6: FUT Starlight T2 APD DRP | CH6: =-I6 -> 0 | CI6: Direct Premium Written | CJ6: 100 | CK6: 400100 | CL6: 00 | CM6: 2002 | CN6: 000212 | CO6: {=RIGHT(CELL("filename",A1),LEN(CELL("filename",A1))-FIND("]",CELL("filename",A1)))} -> #VALUE! | CP6: 0000 | CR6: FUT Starlight T2 APD DRP | CS6: =-J6 -> 0 | CT6: Direct Premium Written | CU6: 100 | CV6: 400100 | CW6: 00 | CX6: 2002 | CY6: 000212 | CZ6: {=RIGHT(CELL("filename",A1),LEN(CELL("filename",A1))-FIND("]",CELL("filename",A1)))} -> #VALUE! | DA6: 0000 | DC6: FUT Starlight T2 APD DRP | DD6: =-K6 -> 0 | DE6: Direct Premium Written | DF6: 100 | DG6: 400100 | DH6: 00 | DI6: 2002 | DJ6: 000212 | DK6: {=RIGHT(CELL("filename",A1),LEN(CELL("filename",A1))-FIND("]",CELL("filename",A1)))} -> #VALUE! | DL6: 0000 | DN6: FUT Starlight T2 APD DRP | DO6: =-L6 -> 0 | DP6: Direct Premium Written | DQ6: 100 | DR6: 400100 | DS6: 00 | DT6: 2002 | DU6: 000212 | DV6: {=RIGHT(CELL("filename",A1),LEN(CELL("filename",A1))-FIND("]",CELL("filename",A1)))} -> #VALUE! | DW6: 0000 | DY6: FUT Starlight T2 APD DRP | DZ6: =-M6 -> 0 | EA6: Direct Premium Written | EB6: 100 | EC6: 400100 | ED6: 00 | EE6: 2002 | EF6: 000212 | EG6: {=RIGHT(CELL("filename",A1),LEN(CELL("filename",A1))-FIND("]",CELL("filename",A1)))} -> #VALUE! | EH6: 0000 | EJ6: FUT Starlight T2 APD DRP | EK6: =-N6 -> 0 | EL6: Direct Premium Written | EM6: 100 | EN6: 400100 | EO6: 00 | EP6: 2002 | EQ6: 000212 | ER6: {=RIGHT(CELL("filename",A1),LEN(CELL("filename",A1))-FIND("]",CELL("filename",A1)))} -> #VALUE! | ES6: 0000 | EU6: FUT Starlight T2 APD DRP | EV6: =-O6 -> 0
B7: Change in UEP | C7: 0 | D7: =C51-D51 -> 0 | P7: =SUM(D7:O7) -> 0 | Q7: =+C7+P7 -> 0 | R7: =Q7 -> 0 | S7: =Q7-R7 -> 0 | U7: Change in Unearned Premium Direct | V7: 100 | W7: 411100 | X7: 00 | Y7: 2002 | Z7: 000212 | AA7: {=RIGHT(CELL("filename",A1),LEN(CELL("filename",A1))-FIND("]",CELL("filename",A1)))} -> #VALUE! | AB7: 0000 | AD7: FUT Starlight T2 APD DRP | AE7: =-D7 -> 0 | AF7: Change in Unearned Premium Direct | AG7: 100 | AH7: 411100 | AI7: 00 | AJ7: 2002 | AK7: 000212 | AL7: {=RIGHT(CELL("filename",A1),LEN(CELL("filename",A1))-FIND("]",CELL("filename",A1)))} -> #VALUE! | AM7: 0000 | AO7: FUT Starlight T2 APD DRP | AP7: =-E7 -> 0 | AQ7: Change in Unearned Premium Direct | AR7: 100 | AS7: 411100 | AT7: 00 | AU7: 2002 | AV7: 000212 | AW7: {=RIGHT(CELL("filename",A1),LEN(CELL("filename",A1))-FIND("]",CELL("filename",A1)))} -> #VALUE! | AX7: 0000 | AZ7: FUT Starlight T2 APD DRP | BA7: =-F7 -> 0 | BB7: Change in Unearned Premium Direct | BC7: 100 | BD7: 411100 | BE7: 00 | BF7: 2002 | BG7: 000212 | BH7: {=RIGHT(CELL("filename",A1),LEN(CELL("filename",A1))-FIND("]",CELL("filename",A1)))} -> #VALUE! | BI7: 0000 | BK7: FUT Starlight T2 APD DRP | BL7: =-G7 -> 0 | BM7: Change in Unearned Premium Direct | BN7: 100 | BO7: 411100 | BP7: 00 | BQ7: 2002 | BR7: 000212 | BS7: {=RIGHT(CELL("filename",A1),LEN(CELL("filename",A1))-FIND("]",CELL("filename",A1)))} -> #VALUE! | BT7: 0000 | BV7: FUT Starlight T2 APD DRP | BW7: =-H7 -> 0 | BX7: Change in Unearned Premium Direct | BY7: 100 | BZ7: 411100 | CA7: 00 | CB7: 2002 | CC7: 000212 | CD7: {=RIGHT(CELL("filename",A1),LEN(CELL("filename",A1))-FIND("]",CELL("filename",A1)))} -> #VALUE! | CE7: 0000 | CG7: FUT Starlight T2 APD DRP | CH7: =-I7 -> 0 | CI7: Change in Unearned Premium Direct | CJ7: 100 | CK7: 411100 | CL7: 00 | CM7: 2002 | CN7: 000212 | CO7: {=RIGHT(CELL("filename",A1),LEN(CELL("filename",A1))-FIND("]",CELL("filename",A1)))} -> #VALUE! | CP7: 0000 | CR7: FUT Starlight T2 APD DRP | CS7: =-J7 -> 0 | CT7: Change in Unearned Premium Direct | CU7: 100 | CV7: 411100 | CW7: 00 | CX7: 2002 | CY7: 000212 | CZ7: {=RIGHT(CELL("filename",A1),LEN(CELL("filename",A1))-FIND("]",CELL("filename",A1)))} -> #VALUE! | DA7: 0000 | DC7: FUT Starlight T2 APD DRP | DD7: =-K7 -> 0 | DE7: Change in Unearned Premium Direct | DF7: 100 | DG7: 411100 | DH7: 00 | DI7: 2002 | DJ7: 000212 | DK7: {=RIGHT(CELL("filename",A1),LEN(CELL("filename",A1))-FIND("]",CELL("filename",A1)))} -> #VALUE! | DL7: 0000 | DN7: FUT Starlight T2 APD DRP | DO7: =-L7 -> 0 | DP7: Change in Unearned Premium Direct | DQ7: 100 | DR7: 411100 | DS7: 00 | DT7: 2002 | DU7: 000212 | DV7: {=RIGHT(CELL("filename",A1),LEN(CELL("filename",A1))-FIND("]",CELL("filename",A1)))} -> #VALUE! | DW7: 0000 | DY7: FUT Starlight T2 APD DRP | DZ7: =-M7 -> 0 | EA7: Change in Unearned Premium Direct | EB7: 100 | EC7: 411100 | ED7: 00 | EE7: 2002 | EF7: 000212 | EG7: {=RIGHT(CELL("filename",A1),LEN(CELL("filename",A1))-FIND("]",CELL("filename",A1)))} -> #VALUE! | EH7: 0000 | EJ7: FUT Starlight T2 APD DRP | EK7: =-N7 -> 0 | EL7: Change in Unearned Premium Direct | EM7: 100 | EN7: 411100 | EO7: 00 | EP7: 2002 | EQ7: 000212 | ER7: {=RIGHT(CELL("filename",A1),LEN(CELL("filename",A1))-FIND("]",CELL("filename",A1)))} -> #VALUE! | ES7: 0000 | EU7: FUT Starlight T2 APD DRP | EV7: =-O7 -> 0
B8: Premiums Earned | C8: =SUM(C6:C7) -> 0 | D8: =SUM(D6:D7) -> 0 | P8: =SUM(P6:P7) -> 0 | Q8: =SUM(Q6:Q7) -> 0 | R8: =SUM(R6:R7) -> 0 | S8: =SUM(S6:S7) -> 0 | U8: Unearned Premium Direct | V8: 100 | W8: 230100 | X8: 00 | Y8: 2002 | Z8: 000212 | AA8: {=RIGHT(CELL("filename",A1),LEN(CELL("filename",A1))-FIND("]",CELL("filename",A1)))} -> #VALUE! | AB8: 0000 | AD8: FUT Starlight T2 APD DRP | AE8: =D7 -> 0 | AF8: Unearned Premium Direct | AG8: 100 | AH8: 230100 | AI8: 00 | AJ8: 2002 | AK8: 000212 | AL8: {=RIGHT(CELL("filename",A1),LEN(CELL("filename",A1))-FIND("]",CELL("filename",A1)))} -> #VALUE! | AM8: 0000 | AO8: FUT Starlight T2 APD DRP | AP8: =E7 -> 0 | AQ8: Unearned Premium Direct | AR8: 100 | AS8: 230100 | AT8: 00 | AU8: 2002 | AV8: 000212 | AW8: {=RIGHT(CELL("filename",A1),LEN(CELL("filename",A1))-FIND("]",CELL("filename",A1)))} -> #VALUE! | AX8: 0000 | AZ8: FUT Starlight T2 APD DRP | BA8: =+F7 -> 0 | BB8: Unearned Premium Direct | BC8: 100 | BD8: 230100 | BE8: 00 | BF8: 2002 | BG8: 000212 | BH8: {=RIGHT(CELL("filename",A1),LEN(CELL("filename",A1))-FIND("]",CELL("filename",A1)))} -> #VALUE! | BI8: 0000 | BK8: FUT Starlight T2 APD DRP | BL8: =G7 -> 0 | BM8: Unearned Premium Direct | BN8: 100 | BO8: 230100 | BP8: 00 | BQ8: 2002 | BR8: 000212 | BS8: {=RIGHT(CELL("filename",A1),LEN(CELL("filename",A1))-FIND("]",CELL("filename",A1)))} -> #VALUE! | BT8: 0000 | BV8: FUT Starlight T2 APD DRP | BW8: =H7 -> 0 | BX8: Unearned Premium Direct | BY8: 100 | BZ8: 230100 | CA8: 00 | CB8: 2002 | CC8: 000212 | CD8: {=RIGHT(CELL("filename",A1),LEN(CELL("filename",A1))-FIND("]",CELL("filename",A1)))} -> #VALUE! | CE8: 0000 | CG8: FUT Starlight T2 APD DRP | CH8: =I7 -> 0 | CI8: Unearned Premium Direct | CJ8: 100 | CK8: 230100 | CL8: 00 | CM8: 2002 | CN8: 000212 | CO8: {=RIGHT(CELL("filename",A1),LEN(CELL("filename",A1))-FIND("]",CELL("filename",A1)))} -> #VALUE! | CP8: 0000 | CR8: FUT Starlight T2 APD DRP | CS8: =J7 -> 0 | CT8: Unearned Premium Direct | CU8: 100 | CV8: 230100 | CW8: 00 | CX8: 2002 | CY8: 000212 | CZ8: {=RIGHT(CELL("filename",A1),LEN(CELL("filename",A1))-FIND("]",CELL("filename",A1)))} -> #VALUE! | DA8: 0000 | DC8: FUT Starlight T2 APD DRP | DD8: =K7 -> 0 | DE8: Unearned Premium Direct | DF8: 100 | DG8: 230100 | DH8: 00 | DI8: 2002 | DJ8: 000212 | DK8: {=RIGHT(CELL("filename",A1),LEN(CELL("filename",A1))-FIND("]",CELL("filename",A1)))} -> #VALUE! | DL8: 0000 | DN8: FUT Starlight T2 APD DRP | DO8: =L7 -> 0 | DP8: Unearned Premium Direct | DQ8: 100 | DR8: 230100 | DS8: 00 | DT8: 2002 | DU8: 000212 | DV8: {=RIGHT(CELL("filename",A1),LEN(CELL("filename",A1))-FIND("]",CELL("filename",A1)))} -> #VALUE! | DW8: 0000 | DY8: FUT Starlight T2 APD DRP | DZ8: =M7 -> 0 | EA8: Unearned Premium Direct | EB8: 100 | EC8: 230100 | ED8: 00 | EE8: 2002 | EF8: 000212 | EG8: {=RIGHT(CELL("filename",A1),LEN(CELL("filename",A1))-FIND("]",CELL("filename",A1)))} -> #VALUE! | EH8: 0000 | EJ8: FUT Starlight T2 APD DRP | EK8: =N7 -> 0 | EL8: Unearned Premium Direct | EM8: 100 | EN8: 230100 | EO8: 00 | EP8: 2002 | EQ8: 000212 | ER8: {=RIGHT(CELL("filename",A1),LEN(CELL("filename",A1))-FIND("]",CELL("filename",A1)))} -> #VALUE! | ES8: 0000 | EU8: FUT Starlight T2 APD DRP | EV8: =O7 -> 0
U9: Ceded Premium Written | V9: 100 | W9: 400300 | X9: 00 | Y9: 2002 | Z9: 000212 | AA9: 00 | AB9: 0000 | AD9: FUT Starlight T2 APD DRP | AE9: =+D6 -> 0 | AF9: Ceded Premium Written | AG9: 100 | AH9: 400300 | AI9: 00 | AJ9: 2002 | AK9: 000212 | AL9: 00 | AM9: 0000 | AO9: FUT Starlight T2 APD DRP | AP9: =+E6 -> 0 | AQ9: Ceded Premium Written | AR9: 100 | AS9: 400300 | AT9: 00 | AU9: 2002 | AV9: 000212 | AW9: 00 | AX9: 0000 | AZ9: FUT Starlight T2 APD DRP | BA9: =+F6 -> 0 | BB9: Ceded Premium Written | BC9: 100 | BD9: 400300 | BE9: 00 | BF9: 2002 | BG9: 000212 | BH9: 00 | BI9: 0000 | BK9: FUT Starlight T2 APD DRP | BL9: =+G6 -> 0 | BM9: Ceded Premium Written | BN9: 100 | BO9: 400300 | BP9: 00 | BQ9: 2002 | BR9: 000212 | BS9: 00 | BT9: 0000 | BV9: FUT Starlight T2 APD DRP | BW9: =+H6 -> 0 | BX9: Ceded Premium Written | BY9: 100 | BZ9: 400300 | CA9: 00 | CB9: 2002 | CC9: 000212 | CD9: 00 | CE9: 0000 | CG9: FUT Starlight T2 APD DRP | CH9: =+I6 -> 0 | CI9: Ceded Premium Written | CJ9: 100 | CK9: 400300 | CL9: 00 | CM9: 2002 | CN9: 000212 | CO9: 00 | CP9: 0000 | CR9: FUT Starlight T2 APD DRP | CS9: =+J6 -> 0 | CT9: Ceded Premium Written | CU9: 100 | CV9: 400300 | CW9: 00 | CX9: 2002 | CY9: 000212 | CZ9: 00 | DA9: 0000 | DC9: FUT Starlight T2 APD DRP | DD9: =+K6 -> 0 | DE9: Ceded Premium Written | DF9: 100 | DG9: 400300 | DH9: 00 | DI9: 2002 | DJ9: 000212 | DK9: 00 | DL9: 0000 | DN9: FUT Starlight T2 APD DRP | DO9: =+L6 -> 0 | DP9: Ceded Premium Written | DQ9: 100 | DR9: 400300 | DS9: 00 | DT9: 2002 | DU9: 000212 | DV9: 00 | DW9: 0000 | DY9: FUT Starlight T2 APD DRP | DZ9: =+M6 -> 0 | EA9: Ceded Premium Written | EB9: 100 | EC9: 400300 | ED9: 00 | EE9: 2002 | EF9: 000212 | EG9: 00 | EH9: 0000 | EJ9: FUT Starlight T2 APD DRP | EK9: =+N6 -> 0 | EL9: Ceded Premium Written | EM9: 100 | EN9: 400300 | EO9: 00 | EP9: 2002 | EQ9: 000212 | ER9: 00 | ES9: 0000 | EU9: FUT Starlight T2 APD DRP | EV9: =+O6 -> 0
B10: Less: | U10: Ceded Reinsurance Premiums Payable | V10: 100 | W10: 243100 | X10: 00 | Y10: 2002 | Z10: 000212 | AA10: 00 | AB10: 0000 | AD10: FUT Starlight T2 APD DRP | AE10: =-D6 -> 0 | AF10: Ceded Reinsurance Premiums Payable | AG10: 100 | AH10: 243100 | AI10: 00 | AJ10: 2002 | AK10: 000212 | AL10: 00 | AM10: 0000 | AO10: FUT Starlight T2 APD DRP | AP10: =-E6 -> 0 | AQ10: Ceded Reinsurance Premiums Payable | AR10: 100 | AS10: 243100 | AT10: 00 | AU10: 2002 | AV10: 000212 | AW10: 00 | AX10: 0000 | AZ10: FUT Starlight T2 APD DRP | BA10: =-F6 -> 0 | BB10: Ceded Reinsurance Premiums Payable | BC10: 100 | BD10: 243100 | BE10: 00 | BF10: 2002 | BG10: 000212 | BH10: 00 | BI10: 0000 | BK10: FUT Starlight T2 APD DRP | BL10: =-G6 -> 0 | BM10: Ceded Reinsurance Premiums Payable | BN10: 100 | BO10: 243100 | BP10: 00 | BQ10: 2002 | BR10: 000212 | BS10: 00 | BT10: 0000 | BV10: FUT Starlight T2 APD DRP | BW10: =-H6 -> 0 | BX10: Ceded Reinsurance Premiums Payable | BY10: 100 | BZ10: 243100 | CA10: 00 | CB10: 2002 | CC10: 000212 | CD10: 00 | CE10: 0000 | CG10: FUT Starlight T2 APD DRP | CH10: =-I6 -> 0 | CI10: Ceded Reinsurance Premiums Payable | CJ10: 100 | CK10: 243100 | CL10: 00 | CM10: 2002 | CN10: 000212 | CO10: 00 | CP10: 0000 | CR10: FUT Starlight T2 APD DRP | CS10: =-J6 -> 0 | CT10: Ceded Reinsurance Premiums Payable | CU10: 100 | CV10: 243100 | CW10: 00 | CX10: 2002 | CY10: 000212 | CZ10: 00 | DA10: 0000 | DC10: FUT Starlight T2 APD DRP | DD10: =-K6 -> 0 | DE10: Ceded Reinsurance Premiums Payable | DF10: 100 | DG10: 243100 | DH10: 00 | DI10: 2002 | DJ10: 000212 | DK10: 00 | DL10: 0000 | DN10: FUT Starlight T2 APD DRP | DO10: =-L6 -> 0 | DP10: Ceded Reinsurance Premiums Payable | DQ10: 100 | DR10: 243100 | DS10: 00 | DT10: 2002 | DU10: 000212 | DV10: 00 | DW10: 0000 | DY10: FUT Starlight T2 APD DRP | DZ10: =-M6 -> 0 | EA10: Ceded Reinsurance Premiums Payable | EB10: 100 | EC10: 243100 | ED10: 00 | EE10: 2002 | EF10: 000212 | EG10: 00 | EH10: 0000 | EJ10: FUT Starlight T2 APD DRP | EK10: =-N6 -> 0 | EL10: Ceded Reinsurance Premiums Payable | EM10: 100 | EN10: 243100 | EO10: 00 | EP10: 2002 | EQ10: 000212 | ER10: 00 | ES10: 0000 | EU10: FUT Starlight T2 APD DRP | EV10: =-O6 -> 0
A11: b. | B11: Ceding Commissions at 29% | C11: 0 | D11: =+D6*0.29 -> 0 | P11: =SUM(D11:O11) -> 0 | Q11: =+C11+P11 -> 0 | U11: Unearned Premium Ceded | V11: 100 | W11: 230300 | X11: 00 | Y11: 2002 | Z11: 000212 | AA11: 00 | AB11: 0000 | AD11: FUT Starlight T2 APD DRP | AE11: =-D7 -> 0 | AF11: Unearned Premium Ceded | AG11: 100 | AH11: 230300 | AI11: 00 | AJ11: 2002 | AK11: 000212 | AL11: 00 | AM11: 0000 | AO11: FUT Starlight T2 APD DRP | AP11: =-E7 -> 0 | AQ11: Unearned Premium Ceded | AR11: 100 | AS11: 230300 | AT11: 00 | AU11: 2002 | AV11: 000212 | AW11: 00 | AX11: 0000 | AZ11: FUT Starlight T2 APD DRP | BA11: =-F7 -> 0 | BB11: Unearned Premium Ceded | BC11: 100 | BD11: 230300 | BE11: 00 | BF11: 2002 | BG11: 000212 | BH11: 00 | BI11: 0000 | BK11: FUT Starlight T2 APD DRP | BL11: =-G7 -> 0 | BM11: Unearned Premium Ceded | BN11: 100 | BO11: 230300 | BP11: 00 | BQ11: 2002 | BR11: 000212 | BS11: 00 | BT11: 0000 | BV11: FUT Starlight T2 APD DRP | BW11: =-H7 -> 0 | BX11: Unearned Premium Ceded | BY11: 100 | BZ11: 230300 | CA11: 00 | CB11: 2002 | CC11: 000212 | CD11: 00 | CE11: 0000 | CG11: FUT Starlight T2 APD DRP | CH11: =-I7 -> 0 | CI11: Unearned Premium Ceded | CJ11: 100 | CK11: 230300 | CL11: 00 | CM11: 2002 | CN11: 000212 | CO11: 00 | CP11: 0000 | CR11: FUT Starlight T2 APD DRP | CS11: =-J7 -> 0 | CT11: Unearned Premium Ceded | CU11: 100 | CV11: 230300 | CW11: 00 | CX11: 2002 | CY11: 000212 | CZ11: 00 | DA11: 0000 | DC11: FUT Starlight T2 APD DRP | DD11: =-K7 -> 0 | DE11: Unearned Premium Ceded | DF11: 100 | DG11: 230300 | DH11: 00 | DI11: 2002 | DJ11: 000212 | DK11: 00 | DL11: 0000 | DN11: FUT Starlight T2 APD DRP | DO11: =-L7 -> 0 | DP11: Unearned Premium Ceded | DQ11: 100 | DR11: 230300 | DS11: 00 | DT11: 2002 | DU11: 000212 | DV11: 00 | DW11: 0000 | DY11: FUT Starlight T2 APD DRP | DZ11: =-M7 -> 0 | EA11: Unearned Premium Ceded | EB11: 100 | EC11: 230300 | ED11: 00 | EE11: 2002 | EF11: 000212 | EG11: 00 | EH11: 0000 | EJ11: FUT Starlight T2 APD DRP | EK11: =-N7 -> 0 | EL11: Unearned Premium Ceded | EM11: 100 | EN11: 230300 | EO11: 00 | EP11: 2002 | EQ11: 000212 | ER11: 00 | ES11: 0000 | EU11: FUT Starlight T2 APD DRP | EV11: =-O7 -> 0
B12: Ceding Commissions on UEP | C12: 0 | D12: 0 | P12: =SUM(D12:O12) -> 0 | Q12: =+C12+P12 -> 0 | U12: Change in Unearned Premium Ceded | V12: 100 | W12: 411300 | X12: 00 | Y12: 2002 | Z12: 000212 | AA12: 00 | AB12: 0000 | AD12: FUT Starlight T2 APD DRP | AE12: =D7 -> 0 | AF12: Change in Unearned Premium Ceded | AG12: 100 | AH12: 411300 | AI12: 00 | AJ12: 2002 | AK12: 000212 | AL12: 00 | AM12: 0000 | AO12: FUT Starlight T2 APD DRP | AP12: =E7 -> 0 | AQ12: Change in Unearned Premium Ceded | AR12: 100 | AS12: 411300 | AT12: 00 | AU12: 2002 | AV12: 000212 | AW12: 00 | AX12: 0000 | AZ12: FUT Starlight T2 APD DRP | BA12: =+F7 -> 0 | BB12: Change in Unearned Premium Ceded | BC12: 100 | BD12: 411300 | BE12: 00 | BF12: 2002 | BG12: 000212 | BH12: 00 | BI12: 0000 | BK12: FUT Starlight T2 APD DRP | BL12: =G7 -> 0 | BM12: Change in Unearned Premium Ceded | BN12: 100 | BO12: 411300 | BP12: 00 | BQ12: 2002 | BR12: 000212 | BS12: 00 | BT12: 0000 | BV12: FUT Starlight T2 APD DRP | BW12: =H7 -> 0 | BX12: Change in Unearned Premium Ceded | BY12: 100 | BZ12: 411300 | CA12: 00 | CB12: 2002 | CC12: 000212 | CD12: 00 | CE12: 0000 | CG12: FUT Starlight T2 APD DRP | CH12: =I7 -> 0 | CI12: Change in Unearned Premium Ceded | CJ12: 100 | CK12: 411300 | CL12: 00 | CM12: 2002 | CN12: 000212 | CO12: 00 | CP12: 0000 | CR12: FUT Starlight T2 APD DRP | CS12: =J7 -> 0 | CT12: Change in Unearned Premium Ceded | CU12: 100 | CV12: 411300 | CW12: 00 | CX12: 2002 | CY12: 000212 | CZ12: 00 | DA12: 0000 | DC12: FUT Starlight T2 APD DRP | DD12: =K7 -> 0 | DE12: Change in Unearned Premium Ceded | DF12: 100 | DG12: 411300 | DH12: 00 | DI12: 2002 | DJ12: 000212 | DK12: 00 | DL12: 0000 | DN12: FUT Starlight T2 APD DRP | DO12: =L7 -> 0 | DP12: Change in Unearned Premium Ceded | DQ12: 100 | DR12: 411300 | DS12: 00 | DT12: 2002 | DU12: 000212 | DV12: 00 | DW12: 0000 | DY12: FUT Starlight T2 APD DRP | DZ12: =M7 -> 0 | EA12: Change in Unearned Premium Ceded | EB12: 100 | EC12: 411300 | ED12: 00 | EE12: 2002 | EF12: 000212 | EG12: 00 | EH12: 0000 | EJ12: FUT Starlight T2 APD DRP | EK12: =N7 -> 0 | EL12: Change in Unearned Premium Ceded | EM12: 100 | EN12: 411300 | EO12: 00 | EP12: 2002 | EQ12: 000212 | ER12: 00 | ES12: 0000 | EU12: FUT Starlight T2 APD DRP | EV12: =O7 -> 0
B13: Ceding Commissions Earned | C13: =SUM(C11:C12) -> 0 | D13: =SUM(D11:D12) -> 0 | P13: =SUM(P11:P12) -> 0 | Q13: =SUM(Q11:Q12) -> 0 | U13: Commissions Direct | V13: 100 | W13: 500100 | X13: 00 | Y13: 2002 | Z13: 000212 | AA13: {=RIGHT(CELL("filename",A1),LEN(CELL("filename",A1))-FIND("]",CELL("filename",A1)))} -> #VALUE! | AB13: 0000 | AD13: FUT Starlight T2 APD DRP | AE13: =+D11 -> 0 | AF13: Commissions Direct | AG13: 100 | AH13: 500100 | AI13: 00 | AJ13: 2002 | AK13: 000212 | AL13: {=RIGHT(CELL("filename",A1),LEN(CELL("filename",A1))-FIND("]",CELL("filename",A1)))} -> #VALUE! | AM13: 0000 | AO13: FUT Starlight T2 APD DRP | AP13: =+E11 -> 0 | AQ13: Commissions Direct | AR13: 100 | AS13: 500100 | AT13: 00 | AU13: 2002 | AV13: 000212 | AW13: {=RIGHT(CELL("filename",A1),LEN(CELL("filename",A1))-FIND("]",CELL("filename",A1)))} -> #VALUE! | AX13: 0000 | AZ13: FUT Starlight T2 APD DRP | BA13: =+F11 -> 0 | BB13: Commissions Direct | BC13: 100 | BD13: 500100 | BE13: 00 | BF13: 2002 | BG13: 000212 | BH13: {=RIGHT(CELL("filename",A1),LEN(CELL("filename",A1))-FIND("]",CELL("filename",A1)))} -> #VALUE! | BI13: 0000 | BK13: FUT Starlight T2 APD DRP | BL13: =+G11 -> 0 | BM13: Commissions Direct | BN13: 100 | BO13: 500100 | BP13: 00 | BQ13: 2002 | BR13: 000212 | BS13: {=RIGHT(CELL("filename",A1),LEN(CELL("filename",A1))-FIND("]",CELL("filename",A1)))} -> #VALUE! | BT13: 0000 | BV13: FUT Starlight T2 APD DRP | BW13: =+H11 -> 0 | BX13: Commissions Direct | BY13: 100 | BZ13: 500100 | CA13: 00 | CB13: 2002 | CC13: 000212 | CD13: {=RIGHT(CELL("filename",A1),LEN(CELL("filename",A1))-FIND("]",CELL("filename",A1)))} -> #VALUE! | CE13: 0000 | CG13: FUT Starlight T2 APD DRP | CH13: =+I11 -> 0 | CI13: Commissions Direct | CJ13: 100 | CK13: 500100 | CL13: 00 | CM13: 2002 | CN13: 000212 | CO13: {=RIGHT(CELL("filename",A1),LEN(CELL("filename",A1))-FIND("]",CELL("filename",A1)))} -> #VALUE! | CP13: 0000 | CR13: FUT Starlight T2 APD DRP | CS13: =+J11 -> 0 | CT13: Commissions Direct | CU13: 100 | CV13: 500100 | CW13: 00 | CX13: 2002 | CY13: 000212 | CZ13: {=RIGHT(CELL("filename",A1),LEN(CELL("filename",A1))-FIND("]",CELL("filename",A1)))} -> #VALUE! | DA13: 0000 | DC13: FUT Starlight T2 APD DRP | DD13: =+K11 -> 0 | DE13: Commissions Direct | DF13: 100 | DG13: 500100 | DH13: 00 | DI13: 2002 | DJ13: 000212 | DK13: {=RIGHT(CELL("filename",A1),LEN(CELL("filename",A1))-FIND("]",CELL("filename",A1)))} -> #VALUE! | DL13: 0000 | DN13: FUT Starlight T2 APD DRP | DO13: =+L11 -> 0 | DP13: Commissions Direct | DQ13: 100 | DR13: 500100 | DS13: 00 | DT13: 2002 | DU13: 000212 | DV13: {=RIGHT(CELL("filename",A1),LEN(CELL("filename",A1))-FIND("]",CELL("filename",A1)))} -> #VALUE! | DW13: 0000 | DY13: FUT Starlight T2 APD DRP | DZ13: =+M11 -> 0 | EA13: Commissions Direct | EB13: 100 | EC13: 500100 | ED13: 00 | EE13: 2002 | EF13: 000212 | EG13: {=RIGHT(CELL("filename",A1),LEN(CELL("filename",A1))-FIND("]",CELL("filename",A1)))} -> #VALUE! | EH13: 0000 | EJ13: FUT Starlight T2 APD DRP | EK13: =+N11 -> 0 | EL13: Commissions Direct | EM13: 100 | EN13: 500100 | EO13: 00 | EP13: 2002 | EQ13: 000212 | ER13: {=RIGHT(CELL("filename",A1),LEN(CELL("filename",A1))-FIND("]",CELL("filename",A1)))} -> #VALUE! | ES13: 0000 | EU13: FUT Starlight T2 APD DRP | EV13: =+O11 -> 0
U14: Uncollected Premium Direct | V14: 100 | W14: 120100 | X14: 00 | Y14: 2002 | Z14: 000212 | AA14: 00 | AB14: 0000 | AD14: FUT Starlight T2 APD DRP | AE14: =-D11 -> 0 | AF14: Uncollected Premium Direct | AG14: 100 | AH14: 120100 | AI14: 00 | AJ14: 2002 | AK14: 000212 | AL14: 00 | AM14: 0000 | AO14: FUT Starlight T2 APD DRP | AP14: =-E11 -> 0 | AQ14: Uncollected Premium Direct | AR14: 100 | AS14: 120100 | AT14: 00 | AU14: 2002 | AV14: 000212 | AW14: 00 | AX14: 0000 | AZ14: FUT Starlight T2 APD DRP | BA14: =-F11 -> 0 | BB14: Uncollected Premium Direct | BC14: 100 | BD14: 120100 | BE14: 00 | BF14: 2002 | BG14: 000212 | BH14: 00 | BI14: 0000 | BK14: FUT Starlight T2 APD DRP | BL14: =-G11 -> 0 | BM14: Uncollected Premium Direct | BN14: 100 | BO14: 120100 | BP14: 00 | BQ14: 2002 | BR14: 000212 | BS14: 00 | BT14: 0000 | BV14: FUT Starlight T2 APD DRP | BW14: =-H11 -> 0 | BX14: Uncollected Premium Direct | BY14: 100 | BZ14: 120100 | CA14: 00 | CB14: 2002 | CC14: 000212 | CD14: 00 | CE14: 0000 | CG14: FUT Starlight T2 APD DRP | CH14: =-I11 -> 0 | CI14: Uncollected Premium Direct | CJ14: 100 | CK14: 120100 | CL14: 00 | CM14: 2002 | CN14: 000212 | CO14: 00 | CP14: 0000 | CR14: FUT Starlight T2 APD DRP | CS14: =-J11 -> 0 | CT14: Uncollected Premium Direct | CU14: 100 | CV14: 120100 | CW14: 00 | CX14: 2002 | CY14: 000212 | CZ14: 00 | DA14: 0000 | DC14: FUT Starlight T2 APD DRP | DD14: =-K11 -> 0 | DE14: Uncollected Premium Direct | DF14: 100 | DG14: 120100 | DH14: 00 | DI14: 2002 | DJ14: 000212 | DK14: 00 | DL14: 0000 | DN14: FUT Starlight T2 APD DRP | DO14: =-L11 -> 0 | DP14: Uncollected Premium Direct | DQ14: 100 | DR14: 120100 | DS14: 00 | DT14: 2002 | DU14: 000212 | DV14: 00 | DW14: 0000 | DY14: FUT Starlight T2 APD DRP | DZ14: =-M11 -> 0 | EA14: Uncollected Premium Direct | EB14: 100 | EC14: 120100 | ED14: 00 | EE14: 2002 | EF14: 000212 | EG14: 00 | EH14: 0000 | EJ14: FUT Starlight T2 APD DRP | EK14: =-N11 -> 0 | EL14: Uncollected Premium Direct | EM14: 100 | EN14: 120100 | EO14: 00 | EP14: 2002 | EQ14: 000212 | ER14: 00 | ES14: 0000 | EU14: FUT Starlight T2 APD DRP | EV14: =-O11 -> 0
A15: c. | B15: Losses Paid (net of salvage & subro) | C15: 0 | D15: 0 | P15: =SUM(D15:O15) -> 0 | Q15: =+C15+P15 -> 0 | R15: =Q15 -> 0 | S15: =Q15-R15 -> 0 | U15: Ceded Reinsurance Premiums Payable | V15: 100 | W15: 243100 | X15: 00 | Y15: 2002 | Z15: 000212 | AA15: 00 | AB15: 0000 | AD15: FUT Starlight T2 APD DRP | AE15: =+D11 -> 0 | AF15: Ceded Reinsurance Premiums Payable | AG15: 100 | AH15: 243100 | AI15: 00 | AJ15: 2002 | AK15: 000212 | AL15: 00 | AM15: 0000 | AO15: FUT Starlight T2 APD DRP | AP15: =+E11 -> 0 | AQ15: Ceded Reinsurance Premiums Payable | AR15: 100 | AS15: 243100 | AT15: 00 | AU15: 2002 | AV15: 000212 | AW15: 00 | AX15: 0000 | AZ15: FUT Starlight T2 APD DRP | BA15: =+F11 -> 0 | BB15: Ceded Reinsurance Premiums Payable | BC15: 100 | BD15: 243100 | BE15: 00 | BF15: 2002 | BG15: 000212 | BH15: 00 | BI15: 0000 | BK15: FUT Starlight T2 APD DRP | BL15: =+G11 -> 0 | BM15: Ceded Reinsurance Premiums Payable | BN15: 100 | BO15: 243100 | BP15: 00 | BQ15: 2002 | BR15: 000212 | BS15: 00 | BT15: 0000 | BV15: FUT Starlight T2 APD DRP | BW15: =+H11 -> 0 | BX15: Ceded Reinsurance Premiums Payable | BY15: 100 | BZ15: 243100 | CA15: 00 | CB15: 2002 | CC15: 000212 | CD15: 00 | CE15: 0000 | CG15: FUT Starlight T2 APD DRP | CH15: =+I11 -> 0 | CI15: Ceded Reinsurance Premiums Payable | CJ15: 100 | CK15: 243100 | CL15: 00 | CM15: 2002 | CN15: 000212 | CO15: 00 | CP15: 0000 | CR15: FUT Starlight T2 APD DRP | CS15: =+J11 -> 0 | CT15: Ceded Reinsurance Premiums Payable | CU15: 100 | CV15: 243100 | CW15: 00 | CX15: 2002 | CY15: 000212 | CZ15: 00 | DA15: 0000 | DC15: FUT Starlight T2 APD DRP | DD15: =+K11 -> 0 | DE15: Ceded Reinsurance Premiums Payable | DF15: 100 | DG15: 243100 | DH15: 00 | DI15: 2002 | DJ15: 000212 | DK15: 00 | DL15: 0000 | DN15: FUT Starlight T2 APD DRP | DO15: =+L11 -> 0 | DP15: Ceded Reinsurance Premiums Payable | DQ15: 100 | DR15: 243100 | DS15: 00 | DT15: 2002 | DU15: 000212 | DV15: 00 | DW15: 0000 | DY15: FUT Starlight T2 APD DRP | DZ15: =+M11 -> 0 | EA15: Ceded Reinsurance Premiums Payable | EB15: 100 | EC15: 243100 | ED15: 00 | EE15: 2002 | EF15: 000212 | EG15: 00 | EH15: 0000 | EJ15: FUT Starlight T2 APD DRP | EK15: =+N11 -> 0 | EL15: Ceded Reinsurance Premiums Payable | EM15: 100 | EN15: 243100 | EO15: 00 | EP15: 2002 | EQ15: 000212 | ER15: 00 | ES15: 0000 | EU15: FUT Starlight T2 APD DRP | EV15: =+O11 -> 0
B16: Change in Loss Reserves | C16: 0 | D16: =+D52-C52 -> 0 | P16: =SUM(D16:O16) -> 0 | Q16: =+C16+P16 -> 0 | U16: Commissions Ceded | V16: 100 | W16: 500300 | X16: 00 | Y16: 2002 | Z16: 000212 | AA16: {=RIGHT(CELL("filename",A1),LEN(CELL("filename",A1))-FIND("]",CELL("filename",A1)))} -> #VALUE! | AB16: 0000 | AD16: FUT Starlight T2 APD DRP | AE16: =-D11 -> 0 | AF16: Commissions Ceded | AG16: 100 | AH16: 500300 | AI16: 00 | AJ16: 2002 | AK16: 000212 | AL16: {=RIGHT(CELL("filename",A1),LEN(CELL("filename",A1))-FIND("]",CELL("filename",A1)))} -> #VALUE! | AM16: 0000 | AO16: FUT Starlight T2 APD DRP | AP16: =-E11 -> 0 | AQ16: Commissions Ceded | AR16: 100 | AS16: 500300 | AT16: 00 | AU16: 2002 | AV16: 000212 | AW16: {=RIGHT(CELL("filename",A1),LEN(CELL("filename",A1))-FIND("]",CELL("filename",A1)))} -> #VALUE! | AX16: 0000 | AZ16: FUT Starlight T2 APD DRP | BA16: =-F11 -> 0 | BB16: Commissions Ceded | BC16: 100 | BD16: 500300 | BE16: 00 | BF16: 2002 | BG16: 000212 | BH16: {=RIGHT(CELL("filename",A1),LEN(CELL("filename",A1))-FIND("]",CELL("filename",A1)))} -> #VALUE! | BI16: 0000 | BK16: FUT Starlight T2 APD DRP | BL16: =-G11 -> 0 | BM16: Commissions Ceded | BN16: 100 | BO16: 500300 | BP16: 00 | BQ16: 2002 | BR16: 000212 | BS16: {=RIGHT(CELL("filename",A1),LEN(CELL("filename",A1))-FIND("]",CELL("filename",A1)))} -> #VALUE! | BT16: 0000 | BV16: FUT Starlight T2 APD DRP | BW16: =-H11 -> 0 | BX16: Commissions Ceded | BY16: 100 | BZ16: 500300 | CA16: 00 | CB16: 2002 | CC16: 000212 | CD16: {=RIGHT(CELL("filename",A1),LEN(CELL("filename",A1))-FIND("]",CELL("filename",A1)))} -> #VALUE! | CE16: 0000 | CG16: FUT Starlight T2 APD DRP | CH16: =-I11 -> 0 | CI16: Commissions Ceded | CJ16: 100 | CK16: 500300 | CL16: 00 | CM16: 2002 | CN16: 000212 | CO16: {=RIGHT(CELL("filename",A1),LEN(CELL("filename",A1))-FIND("]",CELL("filename",A1)))} -> #VALUE! | CP16: 0000 | CR16: FUT Starlight T2 APD DRP | CS16: =-J11 -> 0 | CT16: Commissions Ceded | CU16: 100 | CV16: 500300 | CW16: 00 | CX16: 2002 | CY16: 000212 | CZ16: {=RIGHT(CELL("filename",A1),LEN(CELL("filename",A1))-FIND("]",CELL("filename",A1)))} -> #VALUE! | DA16: 0000 | DC16: FUT Starlight T2 APD DRP | DD16: =-K11 -> 0 | DE16: Commissions Ceded | DF16: 100 | DG16: 500300 | DH16: 00 | DI16: 2002 | DJ16: 000212 | DK16: {=RIGHT(CELL("filename",A1),LEN(CELL("filename",A1))-FIND("]",CELL("filename",A1)))} -> #VALUE! | DL16: 0000 | DN16: FUT Starlight T2 APD DRP | DO16: =-L11 -> 0 | DP16: Commissions Ceded | DQ16: 100 | DR16: 500300 | DS16: 00 | DT16: 2002 | DU16: 000212 | DV16: {=RIGHT(CELL("filename",A1),LEN(CELL("filename",A1))-FIND("]",CELL("filename",A1)))} -> #VALUE! | DW16: 0000 | DY16: FUT Starlight T2 APD DRP | DZ16: =-M11 -> 0 | EA16: Commissions Ceded | EB16: 100 | EC16: 500300 | ED16: 00 | EE16: 2002 | EF16: 000212 | EG16: {=RIGHT(CELL("filename",A1),LEN(CELL("filename",A1))-FIND("]",CELL("filename",A1)))} -> #VALUE! | EH16: 0000 | EJ16: FUT Starlight T2 APD DRP | EK16: =-N11 -> 0 | EL16: Commissions Ceded | EM16: 100 | EN16: 500300 | EO16: 00 | EP16: 2002 | EQ16: 000212 | ER16: {=RIGHT(CELL("filename",A1),LEN(CELL("filename",A1))-FIND("]",CELL("filename",A1)))} -> #VALUE! | ES16: 0000 | EU16: FUT Starlight T2 APD DRP | EV16: =-O11 -> 0
B17: Change in Loss IBNR Reserves | C17: 0 | D17: =+D53-C53 -> 0 | P17: =SUM(D17:O17) -> 0 | Q17: =+C17+P17 -> 0 | U17: Direct Losses paid | V17: 100 | W17: 600100 | X17: 00 | Y17: 2002 | Z17: 000212 | AA17: {=RIGHT(CELL("filename",A1),LEN(CELL("filename",A1))-FIND("]",CELL("filename",A1)))} -> #VALUE! | AB17: 0000 | AD17: FUT Starlight T2 APD DRP | AE17: =+D15 -> 0 | AF17: Direct Losses paid | AG17: 100 | AH17: 600100 | AI17: 00 | AJ17: 2002 | AK17: 000212 | AL17: {=RIGHT(CELL("filename",A1),LEN(CELL("filename",A1))-FIND("]",CELL("filename",A1)))} -> #VALUE! | AM17: 0000 | AO17: FUT Starlight T2 APD DRP | AP17: =+E15 -> 0 | AQ17: Direct Losses paid | AR17: 100 | AS17: 600100 | AT17: 00 | AU17: 2002 | AV17: 000212 | AW17: {=RIGHT(CELL("filename",A1),LEN(CELL("filename",A1))-FIND("]",CELL("filename",A1)))} -> #VALUE! | AX17: 0000 | AZ17: FUT Starlight T2 APD DRP | BA17: =+F15 -> 0 | BB17: Direct Losses paid | BC17: 100 | BD17: 600100 | BE17: 00 | BF17: 2002 | BG17: 000212 | BH17: {=RIGHT(CELL("filename",A1),LEN(CELL("filename",A1))-FIND("]",CELL("filename",A1)))} -> #VALUE! | BI17: 0000 | BK17: FUT Starlight T2 APD DRP | BL17: =+G15 -> 0 | BM17: Direct Losses paid | BN17: 100 | BO17: 600100 | BP17: 00 | BQ17: 2002 | BR17: 000212 | BS17: {=RIGHT(CELL("filename",A1),LEN(CELL("filename",A1))-FIND("]",CELL("filename",A1)))} -> #VALUE! | BT17: 0000 | BV17: FUT Starlight T2 APD DRP | BW17: =+H15 -> 0 | BX17: Direct Losses paid | BY17: 100 | BZ17: 600100 | CA17: 00 | CB17: 2002 | CC17: 000212 | CD17: {=RIGHT(CELL("filename",A1),LEN(CELL("filename",A1))-FIND("]",CELL("filename",A1)))} -> #VALUE! | CE17: 0000 | CG17: FUT Starlight T2 APD DRP | CH17: =+I15 -> 0 | CI17: Direct Losses paid | CJ17: 100 | CK17: 600100 | CL17: 00 | CM17: 2002 | CN17: 000212 | CO17: {=RIGHT(CELL("filename",A1),LEN(CELL("filename",A1))-FIND("]",CELL("filename",A1)))} -> #VALUE! | CP17: 0000 | CR17: FUT Starlight T2 APD DRP | CS17: =+J15 -> 0 | CT17: Direct Losses paid | CU17: 100 | CV17: 600100 | CW17: 00 | CX17: 2002 | CY17: 000212 | CZ17: {=RIGHT(CELL("filename",A1),LEN(CELL("filename",A1))-FIND("]",CELL("filename",A1)))} -> #VALUE! | DA17: 0000 | DC17: FUT Starlight T2 APD DRP | DD17: =+K15 -> 0 | DE17: Direct Losses paid | DF17: 100 | DG17: 600100 | DH17: 00 | DI17: 2002 | DJ17: 000212 | DK17: {=RIGHT(CELL("filename",A1),LEN(CELL("filename",A1))-FIND("]",CELL("filename",A1)))} -> #VALUE! | DL17: 0000 | DN17: FUT Starlight T2 APD DRP | DO17: =+L15 -> 0 | DP17: Direct Losses paid | DQ17: 100 | DR17: 600100 | DS17: 00 | DT17: 2002 | DU17: 000212 | DV17: {=RIGHT(CELL("filename",A1),LEN(CELL("filename",A1))-FIND("]",CELL("filename",A1)))} -> #VALUE! | DW17: 0000 | DY17: FUT Starlight T2 APD DRP | DZ17: =+M15 -> 0 | EA17: Direct Losses paid | EB17: 100 | EC17: 600100 | ED17: 00 | EE17: 2002 | EF17: 000212 | EG17: {=RIGHT(CELL("filename",A1),LEN(CELL("filename",A1))-FIND("]",CELL("filename",A1)))} -> #VALUE! | EH17: 0000 | EJ17: FUT Starlight T2 APD DRP | EK17: =+N15 -> 0 | EL17: Direct Losses paid | EM17: 100 | EN17: 600100 | EO17: 00 | EP17: 2002 | EQ17: 000212 | ER17: {=RIGHT(CELL("filename",A1),LEN(CELL("filename",A1))-FIND("]",CELL("filename",A1)))} -> #VALUE! | ES17: 0000 | EU17: FUT Starlight T2 APD DRP | EV17: =+O15 -> 0
B18: Losses Incurred | C18: =SUM(C15:C17) -> 0 | D18: =SUM(D15:D17) -> 0 | P18: =SUM(P15:P17) -> 0 | Q18: =SUM(Q15:Q17) -> 0 | U18: Payable to MGA | V18: 100 | W18: 264400 | X18: 00 | Y18: 2002 | Z18: 000212 | AA18: 00 | AB18: 0000 | AD18: FUT Starlight T2 APD DRP | AE18: =-D15 -> 0 | AF18: Payable to MGA | AG18: 100 | AH18: 264400 | AI18: 00 | AJ18: 2002 | AK18: 000212 | AL18: 00 | AM18: 0000 | AO18: FUT Starlight T2 APD DRP | AP18: =-E15 -> 0 | AQ18: Payable to MGA | AR18: 100 | AS18: 264400 | AT18: 00 | AU18: 2002 | AV18: 000212 | AW18: 00 | AX18: 0000 | AZ18: FUT Starlight T2 APD DRP | BA18: =-F15 -> 0 | BB18: Payable to MGA | BC18: 100 | BD18: 264400 | BE18: 00 | BF18: 2002 | BG18: 000212 | BH18: 00 | BI18: 0000 | BK18: FUT Starlight T2 APD DRP | BL18: =-G15 -> 0 | BM18: Payable to MGA | BN18: 100 | BO18: 264400 | BP18: 00 | BQ18: 2002 | BR18: 000212 | BS18: 00 | BT18: 0000 | BV18: FUT Starlight T2 APD DRP | BW18: =-H15 -> 0 | BX18: Payable to MGA | BY18: 100 | BZ18: 264400 | CA18: 00 | CB18: 2002 | CC18: 000212 | CD18: 00 | CE18: 0000 | CG18: FUT Starlight T2 APD DRP | CH18: =-I15 -> 0 | CI18: Payable to MGA | CJ18: 100 | CK18: 264400 | CL18: 00 | CM18: 2002 | CN18: 000212 | CO18: 00 | CP18: 0000 | CR18: FUT Starlight T2 APD DRP | CS18: =-J15 -> 0 | CT18: Payable to MGA | CU18: 100 | CV18: 264400 | CW18: 00 | CX18: 2002 | CY18: 000212 | CZ18: 00 | DA18: 0000 | DC18: FUT Starlight T2 APD DRP | DD18: =-K15 -> 0 | DE18: Payable to MGA | DF18: 100 | DG18: 264400 | DH18: 00 | DI18: 2002 | DJ18: 000212 | DK18: 00 | DL18: 0000 | DN18: FUT Starlight T2 APD DRP | DO18: =-L15 -> 0 | DP18: Payable to MGA | DQ18: 100 | DR18: 264400 | DS18: 00 | DT18: 2002 | DU18: 000212 | DV18: 00 | DW18: 0000 | DY18: FUT Starlight T2 APD DRP | DZ18: =-M15 -> 0 | EA18: Payable to MGA | EB18: 100 | EC18: 264400 | ED18: 00 | EE18: 2002 | EF18: 000212 | EG18: 00 | EH18: 0000 | EJ18: FUT Starlight T2 APD DRP | EK18: =-N15 -> 0 | EL18: Payable to MGA | EM18: 100 | EN18: 264400 | EO18: 00 | EP18: 2002 | EQ18: 000212 | ER18: 00 | ES18: 0000 | EU18: FUT Starlight T2 APD DRP | EV18: =-O15 -> 0
U19: Amounts recoverable from reinsurers | V19: 100 | W19: 125100 | X19: 00 | Y19: 2002 | Z19: 000212 | AA19: 00 | AB19: 0000 | AD19: FUT Starlight T2 APD DRP | AE19: =+D15 -> 0 | AF19: Amounts recoverable from reinsurers | AG19: 100 | AH19: 125100 | AI19: 00 | AJ19: 2002 | AK19: 000212 | AL19: 00 | AM19: 0000 | AO19: FUT Starlight T2 APD DRP | AP19: =+E15 -> 0 | AQ19: Amounts recoverable from reinsurers | AR19: 100 | AS19: 125100 | AT19: 00 | AU19: 2002 | AV19: 000212 | AW19: 00 | AX19: 0000 | AZ19: FUT Starlight T2 APD DRP | BA19: =+F15 -> 0 | BB19: Amounts recoverable from reinsurers | BC19: 100 | BD19: 125100 | BE19: 00 | BF19: 2002 | BG19: 000212 | BH19: 00 | BI19: 0000 | BK19: FUT Starlight T2 APD DRP | BL19: =+G15 -> 0 | BM19: Amounts recoverable from reinsurers | BN19: 100 | BO19: 125100 | BP19: 00 | BQ19: 2002 | BR19: 000212 | BS19: 00 | BT19: 0000 | BV19: FUT Starlight T2 APD DRP | BW19: =+H15 -> 0 | BX19: Amounts recoverable from reinsurers | BY19: 100 | BZ19: 125100 | CA19: 00 | CB19: 2002 | CC19: 000212 | CD19: 00 | CE19: 0000 | CG19: FUT Starlight T2 APD DRP | CH19: =+I15 -> 0 | CI19: Amounts recoverable from reinsurers | CJ19: 100 | CK19: 125100 | CL19: 00 | CM19: 2002 | CN19: 000212 | CO19: 00 | CP19: 0000 | CR19: FUT Starlight T2 APD DRP | CS19: =+J15 -> 0 | CT19: Amounts recoverable from reinsurers | CU19: 100 | CV19: 125100 | CW19: 00 | CX19: 2002 | CY19: 000212 | CZ19: 00 | DA19: 0000 | DC19: FUT Starlight T2 APD DRP | DD19: =+K15 -> 0 | DE19: Amounts recoverable from reinsurers | DF19: 100 | DG19: 125100 | DH19: 00 | DI19: 2002 | DJ19: 000212 | DK19: 00 | DL19: 0000 | DN19: FUT Starlight T2 APD DRP | DO19: =+L15 -> 0 | DP19: Amounts recoverable from reinsurers | DQ19: 100 | DR19: 125100 | DS19: 00 | DT19: 2002 | DU19: 000212 | DV19: 00 | DW19: 0000 | DY19: FUT Starlight T2 APD DRP | DZ19: =+M15 -> 0 | EA19: Amounts recoverable from reinsurers | EB19: 100 | EC19: 125100 | ED19: 00 | EE19: 2002 | EF19: 000212 | EG19: 00 | EH19: 0000 | EJ19: FUT Starlight T2 APD DRP | EK19: =+N15 -> 0 | EL19: Amounts recoverable from reinsurers | EM19: 100 | EN19: 125100 | EO19: 00 | EP19: 2002 | EQ19: 000212 | ER19: 00 | ES19: 0000 | EU19: FUT Starlight T2 APD DRP | EV19: =+O15 -> 0
A20: d. | B20: Defense and Cost Containment Expense Paid (DCC) | C20: 0 | D20: 0 | P20: =SUM(D20:O20) -> 0 | Q20: =+C20+P20 -> 0 | R20: =Q20 -> 0 | S20: =Q20-R20 -> 0 | U20: Ceded Losses Paid | V20: 100 | W20: 600300 | X20: 00 | Y20: 2002 | Z20: 000212 | AA20: 00 | AB20: 0000 | AD20: FUT Starlight T2 APD DRP | AE20: =-D15 -> 0 | AF20: Ceded Losses Paid | AG20: 100 | AH20: 600300 | AI20: 00 | AJ20: 2002 | AK20: 000212 | AL20: 00 | AM20: 0000 | AO20: FUT Starlight T2 APD DRP | AP20: =-E15 -> 0 | AQ20: Ceded Losses Paid | AR20: 100 | AS20: 600300 | AT20: 00 | AU20: 2002 | AV20: 000212 | AW20: 00 | AX20: 0000 | AZ20: FUT Starlight T2 APD DRP | BA20: =-F15 -> 0 | BB20: Ceded Losses Paid | BC20: 100 | BD20: 600300 | BE20: 00 | BF20: 2002 | BG20: 000212 | BH20: 00 | BI20: 0000 | BK20: FUT Starlight T2 APD DRP | BL20: =-G15 -> 0 | BM20: Ceded Losses Paid | BN20: 100 | BO20: 600300 | BP20: 00 | BQ20: 2002 | BR20: 000212 | BS20: 00 | BT20: 0000 | BV20: FUT Starlight T2 APD DRP | BW20: =-H15 -> 0 | BX20: Ceded Losses Paid | BY20: 100 | BZ20: 600300 | CA20: 00 | CB20: 2002 | CC20: 000212 | CD20: 00 | CE20: 0000 | CG20: FUT Starlight T2 APD DRP | CH20: =-I15 -> 0 | CI20: Ceded Losses Paid | CJ20: 100 | CK20: 600300 | CL20: 00 | CM20: 2002 | CN20: 000212 | CO20: 00 | CP20: 0000 | CR20: FUT Starlight T2 APD DRP | CS20: =-J15 -> 0 | CT20: Ceded Losses Paid | CU20: 100 | CV20: 600300 | CW20: 00 | CX20: 2002 | CY20: 000212 | CZ20: 00 | DA20: 0000 | DC20: FUT Starlight T2 APD DRP | DD20: =-K15 -> 0 | DE20: Ceded Losses Paid | DF20: 100 | DG20: 600300 | DH20: 00 | DI20: 2002 | DJ20: 000212 | DK20: 00 | DL20: 0000 | DN20: FUT Starlight T2 APD DRP | DO20: =-L15 -> 0 | DP20: Ceded Losses Paid | DQ20: 100 | DR20: 600300 | DS20: 00 | DT20: 2002 | DU20: 000212 | DV20: 00 | DW20: 0000 | DY20: FUT Starlight T2 APD DRP | DZ20: =-M15 -> 0 | EA20: Ceded Losses Paid | EB20: 100 | EC20: 600300 | ED20: 00 | EE20: 2002 | EF20: 000212 | EG20: 00 | EH20: 0000 | EJ20: FUT Starlight T2 APD DRP | EK20: =-N15 -> 0 | EL20: Ceded Losses Paid | EM20: 100 | EN20: 600300 | EO20: 00 | EP20: 2002 | EQ20: 000212 | ER20: 00 | ES20: 0000 | EU20: FUT Starlight T2 APD DRP | EV20: =-O15 -> 0
B21: Change in DCC Reserves | C21: 0 | D21: =+D54-C54 -> 0 | P21: =SUM(D21:O21) -> 0 | Q21: =+C21+P21 -> 0 | U21: Change in Case Loss Reserves - Direct | V21: 100 | W21: 550100 | X21: 00 | Y21: 2002 | Z21: 000212 | AA21: {=RIGHT(CELL("filename",A1),LEN(CELL("filename",A1))-FIND("]",CELL("filename",A1)))} -> #VALUE! | AB21: 0000 | AD21: FUT Starlight T2 APD DRP | AE21: =+D16 -> 0 | AF21: Change in Case Loss Reserves - Direct | AG21: 100 | AH21: 550100 | AI21: 00 | AJ21: 2002 | AK21: 000212 | AL21: {=RIGHT(CELL("filename",A1),LEN(CELL("filename",A1))-FIND("]",CELL("filename",A1)))} -> #VALUE! | AM21: 0000 | AO21: FUT Starlight T2 APD DRP | AP21: =+E16 -> 0 | AQ21: Change in Case Loss Reserves - Direct | AR21: 100 | AS21: 550100 | AT21: 00 | AU21: 2002 | AV21: 000212 | AW21: {=RIGHT(CELL("filename",A1),LEN(CELL("filename",A1))-FIND("]",CELL("filename",A1)))} -> #VALUE! | AX21: 0000 | AZ21: FUT Starlight T2 APD DRP | BA21: =+F16 -> 0 | BB21: Change in Case Loss Reserves - Direct | BC21: 100 | BD21: 550100 | BE21: 00 | BF21: 2002 | BG21: 000212 | BH21: {=RIGHT(CELL("filename",A1),LEN(CELL("filename",A1))-FIND("]",CELL("filename",A1)))} -> #VALUE! | BI21: 0000 | BK21: FUT Starlight T2 APD DRP | BL21: =+G16 -> 0 | BM21: Change in Case Loss Reserves - Direct | BN21: 100 | BO21: 550100 | BP21: 00 | BQ21: 2002 | BR21: 000212 | BS21: {=RIGHT(CELL("filename",A1),LEN(CELL("filename",A1))-FIND("]",CELL("filename",A1)))} -> #VALUE! | BT21: 0000 | BV21: FUT Starlight T2 APD DRP | BW21: =+H16 -> 0 | BX21: Change in Case Loss Reserves - Direct | BY21: 100 | BZ21: 550100 | CA21: 00 | CB21: 2002 | CC21: 000212 | CD21: {=RIGHT(CELL("filename",A1),LEN(CELL("filename",A1))-FIND("]",CELL("filename",A1)))} -> #VALUE! | CE21: 0000 | CG21: FUT Starlight T2 APD DRP | CH21: =+I16 -> 0 | CI21: Change in Case Loss Reserves - Direct | CJ21: 100 | CK21: 550100 | CL21: 00 | CM21: 2002 | CN21: 000212 | CO21: {=RIGHT(CELL("filename",A1),LEN(CELL("filename",A1))-FIND("]",CELL("filename",A1)))} -> #VALUE! | CP21: 0000 | CR21: FUT Starlight T2 APD DRP | CS21: =+J16 -> 0 | CT21: Change in Case Loss Reserves - Direct | CU21: 100 | CV21: 550100 | CW21: 00 | CX21: 2002 | CY21: 000212 | CZ21: {=RIGHT(CELL("filename",A1),LEN(CELL("filename",A1))-FIND("]",CELL("filename",A1)))} -> #VALUE! | DA21: 0000 | DC21: FUT Starlight T2 APD DRP | DD21: =+K16 -> 0 | DE21: Change in Case Loss Reserves - Direct | DF21: 100 | DG21: 550100 | DH21: 00 | DI21: 2002 | DJ21: 000212 | DK21: {=RIGHT(CELL("filename",A1),LEN(CELL("filename",A1))-FIND("]",CELL("filename",A1)))} -> #VALUE! | DL21: 0000 | DN21: FUT Starlight T2 APD DRP | DO21: =+L16 -> 0 | DP21: Change in Case Loss Reserves - Direct | DQ21: 100 | DR21: 550100 | DS21: 00 | DT21: 2002 | DU21: 000212 | DV21: {=RIGHT(CELL("filename",A1),LEN(CELL("filename",A1))-FIND("]",CELL("filename",A1)))} -> #VALUE! | DW21: 0000 | DY21: FUT Starlight T2 APD DRP | DZ21: =+M16 -> 0 | EA21: Change in Case Loss Reserves - Direct | EB21: 100 | EC21: 550100 | ED21: 00 | EE21: 2002 | EF21: 000212 | EG21: {=RIGHT(CELL("filename",A1),LEN(CELL("filename",A1))-FIND("]",CELL("filename",A1)))} -> #VALUE! | EH21: 0000 | EJ21: FUT Starlight T2 APD DRP | EK21: =+N16 -> 0 | EL21: Change in Case Loss Reserves - Direct | EM21: 100 | EN21: 550100 | EO21: 00 | EP21: 2002 | EQ21: 000212 | ER21: {=RIGHT(CELL("filename",A1),LEN(CELL("filename",A1))-FIND("]",CELL("filename",A1)))} -> #VALUE! | ES21: 0000 | EU21: FUT Starlight T2 APD DRP | EV21: =+O16 -> 0
B22: Change in DCC IBNR Reserves | C22: 0 | D22: =+D55-C55 -> 0 | P22: =SUM(D22:O22) -> 0 | Q22: =+C22+P22 -> 0 | U22: Case Loss Reserves - Direct | V22: 100 | W22: 200100 | X22: 00 | Y22: 2002 | Z22: 000212 | AA22: {=RIGHT(CELL("filename",A1),LEN(CELL("filename",A1))-FIND("]",CELL("filename",A1)))} -> #VALUE! | AB22: 0000 | AD22: FUT Starlight T2 APD DRP | AE22: =-D16 -> 0 | AF22: Case Loss Reserves - Direct | AG22: 100 | AH22: 200100 | AI22: 00 | AJ22: 2002 | AK22: 000212 | AL22: {=RIGHT(CELL("filename",A1),LEN(CELL("filename",A1))-FIND("]",CELL("filename",A1)))} -> #VALUE! | AM22: 0000 | AO22: FUT Starlight T2 APD DRP | AP22: =-E16 -> 0 | AQ22: Case Loss Reserves - Direct | AR22: 100 | AS22: 200100 | AT22: 00 | AU22: 2002 | AV22: 000212 | AW22: {=RIGHT(CELL("filename",A1),LEN(CELL("filename",A1))-FIND("]",CELL("filename",A1)))} -> #VALUE! | AX22: 0000 | AZ22: FUT Starlight T2 APD DRP | BA22: =-F16 -> 0 | BB22: Case Loss Reserves - Direct | BC22: 100 | BD22: 200100 | BE22: 00 | BF22: 2002 | BG22: 000212 | BH22: {=RIGHT(CELL("filename",A1),LEN(CELL("filename",A1))-FIND("]",CELL("filename",A1)))} -> #VALUE! | BI22: 0000 | BK22: FUT Starlight T2 APD DRP | BL22: =-G16 -> 0 | BM22: Case Loss Reserves - Direct | BN22: 100 | BO22: 200100 | BP22: 00 | BQ22: 2002 | BR22: 000212 | BS22: {=RIGHT(CELL("filename",A1),LEN(CELL("filename",A1))-FIND("]",CELL("filename",A1)))} -> #VALUE! | BT22: 0000 | BV22: FUT Starlight T2 APD DRP | BW22: =-H16 -> 0 | BX22: Case Loss Reserves - Direct | BY22: 100 | BZ22: 200100 | CA22: 00 | CB22: 2002 | CC22: 000212 | CD22: {=RIGHT(CELL("filename",A1),LEN(CELL("filename",A1))-FIND("]",CELL("filename",A1)))} -> #VALUE! | CE22: 0000 | CG22: FUT Starlight T2 APD DRP | CH22: =-I16 -> 0 | CI22: Case Loss Reserves - Direct | CJ22: 100 | CK22: 200100 | CL22: 00 | CM22: 2002 | CN22: 000212 | CO22: {=RIGHT(CELL("filename",A1),LEN(CELL("filename",A1))-FIND("]",CELL("filename",A1)))} -> #VALUE! | CP22: 0000 | CR22: FUT Starlight T2 APD DRP | CS22: =-J16 -> 0 | CT22: Case Loss Reserves - Direct | CU22: 100 | CV22: 200100 | CW22: 00 | CX22: 2002 | CY22: 000212 | CZ22: {=RIGHT(CELL("filename",A1),LEN(CELL("filename",A1))-FIND("]",CELL("filename",A1)))} -> #VALUE! | DA22: 0000 | DC22: FUT Starlight T2 APD DRP | DD22: =-K16 -> 0 | DE22: Case Loss Reserves - Direct | DF22: 100 | DG22: 200100 | DH22: 00 | DI22: 2002 | DJ22: 000212 | DK22: {=RIGHT(CELL("filename",A1),LEN(CELL("filename",A1))-FIND("]",CELL("filename",A1)))} -> #VALUE! | DL22: 0000 | DN22: FUT Starlight T2 APD DRP | DO22: =-L16 -> 0 | DP22: Case Loss Reserves - Direct | DQ22: 100 | DR22: 200100 | DS22: 00 | DT22: 2002 | DU22: 000212 | DV22: {=RIGHT(CELL("filename",A1),LEN(CELL("filename",A1))-FIND("]",CELL("filename",A1)))} -> #VALUE! | DW22: 0000 | DY22: FUT Starlight T2 APD DRP | DZ22: =-M16 -> 0 | EA22: Case Loss Reserves - Direct | EB22: 100 | EC22: 200100 | ED22: 00 | EE22: 2002 | EF22: 000212 | EG22: {=RIGHT(CELL("filename",A1),LEN(CELL("filename",A1))-FIND("]",CELL("filename",A1)))} -> #VALUE! | EH22: 0000 | EJ22: FUT Starlight T2 APD DRP | EK22: =-N16 -> 0 | EL22: Case Loss Reserves - Direct | EM22: 100 | EN22: 200100 | EO22: 00 | EP22: 2002 | EQ22: 000212 | ER22: {=RIGHT(CELL("filename",A1),LEN(CELL("filename",A1))-FIND("]",CELL("filename",A1)))} -> #VALUE! | ES22: 0000 | EU22: FUT Starlight T2 APD DRP | EV22: =-O16 -> 0
A23: e. | B23: Adjusting & Other Expense Paid (AOE) | C23: 0 | D23: 0 | P23: =SUM(D23:O23) -> 0 | Q23: =+C23+P23 -> 0 | R23: =Q23 -> 0 | S23: =Q23-R23 -> 0 | U23: Case Loss Reserves - Ceded | V23: 100 | W23: 200300 | X23: 00 | Y23: 2002 | Z23: 000212 | AA23: 00 | AB23: 0000 | AD23: FUT Starlight T2 APD DRP | AE23: =+D16 -> 0 | AF23: Case Loss Reserves - Ceded | AG23: 100 | AH23: 200300 | AI23: 00 | AJ23: 2002 | AK23: 000212 | AL23: 00 | AM23: 0000 | AO23: FUT Starlight T2 APD DRP | AP23: =+E16 -> 0 | AQ23: Case Loss Reserves - Ceded | AR23: 100 | AS23: 200300 | AT23: 00 | AU23: 2002 | AV23: 000212 | AW23: 00 | AX23: 0000 | AZ23: FUT Starlight T2 APD DRP | BA23: =+F16 -> 0 | BB23: Case Loss Reserves - Ceded | BC23: 100 | BD23: 200300 | BE23: 00 | BF23: 2002 | BG23: 000212 | BH23: 00 | BI23: 0000 | BK23: FUT Starlight T2 APD DRP | BL23: =+G16 -> 0 | BM23: Case Loss Reserves - Ceded | BN23: 100 | BO23: 200300 | BP23: 00 | BQ23: 2002 | BR23: 000212 | BS23: 00 | BT23: 0000 | BV23: FUT Starlight T2 APD DRP | BW23: =+H16 -> 0 | BX23: Case Loss Reserves - Ceded | BY23: 100 | BZ23: 200300 | CA23: 00 | CB23: 2002 | CC23: 000212 | CD23: 00 | CE23: 0000 | CG23: FUT Starlight T2 APD DRP | CH23: =+I16 -> 0 | CI23: Case Loss Reserves - Ceded | CJ23: 100 | CK23: 200300 | CL23: 00 | CM23: 2002 | CN23: 000212 | CO23: 00 | CP23: 0000 | CR23: FUT Starlight T2 APD DRP | CS23: =+J16 -> 0 | CT23: Case Loss Reserves - Ceded | CU23: 100 | CV23: 200300 | CW23: 00 | CX23: 2002 | CY23: 000212 | CZ23: 00 | DA23: 0000 | DC23: FUT Starlight T2 APD DRP | DD23: =+K16 -> 0 | DE23: Case Loss Reserves - Ceded | DF23: 100 | DG23: 200300 | DH23: 00 | DI23: 2002 | DJ23: 000212 | DK23: 00 | DL23: 0000 | DN23: FUT Starlight T2 APD DRP | DO23: =+L16 -> 0 | DP23: Case Loss Reserves - Ceded | DQ23: 100 | DR23: 200300 | DS23: 00 | DT23: 2002 | DU23: 000212 | DV23: 00 | DW23: 0000 | DY23: FUT Starlight T2 APD DRP | DZ23: =+M16 -> 0 | EA23: Case Loss Reserves - Ceded | EB23: 100 | EC23: 200300 | ED23: 00 | EE23: 2002 | EF23: 000212 | EG23: 00 | EH23: 0000 | EJ23: FUT Starlight T2 APD DRP | EK23: =+N16 -> 0 | EL23: Case Loss Reserves - Ceded | EM23: 100 | EN23: 200300 | EO23: 00 | EP23: 2002 | EQ23: 000212 | ER23: 00 | ES23: 0000 | EU23: FUT Starlight T2 APD DRP | EV23: =+O16 -> 0
B24: Change in AOE Reserves | C24: 0 | D24: =+D56-C56 -> 0 | P24: =SUM(D24:O24) -> 0 | Q24: =+C24+P24 -> 0 | U24: Change in Case Loss Reserves - Ceded | V24: 100 | W24: 550300 | X24: 00 | Y24: 2002 | Z24: 000212 | AA24: 00 | AB24: 0000 | AD24: FUT Starlight T2 APD DRP | AE24: =-D16 -> 0 | AF24: Change in Case Loss Reserves - Ceded | AG24: 100 | AH24: 550300 | AI24: 00 | AJ24: 2002 | AK24: 000212 | AL24: 00 | AM24: 0000 | AO24: FUT Starlight T2 APD DRP | AP24: =-E16 -> 0 | AQ24: Change in Case Loss Reserves - Ceded | AR24: 100 | AS24: 550300 | AT24: 00 | AU24: 2002 | AV24: 000212 | AW24: 00 | AX24: 0000 | AZ24: FUT Starlight T2 APD DRP | BA24: =-F16 -> 0 | BB24: Change in Case Loss Reserves - Ceded | BC24: 100 | BD24: 550300 | BE24: 00 | BF24: 2002 | BG24: 000212 | BH24: 00 | BI24: 0000 | BK24: FUT Starlight T2 APD DRP | BL24: =-G16 -> 0 | BM24: Change in Case Loss Reserves - Ceded | BN24: 100 | BO24: 550300 | BP24: 00 | BQ24: 2002 | BR24: 000212 | BS24: 00 | BT24: 0000 | BV24: FUT Starlight T2 APD DRP | BW24: =-H16 -> 0 | BX24: Change in Case Loss Reserves - Ceded | BY24: 100 | BZ24: 550300 | CA24: 00 | CB24: 2002 | CC24: 000212 | CD24: 00 | CE24: 0000 | CG24: FUT Starlight T2 APD DRP | CH24: =-I16 -> 0 | CI24: Change in Case Loss Reserves - Ceded | CJ24: 100 | CK24: 550300 | CL24: 00 | CM24: 2002 | CN24: 000212 | CO24: 00 | CP24: 0000 | CR24: FUT Starlight T2 APD DRP | CS24: =-J16 -> 0 | CT24: Change in Case Loss Reserves - Ceded | CU24: 100 | CV24: 550300 | CW24: 00 | CX24: 2002 | CY24: 000212 | CZ24: 00 | DA24: 0000 | DC24: FUT Starlight T2 APD DRP | DD24: =-K16 -> 0 | DE24: Change in Case Loss Reserves - Ceded | DF24: 100 | DG24: 550300 | DH24: 00 | DI24: 2002 | DJ24: 000212 | DK24: 00 | DL24: 0000 | DN24: FUT Starlight T2 APD DRP | DO24: =-L16 -> 0 | DP24: Change in Case Loss Reserves - Ceded | DQ24: 100 | DR24: 550300 | DS24: 00 | DT24: 2002 | DU24: 000212 | DV24: 00 | DW24: 0000 | DY24: FUT Starlight T2 APD DRP | DZ24: =-M16 -> 0 | EA24: Change in Case Loss Reserves - Ceded | EB24: 100 | EC24: 550300 | ED24: 00 | EE24: 2002 | EF24: 000212 | EG24: 00 | EH24: 0000 | EJ24: FUT Starlight T2 APD DRP | EK24: =-N16 -> 0 | EL24: Change in Case Loss Reserves - Ceded | EM24: 100 | EN24: 550300 | EO24: 00 | EP24: 2002 | EQ24: 000212 | ER24: 00 | ES24: 0000 | EU24: FUT Starlight T2 APD DRP | EV24: =-O16 -> 0
B25: Change in AOE IBNR Reserves | C25: 0 | D25: =+D57-C57 -> 0 | P25: =SUM(D25:O25) -> 0 | Q25: =+C25+P25 -> 0 | U25: Change in IBNR Loss Reserves - Direct | V25: 100 | W25: 550400 | X25: 00 | Y25: 2002 | Z25: 000212 | AA25: {=RIGHT(CELL("filename",A1),LEN(CELL("filename",A1))-FIND("]",CELL("filename",A1)))} -> #VALUE! | AB25: 0000 | AD25: FUT Starlight T2 APD DRP | AE25: =+D17 -> 0 | AF25: Change in IBNR Loss Reserves - Direct | AG25: 100 | AH25: 550400 | AI25: 00 | AJ25: 2002 | AK25: 000212 | AL25: {=RIGHT(CELL("filename",A1),LEN(CELL("filename",A1))-FIND("]",CELL("filename",A1)))} -> #VALUE! | AM25: 0000 | AO25: FUT Starlight T2 APD DRP | AP25: =+E17 -> 0 | AQ25: Change in IBNR Loss Reserves - Direct | AR25: 100 | AS25: 550400 | AT25: 00 | AU25: 2002 | AV25: 000212 | AW25: {=RIGHT(CELL("filename",A1),LEN(CELL("filename",A1))-FIND("]",CELL("filename",A1)))} -> #VALUE! | AX25: 0000 | AZ25: FUT Starlight T2 APD DRP | BA25: =+F17 -> 0 | BB25: Change in IBNR Loss Reserves - Direct | BC25: 100 | BD25: 550400 | BE25: 00 | BF25: 2002 | BG25: 000212 | BH25: {=RIGHT(CELL("filename",A1),LEN(CELL("filename",A1))-FIND("]",CELL("filename",A1)))} -> #VALUE! | BI25: 0000 | BK25: FUT Starlight T2 APD DRP | BL25: =+G17 -> 0 | BM25: Change in IBNR Loss Reserves - Direct | BN25: 100 | BO25: 550400 | BP25: 00 | BQ25: 2002 | BR25: 000212 | BS25: {=RIGHT(CELL("filename",A1),LEN(CELL("filename",A1))-FIND("]",CELL("filename",A1)))} -> #VALUE! | BT25: 0000 | BV25: FUT Starlight T2 APD DRP | BW25: =+H17 -> 0 | BX25: Change in IBNR Loss Reserves - Direct | BY25: 100 | BZ25: 550400 | CA25: 00 | CB25: 2002 | CC25: 000212 | CD25: {=RIGHT(CELL("filename",A1),LEN(CELL("filename",A1))-FIND("]",CELL("filename",A1)))} -> #VALUE! | CE25: 0000 | CG25: FUT Starlight T2 APD DRP | CH25: =+I17 -> 0 | CI25: Change in IBNR Loss Reserves - Direct | CJ25: 100 | CK25: 550400 | CL25: 00 | CM25: 2002 | CN25: 000212 | CO25: {=RIGHT(CELL("filename",A1),LEN(CELL("filename",A1))-FIND("]",CELL("filename",A1)))} -> #VALUE! | CP25: 0000 | CR25: FUT Starlight T2 APD DRP | CS25: =+J17 -> 0 | CT25: Change in IBNR Loss Reserves - Direct | CU25: 100 | CV25: 550400 | CW25: 00 | CX25: 2002 | CY25: 000212 | CZ25: {=RIGHT(CELL("filename",A1),LEN(CELL("filename",A1))-FIND("]",CELL("filename",A1)))} -> #VALUE! | DA25: 0000 | DC25: FUT Starlight T2 APD DRP | DD25: =+K17 -> 0 | DE25: Change in IBNR Loss Reserves - Direct | DF25: 100 | DG25: 550400 | DH25: 00 | DI25: 2002 | DJ25: 000212 | DK25: {=RIGHT(CELL("filename",A1),LEN(CELL("filename",A1))-FIND("]",CELL("filename",A1)))} -> #VALUE! | DL25: 0000 | DN25: FUT Starlight T2 APD DRP | DO25: =+L17 -> 0 | DP25: Change in IBNR Loss Reserves - Direct | DQ25: 100 | DR25: 550400 | DS25: 00 | DT25: 2002 | DU25: 000212 | DV25: {=RIGHT(CELL("filename",A1),LEN(CELL("filename",A1))-FIND("]",CELL("filename",A1)))} -> #VALUE! | DW25: 0000 | DY25: FUT Starlight T2 APD DRP | DZ25: =+M17 -> 0 | EA25: Change in IBNR Loss Reserves - Direct | EB25: 100 | EC25: 550400 | ED25: 00 | EE25: 2002 | EF25: 000212 | EG25: {=RIGHT(CELL("filename",A1),LEN(CELL("filename",A1))-FIND("]",CELL("filename",A1)))} -> #VALUE! | EH25: 0000 | EJ25: FUT Starlight T2 APD DRP | EK25: =+N17 -> 0 | EL25: Change in IBNR Loss Reserves - Direct | EM25: 100 | EN25: 550400 | EO25: 00 | EP25: 2002 | EQ25: 000212 | ER25: {=RIGHT(CELL("filename",A1),LEN(CELL("filename",A1))-FIND("]",CELL("filename",A1)))} -> #VALUE! | ES25: 0000 | EU25: FUT Starlight T2 APD DRP | EV25: =+O17 -> 0
A26: f. | B26: Unallocated Loss Adjustment Expense at 7% | C26: 0 | D26: =+D6*0.07 -> 0 | P26: =SUM(D26:O26) -> 0 | Q26: =+C26+P26 -> 0 | U26: IBNR Loss Reserves - Direct | V26: 100 | W26: 200400 | X26: 00 | Y26: 2002 | Z26: 000212 | AA26: {=RIGHT(CELL("filename",A1),LEN(CELL("filename",A1))-FIND("]",CELL("filename",A1)))} -> #VALUE! | AB26: 0000 | AD26: FUT Starlight T2 APD DRP | AE26: =-D17 -> 0 | AF26: IBNR Loss Reserves - Direct | AG26: 100 | AH26: 200400 | AI26: 00 | AJ26: 2002 | AK26: 000212 | AL26: {=RIGHT(CELL("filename",A1),LEN(CELL("filename",A1))-FIND("]",CELL("filename",A1)))} -> #VALUE! | AM26: 0000 | AO26: FUT Starlight T2 APD DRP | AP26: =-E17 -> 0 | AQ26: IBNR Loss Reserves - Direct | AR26: 100 | AS26: 200400 | AT26: 00 | AU26: 2002 | AV26: 000212 | AW26: {=RIGHT(CELL("filename",A1),LEN(CELL("filename",A1))-FIND("]",CELL("filename",A1)))} -> #VALUE! | AX26: 0000 | AZ26: FUT Starlight T2 APD DRP | BA26: =-F17 -> 0 | BB26: IBNR Loss Reserves - Direct | BC26: 100 | BD26: 200400 | BE26: 00 | BF26: 2002 | BG26: 000212 | BH26: {=RIGHT(CELL("filename",A1),LEN(CELL("filename",A1))-FIND("]",CELL("filename",A1)))} -> #VALUE! | BI26: 0000 | BK26: FUT Starlight T2 APD DRP | BL26: =-G17 -> 0 | BM26: IBNR Loss Reserves - Direct | BN26: 100 | BO26: 200400 | BP26: 00 | BQ26: 2002 | BR26: 000212 | BS26: {=RIGHT(CELL("filename",A1),LEN(CELL("filename",A1))-FIND("]",CELL("filename",A1)))} -> #VALUE! | BT26: 0000 | BV26: FUT Starlight T2 APD DRP | BW26: =-H17 -> 0 | BX26: IBNR Loss Reserves - Direct | BY26: 100 | BZ26: 200400 | CA26: 00 | CB26: 2002 | CC26: 000212 | CD26: {=RIGHT(CELL("filename",A1),LEN(CELL("filename",A1))-FIND("]",CELL("filename",A1)))} -> #VALUE! | CE26: 0000 | CG26: FUT Starlight T2 APD DRP | CH26: =-I17 -> 0 | CI26: IBNR Loss Reserves - Direct | CJ26: 100 | CK26: 200400 | CL26: 00 | CM26: 2002 | CN26: 000212 | CO26: {=RIGHT(CELL("filename",A1),LEN(CELL("filename",A1))-FIND("]",CELL("filename",A1)))} -> #VALUE! | CP26: 0000 | CR26: FUT Starlight T2 APD DRP | CS26: =-J17 -> 0 | CT26: IBNR Loss Reserves - Direct | CU26: 100 | CV26: 200400 | CW26: 00 | CX26: 2002 | CY26: 000212 | CZ26: {=RIGHT(CELL("filename",A1),LEN(CELL("filename",A1))-FIND("]",CELL("filename",A1)))} -> #VALUE! | DA26: 0000 | DC26: FUT Starlight T2 APD DRP | DD26: =-K17 -> 0 | DE26: IBNR Loss Reserves - Direct | DF26: 100 | DG26: 200400 | DH26: 00 | DI26: 2002 | DJ26: 000212 | DK26: {=RIGHT(CELL("filename",A1),LEN(CELL("filename",A1))-FIND("]",CELL("filename",A1)))} -> #VALUE! | DL26: 0000 | DN26: FUT Starlight T2 APD DRP | DO26: =-L17 -> 0 | DP26: IBNR Loss Reserves - Direct | DQ26: 100 | DR26: 200400 | DS26: 00 | DT26: 2002 | DU26: 000212 | DV26: {=RIGHT(CELL("filename",A1),LEN(CELL("filename",A1))-FIND("]",CELL("filename",A1)))} -> #VALUE! | DW26: 0000 | DY26: FUT Starlight T2 APD DRP | DZ26: =-M17 -> 0 | EA26: IBNR Loss Reserves - Direct | EB26: 100 | EC26: 200400 | ED26: 00 | EE26: 2002 | EF26: 000212 | EG26: {=RIGHT(CELL("filename",A1),LEN(CELL("filename",A1))-FIND("]",CELL("filename",A1)))} -> #VALUE! | EH26: 0000 | EJ26: FUT Starlight T2 APD DRP | EK26: =-N17 -> 0 | EL26: IBNR Loss Reserves - Direct | EM26: 100 | EN26: 200400 | EO26: 00 | EP26: 2002 | EQ26: 000212 | ER26: {=RIGHT(CELL("filename",A1),LEN(CELL("filename",A1))-FIND("]",CELL("filename",A1)))} -> #VALUE! | ES26: 0000 | EU26: FUT Starlight T2 APD DRP | EV26: =-O17 -> 0
B27: Change in ULAE IBNR Reserves | C27: =((+C16*0.5)+C17)*0.005 -> 0 | D27: =((+D16*0.5)+D17)*0.005 -> 0 | E27: =((+E16*0.5)+E17)*0.005 -> 0 | F27: =((+F16*0.5)+F17)*0.005 -> 0 | P27: =SUM(D27:O27) -> 0 | Q27: =+C27+P27 -> 0 | U27: IBNR Loss Reserves - Ceded | V27: 100 | W27: 200600 | X27: 00 | Y27: 2002 | Z27: 000212 | AA27: 00 | AB27: 0000 | AD27: FUT Starlight T2 APD DRP | AE27: =+D17 -> 0 | AF27: IBNR Loss Reserves - Ceded | AG27: 100 | AH27: 200600 | AI27: 00 | AJ27: 2002 | AK27: 000212 | AL27: 00 | AM27: 0000 | AO27: FUT Starlight T2 APD DRP | AP27: =+E17 -> 0 | AQ27: IBNR Loss Reserves - Ceded | AR27: 100 | AS27: 200600 | AT27: 00 | AU27: 2002 | AV27: 000212 | AW27: 00 | AX27: 0000 | AZ27: FUT Starlight T2 APD DRP | BA27: =+F17 -> 0 | BB27: IBNR Loss Reserves - Ceded | BC27: 100 | BD27: 200600 | BE27: 00 | BF27: 2002 | BG27: 000212 | BH27: 00 | BI27: 0000 | BK27: FUT Starlight T2 APD DRP | BL27: =+G17 -> 0 | BM27: IBNR Loss Reserves - Ceded | BN27: 100 | BO27: 200600 | BP27: 00 | BQ27: 2002 | BR27: 000212 | BS27: 00 | BT27: 0000 | BV27: FUT Starlight T2 APD DRP | BW27: =+H17 -> 0 | BX27: IBNR Loss Reserves - Ceded | BY27: 100 | BZ27: 200600 | CA27: 00 | CB27: 2002 | CC27: 000212 | CD27: 00 | CE27: 0000 | CG27: FUT Starlight T2 APD DRP | CH27: =+I17 -> 0 | CI27: IBNR Loss Reserves - Ceded | CJ27: 100 | CK27: 200600 | CL27: 00 | CM27: 2002 | CN27: 000212 | CO27: 00 | CP27: 0000 | CR27: FUT Starlight T2 APD DRP | CS27: =+J17 -> 0 | CT27: IBNR Loss Reserves - Ceded | CU27: 100 | CV27: 200600 | CW27: 00 | CX27: 2002 | CY27: 000212 | CZ27: 00 | DA27: 0000 | DC27: FUT Starlight T2 APD DRP | DD27: =+K17 -> 0 | DE27: IBNR Loss Reserves - Ceded | DF27: 100 | DG27: 200600 | DH27: 00 | DI27: 2002 | DJ27: 000212 | DK27: 00 | DL27: 0000 | DN27: FUT Starlight T2 APD DRP | DO27: =+L17 -> 0 | DP27: IBNR Loss Reserves - Ceded | DQ27: 100 | DR27: 200600 | DS27: 00 | DT27: 2002 | DU27: 000212 | DV27: 00 | DW27: 0000 | DY27: FUT Starlight T2 APD DRP | DZ27: =+M17 -> 0 | EA27: IBNR Loss Reserves - Ceded | EB27: 100 | EC27: 200600 | ED27: 00 | EE27: 2002 | EF27: 000212 | EG27: 00 | EH27: 0000 | EJ27: FUT Starlight T2 APD DRP | EK27: =+N17 -> 0 | EL27: IBNR Loss Reserves - Ceded | EM27: 100 | EN27: 200600 | EO27: 00 | EP27: 2002 | EQ27: 000212 | ER27: 00 | ES27: 0000 | EU27: FUT Starlight T2 APD DRP | EV27: =+O17 -> 0
B28: Loss Adjustment Expenses Incurred | C28: =SUM(C20:C27) -> 0 | D28: =SUM(D20:D27) -> 0 | P28: =SUM(P20:P27) -> 0 | Q28: =SUM(Q20:Q27) -> 0 | U28: Change in IBNR Loss Reserves - Ceded | V28: 100 | W28: 550600 | X28: 00 | Y28: 2002 | Z28: 000212 | AA28: 00 | AB28: 0000 | AD28: FUT Starlight T2 APD DRP | AE28: =-D17 -> 0 | AF28: Change in IBNR Loss Reserves - Ceded | AG28: 100 | AH28: 550600 | AI28: 00 | AJ28: 2002 | AK28: 000212 | AL28: 00 | AM28: 0000 | AO28: FUT Starlight T2 APD DRP | AP28: =-E17 -> 0 | AQ28: Change in IBNR Loss Reserves - Ceded | AR28: 100 | AS28: 550600 | AT28: 00 | AU28: 2002 | AV28: 000212 | AW28: 00 | AX28: 0000 | AZ28: FUT Starlight T2 APD DRP | BA28: =-F17 -> 0 | BB28: Change in IBNR Loss Reserves - Ceded | BC28: 100 | BD28: 550600 | BE28: 00 | BF28: 2002 | BG28: 000212 | BH28: 00 | BI28: 0000 | BK28: FUT Starlight T2 APD DRP | BL28: =-G17 -> 0 | BM28: Change in IBNR Loss Reserves - Ceded | BN28: 100 | BO28: 550600 | BP28: 00 | BQ28: 2002 | BR28: 000212 | BS28: 00 | BT28: 0000 | BV28: FUT Starlight T2 APD DRP | BW28: =-H17 -> 0 | BX28: Change in IBNR Loss Reserves - Ceded | BY28: 100 | BZ28: 550600 | CA28: 00 | CB28: 2002 | CC28: 000212 | CD28: 00 | CE28: 0000 | CG28: FUT Starlight T2 APD DRP | CH28: =-I17 -> 0 | CI28: Change in IBNR Loss Reserves - Ceded | CJ28: 100 | CK28: 550600 | CL28: 00 | CM28: 2002 | CN28: 000212 | CO28: 00 | CP28: 0000 | CR28: FUT Starlight T2 APD DRP | CS28: =-J17 -> 0 | CT28: Change in IBNR Loss Reserves - Ceded | CU28: 100 | CV28: 550600 | CW28: 00 | CX28: 2002 | CY28: 000212 | CZ28: 00 | DA28: 0000 | DC28: FUT Starlight T2 APD DRP | DD28: =-K17 -> 0 | DE28: Change in IBNR Loss Reserves - Ceded | DF28: 100 | DG28: 550600 | DH28: 00 | DI28: 2002 | DJ28: 000212 | DK28: 00 | DL28: 0000 | DN28: FUT Starlight T2 APD DRP | DO28: =-L17 -> 0 | DP28: Change in IBNR Loss Reserves - Ceded | DQ28: 100 | DR28: 550600 | DS28: 00 | DT28: 2002 | DU28: 000212 | DV28: 00 | DW28: 0000 | DY28: FUT Starlight T2 APD DRP | DZ28: =-M17 -> 0 | EA28: Change in IBNR Loss Reserves - Ceded | EB28: 100 | EC28: 550600 | ED28: 00 | EE28: 2002 | EF28: 000212 | EG28: 00 | EH28: 0000 | EJ28: FUT Starlight T2 APD DRP | EK28: =-N17 -> 0 | EL28: Change in IBNR Loss Reserves - Ceded | EM28: 100 | EN28: 550600 | EO28: 00 | EP28: 2002 | EQ28: 000212 | ER28: 00 | ES28: 0000 | EU28: FUT Starlight T2 APD DRP | EV28: =-O17 -> 0
U29: Direct LAE DCC Paid | V29: 100 | W29: 601100 | X29: 00 | Y29: 2002 | Z29: 000212 | AA29: {=RIGHT(CELL("filename",A1),LEN(CELL("filename",A1))-FIND("]",CELL("filename",A1)))} -> #VALUE! | AB29: 0000 | AD29: FUT Starlight T2 APD DRP | AE29: =+D20 -> 0 | AF29: Direct LAE DCC Paid | AG29: 100 | AH29: 601100 | AI29: 00 | AJ29: 2002 | AK29: 000212 | AL29: {=RIGHT(CELL("filename",A1),LEN(CELL("filename",A1))-FIND("]",CELL("filename",A1)))} -> #VALUE! | AM29: 0000 | AO29: FUT Starlight T2 APD DRP | AP29: =+E20 -> 0 | AQ29: Direct LAE DCC Paid | AR29: 100 | AS29: 601100 | AT29: 00 | AU29: 2002 | AV29: 000212 | AW29: {=RIGHT(CELL("filename",A1),LEN(CELL("filename",A1))-FIND("]",CELL("filename",A1)))} -> #VALUE! | AX29: 0000 | AZ29: FUT Starlight T2 APD DRP | BA29: =+F20 -> 0 | BB29: Direct LAE DCC Paid | BC29: 100 | BD29: 601100 | BE29: 00 | BF29: 2002 | BG29: 000212 | BH29: {=RIGHT(CELL("filename",A1),LEN(CELL("filename",A1))-FIND("]",CELL("filename",A1)))} -> #VALUE! | BI29: 0000 | BK29: FUT Starlight T2 APD DRP | BL29: =+G20 -> 0 | BM29: Direct LAE DCC Paid | BN29: 100 | BO29: 601100 | BP29: 00 | BQ29: 2002 | BR29: 000212 | BS29: {=RIGHT(CELL("filename",A1),LEN(CELL("filename",A1))-FIND("]",CELL("filename",A1)))} -> #VALUE! | BT29: 0000 | BV29: FUT Starlight T2 APD DRP | BW29: =+H20 -> 0 | BX29: Direct LAE DCC Paid | BY29: 100 | BZ29: 601100 | CA29: 00 | CB29: 2002 | CC29: 000212 | CD29: {=RIGHT(CELL("filename",A1),LEN(CELL("filename",A1))-FIND("]",CELL("filename",A1)))} -> #VALUE! | CE29: 0000 | CG29: FUT Starlight T2 APD DRP | CH29: =+I20 -> 0 | CI29: Direct LAE DCC Paid | CJ29: 100 | CK29: 601100 | CL29: 00 | CM29: 2002 | CN29: 000212 | CO29: {=RIGHT(CELL("filename",A1),LEN(CELL("filename",A1))-FIND("]",CELL("filename",A1)))} -> #VALUE! | CP29: 0000 | CR29: FUT Starlight T2 APD DRP | CS29: =+J20 -> 0 | CT29: Direct LAE DCC Paid | CU29: 100 | CV29: 601100 | CW29: 00 | CX29: 2002 | CY29: 000212 | CZ29: {=RIGHT(CELL("filename",A1),LEN(CELL("filename",A1))-FIND("]",CELL("filename",A1)))} -> #VALUE! | DA29: 0000 | DC29: FUT Starlight T2 APD DRP | DD29: =+K20 -> 0 | DE29: Direct LAE DCC Paid | DF29: 100 | DG29: 601100 | DH29: 00 | DI29: 2002 | DJ29: 000212 | DK29: {=RIGHT(CELL("filename",A1),LEN(CELL("filename",A1))-FIND("]",CELL("filename",A1)))} -> #VALUE! | DL29: 0000 | DN29: FUT Starlight T2 APD DRP | DO29: =+L20 -> 0 | DP29: Direct LAE DCC Paid | DQ29: 100 | DR29: 601100 | DS29: 00 | DT29: 2002 | DU29: 000212 | DV29: {=RIGHT(CELL("filename",A1),LEN(CELL("filename",A1))-FIND("]",CELL("filename",A1)))} -> #VALUE! | DW29: 0000 | DY29: FUT Starlight T2 APD DRP | DZ29: =+M20 -> 0 | EA29: Direct LAE DCC Paid | EB29: 100 | EC29: 601100 | ED29: 00 | EE29: 2002 | EF29: 000212 | EG29: {=RIGHT(CELL("filename",A1),LEN(CELL("filename",A1))-FIND("]",CELL("filename",A1)))} -> #VALUE! | EH29: 0000 | EJ29: FUT Starlight T2 APD DRP | EK29: =+N20 -> 0 | EL29: Direct LAE DCC Paid | EM29: 100 | EN29: 601100 | EO29: 00 | EP29: 2002 | EQ29: 000212 | ER29: {=RIGHT(CELL("filename",A1),LEN(CELL("filename",A1))-FIND("]",CELL("filename",A1)))} -> #VALUE! | ES29: 0000 | EU29: FUT Starlight T2 APD DRP | EV29: =+O20 -> 0
A30: g. | B30: Boards & Bureaus / ISO Charge at .4% | C30: =+C6*0.004 -> 0 | D30: =+D6*0.004 -> 0 | P30: =SUM(D30:O30) -> 0 | Q30: =+C30+P30 -> 0 | U30: Payable to MGA | V30: 100 | W30: 264400 | X30: 00 | Y30: 2002 | Z30: 000212 | AA30: 00 | AB30: 0000 | AD30: FUT Starlight T2 APD DRP | AE30: =-D20 -> 0 | AF30: Payable to MGA | AG30: 100 | AH30: 264400 | AI30: 00 | AJ30: 2002 | AK30: 000212 | AL30: 00 | AM30: 0000 | AO30: FUT Starlight T2 APD DRP | AP30: =-E20 -> 0 | AQ30: Payable to MGA | AR30: 100 | AS30: 264400 | AT30: 00 | AU30: 2002 | AV30: 000212 | AW30: 00 | AX30: 0000 | AZ30: FUT Starlight T2 APD DRP | BA30: =-F20 -> 0 | BB30: Payable to MGA | BC30: 100 | BD30: 264400 | BE30: 00 | BF30: 2002 | BG30: 000212 | BH30: 00 | BI30: 0000 | BK30: FUT Starlight T2 APD DRP | BL30: =-G20 -> 0 | BM30: Payable to MGA | BN30: 100 | BO30: 264400 | BP30: 00 | BQ30: 2002 | BR30: 000212 | BS30: 00 | BT30: 0000 | BV30: FUT Starlight T2 APD DRP | BW30: =-H20 -> 0 | BX30: Payable to MGA | BY30: 100 | BZ30: 264400 | CA30: 00 | CB30: 2002 | CC30: 000212 | CD30: 00 | CE30: 0000 | CG30: FUT Starlight T2 APD DRP | CH30: =-I20 -> 0 | CI30: Payable to MGA | CJ30: 100 | CK30: 264400 | CL30: 00 | CM30: 2002 | CN30: 000212 | CO30: 00 | CP30: 0000 | CR30: FUT Starlight T2 APD DRP | CS30: =-J20 -> 0 | CT30: Payable to MGA | CU30: 100 | CV30: 264400 | CW30: 00 | CX30: 2002 | CY30: 000212 | CZ30: 00 | DA30: 0000 | DC30: FUT Starlight T2 APD DRP | DD30: =-K20 -> 0 | DE30: Payable to MGA | DF30: 100 | DG30: 264400 | DH30: 00 | DI30: 2002 | DJ30: 000212 | DK30: 00 | DL30: 0000 | DN30: FUT Starlight T2 APD DRP | DO30: =-L20 -> 0 | DP30: Payable to MGA | DQ30: 100 | DR30: 264400 | DS30: 00 | DT30: 2002 | DU30: 000212 | DV30: 00 | DW30: 0000 | DY30: FUT Starlight T2 APD DRP | DZ30: =-M20 -> 0 | EA30: Payable to MGA | EB30: 100 | EC30: 264400 | ED30: 00 | EE30: 2002 | EF30: 000212 | EG30: 00 | EH30: 0000 | EJ30: FUT Starlight T2 APD DRP | EK30: =-N20 -> 0 | EL30: Payable to MGA | EM30: 100 | EN30: 264400 | EO30: 00 | EP30: 2002 | EQ30: 000212 | ER30: 00 | ES30: 0000 | EU30: FUT Starlight T2 APD DRP | EV30: =-O20 -> 0
B31: Boards & Bureaus / ISO Charge at .4% on UEP | C31: =+C7*0.004 -> 0 | D31: =+D7*0.004 -> 0 | P31: =SUM(D31:O31) -> 0 | Q31: =+C31+P31 -> 0 | U31: Amounts recoverable from reinsurers | V31: 100 | W31: 125100 | X31: 00 | Y31: 2002 | Z31: 000212 | AA31: 00 | AB31: 0000 | AD31: FUT Starlight T2 APD DRP | AE31: =+D20 -> 0 | AF31: Amounts recoverable from reinsurers | AG31: 100 | AH31: 125100 | AI31: 00 | AJ31: 2002 | AK31: 000212 | AL31: 00 | AM31: 0000 | AO31: FUT Starlight T2 APD DRP | AP31: =+E20 -> 0 | AQ31: Amounts recoverable from reinsurers | AR31: 100 | AS31: 125100 | AT31: 00 | AU31: 2002 | AV31: 000212 | AW31: 00 | AX31: 0000 | AZ31: FUT Starlight T2 APD DRP | BA31: =+F20 -> 0 | BB31: Amounts recoverable from reinsurers | BC31: 100 | BD31: 125100 | BE31: 00 | BF31: 2002 | BG31: 000212 | BH31: 00 | BI31: 0000 | BK31: FUT Starlight T2 APD DRP | BL31: =+G20 -> 0 | BM31: Amounts recoverable from reinsurers | BN31: 100 | BO31: 125100 | BP31: 00 | BQ31: 2002 | BR31: 000212 | BS31: 00 | BT31: 0000 | BV31: FUT Starlight T2 APD DRP | BW31: =+H20 -> 0 | BX31: Amounts recoverable from reinsurers | BY31: 100 | BZ31: 125100 | CA31: 00 | CB31: 2002 | CC31: 000212 | CD31: 00 | CE31: 0000 | CG31: FUT Starlight T2 APD DRP | CH31: =+I20 -> 0 | CI31: Amounts recoverable from reinsurers | CJ31: 100 | CK31: 125100 | CL31: 00 | CM31: 2002 | CN31: 000212 | CO31: 00 | CP31: 0000 | CR31: FUT Starlight T2 APD DRP | CS31: =+J20 -> 0 | CT31: Amounts recoverable from reinsurers | CU31: 100 | CV31: 125100 | CW31: 00 | CX31: 2002 | CY31: 000212 | CZ31: 00 | DA31: 0000 | DC31: FUT Starlight T2 APD DRP | DD31: =+K20 -> 0 | DE31: Amounts recoverable from reinsurers | DF31: 100 | DG31: 125100 | DH31: 00 | DI31: 2002 | DJ31: 000212 | DK31: 00 | DL31: 0000 | DN31: FUT Starlight T2 APD DRP | DO31: =+L20 -> 0 | DP31: Amounts recoverable from reinsurers | DQ31: 100 | DR31: 125100 | DS31: 00 | DT31: 2002 | DU31: 000212 | DV31: 00 | DW31: 0000 | DY31: FUT Starlight T2 APD DRP | DZ31: =+M20 -> 0 | EA31: Amounts recoverable from reinsurers | EB31: 100 | EC31: 125100 | ED31: 00 | EE31: 2002 | EF31: 000212 | EG31: 00 | EH31: 0000 | EJ31: FUT Starlight T2 APD DRP | EK31: =+N20 -> 0 | EL31: Amounts recoverable from reinsurers | EM31: 100 | EN31: 125100 | EO31: 00 | EP31: 2002 | EQ31: 000212 | ER31: 00 | ES31: 0000 | EU31: FUT Starlight T2 APD DRP | EV31: =+O20 -> 0
A32: h. | B32: Loss Ratio Cap Charge at 0% | C32: =+C6*0.02 -> 0 | D32: =+D6*0.02 -> 0 | P32: =SUM(D32:O32) -> 0 | Q32: =+C32+P32 -> 0 | U32: Ceded LAE DCC Paid | V32: 100 | W32: 601300 | X32: 00 | Y32: 2002 | Z32: 000212 | AA32: 00 | AB32: 0000 | AD32: FUT Starlight T2 APD DRP | AE32: =-D20 -> 0 | AF32: Ceded LAE DCC Paid | AG32: 100 | AH32: 601300 | AI32: 00 | AJ32: 2002 | AK32: 000212 | AL32: 00 | AM32: 0000 | AO32: FUT Starlight T2 APD DRP | AP32: =-E20 -> 0 | AQ32: Ceded LAE DCC Paid | AR32: 100 | AS32: 601300 | AT32: 00 | AU32: 2002 | AV32: 000212 | AW32: 00 | AX32: 0000 | AZ32: FUT Starlight T2 APD DRP | BA32: =-F20 -> 0 | BB32: Ceded LAE DCC Paid | BC32: 100 | BD32: 601300 | BE32: 00 | BF32: 2002 | BG32: 000212 | BH32: 00 | BI32: 0000 | BK32: FUT Starlight T2 APD DRP | BL32: =-G20 -> 0 | BM32: Ceded LAE DCC Paid | BN32: 100 | BO32: 601300 | BP32: 00 | BQ32: 2002 | BR32: 000212 | BS32: 00 | BT32: 0000 | BV32: FUT Starlight T2 APD DRP | BW32: =-H20 -> 0 | BX32: Ceded LAE DCC Paid | BY32: 100 | BZ32: 601300 | CA32: 00 | CB32: 2002 | CC32: 000212 | CD32: 00 | CE32: 0000 | CG32: FUT Starlight T2 APD DRP | CH32: =-I20 -> 0 | CI32: Ceded LAE DCC Paid | CJ32: 100 | CK32: 601300 | CL32: 00 | CM32: 2002 | CN32: 000212 | CO32: 00 | CP32: 0000 | CR32: FUT Starlight T2 APD DRP | CS32: =-J20 -> 0 | CT32: Ceded LAE DCC Paid | CU32: 100 | CV32: 601300 | CW32: 00 | CX32: 2002 | CY32: 000212 | CZ32: 00 | DA32: 0000 | DC32: FUT Starlight T2 APD DRP | DD32: =-K20 -> 0 | DE32: Ceded LAE DCC Paid | DF32: 100 | DG32: 601300 | DH32: 00 | DI32: 2002 | DJ32: 000212 | DK32: 00 | DL32: 0000 | DN32: FUT Starlight T2 APD DRP | DO32: =-L20 -> 0 | DP32: Ceded LAE DCC Paid | DQ32: 100 | DR32: 601300 | DS32: 00 | DT32: 2002 | DU32: 000212 | DV32: 00 | DW32: 0000 | DY32: FUT Starlight T2 APD DRP | DZ32: =-M20 -> 0 | EA32: Ceded LAE DCC Paid | EB32: 100 | EC32: 601300 | ED32: 00 | EE32: 2002 | EF32: 000212 | EG32: 00 | EH32: 0000 | EJ32: FUT Starlight T2 APD DRP | EK32: =-N20 -> 0 | EL32: Ceded LAE DCC Paid | EM32: 100 | EN32: 601300 | EO32: 00 | EP32: 2002 | EQ32: 000212 | ER32: 00 | ES32: 0000 | EU32: FUT Starlight T2 APD DRP | EV32: =-O20 -> 0
B33: Loss Ratio Cap on UEP | C33: =+C7*0.02 -> 0 | D33: =+D7*0.02 -> 0 | P33: =SUM(D33:O33) -> 0 | Q33: =+C33+P33 -> 0 | U33: Change in LAE DCC Reserves - Direct | V33: 100 | W33: 557100 | X33: 00 | Y33: 2002 | Z33: 000212 | AA33: {=RIGHT(CELL("filename",A1),LEN(CELL("filename",A1))-FIND("]",CELL("filename",A1)))} -> #VALUE! | AB33: 0000 | AD33: FUT Starlight T2 APD DRP | AE33: =+D21 -> 0 | AF33: Change in LAE DCC Reserves - Direct | AG33: 100 | AH33: 557100 | AI33: 00 | AJ33: 2002 | AK33: 000212 | AL33: {=RIGHT(CELL("filename",A1),LEN(CELL("filename",A1))-FIND("]",CELL("filename",A1)))} -> #VALUE! | AM33: 0000 | AO33: FUT Starlight T2 APD DRP | AP33: =+E21 -> 0 | AQ33: Change in LAE DCC Reserves - Direct | AR33: 100 | AS33: 557100 | AT33: 00 | AU33: 2002 | AV33: 000212 | AW33: {=RIGHT(CELL("filename",A1),LEN(CELL("filename",A1))-FIND("]",CELL("filename",A1)))} -> #VALUE! | AX33: 0000 | AZ33: FUT Starlight T2 APD DRP | BA33: =+F21 -> 0 | BB33: Change in LAE DCC Reserves - Direct | BC33: 100 | BD33: 557100 | BE33: 00 | BF33: 2002 | BG33: 000212 | BH33: {=RIGHT(CELL("filename",A1),LEN(CELL("filename",A1))-FIND("]",CELL("filename",A1)))} -> #VALUE! | BI33: 0000 | BK33: FUT Starlight T2 APD DRP | BL33: =+G21 -> 0 | BM33: Change in LAE DCC Reserves - Direct | BN33: 100 | BO33: 557100 | BP33: 00 | BQ33: 2002 | BR33: 000212 | BS33: {=RIGHT(CELL("filename",A1),LEN(CELL("filename",A1))-FIND("]",CELL("filename",A1)))} -> #VALUE! | BT33: 0000 | BV33: FUT Starlight T2 APD DRP | BW33: =+H21 -> 0 | BX33: Change in LAE DCC Reserves - Direct | BY33: 100 | BZ33: 557100 | CA33: 00 | CB33: 2002 | CC33: 000212 | CD33: {=RIGHT(CELL("filename",A1),LEN(CELL("filename",A1))-FIND("]",CELL("filename",A1)))} -> #VALUE! | CE33: 0000 | CG33: FUT Starlight T2 APD DRP | CH33: =+I21 -> 0 | CI33: Change in LAE DCC Reserves - Direct | CJ33: 100 | CK33: 557100 | CL33: 00 | CM33: 2002 | CN33: 000212 | CO33: {=RIGHT(CELL("filename",A1),LEN(CELL("filename",A1))-FIND("]",CELL("filename",A1)))} -> #VALUE! | CP33: 0000 | CR33: FUT Starlight T2 APD DRP | CS33: =+J21 -> 0 | CT33: Change in LAE DCC Reserves - Direct | CU33: 100 | CV33: 557100 | CW33: 00 | CX33: 2002 | CY33: 000212 | CZ33: {=RIGHT(CELL("filename",A1),LEN(CELL("filename",A1))-FIND("]",CELL("filename",A1)))} -> #VALUE! | DA33: 0000 | DC33: FUT Starlight T2 APD DRP | DD33: =+K21 -> 0 | DE33: Change in LAE DCC Reserves - Direct | DF33: 100 | DG33: 557100 | DH33: 00 | DI33: 2002 | DJ33: 000212 | DK33: {=RIGHT(CELL("filename",A1),LEN(CELL("filename",A1))-FIND("]",CELL("filename",A1)))} -> #VALUE! | DL33: 0000 | DN33: FUT Starlight T2 APD DRP | DO33: =+L21 -> 0 | DP33: Change in LAE DCC Reserves - Direct | DQ33: 100 | DR33: 557100 | DS33: 00 | DT33: 2002 | DU33: 000212 | DV33: {=RIGHT(CELL("filename",A1),LEN(CELL("filename",A1))-FIND("]",CELL("filename",A1)))} -> #VALUE! | DW33: 0000 | DY33: FUT Starlight T2 APD DRP | DZ33: =+M21 -> 0 | EA33: Change in LAE DCC Reserves - Direct | EB33: 100 | EC33: 557100 | ED33: 00 | EE33: 2002 | EF33: 000212 | EG33: {=RIGHT(CELL("filename",A1),LEN(CELL("filename",A1))-FIND("]",CELL("filename",A1)))} -> #VALUE! | EH33: 0000 | EJ33: FUT Starlight T2 APD DRP | EK33: =+N21 -> 0 | EL33: Change in LAE DCC Reserves - Direct | EM33: 100 | EN33: 557100 | EO33: 00 | EP33: 2002 | EQ33: 000212 | ER33: {=RIGHT(CELL("filename",A1),LEN(CELL("filename",A1))-FIND("]",CELL("filename",A1)))} -> #VALUE! | ES33: 0000 | EU33: FUT Starlight T2 APD DRP | EV33: =+O21 -> 0
B34: Other Expenses Incurred | C34: =SUM(C30:C33) -> 0 | D34: =SUM(D30:D33) -> 0 | P34: =SUM(P30:P33) -> 0 | Q34: =SUM(Q30:Q33) -> 0 | U34: LAE DCC Reserves - Direct | V34: 100 | W34: 207100 | X34: 00 | Y34: 2002 | Z34: 000212 | AA34: {=RIGHT(CELL("filename",A1),LEN(CELL("filename",A1))-FIND("]",CELL("filename",A1)))} -> #VALUE! | AB34: 0000 | AD34: FUT Starlight T2 APD DRP | AE34: =-D21 -> 0 | AF34: LAE DCC Reserves - Direct | AG34: 100 | AH34: 207100 | AI34: 00 | AJ34: 2002 | AK34: 000212 | AL34: {=RIGHT(CELL("filename",A1),LEN(CELL("filename",A1))-FIND("]",CELL("filename",A1)))} -> #VALUE! | AM34: 0000 | AO34: FUT Starlight T2 APD DRP | AP34: =-E21 -> 0 | AQ34: LAE DCC Reserves - Direct | AR34: 100 | AS34: 207100 | AT34: 00 | AU34: 2002 | AV34: 000212 | AW34: {=RIGHT(CELL("filename",A1),LEN(CELL("filename",A1))-FIND("]",CELL("filename",A1)))} -> #VALUE! | AX34: 0000 | AZ34: FUT Starlight T2 APD DRP | BA34: =-F21 -> 0 | BB34: LAE DCC Reserves - Direct | BC34: 100 | BD34: 207100 | BE34: 00 | BF34: 2002 | BG34: 000212 | BH34: {=RIGHT(CELL("filename",A1),LEN(CELL("filename",A1))-FIND("]",CELL("filename",A1)))} -> #VALUE! | BI34: 0000 | BK34: FUT Starlight T2 APD DRP | BL34: =-G21 -> 0 | BM34: LAE DCC Reserves - Direct | BN34: 100 | BO34: 207100 | BP34: 00 | BQ34: 2002 | BR34: 000212 | BS34: {=RIGHT(CELL("filename",A1),LEN(CELL("filename",A1))-FIND("]",CELL("filename",A1)))} -> #VALUE! | BT34: 0000 | BV34: FUT Starlight T2 APD DRP | BW34: =-H21 -> 0 | BX34: LAE DCC Reserves - Direct | BY34: 100 | BZ34: 207100 | CA34: 00 | CB34: 2002 | CC34: 000212 | CD34: {=RIGHT(CELL("filename",A1),LEN(CELL("filename",A1))-FIND("]",CELL("filename",A1)))} -> #VALUE! | CE34: 0000 | CG34: FUT Starlight T2 APD DRP | CH34: =-I21 -> 0 | CI34: LAE DCC Reserves - Direct | CJ34: 100 | CK34: 207100 | CL34: 00 | CM34: 2002 | CN34: 000212 | CO34: {=RIGHT(CELL("filename",A1),LEN(CELL("filename",A1))-FIND("]",CELL("filename",A1)))} -> #VALUE! | CP34: 0000 | CR34: FUT Starlight T2 APD DRP | CS34: =-J21 -> 0 | CT34: LAE DCC Reserves - Direct | CU34: 100 | CV34: 207100 | CW34: 00 | CX34: 2002 | CY34: 000212 | CZ34: {=RIGHT(CELL("filename",A1),LEN(CELL("filename",A1))-FIND("]",CELL("filename",A1)))} -> #VALUE! | DA34: 0000 | DC34: FUT Starlight T2 APD DRP | DD34: =-K21 -> 0 | DE34: LAE DCC Reserves - Direct | DF34: 100 | DG34: 207100 | DH34: 00 | DI34: 2002 | DJ34: 000212 | DK34: {=RIGHT(CELL("filename",A1),LEN(CELL("filename",A1))-FIND("]",CELL("filename",A1)))} -> #VALUE! | DL34: 0000 | DN34: FUT Starlight T2 APD DRP | DO34: =-L21 -> 0 | DP34: LAE DCC Reserves - Direct | DQ34: 100 | DR34: 207100 | DS34: 00 | DT34: 2002 | DU34: 000212 | DV34: {=RIGHT(CELL("filename",A1),LEN(CELL("filename",A1))-FIND("]",CELL("filename",A1)))} -> #VALUE! | DW34: 0000 | DY34: FUT Starlight T2 APD DRP | DZ34: =-M21 -> 0 | EA34: LAE DCC Reserves - Direct | EB34: 100 | EC34: 207100 | ED34: 00 | EE34: 2002 | EF34: 000212 | EG34: {=RIGHT(CELL("filename",A1),LEN(CELL("filename",A1))-FIND("]",CELL("filename",A1)))} -> #VALUE! | EH34: 0000 | EJ34: FUT Starlight T2 APD DRP | EK34: =-N21 -> 0 | EL34: LAE DCC Reserves - Direct | EM34: 100 | EN34: 207100 | EO34: 00 | EP34: 2002 | EQ34: 000212 | ER34: {=RIGHT(CELL("filename",A1),LEN(CELL("filename",A1))-FIND("]",CELL("filename",A1)))} -> #VALUE! | ES34: 0000 | EU34: FUT Starlight T2 APD DRP | EV34: =-O21 -> 0
U35: LAE DCC Reserves - Ceded | V35: 100 | W35: 207300 | X35: 00 | Y35: 2002 | Z35: 000212 | AA35: 00 | AB35: 0000 | AD35: FUT Starlight T2 APD DRP | AE35: =+D21 -> 0 | AF35: LAE DCC Reserves - Ceded | AG35: 100 | AH35: 207300 | AI35: 00 | AJ35: 2002 | AK35: 000212 | AL35: 00 | AM35: 0000 | AO35: FUT Starlight T2 APD DRP | AP35: =+E21 -> 0 | AQ35: LAE DCC Reserves - Ceded | AR35: 100 | AS35: 207300 | AT35: 00 | AU35: 2002 | AV35: 000212 | AW35: 00 | AX35: 0000 | AZ35: FUT Starlight T2 APD DRP | BA35: =+F21 -> 0 | BB35: LAE DCC Reserves - Ceded | BC35: 100 | BD35: 207300 | BE35: 00 | BF35: 2002 | BG35: 000212 | BH35: 00 | BI35: 0000 | BK35: FUT Starlight T2 APD DRP | BL35: =+G21 -> 0 | BM35: LAE DCC Reserves - Ceded | BN35: 100 | BO35: 207300 | BP35: 00 | BQ35: 2002 | BR35: 000212 | BS35: 00 | BT35: 0000 | BV35: FUT Starlight T2 APD DRP | BW35: =+H21 -> 0 | BX35: LAE DCC Reserves - Ceded | BY35: 100 | BZ35: 207300 | CA35: 00 | CB35: 2002 | CC35: 000212 | CD35: 00 | CE35: 0000 | CG35: FUT Starlight T2 APD DRP | CH35: =+I21 -> 0 | CI35: LAE DCC Reserves - Ceded | CJ35: 100 | CK35: 207300 | CL35: 00 | CM35: 2002 | CN35: 000212 | CO35: 00 | CP35: 0000 | CR35: FUT Starlight T2 APD DRP | CS35: =+J21 -> 0 | CT35: LAE DCC Reserves - Ceded | CU35: 100 | CV35: 207300 | CW35: 00 | CX35: 2002 | CY35: 000212 | CZ35: 00 | DA35: 0000 | DC35: FUT Starlight T2 APD DRP | DD35: =+K21 -> 0 | DE35: LAE DCC Reserves - Ceded | DF35: 100 | DG35: 207300 | DH35: 00 | DI35: 2002 | DJ35: 000212 | DK35: 00 | DL35: 0000 | DN35: FUT Starlight T2 APD DRP | DO35: =+L21 -> 0 | DP35: LAE DCC Reserves - Ceded | DQ35: 100 | DR35: 207300 | DS35: 00 | DT35: 2002 | DU35: 000212 | DV35: 00 | DW35: 0000 | DY35: FUT Starlight T2 APD DRP | DZ35: =+M21 -> 0 | EA35: LAE DCC Reserves - Ceded | EB35: 100 | EC35: 207300 | ED35: 00 | EE35: 2002 | EF35: 000212 | EG35: 00 | EH35: 0000 | EJ35: FUT Starlight T2 APD DRP | EK35: =+N21 -> 0 | EL35: LAE DCC Reserves - Ceded | EM35: 100 | EN35: 207300 | EO35: 00 | EP35: 2002 | EQ35: 000212 | ER35: 00 | ES35: 0000 | EU35: FUT Starlight T2 APD DRP | EV35: =+O21 -> 0
U36: Change in LAE DCC Reserves - Ceded | V36: 100 | W36: 557300 | X36: 00 | Y36: 2002 | Z36: 000212 | AA36: 00 | AB36: 0000 | AD36: FUT Starlight T2 APD DRP | AE36: =-D21 -> 0 | AF36: Change in LAE DCC Reserves - Ceded | AG36: 100 | AH36: 557300 | AI36: 00 | AJ36: 2002 | AK36: 000212 | AL36: 00 | AM36: 0000 | AO36: FUT Starlight T2 APD DRP | AP36: =-E21 -> 0 | AQ36: Change in LAE DCC Reserves - Ceded | AR36: 100 | AS36: 557300 | AT36: 00 | AU36: 2002 | AV36: 000212 | AW36: 00 | AX36: 0000 | AZ36: FUT Starlight T2 APD DRP | BA36: =-F21 -> 0 | BB36: Change in LAE DCC Reserves - Ceded | BC36: 100 | BD36: 557300 | BE36: 00 | BF36: 2002 | BG36: 000212 | BH36: 00 | BI36: 0000 | BK36: FUT Starlight T2 APD DRP | BL36: =-G21 -> 0 | BM36: Change in LAE DCC Reserves - Ceded | BN36: 100 | BO36: 557300 | BP36: 00 | BQ36: 2002 | BR36: 000212 | BS36: 00 | BT36: 0000 | BV36: FUT Starlight T2 APD DRP | BW36: =-H21 -> 0 | BX36: Change in LAE DCC Reserves - Ceded | BY36: 100 | BZ36: 557300 | CA36: 00 | CB36: 2002 | CC36: 000212 | CD36: 00 | CE36: 0000 | CG36: FUT Starlight T2 APD DRP | CH36: =-I21 -> 0 | CI36: Change in LAE DCC Reserves - Ceded | CJ36: 100 | CK36: 557300 | CL36: 00 | CM36: 2002 | CN36: 000212 | CO36: 00 | CP36: 0000 | CR36: FUT Starlight T2 APD DRP | CS36: =-J21 -> 0 | CT36: Change in LAE DCC Reserves - Ceded | CU36: 100 | CV36: 557300 | CW36: 00 | CX36: 2002 | CY36: 000212 | CZ36: 00 | DA36: 0000 | DC36: FUT Starlight T2 APD DRP | DD36: =-K21 -> 0 | DE36: Change in LAE DCC Reserves - Ceded | DF36: 100 | DG36: 557300 | DH36: 00 | DI36: 2002 | DJ36: 000212 | DK36: 00 | DL36: 0000 | DN36: FUT Starlight T2 APD DRP | DO36: =-L21 -> 0 | DP36: Change in LAE DCC Reserves - Ceded | DQ36: 100 | DR36: 557300 | DS36: 00 | DT36: 2002 | DU36: 000212 | DV36: 00 | DW36: 0000 | DY36: FUT Starlight T2 APD DRP | DZ36: =-M21 -> 0 | EA36: Change in LAE DCC Reserves - Ceded | EB36: 100 | EC36: 557300 | ED36: 00 | EE36: 2002 | EF36: 000212 | EG36: 00 | EH36: 0000 | EJ36: FUT Starlight T2 APD DRP | EK36: =-N21 -> 0 | EL36: Change in LAE DCC Reserves - Ceded | EM36: 100 | EN36: 557300 | EO36: 00 | EP36: 2002 | EQ36: 000212 | ER36: 00 | ES36: 0000 | EU36: FUT Starlight T2 APD DRP | EV36: =-O21 -> 0
B37: Total Profit (Loss) | C37: =+C8-C13-C18-C28-C34 -> 0 | D37: =+D8-D13-D18-D28-D34 -> 0 | P37: =+P8-P13-P18-P28-P34 -> 0 | Q37: =+Q8-Q13-Q18-Q28-Q34 -> 0 | U37: Change in IBNR DCC Reserves - Direct | V37: 100 | W37: 557400 | X37: 00 | Y37: 2002 | Z37: 000212 | AA37: {=RIGHT(CELL("filename",A1),LEN(CELL("filename",A1))-FIND("]",CELL("filename",A1)))} -> #VALUE! | AB37: 0000 | AD37: FUT Starlight T2 APD DRP | AE37: =+D22 -> 0 | AF37: Change in IBNR DCC Reserves - Direct | AG37: 100 | AH37: 557400 | AI37: 00 | AJ37: 2002 | AK37: 000212 | AL37: {=RIGHT(CELL("filename",A1),LEN(CELL("filename",A1))-FIND("]",CELL("filename",A1)))} -> #VALUE! | AM37: 0000 | AO37: FUT Starlight T2 APD DRP | AP37: =+E22 -> 0 | AQ37: Change in IBNR DCC Reserves - Direct | AR37: 100 | AS37: 557400 | AT37: 00 | AU37: 2002 | AV37: 000212 | AW37: {=RIGHT(CELL("filename",A1),LEN(CELL("filename",A1))-FIND("]",CELL("filename",A1)))} -> #VALUE! | AX37: 0000 | AZ37: FUT Starlight T2 APD DRP | BA37: =+F22 -> 0 | BB37: Change in IBNR DCC Reserves - Direct | BC37: 100 | BD37: 557400 | BE37: 00 | BF37: 2002 | BG37: 000212 | BH37: {=RIGHT(CELL("filename",A1),LEN(CELL("filename",A1))-FIND("]",CELL("filename",A1)))} -> #VALUE! | BI37: 0000 | BK37: FUT Starlight T2 APD DRP | BL37: =+G22 -> 0 | BM37: Change in IBNR DCC Reserves - Direct | BN37: 100 | BO37: 557400 | BP37: 00 | BQ37: 2002 | BR37: 000212 | BS37: {=RIGHT(CELL("filename",A1),LEN(CELL("filename",A1))-FIND("]",CELL("filename",A1)))} -> #VALUE! | BT37: 0000 | BV37: FUT Starlight T2 APD DRP | BW37: =+H22 -> 0 | BX37: Change in IBNR DCC Reserves - Direct | BY37: 100 | BZ37: 557400 | CA37: 00 | CB37: 2002 | CC37: 000212 | CD37: {=RIGHT(CELL("filename",A1),LEN(CELL("filename",A1))-FIND("]",CELL("filename",A1)))} -> #VALUE! | CE37: 0000 | CG37: FUT Starlight T2 APD DRP | CH37: =+I22 -> 0 | CI37: Change in IBNR DCC Reserves - Direct | CJ37: 100 | CK37: 557400 | CL37: 00 | CM37: 2002 | CN37: 000212 | CO37: {=RIGHT(CELL("filename",A1),LEN(CELL("filename",A1))-FIND("]",CELL("filename",A1)))} -> #VALUE! | CP37: 0000 | CR37: FUT Starlight T2 APD DRP | CS37: =+J22 -> 0 | CT37: Change in IBNR DCC Reserves - Direct | CU37: 100 | CV37: 557400 | CW37: 00 | CX37: 2002 | CY37: 000212 | CZ37: {=RIGHT(CELL("filename",A1),LEN(CELL("filename",A1))-FIND("]",CELL("filename",A1)))} -> #VALUE! | DA37: 0000 | DC37: FUT Starlight T2 APD DRP | DD37: =+K22 -> 0 | DE37: Change in IBNR DCC Reserves - Direct | DF37: 100 | DG37: 557400 | DH37: 00 | DI37: 2002 | DJ37: 000212 | DK37: {=RIGHT(CELL("filename",A1),LEN(CELL("filename",A1))-FIND("]",CELL("filename",A1)))} -> #VALUE! | DL37: 0000 | DN37: FUT Starlight T2 APD DRP | DO37: =+L22 -> 0 | DP37: Change in IBNR DCC Reserves - Direct | DQ37: 100 | DR37: 557400 | DS37: 00 | DT37: 2002 | DU37: 000212 | DV37: {=RIGHT(CELL("filename",A1),LEN(CELL("filename",A1))-FIND("]",CELL("filename",A1)))} -> #VALUE! | DW37: 0000 | DY37: FUT Starlight T2 APD DRP | DZ37: =+M22 -> 0 | EA37: Change in IBNR DCC Reserves - Direct | EB37: 100 | EC37: 557400 | ED37: 00 | EE37: 2002 | EF37: 000212 | EG37: {=RIGHT(CELL("filename",A1),LEN(CELL("filename",A1))-FIND("]",CELL("filename",A1)))} -> #VALUE! | EH37: 0000 | EJ37: FUT Starlight T2 APD DRP | EK37: =+N22 -> 0 | EL37: Change in IBNR DCC Reserves - Direct | EM37: 100 | EN37: 557400 | EO37: 00 | EP37: 2002 | EQ37: 000212 | ER37: {=RIGHT(CELL("filename",A1),LEN(CELL("filename",A1))-FIND("]",CELL("filename",A1)))} -> #VALUE! | ES37: 0000 | EU37: FUT Starlight T2 APD DRP | EV37: =+O22 -> 0
U38: IBNR DCC Reserves - Direct | V38: 100 | W38: 207400 | X38: 00 | Y38: 2002 | Z38: 000212 | AA38: {=RIGHT(CELL("filename",A1),LEN(CELL("filename",A1))-FIND("]",CELL("filename",A1)))} -> #VALUE! | AB38: 0000 | AD38: FUT Starlight T2 APD DRP | AE38: =-D22 -> 0 | AF38: IBNR DCC Reserves - Direct | AG38: 100 | AH38: 207400 | AI38: 00 | AJ38: 2002 | AK38: 000212 | AL38: {=RIGHT(CELL("filename",A1),LEN(CELL("filename",A1))-FIND("]",CELL("filename",A1)))} -> #VALUE! | AM38: 0000 | AO38: FUT Starlight T2 APD DRP | AP38: =-E22 -> 0 | AQ38: IBNR DCC Reserves - Direct | AR38: 100 | AS38: 207400 | AT38: 00 | AU38: 2002 | AV38: 000212 | AW38: {=RIGHT(CELL("filename",A1),LEN(CELL("filename",A1))-FIND("]",CELL("filename",A1)))} -> #VALUE! | AX38: 0000 | AZ38: FUT Starlight T2 APD DRP | BA38: =-F22 -> 0 | BB38: IBNR DCC Reserves - Direct | BC38: 100 | BD38: 207400 | BE38: 00 | BF38: 2002 | BG38: 000212 | BH38: {=RIGHT(CELL("filename",A1),LEN(CELL("filename",A1))-FIND("]",CELL("filename",A1)))} -> #VALUE! | BI38: 0000 | BK38: FUT Starlight T2 APD DRP | BL38: =-G22 -> 0 | BM38: IBNR DCC Reserves - Direct | BN38: 100 | BO38: 207400 | BP38: 00 | BQ38: 2002 | BR38: 000212 | BS38: {=RIGHT(CELL("filename",A1),LEN(CELL("filename",A1))-FIND("]",CELL("filename",A1)))} -> #VALUE! | BT38: 0000 | BV38: FUT Starlight T2 APD DRP | BW38: =-H22 -> 0 | BX38: IBNR DCC Reserves - Direct | BY38: 100 | BZ38: 207400 | CA38: 00 | CB38: 2002 | CC38: 000212 | CD38: {=RIGHT(CELL("filename",A1),LEN(CELL("filename",A1))-FIND("]",CELL("filename",A1)))} -> #VALUE! | CE38: 0000 | CG38: FUT Starlight T2 APD DRP | CH38: =-I22 -> 0 | CI38: IBNR DCC Reserves - Direct | CJ38: 100 | CK38: 207400 | CL38: 00 | CM38: 2002 | CN38: 000212 | CO38: {=RIGHT(CELL("filename",A1),LEN(CELL("filename",A1))-FIND("]",CELL("filename",A1)))} -> #VALUE! | CP38: 0000 | CR38: FUT Starlight T2 APD DRP | CS38: =-J22 -> 0 | CT38: IBNR DCC Reserves - Direct | CU38: 100 | CV38: 207400 | CW38: 00 | CX38: 2002 | CY38: 000212 | CZ38: {=RIGHT(CELL("filename",A1),LEN(CELL("filename",A1))-FIND("]",CELL("filename",A1)))} -> #VALUE! | DA38: 0000 | DC38: FUT Starlight T2 APD DRP | DD38: =-K22 -> 0 | DE38: IBNR DCC Reserves - Direct | DF38: 100 | DG38: 207400 | DH38: 00 | DI38: 2002 | DJ38: 000212 | DK38: {=RIGHT(CELL("filename",A1),LEN(CELL("filename",A1))-FIND("]",CELL("filename",A1)))} -> #VALUE! | DL38: 0000 | DN38: FUT Starlight T2 APD DRP | DO38: =-L22 -> 0 | DP38: IBNR DCC Reserves - Direct | DQ38: 100 | DR38: 207400 | DS38: 00 | DT38: 2002 | DU38: 000212 | DV38: {=RIGHT(CELL("filename",A1),LEN(CELL("filename",A1))-FIND("]",CELL("filename",A1)))} -> #VALUE! | DW38: 0000 | DY38: FUT Starlight T2 APD DRP | DZ38: =-M22 -> 0 | EA38: IBNR DCC Reserves - Direct | EB38: 100 | EC38: 207400 | ED38: 00 | EE38: 2002 | EF38: 000212 | EG38: {=RIGHT(CELL("filename",A1),LEN(CELL("filename",A1))-FIND("]",CELL("filename",A1)))} -> #VALUE! | EH38: 0000 | EJ38: FUT Starlight T2 APD DRP | EK38: =-N22 -> 0 | EL38: IBNR DCC Reserves - Direct | EM38: 100 | EN38: 207400 | EO38: 00 | EP38: 2002 | EQ38: 000212 | ER38: {=RIGHT(CELL("filename",A1),LEN(CELL("filename",A1))-FIND("]",CELL("filename",A1)))} -> #VALUE! | ES38: 0000 | EU38: FUT Starlight T2 APD DRP | EV38: =-O22 -> 0
A39: i. | B39: Reinsurance Brokerage Fee | C39: 0 | D39: 0 | P39: =SUM(D39:O39) -> 0 | Q39: =+C39+P39 -> 0 | U39: IBNR DCC Reserves - Ceded | V39: 100 | W39: 207600 | X39: 00 | Y39: 2002 | Z39: 000212 | AA39: 00 | AB39: 0000 | AD39: FUT Starlight T2 APD DRP | AE39: =+D22 -> 0 | AF39: IBNR DCC Reserves - Ceded | AG39: 100 | AH39: 207600 | AI39: 00 | AJ39: 2002 | AK39: 000212 | AL39: 00 | AM39: 0000 | AO39: FUT Starlight T2 APD DRP | AP39: =+E22 -> 0 | AQ39: IBNR DCC Reserves - Ceded | AR39: 100 | AS39: 207600 | AT39: 00 | AU39: 2002 | AV39: 000212 | AW39: 00 | AX39: 0000 | AZ39: FUT Starlight T2 APD DRP | BA39: =+F22 -> 0 | BB39: IBNR DCC Reserves - Ceded | BC39: 100 | BD39: 207600 | BE39: 00 | BF39: 2002 | BG39: 000212 | BH39: 00 | BI39: 0000 | BK39: FUT Starlight T2 APD DRP | BL39: =+G22 -> 0 | BM39: IBNR DCC Reserves - Ceded | BN39: 100 | BO39: 207600 | BP39: 00 | BQ39: 2002 | BR39: 000212 | BS39: 00 | BT39: 0000 | BV39: FUT Starlight T2 APD DRP | BW39: =+H22 -> 0 | BX39: IBNR DCC Reserves - Ceded | BY39: 100 | BZ39: 207600 | CA39: 00 | CB39: 2002 | CC39: 000212 | CD39: 00 | CE39: 0000 | CG39: FUT Starlight T2 APD DRP | CH39: =+I22 -> 0 | CI39: IBNR DCC Reserves - Ceded | CJ39: 100 | CK39: 207600 | CL39: 00 | CM39: 2002 | CN39: 000212 | CO39: 00 | CP39: 0000 | CR39: FUT Starlight T2 APD DRP | CS39: =+J22 -> 0 | CT39: IBNR DCC Reserves - Ceded | CU39: 100 | CV39: 207600 | CW39: 00 | CX39: 2002 | CY39: 000212 | CZ39: 00 | DA39: 0000 | DC39: FUT Starlight T2 APD DRP | DD39: =+K22 -> 0 | DE39: IBNR DCC Reserves - Ceded | DF39: 100 | DG39: 207600 | DH39: 00 | DI39: 2002 | DJ39: 000212 | DK39: 00 | DL39: 0000 | DN39: FUT Starlight T2 APD DRP | DO39: =+L22 -> 0 | DP39: IBNR DCC Reserves - Ceded | DQ39: 100 | DR39: 207600 | DS39: 00 | DT39: 2002 | DU39: 000212 | DV39: 00 | DW39: 0000 | DY39: FUT Starlight T2 APD DRP | DZ39: =+M22 -> 0 | EA39: IBNR DCC Reserves - Ceded | EB39: 100 | EC39: 207600 | ED39: 00 | EE39: 2002 | EF39: 000212 | EG39: 00 | EH39: 0000 | EJ39: FUT Starlight T2 APD DRP | EK39: =+N22 -> 0 | EL39: IBNR DCC Reserves - Ceded | EM39: 100 | EN39: 207600 | EO39: 00 | EP39: 2002 | EQ39: 000212 | ER39: 00 | ES39: 0000 | EU39: FUT Starlight T2 APD DRP | EV39: =+O22 -> 0
U40: Change in IBNR DCC Reserves - Ceded | V40: 100 | W40: 557600 | X40: 00 | Y40: 2002 | Z40: 000212 | AA40: 00 | AB40: 0000 | AD40: FUT Starlight T2 APD DRP | AE40: =-D22 -> 0 | AF40: Change in IBNR DCC Reserves - Ceded | AG40: 100 | AH40: 557600 | AI40: 00 | AJ40: 2002 | AK40: 000212 | AL40: 00 | AM40: 0000 | AO40: FUT Starlight T2 APD DRP | AP40: =-E22 -> 0 | AQ40: Change in IBNR DCC Reserves - Ceded | AR40: 100 | AS40: 557600 | AT40: 00 | AU40: 2002 | AV40: 000212 | AW40: 00 | AX40: 0000 | AZ40: FUT Starlight T2 APD DRP | BA40: =-F22 -> 0 | BB40: Change in IBNR DCC Reserves - Ceded | BC40: 100 | BD40: 557600 | BE40: 00 | BF40: 2002 | BG40: 000212 | BH40: 00 | BI40: 0000 | BK40: FUT Starlight T2 APD DRP | BL40: =-G22 -> 0 | BM40: Change in IBNR DCC Reserves - Ceded | BN40: 100 | BO40: 557600 | BP40: 00 | BQ40: 2002 | BR40: 000212 | BS40: 00 | BT40: 0000 | BV40: FUT Starlight T2 APD DRP | BW40: =-H22 -> 0 | BX40: Change in IBNR DCC Reserves - Ceded | BY40: 100 | BZ40: 557600 | CA40: 00 | CB40: 2002 | CC40: 000212 | CD40: 00 | CE40: 0000 | CG40: FUT Starlight T2 APD DRP | CH40: =-I22 -> 0 | CI40: Change in IBNR DCC Reserves - Ceded | CJ40: 100 | CK40: 557600 | CL40: 00 | CM40: 2002 | CN40: 000212 | CO40: 00 | CP40: 0000 | CR40: FUT Starlight T2 APD DRP | CS40: =-J22 -> 0 | CT40: Change in IBNR DCC Reserves - Ceded | CU40: 100 | CV40: 557600 | CW40: 00 | CX40: 2002 | CY40: 000212 | CZ40: 00 | DA40: 0000 | DC40: FUT Starlight T2 APD DRP | DD40: =-K22 -> 0 | DE40: Change in IBNR DCC Reserves - Ceded | DF40: 100 | DG40: 557600 | DH40: 00 | DI40: 2002 | DJ40: 000212 | DK40: 00 | DL40: 0000 | DN40: FUT Starlight T2 APD DRP | DO40: =-L22 -> 0 | DP40: Change in IBNR DCC Reserves - Ceded | DQ40: 100 | DR40: 557600 | DS40: 00 | DT40: 2002 | DU40: 000212 | DV40: 00 | DW40: 0000 | DY40: FUT Starlight T2 APD DRP | DZ40: =-M22 -> 0 | EA40: Change in IBNR DCC Reserves - Ceded | EB40: 100 | EC40: 557600 | ED40: 00 | EE40: 2002 | EF40: 000212 | EG40: 00 | EH40: 0000 | EJ40: FUT Starlight T2 APD DRP | EK40: =-N22 -> 0 | EL40: Change in IBNR DCC Reserves - Ceded | EM40: 100 | EN40: 557600 | EO40: 00 | EP40: 2002 | EQ40: 000212 | ER40: 00 | ES40: 0000 | EU40: FUT Starlight T2 APD DRP | EV40: =-O22 -> 0
B41: Net Settlement due to/(from) Reinsurer | C41: =+C6-C11-C15-C20-C23-C26-C30-C32-C39 -> 0 | D41: =+D6-D11-D15-D20-D23-D26-D30-D32-D39 -> 0 | P41: =+P6-P11-P15-P20-P23-P26-P30-P32-P39 -> 0 | Q41: =+Q6-Q11-Q15-Q20-Q23-Q26-Q30-Q32-Q39 -> 0 | U41: Direct LAE A&O Paid | V41: 100 | W41: 602100 | X41: 00 | Y41: 2002 | Z41: 000212 | AA41: {=RIGHT(CELL("filename",A1),LEN(CELL("filename",A1))-FIND("]",CELL("filename",A1)))} -> #VALUE! | AB41: 0000 | AD41: FUT Starlight T2 APD DRP | AE41: =+D23 -> 0 | AF41: Direct LAE A&O Paid | AG41: 100 | AH41: 602100 | AI41: 00 | AJ41: 2002 | AK41: 000212 | AL41: {=RIGHT(CELL("filename",A1),LEN(CELL("filename",A1))-FIND("]",CELL("filename",A1)))} -> #VALUE! | AM41: 0000 | AO41: FUT Starlight T2 APD DRP | AP41: =+E23 -> 0 | AQ41: Direct LAE A&O Paid | AR41: 100 | AS41: 602100 | AT41: 00 | AU41: 2002 | AV41: 000212 | AW41: {=RIGHT(CELL("filename",A1),LEN(CELL("filename",A1))-FIND("]",CELL("filename",A1)))} -> #VALUE! | AX41: 0000 | AZ41: FUT Starlight T2 APD DRP | BA41: =+F23 -> 0 | BB41: Direct LAE A&O Paid | BC41: 100 | BD41: 602100 | BE41: 00 | BF41: 2002 | BG41: 000212 | BH41: {=RIGHT(CELL("filename",A1),LEN(CELL("filename",A1))-FIND("]",CELL("filename",A1)))} -> #VALUE! | BI41: 0000 | BK41: FUT Starlight T2 APD DRP | BL41: =+G23 -> 0 | BM41: Direct LAE A&O Paid | BN41: 100 | BO41: 602100 | BP41: 00 | BQ41: 2002 | BR41: 000212 | BS41: {=RIGHT(CELL("filename",A1),LEN(CELL("filename",A1))-FIND("]",CELL("filename",A1)))} -> #VALUE! | BT41: 0000 | BV41: FUT Starlight T2 APD DRP | BW41: =+H23 -> 0 | BX41: Direct LAE A&O Paid | BY41: 100 | BZ41: 602100 | CA41: 00 | CB41: 2002 | CC41: 000212 | CD41: {=RIGHT(CELL("filename",A1),LEN(CELL("filename",A1))-FIND("]",CELL("filename",A1)))} -> #VALUE! | CE41: 0000 | CG41: FUT Starlight T2 APD DRP | CH41: =+I23 -> 0 | CI41: Direct LAE A&O Paid | CJ41: 100 | CK41: 602100 | CL41: 00 | CM41: 2002 | CN41: 000212 | CO41: {=RIGHT(CELL("filename",A1),LEN(CELL("filename",A1))-FIND("]",CELL("filename",A1)))} -> #VALUE! | CP41: 0000 | CR41: FUT Starlight T2 APD DRP | CS41: =+J23 -> 0 | CT41: Direct LAE A&O Paid | CU41: 100 | CV41: 602100 | CW41: 00 | CX41: 2002 | CY41: 000212 | CZ41: {=RIGHT(CELL("filename",A1),LEN(CELL("filename",A1))-FIND("]",CELL("filename",A1)))} -> #VALUE! | DA41: 0000 | DC41: FUT Starlight T2 APD DRP | DD41: =+K23 -> 0 | DE41: Direct LAE A&O Paid | DF41: 100 | DG41: 602100 | DH41: 00 | DI41: 2002 | DJ41: 000212 | DK41: {=RIGHT(CELL("filename",A1),LEN(CELL("filename",A1))-FIND("]",CELL("filename",A1)))} -> #VALUE! | DL41: 0000 | DN41: FUT Starlight T2 APD DRP | DO41: =+L23 -> 0 | DP41: Direct LAE A&O Paid | DQ41: 100 | DR41: 602100 | DS41: 00 | DT41: 2002 | DU41: 000212 | DV41: {=RIGHT(CELL("filename",A1),LEN(CELL("filename",A1))-FIND("]",CELL("filename",A1)))} -> #VALUE! | DW41: 0000 | DY41: FUT Starlight T2 APD DRP | DZ41: =+M23 -> 0 | EA41: Direct LAE A&O Paid | EB41: 100 | EC41: 602100 | ED41: 00 | EE41: 2002 | EF41: 000212 | EG41: {=RIGHT(CELL("filename",A1),LEN(CELL("filename",A1))-FIND("]",CELL("filename",A1)))} -> #VALUE! | EH41: 0000 | EJ41: FUT Starlight T2 APD DRP | EK41: =+N23 -> 0 | EL41: Direct LAE A&O Paid | EM41: 100 | EN41: 602100 | EO41: 00 | EP41: 2002 | EQ41: 000212 | ER41: {=RIGHT(CELL("filename",A1),LEN(CELL("filename",A1))-FIND("]",CELL("filename",A1)))} -> #VALUE! | ES41: 0000 | EU41: FUT Starlight T2 APD DRP | EV41: =+O23 -> 0
U42: Payable to MGA | V42: 100 | W42: 264400 | X42: 00 | Y42: 2002 | Z42: 000212 | AA42: 00 | AB42: 0000 | AD42: FUT Starlight T2 APD DRP | AE42: =-D23 -> 0 | AF42: Payable to MGA | AG42: 100 | AH42: 264400 | AI42: 00 | AJ42: 2002 | AK42: 000212 | AL42: 00 | AM42: 0000 | AO42: FUT Starlight T2 APD DRP | AP42: =-E23 -> 0 | AQ42: Payable to MGA | AR42: 100 | AS42: 264400 | AT42: 00 | AU42: 2002 | AV42: 000212 | AW42: 00 | AX42: 0000 | AZ42: FUT Starlight T2 APD DRP | BA42: =-F23 -> 0 | BB42: Payable to MGA | BC42: 100 | BD42: 264400 | BE42: 00 | BF42: 2002 | BG42: 000212 | BH42: 00 | BI42: 0000 | BK42: FUT Starlight T2 APD DRP | BL42: =-G23 -> 0 | BM42: Payable to MGA | BN42: 100 | BO42: 264400 | BP42: 00 | BQ42: 2002 | BR42: 000212 | BS42: 00 | BT42: 0000 | BV42: FUT Starlight T2 APD DRP | BW42: =-H23 -> 0 | BX42: Payable to MGA | BY42: 100 | BZ42: 264400 | CA42: 00 | CB42: 2002 | CC42: 000212 | CD42: 00 | CE42: 0000 | CG42: FUT Starlight T2 APD DRP | CH42: =-I23 -> 0 | CI42: Payable to MGA | CJ42: 100 | CK42: 264400 | CL42: 00 | CM42: 2002 | CN42: 000212 | CO42: 00 | CP42: 0000 | CR42: FUT Starlight T2 APD DRP | CS42: =-J23 -> 0 | CT42: Payable to MGA | CU42: 100 | CV42: 264400 | CW42: 00 | CX42: 2002 | CY42: 000212 | CZ42: 00 | DA42: 0000 | DC42: FUT Starlight T2 APD DRP | DD42: =-K23 -> 0 | DE42: Payable to MGA | DF42: 100 | DG42: 264400 | DH42: 00 | DI42: 2002 | DJ42: 000212 | DK42: 00 | DL42: 0000 | DN42: FUT Starlight T2 APD DRP | DO42: =-L23 -> 0 | DP42: Payable to MGA | DQ42: 100 | DR42: 264400 | DS42: 00 | DT42: 2002 | DU42: 000212 | DV42: 00 | DW42: 0000 | DY42: FUT Starlight T2 APD DRP | DZ42: =-M23 -> 0 | EA42: Payable to MGA | EB42: 100 | EC42: 264400 | ED42: 00 | EE42: 2002 | EF42: 000212 | EG42: 00 | EH42: 0000 | EJ42: FUT Starlight T2 APD DRP | EK42: =-N23 -> 0 | EL42: Payable to MGA | EM42: 100 | EN42: 264400 | EO42: 00 | EP42: 2002 | EQ42: 000212 | ER42: 00 | ES42: 0000 | EU42: FUT Starlight T2 APD DRP | EV42: =-O23 -> 0
A43: j. | B43: Loss Funding | C43: 0 | D43: 0 | P43: =SUM(D43:O43) -> 0 | Q43: =+C43+P43 -> 0 | U43: Amounts recoverable from reinsurers | V43: 100 | W43: 125100 | X43: 00 | Y43: 2002 | Z43: 000212 | AA43: 00 | AB43: 0000 | AD43: FUT Starlight T2 APD DRP | AE43: =+D23 -> 0 | AF43: Amounts recoverable from reinsurers | AG43: 100 | AH43: 125100 | AI43: 00 | AJ43: 2002 | AK43: 000212 | AL43: 00 | AM43: 0000 | AO43: FUT Starlight T2 APD DRP | AP43: =+E23 -> 0 | AQ43: Amounts recoverable from reinsurers | AR43: 100 | AS43: 125100 | AT43: 00 | AU43: 2002 | AV43: 000212 | AW43: 00 | AX43: 0000 | AZ43: FUT Starlight T2 APD DRP | BA43: =+F23 -> 0 | BB43: Amounts recoverable from reinsurers | BC43: 100 | BD43: 125100 | BE43: 00 | BF43: 2002 | BG43: 000212 | BH43: 00 | BI43: 0000 | BK43: FUT Starlight T2 APD DRP | BL43: =+G23 -> 0 | BM43: Amounts recoverable from reinsurers | BN43: 100 | BO43: 125100 | BP43: 00 | BQ43: 2002 | BR43: 000212 | BS43: 00 | BT43: 0000 | BV43: FUT Starlight T2 APD DRP | BW43: =+H23 -> 0 | BX43: Amounts recoverable from reinsurers | BY43: 100 | BZ43: 125100 | CA43: 00 | CB43: 2002 | CC43: 000212 | CD43: 00 | CE43: 0000 | CG43: FUT Starlight T2 APD DRP | CH43: =+I23 -> 0 | CI43: Amounts recoverable from reinsurers | CJ43: 100 | CK43: 125100 | CL43: 00 | CM43: 2002 | CN43: 000212 | CO43: 00 | CP43: 0000 | CR43: FUT Starlight T2 APD DRP | CS43: =+J23 -> 0 | CT43: Amounts recoverable from reinsurers | CU43: 100 | CV43: 125100 | CW43: 00 | CX43: 2002 | CY43: 000212 | CZ43: 00 | DA43: 0000 | DC43: FUT Starlight T2 APD DRP | DD43: =+K23 -> 0 | DE43: Amounts recoverable from reinsurers | DF43: 100 | DG43: 125100 | DH43: 00 | DI43: 2002 | DJ43: 000212 | DK43: 00 | DL43: 0000 | DN43: FUT Starlight T2 APD DRP | DO43: =+L23 -> 0 | DP43: Amounts recoverable from reinsurers | DQ43: 100 | DR43: 125100 | DS43: 00 | DT43: 2002 | DU43: 000212 | DV43: 00 | DW43: 0000 | DY43: FUT Starlight T2 APD DRP | DZ43: =+M23 -> 0 | EA43: Amounts recoverable from reinsurers | EB43: 100 | EC43: 125100 | ED43: 00 | EE43: 2002 | EF43: 000212 | EG43: 00 | EH43: 0000 | EJ43: FUT Starlight T2 APD DRP | EK43: =+N23 -> 0 | EL43: Amounts recoverable from reinsurers | EM43: 100 | EN43: 125100 | EO43: 00 | EP43: 2002 | EQ43: 000212 | ER43: 00 | ES43: 0000 | EU43: FUT Starlight T2 APD DRP | EV43: =+O23 -> 0
U44: Ceded LAE A&O Paid | V44: 100 | W44: 602300 | X44: 00 | Y44: 2002 | Z44: 000212 | AA44: 00 | AB44: 0000 | AD44: FUT Starlight T2 APD DRP | AE44: =-D23 -> 0 | AF44: Ceded LAE A&O Paid | AG44: 100 | AH44: 602300 | AI44: 00 | AJ44: 2002 | AK44: 000212 | AL44: 00 | AM44: 0000 | AO44: FUT Starlight T2 APD DRP | AP44: =-E23 -> 0 | AQ44: Ceded LAE A&O Paid | AR44: 100 | AS44: 602300 | AT44: 00 | AU44: 2002 | AV44: 000212 | AW44: 00 | AX44: 0000 | AZ44: FUT Starlight T2 APD DRP | BA44: =-F23 -> 0 | BB44: Ceded LAE A&O Paid | BC44: 100 | BD44: 602300 | BE44: 00 | BF44: 2002 | BG44: 000212 | BH44: 00 | BI44: 0000 | BK44: FUT Starlight T2 APD DRP | BL44: =-G23 -> 0 | BM44: Ceded LAE A&O Paid | BN44: 100 | BO44: 602300 | BP44: 00 | BQ44: 2002 | BR44: 000212 | BS44: 00 | BT44: 0000 | BV44: FUT Starlight T2 APD DRP | BW44: =-H23 -> 0 | BX44: Ceded LAE A&O Paid | BY44: 100 | BZ44: 602300 | CA44: 00 | CB44: 2002 | CC44: 000212 | CD44: 00 | CE44: 0000 | CG44: FUT Starlight T2 APD DRP | CH44: =-I23 -> 0 | CI44: Ceded LAE A&O Paid | CJ44: 100 | CK44: 602300 | CL44: 00 | CM44: 2002 | CN44: 000212 | CO44: 00 | CP44: 0000 | CR44: FUT Starlight T2 APD DRP | CS44: =-J23 -> 0 | CT44: Ceded LAE A&O Paid | CU44: 100 | CV44: 602300 | CW44: 00 | CX44: 2002 | CY44: 000212 | CZ44: 00 | DA44: 0000 | DC44: FUT Starlight T2 APD DRP | DD44: =-K23 -> 0 | DE44: Ceded LAE A&O Paid | DF44: 100 | DG44: 602300 | DH44: 00 | DI44: 2002 | DJ44: 000212 | DK44: 00 | DL44: 0000 | DN44: FUT Starlight T2 APD DRP | DO44: =-L23 -> 0 | DP44: Ceded LAE A&O Paid | DQ44: 100 | DR44: 602300 | DS44: 00 | DT44: 2002 | DU44: 000212 | DV44: 00 | DW44: 0000 | DY44: FUT Starlight T2 APD DRP | DZ44: =-M23 -> 0 | EA44: Ceded LAE A&O Paid | EB44: 100 | EC44: 602300 | ED44: 00 | EE44: 2002 | EF44: 000212 | EG44: 00 | EH44: 0000 | EJ44: FUT Starlight T2 APD DRP | EK44: =-N23 -> 0 | EL44: Ceded LAE A&O Paid | EM44: 100 | EN44: 602300 | EO44: 00 | EP44: 2002 | EQ44: 000212 | ER44: 00 | ES44: 0000 | EU44: FUT Starlight T2 APD DRP | EV44: =-O23 -> 0
B45: Net Settlement due from NTA | C45: =+C6-C11-C15-C20-C23-C26-C43 -> 0 | D45: =+D6-D11-D15-D20-D23-D26-D43 -> 0 | P45: =+P6-P11-P15-P20-P23-P26-P43 -> 0 | Q45: =+Q6-Q11-Q15-Q20-Q23-Q26-Q43 -> 0 | U45: Change in LAE A&O Reserves - Direct | V45: 100 | W45: 558100 | X45: 00 | Y45: 2002 | Z45: 000212 | AA45: {=RIGHT(CELL("filename",A1),LEN(CELL("filename",A1))-FIND("]",CELL("filename",A1)))} -> #VALUE! | AB45: 0000 | AD45: FUT Starlight T2 APD DRP | AE45: =+D24 -> 0 | AF45: Change in LAE A&O Reserves - Direct | AG45: 100 | AH45: 558100 | AI45: 00 | AJ45: 2002 | AK45: 000212 | AL45: {=RIGHT(CELL("filename",A1),LEN(CELL("filename",A1))-FIND("]",CELL("filename",A1)))} -> #VALUE! | AM45: 0000 | AO45: FUT Starlight T2 APD DRP | AP45: =+E24 -> 0 | AQ45: Change in LAE A&O Reserves - Direct | AR45: 100 | AS45: 558100 | AT45: 00 | AU45: 2002 | AV45: 000212 | AW45: {=RIGHT(CELL("filename",A1),LEN(CELL("filename",A1))-FIND("]",CELL("filename",A1)))} -> #VALUE! | AX45: 0000 | AZ45: FUT Starlight T2 APD DRP | BA45: =+F24 -> 0 | BB45: Change in LAE A&O Reserves - Direct | BC45: 100 | BD45: 558100 | BE45: 00 | BF45: 2002 | BG45: 000212 | BH45: {=RIGHT(CELL("filename",A1),LEN(CELL("filename",A1))-FIND("]",CELL("filename",A1)))} -> #VALUE! | BI45: 0000 | BK45: FUT Starlight T2 APD DRP | BL45: =+G24 -> 0 | BM45: Change in LAE A&O Reserves - Direct | BN45: 100 | BO45: 558100 | BP45: 00 | BQ45: 2002 | BR45: 000212 | BS45: {=RIGHT(CELL("filename",A1),LEN(CELL("filename",A1))-FIND("]",CELL("filename",A1)))} -> #VALUE! | BT45: 0000 | BV45: FUT Starlight T2 APD DRP | BW45: =+H24 -> 0 | BX45: Change in LAE A&O Reserves - Direct | BY45: 100 | BZ45: 558100 | CA45: 00 | CB45: 2002 | CC45: 000212 | CD45: {=RIGHT(CELL("filename",A1),LEN(CELL("filename",A1))-FIND("]",CELL("filename",A1)))} -> #VALUE! | CE45: 0000 | CG45: FUT Starlight T2 APD DRP | CH45: =+I24 -> 0 | CI45: Change in LAE A&O Reserves - Direct | CJ45: 100 | CK45: 558100 | CL45: 00 | CM45: 2002 | CN45: 000212 | CO45: {=RIGHT(CELL("filename",A1),LEN(CELL("filename",A1))-FIND("]",CELL("filename",A1)))} -> #VALUE! | CP45: 0000 | CR45: FUT Starlight T2 APD DRP | CS45: =+J24 -> 0 | CT45: Change in LAE A&O Reserves - Direct | CU45: 100 | CV45: 558100 | CW45: 00 | CX45: 2002 | CY45: 000212 | CZ45: {=RIGHT(CELL("filename",A1),LEN(CELL("filename",A1))-FIND("]",CELL("filename",A1)))} -> #VALUE! | DA45: 0000 | DC45: FUT Starlight T2 APD DRP | DD45: =+K24 -> 0 | DE45: Change in LAE A&O Reserves - Direct | DF45: 100 | DG45: 558100 | DH45: 00 | DI45: 2002 | DJ45: 000212 | DK45: {=RIGHT(CELL("filename",A1),LEN(CELL("filename",A1))-FIND("]",CELL("filename",A1)))} -> #VALUE! | DL45: 0000 | DN45: FUT Starlight T2 APD DRP | DO45: =+L24 -> 0 | DP45: Change in LAE A&O Reserves - Direct | DQ45: 100 | DR45: 558100 | DS45: 00 | DT45: 2002 | DU45: 000212 | DV45: {=RIGHT(CELL("filename",A1),LEN(CELL("filename",A1))-FIND("]",CELL("filename",A1)))} -> #VALUE! | DW45: 0000 | DY45: FUT Starlight T2 APD DRP | DZ45: =+M24 -> 0 | EA45: Change in LAE A&O Reserves - Direct | EB45: 100 | EC45: 558100 | ED45: 00 | EE45: 2002 | EF45: 000212 | EG45: {=RIGHT(CELL("filename",A1),LEN(CELL("filename",A1))-FIND("]",CELL("filename",A1)))} -> #VALUE! | EH45: 0000 | EJ45: FUT Starlight T2 APD DRP | EK45: =+N24 -> 0 | EL45: Change in LAE A&O Reserves - Direct | EM45: 100 | EN45: 558100 | EO45: 00 | EP45: 2002 | EQ45: 000212 | ER45: {=RIGHT(CELL("filename",A1),LEN(CELL("filename",A1))-FIND("]",CELL("filename",A1)))} -> #VALUE! | ES45: 0000 | EU45: FUT Starlight T2 APD DRP | EV45: =+O24 -> 0
U46: LAE A&O Reserves - Direct | V46: 100 | W46: 208100 | X46: 00 | Y46: 2002 | Z46: 000212 | AA46: {=RIGHT(CELL("filename",A1),LEN(CELL("filename",A1))-FIND("]",CELL("filename",A1)))} -> #VALUE! | AB46: 0000 | AD46: FUT Starlight T2 APD DRP | AE46: =-D24 -> 0 | AF46: LAE A&O Reserves - Direct | AG46: 100 | AH46: 208100 | AI46: 00 | AJ46: 2002 | AK46: 000212 | AL46: {=RIGHT(CELL("filename",A1),LEN(CELL("filename",A1))-FIND("]",CELL("filename",A1)))} -> #VALUE! | AM46: 0000 | AO46: FUT Starlight T2 APD DRP | AP46: =-E24 -> 0 | AQ46: LAE A&O Reserves - Direct | AR46: 100 | AS46: 208100 | AT46: 00 | AU46: 2002 | AV46: 000212 | AW46: {=RIGHT(CELL("filename",A1),LEN(CELL("filename",A1))-FIND("]",CELL("filename",A1)))} -> #VALUE! | AX46: 0000 | AZ46: FUT Starlight T2 APD DRP | BA46: =-F24 -> 0 | BB46: LAE A&O Reserves - Direct | BC46: 100 | BD46: 208100 | BE46: 00 | BF46: 2002 | BG46: 000212 | BH46: {=RIGHT(CELL("filename",A1),LEN(CELL("filename",A1))-FIND("]",CELL("filename",A1)))} -> #VALUE! | BI46: 0000 | BK46: FUT Starlight T2 APD DRP | BL46: =-G24 -> 0 | BM46: LAE A&O Reserves - Direct | BN46: 100 | BO46: 208100 | BP46: 00 | BQ46: 2002 | BR46: 000212 | BS46: {=RIGHT(CELL("filename",A1),LEN(CELL("filename",A1))-FIND("]",CELL("filename",A1)))} -> #VALUE! | BT46: 0000 | BV46: FUT Starlight T2 APD DRP | BW46: =-H24 -> 0 | BX46: LAE A&O Reserves - Direct | BY46: 100 | BZ46: 208100 | CA46: 00 | CB46: 2002 | CC46: 000212 | CD46: {=RIGHT(CELL("filename",A1),LEN(CELL("filename",A1))-FIND("]",CELL("filename",A1)))} -> #VALUE! | CE46: 0000 | CG46: FUT Starlight T2 APD DRP | CH46: =-I24 -> 0 | CI46: LAE A&O Reserves - Direct | CJ46: 100 | CK46: 208100 | CL46: 00 | CM46: 2002 | CN46: 000212 | CO46: {=RIGHT(CELL("filename",A1),LEN(CELL("filename",A1))-FIND("]",CELL("filename",A1)))} -> #VALUE! | CP46: 0000 | CR46: FUT Starlight T2 APD DRP | CS46: =-J24 -> 0 | CT46: LAE A&O Reserves - Direct | CU46: 100 | CV46: 208100 | CW46: 00 | CX46: 2002 | CY46: 000212 | CZ46: {=RIGHT(CELL("filename",A1),LEN(CELL("filename",A1))-FIND("]",CELL("filename",A1)))} -> #VALUE! | DA46: 0000 | DC46: FUT Starlight T2 APD DRP | DD46: =-K24 -> 0 | DE46: LAE A&O Reserves - Direct | DF46: 100 | DG46: 208100 | DH46: 00 | DI46: 2002 | DJ46: 000212 | DK46: {=RIGHT(CELL("filename",A1),LEN(CELL("filename",A1))-FIND("]",CELL("filename",A1)))} -> #VALUE! | DL46: 0000 | DN46: FUT Starlight T2 APD DRP | DO46: =-L24 -> 0 | DP46: LAE A&O Reserves - Direct | DQ46: 100 | DR46: 208100 | DS46: 00 | DT46: 2002 | DU46: 000212 | DV46: {=RIGHT(CELL("filename",A1),LEN(CELL("filename",A1))-FIND("]",CELL("filename",A1)))} -> #VALUE! | DW46: 0000 | DY46: FUT Starlight T2 APD DRP | DZ46: =-M24 -> 0 | EA46: LAE A&O Reserves - Direct | EB46: 100 | EC46: 208100 | ED46: 00 | EE46: 2002 | EF46: 000212 | EG46: {=RIGHT(CELL("filename",A1),LEN(CELL("filename",A1))-FIND("]",CELL("filename",A1)))} -> #VALUE! | EH46: 0000 | EJ46: FUT Starlight T2 APD DRP | EK46: =-N24 -> 0 | EL46: LAE A&O Reserves - Direct | EM46: 100 | EN46: 208100 | EO46: 00 | EP46: 2002 | EQ46: 000212 | ER46: {=RIGHT(CELL("filename",A1),LEN(CELL("filename",A1))-FIND("]",CELL("filename",A1)))} -> #VALUE! | ES46: 0000 | EU46: FUT Starlight T2 APD DRP | EV46: =-O24 -> 0
B47: Fronting Fee @ 5% (paid by separate wire from NTA) | C47: =+C6*0.05 -> 0 | D47: =+D6*0.05 -> 0 | P47: =SUM(D47:O47) -> 0 | Q47: =+C47+P47 -> 0 | U47: LAE A&O Reserves - Ceded | V47: 100 | W47: 208300 | X47: 00 | Y47: 2002 | Z47: 000212 | AA47: 00 | AB47: 0000 | AD47: FUT Starlight T2 APD DRP | AE47: =+D24 -> 0 | AF47: LAE A&O Reserves - Ceded | AG47: 100 | AH47: 208300 | AI47: 00 | AJ47: 2002 | AK47: 000212 | AL47: 00 | AM47: 0000 | AO47: FUT Starlight T2 APD DRP | AP47: =+E24 -> 0 | AQ47: LAE A&O Reserves - Ceded | AR47: 100 | AS47: 208300 | AT47: 00 | AU47: 2002 | AV47: 000212 | AW47: 00 | AX47: 0000 | AZ47: FUT Starlight T2 APD DRP | BA47: =+F24 -> 0 | BB47: LAE A&O Reserves - Ceded | BC47: 100 | BD47: 208300 | BE47: 00 | BF47: 2002 | BG47: 000212 | BH47: 00 | BI47: 0000 | BK47: FUT Starlight T2 APD DRP | BL47: =+G24 -> 0 | BM47: LAE A&O Reserves - Ceded | BN47: 100 | BO47: 208300 | BP47: 00 | BQ47: 2002 | BR47: 000212 | BS47: 00 | BT47: 0000 | BV47: FUT Starlight T2 APD DRP | BW47: =+H24 -> 0 | BX47: LAE A&O Reserves - Ceded | BY47: 100 | BZ47: 208300 | CA47: 00 | CB47: 2002 | CC47: 000212 | CD47: 00 | CE47: 0000 | CG47: FUT Starlight T2 APD DRP | CH47: =+I24 -> 0 | CI47: LAE A&O Reserves - Ceded | CJ47: 100 | CK47: 208300 | CL47: 00 | CM47: 2002 | CN47: 000212 | CO47: 00 | CP47: 0000 | CR47: FUT Starlight T2 APD DRP | CS47: =+J24 -> 0 | CT47: LAE A&O Reserves - Ceded | CU47: 100 | CV47: 208300 | CW47: 00 | CX47: 2002 | CY47: 000212 | CZ47: 00 | DA47: 0000 | DC47: FUT Starlight T2 APD DRP | DD47: =+K24 -> 0 | DE47: LAE A&O Reserves - Ceded | DF47: 100 | DG47: 208300 | DH47: 00 | DI47: 2002 | DJ47: 000212 | DK47: 00 | DL47: 0000 | DN47: FUT Starlight T2 APD DRP | DO47: =+L24 -> 0 | DP47: LAE A&O Reserves - Ceded | DQ47: 100 | DR47: 208300 | DS47: 00 | DT47: 2002 | DU47: 000212 | DV47: 00 | DW47: 0000 | DY47: FUT Starlight T2 APD DRP | DZ47: =+M24 -> 0 | EA47: LAE A&O Reserves - Ceded | EB47: 100 | EC47: 208300 | ED47: 00 | EE47: 2002 | EF47: 000212 | EG47: 00 | EH47: 0000 | EJ47: FUT Starlight T2 APD DRP | EK47: =+N24 -> 0 | EL47: LAE A&O Reserves - Ceded | EM47: 100 | EN47: 208300 | EO47: 00 | EP47: 2002 | EQ47: 000212 | ER47: 00 | ES47: 0000 | EU47: FUT Starlight T2 APD DRP | EV47: =+O24 -> 0
B48: Fronting Fee on UEP | C48: =+C7*0.05 -> 0 | D48: =+D7*0.05 -> 0 | P48: =SUM(D48:O48) -> 0 | Q48: =+C48+P48 -> 0 | U48: Change in LAE A&O Reserves - Ceded | V48: 100 | W48: 558300 | X48: 00 | Y48: 2002 | Z48: 000212 | AA48: 00 | AB48: 0000 | AD48: FUT Starlight T2 APD DRP | AE48: =-D24 -> 0 | AF48: Change in LAE A&O Reserves - Ceded | AG48: 100 | AH48: 558300 | AI48: 00 | AJ48: 2002 | AK48: 000212 | AL48: 00 | AM48: 0000 | AO48: FUT Starlight T2 APD DRP | AP48: =-E24 -> 0 | AQ48: Change in LAE A&O Reserves - Ceded | AR48: 100 | AS48: 558300 | AT48: 00 | AU48: 2002 | AV48: 000212 | AW48: 00 | AX48: 0000 | AZ48: FUT Starlight T2 APD DRP | BA48: =-F24 -> 0 | BB48: Change in LAE A&O Reserves - Ceded | BC48: 100 | BD48: 558300 | BE48: 00 | BF48: 2002 | BG48: 000212 | BH48: 00 | BI48: 0000 | BK48: FUT Starlight T2 APD DRP | BL48: =-G24 -> 0 | BM48: Change in LAE A&O Reserves - Ceded | BN48: 100 | BO48: 558300 | BP48: 00 | BQ48: 2002 | BR48: 000212 | BS48: 00 | BT48: 0000 | BV48: FUT Starlight T2 APD DRP | BW48: =-H24 -> 0 | BX48: Change in LAE A&O Reserves - Ceded | BY48: 100 | BZ48: 558300 | CA48: 00 | CB48: 2002 | CC48: 000212 | CD48: 00 | CE48: 0000 | CG48: FUT Starlight T2 APD DRP | CH48: =-I24 -> 0 | CI48: Change in LAE A&O Reserves - Ceded | CJ48: 100 | CK48: 558300 | CL48: 00 | CM48: 2002 | CN48: 000212 | CO48: 00 | CP48: 0000 | CR48: FUT Starlight T2 APD DRP | CS48: =-J24 -> 0 | CT48: Change in LAE A&O Reserves - Ceded | CU48: 100 | CV48: 558300 | CW48: 00 | CX48: 2002 | CY48: 000212 | CZ48: 00 | DA48: 0000 | DC48: FUT Starlight T2 APD DRP | DD48: =-K24 -> 0 | DE48: Change in LAE A&O Reserves - Ceded | DF48: 100 | DG48: 558300 | DH48: 00 | DI48: 2002 | DJ48: 000212 | DK48: 00 | DL48: 0000 | DN48: FUT Starlight T2 APD DRP | DO48: =-L24 -> 0 | DP48: Change in LAE A&O Reserves - Ceded | DQ48: 100 | DR48: 558300 | DS48: 00 | DT48: 2002 | DU48: 000212 | DV48: 00 | DW48: 0000 | DY48: FUT Starlight T2 APD DRP | DZ48: =-M24 -> 0 | EA48: Change in LAE A&O Reserves - Ceded | EB48: 100 | EC48: 558300 | ED48: 00 | EE48: 2002 | EF48: 000212 | EG48: 00 | EH48: 0000 | EJ48: FUT Starlight T2 APD DRP | EK48: =-N24 -> 0 | EL48: Change in LAE A&O Reserves - Ceded | EM48: 100 | EN48: 558300 | EO48: 00 | EP48: 2002 | EQ48: 000212 | ER48: 00 | ES48: 0000 | EU48: FUT Starlight T2 APD DRP | EV48: =-O24 -> 0
B49: Total Fees Earned - SSIC | C49: =+C34+C47+C48 -> 0 | D49: =+D34+D47+D48 -> 0 | P49: =+P34+P47+P48 -> 0 | Q49: =+Q34+Q47+Q48 -> 0 | U49: Change in IBNR A&O Reserves - Direct | V49: 100 | W49: 558400 | X49: 00 | Y49: 2002 | Z49: 000212 | AA49: {=RIGHT(CELL("filename",A1),LEN(CELL("filename",A1))-FIND("]",CELL("filename",A1)))} -> #VALUE! | AB49: 0000 | AD49: FUT Starlight T2 APD DRP | AE49: =+D25 -> 0 | AF49: Change in IBNR A&O Reserves - Direct | AG49: 100 | AH49: 558400 | AI49: 00 | AJ49: 2002 | AK49: 000212 | AL49: {=RIGHT(CELL("filename",A1),LEN(CELL("filename",A1))-FIND("]",CELL("filename",A1)))} -> #VALUE! | AM49: 0000 | AO49: FUT Starlight T2 APD DRP | AP49: =+E25 -> 0 | AQ49: Change in IBNR A&O Reserves - Direct | AR49: 100 | AS49: 558400 | AT49: 00 | AU49: 2002 | AV49: 000212 | AW49: {=RIGHT(CELL("filename",A1),LEN(CELL("filename",A1))-FIND("]",CELL("filename",A1)))} -> #VALUE! | AX49: 0000 | AZ49: FUT Starlight T2 APD DRP | BA49: =+F25 -> 0 | BB49: Change in IBNR A&O Reserves - Direct | BC49: 100 | BD49: 558400 | BE49: 00 | BF49: 2002 | BG49: 000212 | BH49: {=RIGHT(CELL("filename",A1),LEN(CELL("filename",A1))-FIND("]",CELL("filename",A1)))} -> #VALUE! | BI49: 0000 | BK49: FUT Starlight T2 APD DRP | BL49: =+G25 -> 0 | BM49: Change in IBNR A&O Reserves - Direct | BN49: 100 | BO49: 558400 | BP49: 00 | BQ49: 2002 | BR49: 000212 | BS49: {=RIGHT(CELL("filename",A1),LEN(CELL("filename",A1))-FIND("]",CELL("filename",A1)))} -> #VALUE! | BT49: 0000 | BV49: FUT Starlight T2 APD DRP | BW49: =+H25 -> 0 | BX49: Change in IBNR A&O Reserves - Direct | BY49: 100 | BZ49: 558400 | CA49: 00 | CB49: 2002 | CC49: 000212 | CD49: {=RIGHT(CELL("filename",A1),LEN(CELL("filename",A1))-FIND("]",CELL("filename",A1)))} -> #VALUE! | CE49: 0000 | CG49: FUT Starlight T2 APD DRP | CH49: =+I25 -> 0 | CI49: Change in IBNR A&O Reserves - Direct | CJ49: 100 | CK49: 558400 | CL49: 00 | CM49: 2002 | CN49: 000212 | CO49: {=RIGHT(CELL("filename",A1),LEN(CELL("filename",A1))-FIND("]",CELL("filename",A1)))} -> #VALUE! | CP49: 0000 | CR49: FUT Starlight T2 APD DRP | CS49: =+J25 -> 0 | CT49: Change in IBNR A&O Reserves - Direct | CU49: 100 | CV49: 558400 | CW49: 00 | CX49: 2002 | CY49: 000212 | CZ49: {=RIGHT(CELL("filename",A1),LEN(CELL("filename",A1))-FIND("]",CELL("filename",A1)))} -> #VALUE! | DA49: 0000 | DC49: FUT Starlight T2 APD DRP | DD49: =+K25 -> 0 | DE49: Change in IBNR A&O Reserves - Direct | DF49: 100 | DG49: 558400 | DH49: 00 | DI49: 2002 | DJ49: 000212 | DK49: {=RIGHT(CELL("filename",A1),LEN(CELL("filename",A1))-FIND("]",CELL("filename",A1)))} -> #VALUE! | DL49: 0000 | DN49: FUT Starlight T2 APD DRP | DO49: =+L25 -> 0 | DP49: Change in IBNR A&O Reserves - Direct | DQ49: 100 | DR49: 558400 | DS49: 00 | DT49: 2002 | DU49: 000212 | DV49: {=RIGHT(CELL("filename",A1),LEN(CELL("filename",A1))-FIND("]",CELL("filename",A1)))} -> #VALUE! | DW49: 0000 | DY49: FUT Starlight T2 APD DRP | DZ49: =+M25 -> 0 | EA49: Change in IBNR A&O Reserves - Direct | EB49: 100 | EC49: 558400 | ED49: 00 | EE49: 2002 | EF49: 000212 | EG49: {=RIGHT(CELL("filename",A1),LEN(CELL("filename",A1))-FIND("]",CELL("filename",A1)))} -> #VALUE! | EH49: 0000 | EJ49: FUT Starlight T2 APD DRP | EK49: =+N25 -> 0 | EL49: Change in IBNR A&O Reserves - Direct | EM49: 100 | EN49: 558400 | EO49: 00 | EP49: 2002 | EQ49: 000212 | ER49: {=RIGHT(CELL("filename",A1),LEN(CELL("filename",A1))-FIND("]",CELL("filename",A1)))} -> #VALUE! | ES49: 0000 | EU49: FUT Starlight T2 APD DRP | EV49: =+O25 -> 0
U50: IBNR A&O Reserves - Direct | V50: 100 | W50: 208400 | X50: 00 | Y50: 2002 | Z50: 000212 | AA50: {=RIGHT(CELL("filename",A1),LEN(CELL("filename",A1))-FIND("]",CELL("filename",A1)))} -> #VALUE! | AB50: 0000 | AD50: FUT Starlight T2 APD DRP | AE50: =-D25 -> 0 | AF50: IBNR A&O Reserves - Direct | AG50: 100 | AH50: 208400 | AI50: 00 | AJ50: 2002 | AK50: 000212 | AL50: {=RIGHT(CELL("filename",A1),LEN(CELL("filename",A1))-FIND("]",CELL("filename",A1)))} -> #VALUE! | AM50: 0000 | AO50: FUT Starlight T2 APD DRP | AP50: =-E25 -> 0 | AQ50: IBNR A&O Reserves - Direct | AR50: 100 | AS50: 208400 | AT50: 00 | AU50: 2002 | AV50: 000212 | AW50: {=RIGHT(CELL("filename",A1),LEN(CELL("filename",A1))-FIND("]",CELL("filename",A1)))} -> #VALUE! | AX50: 0000 | AZ50: FUT Starlight T2 APD DRP | BA50: =-F25 -> 0 | BB50: IBNR A&O Reserves - Direct | BC50: 100 | BD50: 208400 | BE50: 00 | BF50: 2002 | BG50: 000212 | BH50: {=RIGHT(CELL("filename",A1),LEN(CELL("filename",A1))-FIND("]",CELL("filename",A1)))} -> #VALUE! | BI50: 0000 | BK50: FUT Starlight T2 APD DRP | BL50: =-G25 -> 0 | BM50: IBNR A&O Reserves - Direct | BN50: 100 | BO50: 208400 | BP50: 00 | BQ50: 2002 | BR50: 000212 | BS50: {=RIGHT(CELL("filename",A1),LEN(CELL("filename",A1))-FIND("]",CELL("filename",A1)))} -> #VALUE! | BT50: 0000 | BV50: FUT Starlight T2 APD DRP | BW50: =-H25 -> 0 | BX50: IBNR A&O Reserves - Direct | BY50: 100 | BZ50: 208400 | CA50: 00 | CB50: 2002 | CC50: 000212 | CD50: {=RIGHT(CELL("filename",A1),LEN(CELL("filename",A1))-FIND("]",CELL("filename",A1)))} -> #VALUE! | CE50: 0000 | CG50: FUT Starlight T2 APD DRP | CH50: =-I25 -> 0 | CI50: IBNR A&O Reserves - Direct | CJ50: 100 | CK50: 208400 | CL50: 00 | CM50: 2002 | CN50: 000212 | CO50: {=RIGHT(CELL("filename",A1),LEN(CELL("filename",A1))-FIND("]",CELL("filename",A1)))} -> #VALUE! | CP50: 0000 | CR50: FUT Starlight T2 APD DRP | CS50: =-J25 -> 0 | CT50: IBNR A&O Reserves - Direct | CU50: 100 | CV50: 208400 | CW50: 00 | CX50: 2002 | CY50: 000212 | CZ50: {=RIGHT(CELL("filename",A1),LEN(CELL("filename",A1))-FIND("]",CELL("filename",A1)))} -> #VALUE! | DA50: 0000 | DC50: FUT Starlight T2 APD DRP | DD50: =-K25 -> 0 | DE50: IBNR A&O Reserves - Direct | DF50: 100 | DG50: 208400 | DH50: 00 | DI50: 2002 | DJ50: 000212 | DK50: {=RIGHT(CELL("filename",A1),LEN(CELL("filename",A1))-FIND("]",CELL("filename",A1)))} -> #VALUE! | DL50: 0000 | DN50: FUT Starlight T2 APD DRP | DO50: =-L25 -> 0 | DP50: IBNR A&O Reserves - Direct | DQ50: 100 | DR50: 208400 | DS50: 00 | DT50: 2002 | DU50: 000212 | DV50: {=RIGHT(CELL("filename",A1),LEN(CELL("filename",A1))-FIND("]",CELL("filename",A1)))} -> #VALUE! | DW50: 0000 | DY50: FUT Starlight T2 APD DRP | DZ50: =-M25 -> 0 | EA50: IBNR A&O Reserves - Direct | EB50: 100 | EC50: 208400 | ED50: 00 | EE50: 2002 | EF50: 000212 | EG50: {=RIGHT(CELL("filename",A1),LEN(CELL("filename",A1))-FIND("]",CELL("filename",A1)))} -> #VALUE! | EH50: 0000 | EJ50: FUT Starlight T2 APD DRP | EK50: =-N25 -> 0 | EL50: IBNR A&O Reserves - Direct | EM50: 100 | EN50: 208400 | EO50: 00 | EP50: 2002 | EQ50: 000212 | ER50: {=RIGHT(CELL("filename",A1),LEN(CELL("filename",A1))-FIND("]",CELL("filename",A1)))} -> #VALUE! | ES50: 0000 | EU50: FUT Starlight T2 APD DRP | EV50: =-O25 -> 0
B51: Unearned Premium Reserve | C51: 0 | D51: 0 | P51: =+F51 -> 0 | Q51: =P51 -> 0 | R51: =-R7 -> 0 | S51: =Q51-R51 -> 0 | U51: IBNR A&O Reserves - Ceded | V51: 100 | W51: 208600 | X51: 00 | Y51: 2002 | Z51: 000212 | AA51: 00 | AB51: 0000 | AD51: FUT Starlight T2 APD DRP | AE51: =+D25 -> 0 | AF51: IBNR A&O Reserves - Ceded | AG51: 100 | AH51: 208600 | AI51: 00 | AJ51: 2002 | AK51: 000212 | AL51: 00 | AM51: 0000 | AO51: FUT Starlight T2 APD DRP | AP51: =+E25 -> 0 | AQ51: IBNR A&O Reserves - Ceded | AR51: 100 | AS51: 208600 | AT51: 00 | AU51: 2002 | AV51: 000212 | AW51: 00 | AX51: 0000 | AZ51: FUT Starlight T2 APD DRP | BA51: =+F25 -> 0 | BB51: IBNR A&O Reserves - Ceded | BC51: 100 | BD51: 208600 | BE51: 00 | BF51: 2002 | BG51: 000212 | BH51: 00 | BI51: 0000 | BK51: FUT Starlight T2 APD DRP | BL51: =+G25 -> 0 | BM51: IBNR A&O Reserves - Ceded | BN51: 100 | BO51: 208600 | BP51: 00 | BQ51: 2002 | BR51: 000212 | BS51: 00 | BT51: 0000 | BV51: FUT Starlight T2 APD DRP | BW51: =+H25 -> 0 | BX51: IBNR A&O Reserves - Ceded | BY51: 100 | BZ51: 208600 | CA51: 00 | CB51: 2002 | CC51: 000212 | CD51: 00 | CE51: 0000 | CG51: FUT Starlight T2 APD DRP | CH51: =+I25 -> 0 | CI51: IBNR A&O Reserves - Ceded | CJ51: 100 | CK51: 208600 | CL51: 00 | CM51: 2002 | CN51: 000212 | CO51: 00 | CP51: 0000 | CR51: FUT Starlight T2 APD DRP | CS51: =+J25 -> 0 | CT51: IBNR A&O Reserves - Ceded | CU51: 100 | CV51: 208600 | CW51: 00 | CX51: 2002 | CY51: 000212 | CZ51: 00 | DA51: 0000 | DC51: FUT Starlight T2 APD DRP | DD51: =+K25 -> 0 | DE51: IBNR A&O Reserves - Ceded | DF51: 100 | DG51: 208600 | DH51: 00 | DI51: 2002 | DJ51: 000212 | DK51: 00 | DL51: 0000 | DN51: FUT Starlight T2 APD DRP | DO51: =+L25 -> 0 | DP51: IBNR A&O Reserves - Ceded | DQ51: 100 | DR51: 208600 | DS51: 00 | DT51: 2002 | DU51: 000212 | DV51: 00 | DW51: 0000 | DY51: FUT Starlight T2 APD DRP | DZ51: =+M25 -> 0 | EA51: IBNR A&O Reserves - Ceded | EB51: 100 | EC51: 208600 | ED51: 00 | EE51: 2002 | EF51: 000212 | EG51: 00 | EH51: 0000 | EJ51: FUT Starlight T2 APD DRP | EK51: =+N25 -> 0 | EL51: IBNR A&O Reserves - Ceded | EM51: 100 | EN51: 208600 | EO51: 00 | EP51: 2002 | EQ51: 000212 | ER51: 00 | ES51: 0000 | EU51: FUT Starlight T2 APD DRP | EV51: =+O25 -> 0
B52: Loss Reserves | C52: 0 | D52: 0 | P52: =+F52 -> 0 | Q52: =P52 -> 0 | R52: =Q52 -> 0 | S52: =Q52-R52 -> 0 | U52: Change in IBNR A&O Reserves - Ceded | V52: 100 | W52: 558600 | X52: 00 | Y52: 2002 | Z52: 000212 | AA52: 00 | AB52: 0000 | AD52: FUT Starlight T2 APD DRP | AE52: =-D25 -> 0 | AF52: Change in IBNR A&O Reserves - Ceded | AG52: 100 | AH52: 558600 | AI52: 00 | AJ52: 2002 | AK52: 000212 | AL52: 00 | AM52: 0000 | AO52: FUT Starlight T2 APD DRP | AP52: =-E25 -> 0 | AQ52: Change in IBNR A&O Reserves - Ceded | AR52: 100 | AS52: 558600 | AT52: 00 | AU52: 2002 | AV52: 000212 | AW52: 00 | AX52: 0000 | AZ52: FUT Starlight T2 APD DRP | BA52: =-F25 -> 0 | BB52: Change in IBNR A&O Reserves - Ceded | BC52: 100 | BD52: 558600 | BE52: 00 | BF52: 2002 | BG52: 000212 | BH52: 00 | BI52: 0000 | BK52: FUT Starlight T2 APD DRP | BL52: =-G25 -> 0 | BM52: Change in IBNR A&O Reserves - Ceded | BN52: 100 | BO52: 558600 | BP52: 00 | BQ52: 2002 | BR52: 000212 | BS52: 00 | BT52: 0000 | BV52: FUT Starlight T2 APD DRP | BW52: =-H25 -> 0 | BX52: Change in IBNR A&O Reserves - Ceded | BY52: 100 | BZ52: 558600 | CA52: 00 | CB52: 2002 | CC52: 000212 | CD52: 00 | CE52: 0000 | CG52: FUT Starlight T2 APD DRP | CH52: =-I25 -> 0 | CI52: Change in IBNR A&O Reserves - Ceded | CJ52: 100 | CK52: 558600 | CL52: 00 | CM52: 2002 | CN52: 000212 | CO52: 00 | CP52: 0000 | CR52: FUT Starlight T2 APD DRP | CS52: =-J25 -> 0 | CT52: Change in IBNR A&O Reserves - Ceded | CU52: 100 | CV52: 558600 | CW52: 00 | CX52: 2002 | CY52: 000212 | CZ52: 00 | DA52: 0000 | DC52: FUT Starlight T2 APD DRP | DD52: =-K25 -> 0 | DE52: Change in IBNR A&O Reserves - Ceded | DF52: 100 | DG52: 558600 | DH52: 00 | DI52: 2002 | DJ52: 000212 | DK52: 00 | DL52: 0000 | DN52: FUT Starlight T2 APD DRP | DO52: =-L25 -> 0 | DP52: Change in IBNR A&O Reserves - Ceded | DQ52: 100 | DR52: 558600 | DS52: 00 | DT52: 2002 | DU52: 000212 | DV52: 00 | DW52: 0000 | DY52: FUT Starlight T2 APD DRP | DZ52: =-M25 -> 0 | EA52: Change in IBNR A&O Reserves - Ceded | EB52: 100 | EC52: 558600 | ED52: 00 | EE52: 2002 | EF52: 000212 | EG52: 00 | EH52: 0000 | EJ52: FUT Starlight T2 APD DRP | EK52: =-N25 -> 0 | EL52: Change in IBNR A&O Reserves - Ceded | EM52: 100 | EN52: 558600 | EO52: 00 | EP52: 2002 | EQ52: 000212 | ER52: 00 | ES52: 0000 | EU52: FUT Starlight T2 APD DRP | EV52: =-O25 -> 0
B53: Loss IBNR Reserves | C53: 0 | D53: =+D65-D15-D16+C53 -> 0 | P53: =+P65-P15-P16+C53 -> 0 | Q53: =P53 -> 0 | U53: Direct ULAE Paid | V53: 100 | W53: 603100 | X53: 00 | Y53: 2002 | Z53: 000212 | AA53: {=RIGHT(CELL("filename",A1),LEN(CELL("filename",A1))-FIND("]",CELL("filename",A1)))} -> #VALUE! | AB53: 0000 | AD53: FUT Starlight T2 APD DRP | AE53: =+D26 -> 0 | AF53: Direct ULAE Paid | AG53: 100 | AH53: 603100 | AI53: 00 | AJ53: 2002 | AK53: 000212 | AL53: {=RIGHT(CELL("filename",A1),LEN(CELL("filename",A1))-FIND("]",CELL("filename",A1)))} -> #VALUE! | AM53: 0000 | AO53: FUT Starlight T2 APD DRP | AP53: =+E26 -> 0 | AQ53: Direct ULAE Paid | AR53: 100 | AS53: 603100 | AT53: 00 | AU53: 2002 | AV53: 000212 | AW53: {=RIGHT(CELL("filename",A1),LEN(CELL("filename",A1))-FIND("]",CELL("filename",A1)))} -> #VALUE! | AX53: 0000 | AZ53: FUT Starlight T2 APD DRP | BA53: =+F26 -> 0 | BB53: Direct ULAE Paid | BC53: 100 | BD53: 603100 | BE53: 00 | BF53: 2002 | BG53: 000212 | BH53: {=RIGHT(CELL("filename",A1),LEN(CELL("filename",A1))-FIND("]",CELL("filename",A1)))} -> #VALUE! | BI53: 0000 | BK53: FUT Starlight T2 APD DRP | BL53: =+G26 -> 0 | BM53: Direct ULAE Paid | BN53: 100 | BO53: 603100 | BP53: 00 | BQ53: 2002 | BR53: 000212 | BS53: {=RIGHT(CELL("filename",A1),LEN(CELL("filename",A1))-FIND("]",CELL("filename",A1)))} -> #VALUE! | BT53: 0000 | BV53: FUT Starlight T2 APD DRP | BW53: =+H26 -> 0 | BX53: Direct ULAE Paid | BY53: 100 | BZ53: 603100 | CA53: 00 | CB53: 2002 | CC53: 000212 | CD53: {=RIGHT(CELL("filename",A1),LEN(CELL("filename",A1))-FIND("]",CELL("filename",A1)))} -> #VALUE! | CE53: 0000 | CG53: FUT Starlight T2 APD DRP | CH53: =+I26 -> 0 | CI53: Direct ULAE Paid | CJ53: 100 | CK53: 603100 | CL53: 00 | CM53: 2002 | CN53: 000212 | CO53: {=RIGHT(CELL("filename",A1),LEN(CELL("filename",A1))-FIND("]",CELL("filename",A1)))} -> #VALUE! | CP53: 0000 | CR53: FUT Starlight T2 APD DRP | CS53: =+J26 -> 0 | CT53: Direct ULAE Paid | CU53: 100 | CV53: 603100 | CW53: 00 | CX53: 2002 | CY53: 000212 | CZ53: {=RIGHT(CELL("filename",A1),LEN(CELL("filename",A1))-FIND("]",CELL("filename",A1)))} -> #VALUE! | DA53: 0000 | DC53: FUT Starlight T2 APD DRP | DD53: =+K26 -> 0 | DE53: Direct ULAE Paid | DF53: 100 | DG53: 603100 | DH53: 00 | DI53: 2002 | DJ53: 000212 | DK53: {=RIGHT(CELL("filename",A1),LEN(CELL("filename",A1))-FIND("]",CELL("filename",A1)))} -> #VALUE! | DL53: 0000 | DN53: FUT Starlight T2 APD DRP | DO53: =+L26 -> 0 | DP53: Direct ULAE Paid | DQ53: 100 | DR53: 603100 | DS53: 00 | DT53: 2002 | DU53: 000212 | DV53: {=RIGHT(CELL("filename",A1),LEN(CELL("filename",A1))-FIND("]",CELL("filename",A1)))} -> #VALUE! | DW53: 0000 | DY53: FUT Starlight T2 APD DRP | DZ53: =+M26 -> 0 | EA53: Direct ULAE Paid | EB53: 100 | EC53: 603100 | ED53: 00 | EE53: 2002 | EF53: 000212 | EG53: {=RIGHT(CELL("filename",A1),LEN(CELL("filename",A1))-FIND("]",CELL("filename",A1)))} -> #VALUE! | EH53: 0000 | EJ53: FUT Starlight T2 APD DRP | EK53: =+N26 -> 0 | EL53: Direct ULAE Paid | EM53: 100 | EN53: 603100 | EO53: 00 | EP53: 2002 | EQ53: 000212 | ER53: {=RIGHT(CELL("filename",A1),LEN(CELL("filename",A1))-FIND("]",CELL("filename",A1)))} -> #VALUE! | ES53: 0000 | EU53: FUT Starlight T2 APD DRP | EV53: =+O26 -> 0
B54: LAE Reserves - DCC | C54: 0 | D54: 0 | P54: =+F54 -> 0 | Q54: =P54 -> 0 | R54: =Q54 -> 0 | S54: =Q54-R54 -> 0 | U54: Payable to MGA | V54: 100 | W54: 264400 | X54: 00 | Y54: 2002 | Z54: 000212 | AA54: 00 | AB54: 0000 | AD54: FUT Starlight T2 APD DRP | AE54: =-D26 -> 0 | AF54: Payable to MGA | AG54: 100 | AH54: 264400 | AI54: 00 | AJ54: 2002 | AK54: 000212 | AL54: 00 | AM54: 0000 | AO54: FUT Starlight T2 APD DRP | AP54: =-E26 -> 0 | AQ54: Payable to MGA | AR54: 100 | AS54: 264400 | AT54: 00 | AU54: 2002 | AV54: 000212 | AW54: 00 | AX54: 0000 | AZ54: FUT Starlight T2 APD DRP | BA54: =-F26 -> 0 | BB54: Payable to MGA | BC54: 100 | BD54: 264400 | BE54: 00 | BF54: 2002 | BG54: 000212 | BH54: 00 | BI54: 0000 | BK54: FUT Starlight T2 APD DRP | BL54: =-G26 -> 0 | BM54: Payable to MGA | BN54: 100 | BO54: 264400 | BP54: 00 | BQ54: 2002 | BR54: 000212 | BS54: 00 | BT54: 0000 | BV54: FUT Starlight T2 APD DRP | BW54: =-H26 -> 0 | BX54: Payable to MGA | BY54: 100 | BZ54: 264400 | CA54: 00 | CB54: 2002 | CC54: 000212 | CD54: 00 | CE54: 0000 | CG54: FUT Starlight T2 APD DRP | CH54: =-I26 -> 0 | CI54: Payable to MGA | CJ54: 100 | CK54: 264400 | CL54: 00 | CM54: 2002 | CN54: 000212 | CO54: 00 | CP54: 0000 | CR54: FUT Starlight T2 APD DRP | CS54: =-J26 -> 0 | CT54: Payable to MGA | CU54: 100 | CV54: 264400 | CW54: 00 | CX54: 2002 | CY54: 000212 | CZ54: 00 | DA54: 0000 | DC54: FUT Starlight T2 APD DRP | DD54: =-K26 -> 0 | DE54: Payable to MGA | DF54: 100 | DG54: 264400 | DH54: 00 | DI54: 2002 | DJ54: 000212 | DK54: 00 | DL54: 0000 | DN54: FUT Starlight T2 APD DRP | DO54: =-L26 -> 0 | DP54: Payable to MGA | DQ54: 100 | DR54: 264400 | DS54: 00 | DT54: 2002 | DU54: 000212 | DV54: 00 | DW54: 0000 | DY54: FUT Starlight T2 APD DRP | DZ54: =-M26 -> 0 | EA54: Payable to MGA | EB54: 100 | EC54: 264400 | ED54: 00 | EE54: 2002 | EF54: 000212 | EG54: 00 | EH54: 0000 | EJ54: FUT Starlight T2 APD DRP | EK54: =-N26 -> 0 | EL54: Payable to MGA | EM54: 100 | EN54: 264400 | EO54: 00 | EP54: 2002 | EQ54: 000212 | ER54: 00 | ES54: 0000 | EU54: FUT Starlight T2 APD DRP | EV54: =-O26 -> 0
